Workbook

Sheet Stage_6_API_200
A1: id | B1: Year | C1: Title | D1: Abstract | E1: include_stage6 | F1: reason_stage6 | G1: main_shift | H1: shifts_detected | I1: confidence_stage6
A2: J502 | B2: 2019 | C2: Pdb16 Assessment of Cost-Effectiveness of a 0.2 Mcg/Day Fluocinolone Acetonide (Fac) Implant in Patients with Chronic Diabetic Macular Oedema (Dmo) in an Eye with Cataract | D2: Objectives: The fluocinolone acetonide 0.2 mug/day implant (FAc) is effective in improving visual acuity in patients with chronic diabetic macular oedema (cDMO) but is associated with worsening of cataract. A model previously suggested that FAc is cost-effective in patients with cDMO, who have undergone cataract surgery or not. The aim of this study was to update this model and assess the cost-effectiveness of FAc in the subgroup of patients with symptomatic cataract. Method(s): The existing Markov model was designed to assess costs and QALYs over lifetime in patients treated with FAc implant, compared to usual care (UC), consisting of laser photocoagulation and anti-VEGFs from the UK NHS perspective. Unit costs and health state utility values (HSUVs) were updated. The FAc price was NHS list price. HSUVs were obtained from the FAME trial using the VFQ-UI utility index. Best-Corrected Visual Acuity (BCVA) with UC was supposed to be stable. Additional scenarios were considered, with BCVA decreasing over time in UC arm, according to real-world data, and with possibility of administering FAc after cataract surgery in the UC arm. Result(s): New HSUVs ranged from 0.48 for blind patients to 0.91 for patients with perfect vision in both eyes. The FAc strategy was more expensive compared to usual care, by 3,445 per patients over lifetime, and produced more QALYs (+0.247). The incremental cost-effectiveness ratio (ICER) was estimated at 13,932 per QALY gained. The ICER was sensitive to the baseline visual acuity, patients' age and the probability of cataract surgery. The probability of FAc being cost-effective was 66.1% at a threshold of 20,000 per QALY gained. Scenario analyses showed that the efficacy of UC had a strong influence on results, and ICER decreased to 1,686 per QALY gained when BCVA decreased under UC Conclusion(s): The FAc implant is a cost-effective treatment for cDMO in patients with symptomatic cataract. Copyright Ãƒâ€šÃ‚Â© 2019 | E2: FALSE | F2: Focuses on cost-effectiveness of a treatment, not NHS shifts. | G2: None | I2: 0.9
A3: J503 | B3: 2019 | C3: Fluorides for preventing early tooth decay (demineralised lesions) during fixed brace treatment | D3: - Background Early dental decay or demineralised lesions (DLs, also known as white spot lesions) can appear on teeth during fixed orthodontic (brace) treatment. Fluoride reduces decay in susceptible individuals, including orthodontic patients. This review compared various forms of topical fluoride to prevent the development of DLs during orthodontic treatment. This is the second update of the Cochrane Review first published in 2004 and previously updated in 2013. Objectives The primary objective was to evaluate whether topical fluoride reduces the proportion of orthodontic patients with new DLs after fixed appliances. The secondary objectives were to examine the effectiveness of different modes of topical fluoride delivery in reducing the proportions of orthodontic patients with new DLs, as well as the severity of lesions, in terms of number, size and colour. ParticipantÃƒÂ¢Ã¢â€šÂ¬Ã‚Âassessed outcomes, such as perception of DLs, and oral healthÃƒÂ¢Ã¢â€šÂ¬Ã‚Ârelated quality of life data were to be included, as would reports of adverse effects. Search methods Cochrane Oral Health's Information Specialist searched the following databases: Cochrane Oral Health's Trials Register (to 1 February 2019), the Cochrane Central Register of Controlled Trials (CENTRAL; 2019, Issue 1) in the Cochrane Library (searched 1 February 2019), MEDLINE Ovid (1946 to 1 February 2019), and Embase Ovid (1980 to 1 February 2019). The US National Institutes of Health Ongoing Trials Register (ClinicalTrials.gov) and the World Health Organization International Clinical Trials Registry Platform were searched for ongoing trials. No restrictions were placed on the language or date of publication when searching the electronic databases. Selection criteria ParallelÃƒÂ¢Ã¢â€šÂ¬Ã‚Âgroup, randomised controlled trials comparing the use of a fluorideÃƒÂ¢Ã¢â€šÂ¬Ã‚Âcontaining product versus a placebo, no treatment or a different type of fluoride treatment, in which the outcome of enamel demineralisation was assessed at the start and at the end of orthodontic treatment. Data collection and analysis At least two review authors independently, in duplicate, conducted risk of bias assessments and extracted data. Authors of trials were contacted to obtain missing data or to ask for clarification of aspects of trial methodology. Cochrane's statistical guidelines were followed. Main results This update includes 10 studies and contains data from nine studies, comparing eight interventions, involving 1798 randomised participants (1580 analysed). One report contained insufficient information and the authors have been contacted. We assessed two studies as at low risk of bias, six at unclear risk of bias, and two at high risk of bias. Two placebo (nonÃƒÂ¢Ã¢â€šÂ¬Ã‚Âfluoride) controlled studies, at low risk of bias, investigated the professional application of varnish (7700 or 10,000 parts per million (ppm) fluoride (F)), every six weeks and found insufficient evidence of a difference regarding its effectiveness in preventing new DLs (risk ratio (RR) 0.52, 95% confidence interval (CI) 0.14 to 1.93; 405 participants; lowÃƒÂ¢Ã¢â€šÂ¬Ã‚Âcertainty evidence). One placebo (nonÃƒÂ¢Ã¢â€šÂ¬Ã‚Âfluoride) controlled study, at unclear risk of bias, provides a low level of certainty that fluoride foam (12,300 ppm F), professionally applied every two months, may reduce the incidence of new DLs (12% versus 49%) after fixed orthodontic treatment (RR 0.26, 95% CI 0.11 to 0.57; 95 participants). One study, at unclear risk of bias, also provides a low level of certainty that use of a highÃƒÂ¢Ã¢â€šÂ¬Ã‚Âconcentration fluoride toothpaste (5000 ppm F) by patients may reduce the incidence of new DLs (18% versus 27%) compared with a conventional fluoride toothpaste (1450 ppm F) (RR 0.68, 95% CI 0.46 to 1.00; 380 participants). There was no evidence for a difference in the proportions of orthodontic patients with new DLs on the teeth after treatment with fixed orthodontic appliances for the following comparisons:ÃƒÂ¢Ã¢â€šÂ¬Ã‚Â¨ ÃƒÂ¢Ã¢â€šÂ¬Ã‚Â an amine fluoride and stannous fluoride toothpaste/mouthrinse combination versus a sodium fluoride toothpaste/mouthrinse,ÃƒÂ¢Ã¢â€šÂ¬Ã‚Â¨ ÃƒÂ¢Ã¢â€šÂ¬Ã‚Â an amine fluoride gel versus a nonÃƒÂ¢Ã¢â€šÂ¬Ã‚Âfluoride placebo applied by participants at home once a week and by professional application every three months,ÃƒÂ¢Ã¢â€šÂ¬Ã‚Â¨ ÃƒÂ¢Ã¢â€šÂ¬Ã‚Â resinÃƒÂ¢Ã¢â€šÂ¬Ã‚Âmodified glass ionomer cement versus lightÃƒÂ¢Ã¢â€šÂ¬Ã‚Âcured composite resin for bonding orthodontic brackets,ÃƒÂ¢Ã¢â€šÂ¬Ã‚Â¨ ÃƒÂ¢Ã¢â€šÂ¬Ã‚Â a 250 ppm F mouthrinse versus 0 ppm F placebo mouthrinse,ÃƒÂ¢Ã¢â€šÂ¬Ã‚Â¨ ÃƒÂ¢Ã¢â€šÂ¬Ã‚Â the use of an intraoral fluorideÃƒÂ¢Ã¢â€šÂ¬Ã‚Âreleasing glass bead device attached to the brace versus a daily fluoride mouthrinse. The last two comparisons involved studies that were assessed at high risk of bias, because a substantial number of participants were lost to followÃƒÂ¢Ã¢â€šÂ¬Ã‚Âup. Unfortunately, although the internal validity and hence the quality of the studies has improved since the first version of the review, they have compared different interventions; therefore, the findings are only considered to provide low level of certainty, because none has been replicated by followÃƒÂ¢Ã¢â€šÂ¬Ã‚Âup studies, in different settings, to confirm external validity. A patientÃƒÂ¢Ã¢â€šÂ¬Ã‚Âreported outcome, such as concern about the aesthetics of any DLs, was still not included as an outcome in any study. Reports of adverse effects from topical fluoride applications were rare and unlikely to be significant. One study involving fluorideÃƒÂ¢Ã¢â€šÂ¬Ã‚Âcontaining glass beads reported numerous breakages. Authors' conclusions This review found a low level of certainty that 12,300 ppm F foam applied by a professional every 6 to 8 weeks throughout fixed orthodontic treatment, might be effective in reducing the proportion of orthodontic patients with new DLs. In addition, there is a low level of certainty that the patient use of a high fluoride toothpaste (5000 ppm F) throughout orthodontic treatment, might be more effective than a conventional fluoride toothpaste. These two comparisons were based on single studies. There was insufficient evidence of a difference regarding the professional application of fluoride varnish (7700 or 10,000 ppm F). Further adequately powered, randomised controlled trials are required to increase the certainty of these findings and to determine the best means of preventing DLs in patients undergoing fixed orthodontic treatment. The most accurate means of assessing adherence with the use of fluoride products by patients and any possible adverse effects also need to be considered. Future studies should follow up participants beyond the end of orthodontic treatment to determine the effect of DLs on patient satisfaction with treatment. Plain language summary Fluorides for preventing early tooth decay (demineralised lesions) during fixed brace treatment Review question ÃƒÂ¢Ã¢â€šÂ¬Ã‚Â¨ Ugly white or brown marks sometimes appear on the teeth during treatment with braces to straighten teeth. These are due to early tooth decay and usually occur with fixed, gluedÃƒÂ¢Ã¢â€šÂ¬Ã‚Âon 'train track', braces, which make it more difficult to clean the teeth. We know that fluoride in toothpaste helps to prevent tooth decay and think that if extra fluoride is given to people wearing fixed braces, it will protect them from getting these marks. The aim of this Cochrane Oral Health's review was to look at how well fluorides help to prevent early tooth decay during fixed brace treatment and to find out the best way to get fluoride to the teeth. Background ÃƒÂ¢Ã¢â€šÂ¬Ã‚Â¨ Wearing a fixed brace makes it harder for people to keep their teeth clean and may also cause pain. Pain can make it more difficult for people to brush their teeth. This can lead to a buildÃƒÂ¢Ã¢â€šÂ¬Ã‚Âup of dental plaque around the brackets that attach the fixed brace to the teeth, and if the plaque stays on the tooth for long enough, it will cause early tooth decay, which looks like white or brown marks (demineralised lesions, also known as white spot lesions). People often wear braces for 18 months or longer and if the decay is left to progress, it can cause holes, which are sometimes bad enough to need fillings to be done in the teeth. Fluoride helps the tooth to heal, reducing tooth decay in people who are at risk of developing it. People receiving fixed brace treatment may be given different forms of fluoride treatment. It is important to think about how the fluoride gets to the teeth. Does the fluoride need to be placed by a dentist or dental nurse, or can people having treatment with braces apply the fluoride to their own teeth? Study characteristics ÃƒÂ¢Ã¢â€šÂ¬Ã‚Â¨ This review is upÃƒÂ¢Ã¢â€šÂ¬Ã‚ÂtoÃƒÂ¢Ã¢â€šÂ¬Ã‚Âdate as of 1 February 2019. The review includes 10 studies but we could only use the information from nine studies involving 1798 randomised people. We have asked for more information about one study. The review looks at eight different ways of applying fluoride to the teeth. People taking part in the studies were all having treatment with fixed braces. The number of people with new decay on the teeth at end of fixed brace treatment, as well as the amount of decay in each person, were measured and counted. We compared the following treatments:ÃƒÂ¢Ã¢â€šÂ¬Ã‚Â¨ ÃƒÂ¢Ã¢â€šÂ¬Ã‚Â dentist or nurseÃƒÂ¢Ã¢â€šÂ¬Ã‚Âapplied fluoride e.g. varnish, gel or foam,ÃƒÂ¢Ã¢â€šÂ¬Ã‚Â¨ ÃƒÂ¢Ã¢â€šÂ¬Ã‚Â patientÃƒÂ¢Ã¢â€šÂ¬Ã‚Âapplied/used fluoride e.g. toothpaste, mouthwash, gel or foam, andÃƒÂ¢Ã¢â€šÂ¬Ã‚Â¨ ÃƒÂ¢Ã¢â€šÂ¬Ã‚Â materials that release fluoride over time e.g. glues, elastic bands. Key results ÃƒÂ¢Ã¢â€šÂ¬Ã‚Â¨ One study showed that when the dentist applies a foam with a high level of fluoride in it onto the teeth every time the patient is seen, this might reduce the risk of new decay. Another study found that if patients use a toothpaste with a higher level of fluoride than normal, then this might also reduce the risk of new marks on their teeth. No studies have shown that other ways of giving the teeth extra fluoride reduced the number and/or size of new decay on teeth in people wearing fixed braces. Harmful effects of the different ways of giving the teeth more fluoride were not reported in any of the included studies. Certainty of the evidence ÃƒÂ¢Ã¢â€šÂ¬Ã‚Â¨ The level of belief we have in these findings is low, due to the lack of studies testing the same fluorides and showing the same results. We suggest that more, wellÃƒÂ¢Ã¢â€šÂ¬Ã‚Âconducted studies should be done in this area. | E3: FALSE | F3: Focuses on treatment rather than prevention or community care. | G3: None | I3: 0.9
A4: J504 | B4: 2019 | C4: Pmh28 Assessing the Life-Cycle Value Added of Second-Generation Antipsychotics in Sweden and the Uk: The Case of Risperidone | D4: To estimate the life-cycle value of risperidone - representative of Second-Generation Antipsychotics- relative to First Generation Antipsychotics to balance the view that cost per Quality-Adjusted Life Year (QALY) at launch are enough to guide access decisions. Study aims to drive the discussion on access and price, through recognition of the dynamic nature of value added by pharmaceutical innovation over the long-run. We estimated the number of patients with schizophrenia treated with risperidone in Sweden and the UK (1994-2017). We collected cost-effectiveness data from the literature of risperidone and haloperidol - representative of First-Generation Antipsychotics. We modelled the life-cycle uptake of risperidone to estimate the life-cycle incremental cost, incremental QALYs and Net monetary Benefit (NMB). We also assessed the life-cycle distribution of the consumer (the payer) and the producer (innovator) surpluses. For the UK, the producer surplus represents around 28% of the total surplus before patent expiration and around 5% after patent expiration. Life-cycle NMB for the health system is estimated at 1,116m. During the life-cycle, the NMB significantly increased in response to two events: (i) the launch of Risperidone Long-Acting Injectable (RLAI); and (ii) generic entry. The ICER was negative (dominant) for the whole period. For Sweden, the producer surplus represents around 6% of the total surplus before patent expiration and around 1% after generic competition. Life-cycle NMB is estimated at 803m, and both NMB and ICER follow the same pattern as in the UK. Analysis shows that health systems appropriated most of the life-cycle value (surplus) generated. This suggests that, considering the entire life-cycle, the value added by SGAs to the system is higher than the value estimated using cost-effectiveness analysis at launch. Pricing and reimbursement decisions should take into account the dynamic nature of pharmaceutical markets and the value added by innovative medicines over the long-run. Copyright Ãƒâ€šÃ‚Â© 2019 | E4: FALSE | F4: Focuses on economic evaluation of antipsychotics, not NHS shifts. | G4: None | I4: 0.9
A5: J505 | B5: 2019 | C5: Fetal fibronectin testing for reducing the risk of preterm birth | D5: - Background Fetal fibronectin (FFN) is an extracellular matrix glycoprotein localized at the maternalÃƒÂ¢Ã¢â€šÂ¬Ã‚Âfetal interface of the amniotic membranes, between chorion and decidua, where it is concentrated in this area between decidua and trophoblast. In normal conditions, FFN is found at very low levels in cervicovaginal secretions. Levels greater than or equal to 50 ng/mL at or after 22 weeks have been associated with an increased risk of spontaneous preterm birth. In fact, FFN is one of the best predictors of preterm birth in all populations studied so far, and can help in selecting which women are at significant risk for preterm birth. This is an update of a review first published in 2008. Objectives To assess the effectiveness of management based on knowledge of FFN testing results for preventing preterm birth. Search methods For this update, we searched Cochrane Pregnancy and ChildbirthÃƒÂ¢Ã¢â€šÂ¬Ã¢â€žÂ¢s Trials Register (7 September 2018), ClinicalTrials.gov , the WHO International Clinical Trials Registry Platform ( ICTRP ) (7 September 2018), and reference lists of retrieved studies. Selection criteria Randomized controlled trials of pregnant women screened with FFN for risk of preterm birth. Studies included are based exclusively on knowledge of FFN results versus no such knowledge, and we have excluded studies including women with only positive or only negative FFN results. Data collection and analysis Two review authors independently assessed trials for inclusion and risk of bias, extracted data, and checked them for accuracy. The quality of the evidence was assessed using the GRADE approach. Main results We identified 16 trials, of which six were eligible for inclusion. The six included studies randomized 546 women with singleton gestations and threatened preterm labor (PTL) at 23 0/7 to 34 6/7 weeks. A total of 277 women were randomized to knowledge and 269 to no knowledge of FFN. No trials were identified on asymptomatic women or multiple gestations. The risk of bias of included studies was mixed. For selected important outcomes, preterm birth before 37, 34, and 32 weeks, and maternal hospitalization, we graded the quality of the evidence and created a 'Summary of findings' table. For these outcomes, the evidence was graded as mainly low quality due to the imprecision of effect estimates. Management based on knowledge of FFN results may reduce preterm birth before 37 weeks (20.7%) versus controls without such knowledge (29.2%) (risk ratio (RR) 0.72, 95% confidence interval (CI) 0.52 to 1.01; 5 trials; 434 women; lowÃƒÂ¢Ã¢â€šÂ¬Ã‚Âquality evidence). However, management based on knowledge of FFN results may make little or no difference to preterm birth before 34 (RR 1.09, 95% CI 0.54 to 2.18; 4 trials; 357 women; lowÃƒÂ¢Ã¢â€šÂ¬Ã‚Âquality evidence) or maternal hospitalization (RR 1.06, 95% CI 0.79 to 1.43; 5 trials; 441 women; lowÃƒÂ¢Ã¢â€šÂ¬Ã‚Âquality evidence). The evidence for preterm birth before 32 weeks is uncertain because the quality was found to be very low (average RR 0.79, 95% CI 0.16 to 3.96; 4 trials; 357 women; very lowÃƒÂ¢Ã¢â€šÂ¬Ã‚Âquality evidence). For all other outcomes, for which there were available data (preterm birth less than 28 weeks; gestational age at delivery (weeks); birthweight less than 2500 g; perinatal death; tocolysis; steroids for fetal lung maturity; time to evaluate; respiratory distress syndrome; neonatal intensive care unit (NICU) admission; and NICU days), knowledge of FFN results may make little or no difference to the outcomes. Authors' conclusions The evidence from this review suggests that management based on knowledge of FFN results may reduce preterm birth before 37 weeks. However, our confidence in this result is limited as the evidence was found to be of low quality. Effects on other substantive outcomes are uncertain due to serious concerns in study design, inconsistency, and imprecision of effect estimates. No trials were identified on asymptomatic women, or multiple gestations. Future studies are needed that include specific populations (e.g. singleton gestations with symptoms of preterm labor), a study gro p managed with a protocol based on the FFN results, and that report not only maternal but also important perinatal outcomes. CostÃƒÂ¢Ã¢â€šÂ¬Ã‚Âeffectiveness analyses are also needed. Plain language summary Fetal fibronectin testing for reducing the risk of preterm birth What is the issue? To assess the effectiveness of management of pregnant women based on a knowledge of fetal fibronectin test results for preventing preterm birth, compared with not having that knowledge. Fetal fibronectin (FFN) acts as a ÃƒÂ¢Ã¢â€šÂ¬Ã‹Å“glueÃƒÂ¢Ã¢â€šÂ¬Ã¢â€žÂ¢ between the pregnancy and the uterus. Normally very low levels of FFN can be found in secretions of the vagina and cervix. Raised levels at or after 22 weeks have been associated with an increased risk of spontaneous preterm birth. Why is this important? Preterm birth before 37 weeks is the main cause of sickness and death for newborn infants. Most women who give birth preterm have preterm labor symptoms such as contractions but many of the women with symptoms go on to deliver at term (37 weeks or more). Fetal fibronectin (FFN) is a test that can identify the women with symptoms of preterm labor who are most at risk for preterm birth. The level of FFN is measured in secretions from the vagina or cervix. What evidence did we find? We found six randomised controlled studies involving 546 women who were pregnant with one baby and were showing signs of preterm labor at between 23 to 34 weeks' gestation. We graded the following evidence as mainly low quality because of the low number of women in the studies and a wide variation in findings. We found that the number of births before 37 weeks may be slightly reduced when women and their doctors know the results of the FFN test (20.7% versus 29.2%; 5 trials; 434 women). However, knowledge of FFN results may make little or no difference for the other outcomes with available data, including: maternal hospitalization (5 trials; 441 women); use of uterine relaxants (tocolysis) to try to prevent labor; earlier preterm births; womenÃƒÂ¢Ã¢â€šÂ¬Ã¢â€žÂ¢s gestational age at delivery; babies with a birthweight less than 2500 g; newborn deaths; the number of babies with respiratory distress syndrome; giving steroids to mature the unborn babiesÃƒÂ¢Ã¢â€šÂ¬Ã¢â€žÂ¢ lungs; and number of days in a neonatal intensive care unit (NICU). What does this mean? This review of six studies did not find enough evidence to say whether or not the FFN test should be used in the management of women showing signs of preterm labor. A screening test such as FFN can only be considered effective if interventions based on the screening results, such as giving drugs to relax the uterus, reduce the number of preterm births. Further research should be encouraged. | E5: TRUE | F5: Focus on preventing preterm birth aligns with prevention shift. | G5: Prevention | H5: Prevention | I5: 0.9
A6: J506 | B6: 2019 | C6: Cervical assessment by ultrasound for preventing preterm delivery | D6: - Background Measurement of cervical length by ultrasound is predictive of preterm birth (PTB). There are three methods of ultrasound cervical assessment: transvaginal (TVU), transabdominal (TAU), and transperineal (TPU, also called translabial). Cervical length measured by TVU is a relatively new screening test, and has been associated with better prediction of PTB than previously available tests. It is unclear if cervical length measured by ultrasound is effective for preventing PTB. This is an update of a review last published in 2013. Objectives To assess the effectiveness of antenatal management based on transvaginal, transabdominal, and transperineal (also called translabial) ultrasound screening of cervical length for preventing preterm birth. Search methods For this update, we searched the Cochrane Pregnancy and ChildbirthÃƒÂ¢Ã¢â€šÂ¬Ã¢â€žÂ¢s Trials Register, ClinicalTrials.gov , and the WHO International Clinical Trials Registry Platform ( ICTRP ) to 30 August 2018; reviewed the reference lists of all articles, and contacted experts in the field for additional and ongoing trials. Selection criteria We included published and unpublished randomised controlled trials (RCT) including pregnant women between the gestational ages of 14 to 32 weeks, for whom the cervical length was screened for risk of PTB with TVU, TAU, or TPU. This review focused on studies based on knowledge versus no knowledge of cervical length results, or ultrasound versus no ultrasound for cervical length. We excluded studies based on interventions (e.g. progesterone, cerclage) for short cervical length. Data collection and analysis We followed standard Cochrane methods. Main results We included seven RCTs (N = 923): one examined asymptomatic women with twin pregnancies; four included women with singleton pregnancies and symptoms of preterm labour (PTL); one included women with singleton pregnancies and symptoms of preterm premature rupture of membranes (PPROM); and one included asymptomatic singletons. All trials used TVU for screening. We assessed the risk of bias of the included studies as mixed, and the quality of the evidence for primary outcomes as very low for all populations. For asymptomatic women with twin pregnancies, it is uncertain whether knowledge of TVUÃƒÂ¢Ã¢â€šÂ¬Ã‚Âmeasured cervical length compared to no knowledge reduces PTB at less than 34 weeks (risk ratio (RR) 0.62, 95% confidence intervals (CI) 0.30 to 1.25; 1 study, 125 participants) because the quality of the evidence is very low. The results were also inconclusive for preterm birth at 36, 32, or 30 weeks; gestational age at birth, and other maternal and perinatal outcomes. Four trials examined knowledge of TVUÃƒÂ¢Ã¢â€šÂ¬Ã‚Âmeasured cervical length of singletons with symptoms of PTL versus no knowledge. We are uncertain of the effects because of inconclusive results and very lowÃƒÂ¢Ã¢â€šÂ¬Ã‚Âquality evidence for: preterm births at less than 37 weeks (average RR 0.59, 95% CI 0.26 to 1.32; 2 studies, 242 participants; IÃƒâ€šÃ‚Â² = 66%; TauÃƒâ€šÃ‚Â² = 0.23). Birth occurred about four days later in the knowledge groups (mean difference (MD) 0.64 weeks, 95% CI 0.03 to 1.25; 3 trials, 290 women). The results were inconclusive for the other outcomes for which there were available data: PTB at less than 34 or 28 weeks; birthweight less than 2500 g; perinatal death; maternal hospitalisation; tocolysis; and steroids for fetal lung maturity. The trial of singletons with PPROM (N = 92) evaluated safety of using TVU to measure cervical length in this population as its primary outcome, not its effect on management. The results were inconclusive for incidence of maternal and neonatal infections between the TVU and no ultrasound groups. In the trial of asymptomatic singletons (N = 296), in which women either received TVU or not, the results were inconclusive for preterm birth at less than 37 weeks (RR 1.27, 95% CI 0.61 to 2.61; IÃƒâ€šÃ‚Â² = 0%), gestational age at birth, and other perinatal and maternal outcomes. We downgraded evidence for limitations in study design, inconsistency between the trials, and imprecision, due to small sample si e and wide confidence intervals crossing the line of no effect. No trial compared the effect of knowledge of the CL with no knowledge of CL in other populations, such as asymptomatic women with singleton pregnancies, or symptomatic women with twin pregnancies. Authors' conclusions There are limited data on the effects of knowing the cervical length, measured by ultrasound, for preventing preterm births, which preclude us from drawing any conclusions for women with asymptomatic twin or singleton pregnancies, singleton pregnancies with PPROM, or other populations and clinical scenarios. Limited evidence suggests that knowledge of transvaginal ultrasoundÃƒÂ¢Ã¢â€šÂ¬Ã‚Âmeasured cervical length, used to inform the management of women with singleton pregnancies and symptoms of preterm labour, appears to prolong pregnancy by about four days over women in the no knowledge groups. Future studies could look at specific populations separately (e.g. singleton versus twins; symptoms versus no symptoms of PTL), report on all pertinent maternal and perinatal outcomes, and include costÃƒÂ¢Ã¢â€šÂ¬Ã‚Âeffectiveness analyses. Most importantly, future studies should include a clear protocol for management of women based on TVUÃƒÂ¢Ã¢â€šÂ¬Ã‚Âmeasured cervical length. Plain language summary Cervical assessment by ultrasound for preventing preterm delivery We set out to assess the effectiveness of knowing the cervical length, measured with ultrasound, for preventing preterm birth compared with not knowing the cervical length. What is the issue? The cervix is the lower part of the uterus that connects to the vagina. When women are not pregnant, it is normally at least 3 cm long. During pregnancy, a short cervical length is associated with a risk of spontaneous preterm birth. The shorter the cervical length, the greater the risk. Therefore, measuring cervical length by ultrasound can help predict spontaneous preterm birth. The cervical length is measured by an ultrasound scan through the vagina (transvaginal or TVU), abdomen (transabdominal), or the perineum (transperineal). The most common causes of spontaneous preterm birth are preterm labour or preterm premature rupture of the membranes. Many of the interventions used to prevent preterm birth are used once symptoms develop. Why is this important? Preterm birth before 37 weeks is the main cause of a newborn baby being sick and disabled, or dying. The cervix is the opening or passage through which the baby must pass before being born vaginally. Ultrasound can detect early changes of the cervix, such as shortening of the cervical length, to predict preterm birth. On identifying a short cervical length, interventions can be applied to prevent preterm birth. These interventions include giving the expectant mother progesterone to relax the uterus, or applying a stitch, known as a cerclage, to tighten the opening of the cervix. What evidence did we find? This review assessed if knowing the cervical length can prevent preterm birth. We included seven randomised controlled studies, which involved 923 pregnant women at 14 to 32 weeks' gestation. One study included expectant mothers with twins, without any symptoms of preterm birth or labour, and looked at the number of babies born prematurely before 36 weeks. Four studies included expectant mothers of single babies with threatened preterm labour, and one study involving women with premature rupture of the membranes looked at the safety of transvaginal ultrasound. One trial included expectant mothers with singleton pregnancies who did not have any symptoms of preterm birth or labour to look at the efficacy of transvaginal ultrasound cervical length screening. All studies used transvaginal ultrasound to assess cervical length. For women with twin pregnancies and not showing symptoms of preterm birth, we are unclear of the impact of knowing the cervical length on whether babies are born before 34 weeks' gestation, or their gestational age at birth (1 study, 125 women), because we assessed the quality of the evidence to be very low. For women with a single baby and threatened preterm labour, knowledge of their cervical length may have led to a longer pregnancy by about four days (4 studies, 410 women), but the evidence on the number of babies born before 37 weeks was unclear (2 studies, 242 women). For women whose waters had broken, it is unclear whether healthcare provider knowledge makes any difference to whether the women gave birth preterm, or on the number of infections, again because we judged the quality of evidence as very low. For women with singleton pregnancies not showing symptoms of preterm birth, it is unclear whether an ultrasound to measure cervical length made any difference to whether their babies were born before 37 weeks' gestation (1 study, 296 women; very lowÃƒÂ¢Ã¢â€šÂ¬Ã‚Âquality evidence). What does this mean? We found a limited number of studies including small numbers of women. The studies varied in their design and had a broad spread of results. Women were not blinded to whether they had an ultrasound or not. Currently, there is not enough high quality research to show if knowledge of cervical length in women with twin or singleton pregnancies has any effect. Future studies could include ways of managing women as a result of the cervical length results, and it would be useful to look at specific populations separately, such as single babies versus twins and women with and without symptoms of preterm labour. They could also report on all important maternal and perinatal outcomes, and include costÃƒÂ¢Ã¢â€šÂ¬Ã‚Âeffectiveness analyses. | E6: TRUE | F6: Focus on ultrasound for early detection of preterm birth. | G6: Prevention | H6: Prevention | I6: 0.9
A7: J508 | B7: 2019 | C7: Adalimumab for non-infectious uveitis: Is it cost-effective? | D7: Background/Aims: Uveitis is inflammation inside the eye. Our objective was to assess the cost-effectiveness of adalimumab compared with current practice (immunosuppressants and systemic corticosteroids) in patients with non-infectious intermediate, posterior or panuveitis and to identify areas for future research. Method(s): A Markov model was built to estimate costs and benefits of the interventions. Systematic reviews were performed to identify the available relevant clinical and cost-effectiveness evidence. Data collected in two key randomised controlled trials (VISUAL I and VISUAL II) were used to estimate the interventions' effectiveness compared with the trials' comparator arms (placebo plus limited current practice (LCP)). The analysis was performed from the National Health Service and Personal Social Services perspective. Costs were calculated based on standard UK sources. Result(s): The estimated incremental cost-effectiveness ratios (ICERs) of adalimumab versus LCP for the base case are 92 600 and 318 075 per quality-adjusted life year (QALY) gained for active and inactive uveitis, respectively. In sensitivity analyses, the ICER varied from 15 579 to 120 653 and 35 642 to 800 775 per QALY for active and inactive uveitis. Conclusion(s): The estimated ICERs of adalimumab versus LCP are above generally accepted thresholds for cost-effectiveness in the UK. Adalimumab may be more cost-effective in patients with active uveitis at greater risk of blindness. However, there is an unmet need for additional primary data to provide more reliable estimates in several important areas, including effectiveness of adalimumab versus current practice (instead of LCP), incidence of long-term blindness, adalimumab effectiveness in avoiding blindness, and rates and time to remission while on adalimumab. Copyright Ãƒâ€šÃ‚Â© 2019 Author(s). | E7: FALSE | F7: Focuses on cost-effectiveness of a drug, not NHS shifts. | G7: None | I7: 1
A8: J509 | B8: 2019 | C8: Burden of varicella complications in secondary care, England, 2004 to 2017 | D8: Background: Strategies to control varicella vary across Europe. Evidence from established programmes has prompted the United Kingdom to re-evaluate the need for universal vaccination. The burden of complicated varicella is a key parameter in the cost-effectiveness analysis. Aim(s): Our objective was to estimate the burden of complicated varicella in England. Method(s): This electronic health record surveillance study used data from all NHS hospitals in England to identify varicella admissions between 2004 and 2017. The incidence of pre-defined complications of varicella was estimated using ICD-10 codes. Inpatient costs were calculated based on the payment rules for providers of NHS services. Result(s): There were 61,024 admissions with varicella between 2004 and 2017 and 38.1% had a recognised varicella complication. Incidence of hospitalisation increased by 25% and the proportion with complicated varicella by 24% from 2004/05 to 2016/17. The most common complications were bacterial skin infections (11.25%), pneumonia (4.82%), febrile convulsions (3.39%) and encephalitis (2.44%). Complication rates were higher in older age groups and the type of complications more severe. Length of stay for complicated varicella was 3.1 times longer than for uncomplicated varicella and inpatient costs were 72% greater. Conclusion(s): Complicated varicella has a substantial health and economic burden. These data together with data on impact on quality of life are important in informing the cost-effectiveness analysis of universal varicella vaccination. Copyright Ãƒâ€šÃ‚Â© 2019 European Centre for Disease Prevention and Control (ECDC). All rights reserved. | E8: FALSE | F8: Focuses on varicella complications, not aligned with NHS shifts. | G8: None | I8: 0.9
A9: J510 | B9: 2019 | C9: Treatment for hepatorenal syndrome in people with decompensated liver cirrhosis: a network metaÃƒÂ¢Ã¢â€šÂ¬Ã‚Âanalysis | D9: - Background Hepatorenal syndrome is defined as renal failure in people with cirrhosis in the absence of other causes. In addition to supportive treatment such as albumin to restore fluid balance, the other potential treatments include systemic vasoconstrictor drugs (such as vasopressin analogues or noradrenaline), renal vasodilator drugs (such as dopamine), transjugular intrahepatic portosystemic shunt (TIPS), and liver support with molecular adsorbent recirculating system (MARS). There is uncertainty over the best treatment regimen for hepatorenal syndrome. Objectives To compare the benefits and harms of different treatments for hepatorenal syndrome in people with decompensated liver cirrhosis. Search methods We searched CENTRAL, MEDLINE, Embase, Science Citation Index Expanded, World Health Organization International Clinical Trials Registry Platform, and trial registers until December 2018 to identify randomised clinical trials on hepatorenal syndrome in people with cirrhosis. Selection criteria We included only randomised clinical trials (irrespective of language, blinding, or publication status) in adults with cirrhosis and hepatorenal syndrome. We excluded randomised clinical trials in which participants had previously undergone liver transplantation. Data collection and analysis Two authors independently identified eligible trials and collected data. The outcomes for this review included mortality, serious adverse events, any adverse events, resolution of hepatorenal syndrome, liver transplantation, and other decompensation events. We performed a network metaÃƒÂ¢Ã¢â€šÂ¬Ã‚Âanalysis with OpenBUGS using Bayesian methods and calculated the odds ratio (OR), rate ratio, hazard ratio (HR), and mean difference (MD) with 95% credible intervals (CrI) based on an availableÃƒÂ¢Ã¢â€šÂ¬Ã‚Âcase analysis, according to National Institute of Health and Care Excellence Decision Support Unit guidance. Main results We included a total of 25 trials (1263 participants; 12 interventions) in the review. TwentyÃƒÂ¢Ã¢â€šÂ¬Ã‚Âthree trials (1185 participants) were included in one or more outcomes. All the trials but two were at high risk of bias, and all the evidence was of low or very low certainty. The trials included participants with liver cirrhosis of varied aetiologies as well as a mixture of type I hepatorenal syndrome only, type II hepatorenal syndrome only, or people with both type I and type II hepatorenal syndrome. Participant age ranged from 42 to 60 years, and the proportion of females ranged from 5.8% to 61.5% in the trials that reported this information. The followÃƒÂ¢Ã¢â€šÂ¬Ã‚Âup in the trials ranged from one week to six months. Overall, 59% of participants died during this period and about 35% of participants recovered from hepatorenal syndrome. The most common interventions compared were albumin plus terlipressin, albumin plus noradrenaline, and albumin alone. There was no evidence of a difference in mortality (22 trials; 1153 participants) at maximal followÃƒÂ¢Ã¢â€šÂ¬Ã‚Âup between the different interventions. None of the trials reported healthÃƒÂ¢Ã¢â€šÂ¬Ã‚Ârelated quality of life. There was no evidence of differences in the proportion of people with serious adverse events (three trials; 428 participants), number of participants with serious adverse events per participant (two trials; 166 participants), proportion of participants with any adverse events (four trials; 402 participants), the proportion of people who underwent liver transplantation at maximal followÃƒÂ¢Ã¢â€šÂ¬Ã‚Âup (four trials; 342 participants), or other features of decompensation at maximal followÃƒÂ¢Ã¢â€šÂ¬Ã‚Âup (one trial; 466 participants). Five trials (293 participants) reported number of any adverse events, and five trials (219 participants) reported treatment costs. Albumin plus noradrenaline had fewer numbers of adverse events per participant (rate ratio 0.51, 95% CrI 0.28 to 0.87). Eighteen trials (1047 participants) reported recovery from hepatorenal syndrome (as per definition of hepatorenal syndrome). In terms of recovery from hepatorenal syndrome, in the direct comparisons, albumin plus midodrine plus octreotide and albumin plus octreotide had lower recovery from hepatorenal syndrome than albumin plus terlipressin (HR 0.04; 95% CrI 0.00 to 0.25 and HR 0.26, 95% CrI 0.07 to 0.80 respectively). There was no evidence of differences between the groups in any of the other direct comparisons. In the network metaÃƒÂ¢Ã¢â€šÂ¬Ã‚Âanalysis, albumin and albumin plus midodrine plus octreotide had lower recovery from hepatorenal syndrome compared with albumin plus terlipressin. Funding: two trials were funded by pharmaceutical companies; five trials were funded by parties who had no vested interest in the results of the trial; and 18 trials did not report the source of funding. Authors' conclusions Based on very lowÃƒÂ¢Ã¢â€šÂ¬Ã‚Âcertainty evidence, there is no evidence of benefit or harm of any of the interventions for hepatorenal syndrome with regards to the following outcomes: allÃƒÂ¢Ã¢â€šÂ¬Ã‚Âcause mortality, serious adverse events (proportion), number of serious adverse events per participant, any adverse events (proportion), liver transplantation, or other decompensation events. LowÃƒÂ¢Ã¢â€šÂ¬Ã‚Âcertainty evidence suggests that albumin plus noradrenaline had fewer 'any adverse events per participant' than albumin plus terlipressin. LowÃƒÂ¢Ã¢â€šÂ¬Ã‚Â or very lowÃƒÂ¢Ã¢â€šÂ¬Ã‚Âcertainty evidence also found that albumin plus midodrine plus octreotide and albumin alone had lower recovery from hepatorenal syndrome compared with albumin plus terlipressin. Future randomised clinical trials should be adequately powered; employ blinding, avoid postÃƒÂ¢Ã¢â€šÂ¬Ã‚Ârandomisation dropouts or planned crossÃƒÂ¢Ã¢â€šÂ¬Ã‚Âovers (or perform an intentionÃƒÂ¢Ã¢â€šÂ¬Ã‚ÂtoÃƒÂ¢Ã¢â€šÂ¬Ã‚Âtreat analysis); and report clinically important outcomes such as mortality, healthÃƒÂ¢Ã¢â€šÂ¬Ã‚Ârelated quality of life, adverse events, and recovery from hepatorenal syndrome. Albumin plus noradrenaline and albumin plus terlipressin appear to be the interventions that should be compared in future trials. Plain language summary Treatment of hepatorenal syndrome What is the aim of this Cochrane review? To find out the best treatment for decreased kidney function (hepatorenal syndrome) in people with liver cirrhosis (a form of advanced liver disease with scarring of the liver) with complications. The authors collected and analysed all relevant studies to answer this question and found 25 randomised controlled trials (participants receive the treatment based on method similar to coin toss or lottery; this is to ensure that the people who receive the different treatments are similar in all aspects except the treatment, so that any differences in the results between the treatments can be attributed to the treatment rather than differences in the type of people who received the treatment). During analysis of data, authors used standard Cochrane techniques, which allows comparison of two treatments at a time. Authors also used advanced techniques, that allow comparison of many treatments at the same time (usually referred as 'network metaÃƒÂ¢Ã¢â€šÂ¬Ã‚Âanalysis' or 'multiple treatment comparisons'). The aim is to gather reliable evidence on the relative benefits and harms of the different treatments. Date of literature search ÃƒÂ¢Ã¢â€šÂ¬Ã‚Â¨ December 2018 Key messages ÃƒÂ¢Ã¢â€šÂ¬Ã‚Â¨ Only two studies were conducted well. The remaining studies had one or more flaws. Therefore, there is high uncertainty in the results of the analysis. The authors could not recommend one treatment over another on the basis of risk of death, serious complications, percentage of people who developed any complication, percentage of participants who underwent liver transplantation (replacement of a diseased liver with a healthy one), or the number of other liver failure events. HealthÃƒÂ¢Ã¢â€šÂ¬Ã‚Ârelated quality of life was not reported in any of the trials. The number of complications of any severity was lower with albumin plus noradrenaline than albumin plus terlipressin. Recovery from hepatorenal syndrome may be lower with albumin plus midodrine plus octreotide and albumin alone than albumin plus terlipressin and albumin plus noradrenaline. Funding source was unclear in 18 studies. Industrial organisations funded two studies and the remaining five studies did not receive any funding from industrial organisations. What was studied in the review? This review studied people of any sex, age, and origin, having advanced liver disease due to various causes, and who had developed hepatorenal syndrome. People were administered different treatments. The review authors excluded studies with liverÃƒÂ¢Ã¢â€šÂ¬Ã‚Âtransplanted participants. Participants age, when reported, ranged from 42 to 60 years. The number of females ranged from 6 to 62 out of 100 in the studies that reported this information. The main treatments compared were albumin alone, albumin plus terlipressin, and albumin plus noradrenaline. The authors gathered and analysed data on death, quality of life, serious and nonÃƒÂ¢Ã¢â€šÂ¬Ã‚Âserious complications, time to liver transplantation, recovery from hepatorenal syndrome, and disappearance of symptoms. What were the main results of the review? The 25 studies included a small number of participants (1263 participants). Study data were sparse. TwentyÃƒÂ¢Ã¢â€šÂ¬Ã‚Âthree studies with 1185 participants provided data for analyses. The followÃƒÂ¢Ã¢â€šÂ¬Ã‚Âup in the trials ranged from one week to six months. The review shows that: ÃƒÂ¢Ã¢â€šÂ¬Ã‚Â About 60 out of every 100 people died within three months, and 35 out of every 100 people recovered from hepatorenal syndrome. ÃƒÂ¢Ã¢â€šÂ¬Ã‚Â The provided treatment may make no difference to the percentage of people who died or developed serious complications, number of serious complications per person, percentage of people who developed complications of any severity, or the percentage of people undergoing liver transplantation. ÃƒÂ¢Ã¢â€šÂ¬Ã‚Â None of the trials reported healthÃƒÂ¢Ã¢â€šÂ¬Ã‚Ârelated quality of life. ÃƒÂ¢Ã¢â€šÂ¬Ã‚Â The number of complications of any severity was lower with albumin plus noradrenaline than albumin plus terlipressin. ÃƒÂ¢Ã¢â€šÂ¬Ã‚Â Recovery from hepatorenal syndrome may be lower with albumin plus midodrine plus octreotide and albumin alone than albumin plus terlipressin and albumin plus noradrenaline. ÃƒÂ¢Ã¢â€šÂ¬Ã‚Â We have very low confidence in the overall results. ÃƒÂ¢Ã¢â€šÂ¬Ã‚Â Future trials with proper design and quality are needed to clarify the best treatment for people with advanced liver disease having hepatorenal syndrome. | E9: FALSE | F9: Focuses on treatment comparison, not on NHS shifts. | G9: None | I9: 0.9
A10: J511 | B10: 2019 | C10: Switching from originator infliximab to CT-P13: Single-centre experience from the UK | D10: Background: The infliximab biosimilar (CT-P13) received market authorisation for inflammatory bowel disease in late 2016 with the aim of reducing cost and increasing access to therapy. The prospect of 'switching' patients from originator to CT-P13 has concerned clinicians. #8232;We present an experience of 'switching' from originator infliximab (IFX-O) to CT-P13 and present efficacy, safety, and immunogenicity data from our cohort. Method(s): We performed a retrospective review of patients switched from IFX-O to CT-P13. Disease demographics, clinical course and outcomes were analysed from electronic case records at a median of 8 months and at last follow-up at 13 months. Result(s): Ninety-six patients (35 females) were 'switched' from IFX-O to CT-P13. Of these 44 had Ulcerative colitis (UC) and 52 had Crohn's disease (CD) with a mean age at diagnosis of 34.7 years (median = 33, IQR = 24.5). Montreal phenotype for UC was E1 = 1, E2 = 16, E3 = 27 and for CD (L1 = 10, L2 = 12 , L3 = 29, L4 = 1) and (B1 = 27, #8232;B2 = 14 , B3 = 11), 9 patients had perianal disease. Mean duration of IFX-O treatment was 49. 8 months (median = 44, IQR = 52) and on CT-P13 11.5 months (median 13). At switch, 76 patients had a normal CRP (UC = 33, CD = 43), and in 15 patients it was elevated (UC = 10, CD = 5). At 8 months, 80 patients remained in biochemical remission (UC = 35, CD = 45 ) and in 14 patients (UC = 8, CD = 6 ) CRP increased. Seventy-two patients (UC = 34, CD = 38 ) were in clinical remission (pMayo < 2 and HBI < 5). Of 51 patients (UC = 21, CD = 30) undergoing endoscopic assessment, 31 achieved mucosal healing (UC = 13, CD = 18). At 13 months, 69 patients remained on CT-P13. Twenty-seven discontinued the drug due to immunogenicity (n = 10), loss of response (n = 5), surgery (n = 5), remission (n = 5) , side effects (n = 2 ), and 1 patient died of hospital acquired pneumonia. 39 out of 96 patients had therapeutic drug levels checked within 13 months of switch, of whom 27 had sub-therapeutic levels (below 4 mug/ml). Antibodies to Infliximab were seen in 15 of 39 patients (38.5%), of whom 8 were switched to an alternative biologic, 2 had dose escalation (10 mg/kg IFX), 4 patients stopped IFX with no other intervention, and 1 person continued treatment at same dose with low antibody titre of 6. Conclusion(s): Biosimilar IFX (CT-P13) was well tolerated. Clinical efficacy and loss of response rates with CT-P13 appears to be similar to IFX-O. This holds promise for a wider adoption of 'switching' to fulfil the purported aims of wider access to treatment at a lower cost. | E10: FALSE | F10: Focuses on cost and access, not NHS shifts. | G10: None | I10: 0.9
A11: J512 | B11: 2019 | C11: Switching from originator infliximab to CT-P13: A UK single centre experience | D11: Introduction and Aims The infliximab biosimilar (CT-P13) received market authorization for inflammatory bowel disease in late 2016 with the aim of reducing cost and increasing access to therapy. The prospect of 'switching' patients from originator to CT-P13 has concerned clinicians.We present an experience of 'switching' from originator infliximab (IFX-O) to CT-P13 and present efficacy, safety and immunogenicity data from our cohort. Methods We performed a retrospective review of patients switched from IFX-O to CT-P13 at our center. Disease demographics, clinical course and outcomes were analysed from electronic case records at 8 months and at last follow-up at 13 months. Results Ninety-six patients (35 female) were 'switched' from IFX-O to CT-P13. Of these 44 had Ulcerative colitis (UC) and 52 had Crohn's disease (CD) with a mean age at diagnosis of 34.7 years (median= 33, IQR = 24.5). Montreal phenotype for UC was Proctitis( E1) = 1, Left sided(E2) = 16,Pancolitis ( E3) = 27 and for CD (L1 = 10,L2 = 12, L3 = 29, L4 = 1) and ( B1 = 27,B2 = 14, B3 = 11), 9 patients had perianal disease. Mean duration of IFX-O treatment before switching was 49.8 months (median = 44, IQR = 52) and on CT-P13 11.5 months (median 13). At switch, 76 patients had a normal CRP (UC = 33, CD = 43), and in 15 patients it was elevated (UC= 10, CD= 5). At 8 months, 72 patients (UC = 34, CD = 38) were in clinical remission (pMayo < 2 and HBI < 5) and 80 patients remained in biochemical remission (UC= 35,CD= 45). In 14 patients (UC= 8,CD= 6 ) CRP increased. Of 51 patients (UC= 21, CD= 30) undergoing endoscopic assessment, 31 achieved mucosal healing (UC =13, CD= 18). At 13 months 69 patients remained on CT-P13. 28% discontinued the drug due to immunogenicity(n=10), loss of response(n=5), surgery(n=5), remission (n=5), side effects (n=2) and 1 patient died of hospital acquired pneumonia. 39 out of 96 patients had therapeutic drug levels checked within a median of 13 months from switch. 27 had sub-therapeutic levels (below 4ug/ml ),11 of which were switched to another biologic, 5 referred for surgery, 4 had dose escalated to 10 mg/kg, 5 continued CT-P13( 4 with no antibodies seen and 1 with antibodies of 127),one had immunomodulator added and another stopped CT-P13 being in remission. Antibodies to Infliximab were seen in 15 of 39 patients (38.5%), of whom 8 were switched to an alternative biologic, 2 had dose escalation (10 mg/kg IFX),4 patients stopped IFX with no other intervention and 1 person continued treatment with low antibody titre of 6. Discussion Biosimilar IFX (CT-P13) was well tolerated. Clinical efficacy and loss of response rates with CT-P13 appears to be similar to IFX-O. This holds promise for a wider adoption of 'switching' to fulfil the purported aims of wider access to treatment at a lower cost. | E11: FALSE | F11: Focuses on cost reduction and access, not NHS shifts. | G11: None | I11: 0.9
A12: J513 | B12: 2019 | C12: OnceÃƒÂ¢Ã¢â€šÂ¬Ã‚Âdaily versus multipleÃƒÂ¢Ã¢â€šÂ¬Ã‚Âdaily dosing with intravenous aminoglycosides for cystic fibrosis | D12: - Background People with cystic fibrosis, who are chronically colonised with the organism Pseudomonas aeruginosa , often require multiple courses of intravenous aminoglycoside antibiotics for the management of pulmonary exacerbations. The properties of aminoglycosides suggest that they could be given in higher doses less often. This is an update of a previously published review. Objectives To assess the effectiveness and safety of onceÃƒÂ¢Ã¢â€šÂ¬Ã‚Âdaily versus multipleÃƒÂ¢Ã¢â€šÂ¬Ã‚Âdaily dosing of intravenous aminoglycoside antibiotics for the management of pulmonary exacerbations in cystic fibrosis. Search methods We searched the Cystic Fibrosis Specialist Register held at the Cochrane Cystic Fibrosis and Genetic Disorders Group's editorial base, comprising references identified from comprehensive electronic database searches, handsearching relevant journals and handsearching abstract books of conference proceedings. Date of the most recent search: 31 January 2019. We also searched online trial registries. Date of latest search: 25 February 2019. Selection criteria All randomised controlled trials, whether published or unpublished, in which onceÃƒÂ¢Ã¢â€šÂ¬Ã‚Âdaily dosing of aminoglycosides has been compared with multipleÃƒÂ¢Ã¢â€šÂ¬Ã‚Âdaily dosing in terms of efficacy or toxicity or both, in people with cystic fibrosis. Data collection and analysis The two authors independently selected the studies to be included in the review and assessed the risk of bias of each study; authors also assessed the quality of the evidence using the GRADE criteria. Data were independently extracted by each author. Authors of the included studies were contacted for further information. As yet unpublished data were obtained for one of the included studies. Main results We identified 15 studies for possible inclusion in the review. Five studies reporting results from a total of 354 participants (aged 5 to 50 years) were included in this review. All studies compared onceÃƒÂ¢Ã¢â€šÂ¬Ã‚Âdaily dosing with thriceÃƒÂ¢Ã¢â€šÂ¬Ã‚Âdaily dosing. One crossÃƒÂ¢Ã¢â€šÂ¬Ã‚Âover trial had 26 participants who received the firstÃƒÂ¢Ã¢â€šÂ¬Ã‚Âarm treatment but only 15 received the second arm. One study had a low risk of bias for all criteria assessed; the remaining included studies had a high risk of bias from blinding, but for other criteria were judged to have either an unclear or a low risk of bias. There was little or no difference between treatment groups in: forced expiratory volume in one second, mean difference (MD) 0.33 (95% confidence interval (CI) ÃƒÂ¢Ã¢â€šÂ¬Ã‚Â2.81 to 3.48, moderateÃƒÂ¢Ã¢â€šÂ¬Ã‚Âquality evidence); forced vital capacity, MD 0.29 (95% CI ÃƒÂ¢Ã¢â€šÂ¬Ã‚Â6.58 to 7.16, lowÃƒÂ¢Ã¢â€šÂ¬Ã‚Âquality evidence); % weight for height, MD ÃƒÂ¢Ã¢â€šÂ¬Ã‚Â0.82 (95% CI ÃƒÂ¢Ã¢â€šÂ¬Ã‚Â3.77 to 2.13, lowÃƒÂ¢Ã¢â€šÂ¬Ã‚Âquality evidence); body mass index, MD 0.00 (95% CI ÃƒÂ¢Ã¢â€šÂ¬Ã‚Â0.42 to 0.42, lowÃƒÂ¢Ã¢â€šÂ¬Ã‚Âquality evidence); or in the incidence of ototoxicity, relative risk 0.56 (95% CI 0.04 to 7.96, moderateÃƒÂ¢Ã¢â€šÂ¬Ã‚Âquality evidence). OnceÃƒÂ¢Ã¢â€šÂ¬Ã‚Âdaily treatment in children probably improved the percentage change in creatinine, MD ÃƒÂ¢Ã¢â€šÂ¬Ã‚Â8.20 (95% CI ÃƒÂ¢Ã¢â€šÂ¬Ã‚Â15.32 to ÃƒÂ¢Ã¢â€šÂ¬Ã‚Â1.08, moderateÃƒÂ¢Ã¢â€šÂ¬Ã‚Âquality evidence), but showed no difference in adults, MD 3.25 (95% CI ÃƒÂ¢Ã¢â€šÂ¬Ã‚Â1.82 to 8.33, moderateÃƒÂ¢Ã¢â€šÂ¬Ã‚Âquality evidence). The included trials did not report antibiotic resistance patterns or quality of life. Authors' conclusions OnceÃƒÂ¢Ã¢â€šÂ¬Ã‚Â and threeÃƒÂ¢Ã¢â€šÂ¬Ã‚Âtimes daily aminoglycoside antibiotics appear to be equally effective in the treatment of pulmonary exacerbations of cystic fibrosis. There is evidence of less nephrotoxicity in children. Plain language summary Giving aminoglycoside antibiotics intravenously once daily compared to giving them several times per day in people with cystic fibrosis Review question We looked for evidence to show the differences between giving intravenous antibiotics once daily compared to giving them several times a day when treating flare ups of disease (pulmonary exacerbations) in people with cystic fibrosis. This is an update of an earlier review. Background Most people with cystic fibrosis develop persistent lung infections and they may receive frequent courses of intravenous antibiotics to treat pulmonary exacerbations. Giving the a tibiotics just once per day rather than several doses per day reduces the cost of treatment and the time involved. Search date The evidence is current to 31 January 2019. Study characteristics This review includes five studies with a total of 354 children and adults. All the trials compared onceÃƒÂ¢Ã¢â€šÂ¬Ã‚ÂaÃƒÂ¢Ã¢â€šÂ¬Ã‚Âday dosing with three timesÃƒÂ¢Ã¢â€šÂ¬Ã‚ÂaÃƒÂ¢Ã¢â€šÂ¬Ã‚Âday dosing. Key results The review found that when treating people with cystic fibrosis for pulmonary exacerbations, giving the antibiotics once per day was just as good at as giving them more frequently in terms of lung function and body mass index. The review also found that giving the antibiotics once per day appeared to be less toxic to the kidneys in children. There were no differences between the different treatment schedules for other outcomes that the studies measured. While onceÃƒÂ¢Ã¢â€šÂ¬Ã‚Âdaily treatment can be just as effective and more convenient than threeÃƒÂ¢Ã¢â€šÂ¬Ã‚Âtimes daily treatment, we recommend further studies to look at the longÃƒÂ¢Ã¢â€šÂ¬Ã‚Âterm safety of this treatment schedule. Quality of the evidence We judged that just one of the five studies carried a low risk that any design factors might affect the outcome results. In the remaining four studies, we thought that the fact that it was obvious whether the antibiotics were given once or three times a day could affect some outcome measures (e.g. lung function). Other risk factors were unclear or at low risk of bias. We assessed the evidence for lung function, body mass index and the evidence for side effects (e.g. toxicity) to be moderate to low quality. | E12: FALSE | F12: Focuses on dosing regimens, not NHS Three Shifts. | G12: None | I12: 0.95
A13: J514 | B13: 2019 | C13: ÃƒÂ¢Ã¢â€šÂ¬Ã¢â‚¬Â¹Primary closure versus delayed or no closure for traumatic wounds due to mammalian bite | D13: - Background Mammalian bites are a common presentation in emergency and primary healthcare facilities across the world. The World Health Organization recommends postponing the suturing of a bite wound but this has not been evaluated through a systematic review. Objectives To assess the effects of primary closure compared with delayed closure or no closure for mammalian bite wounds. Search methods In July 2019 we searched the Cochrane Wounds Specialised Register; the Cochrane Central Register of Controlled Trials (CENTRAL); Ovid MEDLINE (including InÃƒÂ¢Ã¢â€šÂ¬Ã‚ÂProcess & Other NonÃƒÂ¢Ã¢â€šÂ¬Ã‚ÂIndexed Citations); Ovid Embase and EBSCO CINAHL Plus. We also searched clinical trials registries for ongoing and unpublished studies, and scanned reference lists of relevant included studies as well as reviews, metaÃƒÂ¢Ã¢â€šÂ¬Ã‚Âanalyses and health technology reports to identify additional studies. There were no restrictions with respect to language, date of publication or study setting. Selection criteria We included randomised controlled trials which compared primary closure with delayed or no closure for traumatic wounds due to mammalian bite. Data collection and analysis Two review authors independently screened titles, abstracts and fullÃƒÂ¢Ã¢â€šÂ¬Ã‚Âtext publications, applied the inclusion criteria, and extracted data. We pooled data using a randomÃƒÂ¢Ã¢â€šÂ¬Ã‚Âeffects model, as appropriate. We used the Cochrane 'Risk of bias' tool and assessed the certainty of the evidence using the GRADE approach. Main results We found three trials (878 participants) that compared primary closure with no closure for dog bites and one trial (120 participants) that compared primary closure with delayed closure. No other mammalian bite studies were identified. The trials were from the UK (one trial), Greece (one trial) and China (two trials). Overall, participants from both sexes and all age groups were represented. We are uncertain whether primary closure improves the proportion of wounds which are infectionÃƒÂ¢Ã¢â€šÂ¬Ã‚Âfree compared with no closure, as the certainty of evidence for this outcome was judged to be very low (risk ratio (RR) 1.01, 95% confidence interval (CI) 0.97 to 1.05; 2 studies, 782 participants; I 2 = 0%). We downgraded the evidence by one level for high risk of bias and two levels for imprecision. There is no clinically important difference in cosmesis (acceptable physical/cosmetic appearance) of dog bite wounds when primary closure is compared with no closure (mean difference (MD) ÃƒÂ¢Ã¢â€šÂ¬Ã‚Â1.31, 95% CI ÃƒÂ¢Ã¢â€šÂ¬Ã‚Â2.03 to ÃƒÂ¢Ã¢â€šÂ¬Ã‚Â0.59; 1 study, 182 participants). The certainty of evidence for this outcome was judged to be moderate (we downgraded our assessment by one level for imprecision). We are uncertain whether primary closure improves the proportion of dog bite wounds that are infectionÃƒÂ¢Ã¢â€šÂ¬Ã‚Âfree compared with delayed closure, as the evidence for this outcome was judged to be very low (RR 0.98, 95% CI 0.90 to 1.07; 1 study, 120 participants; I 2 = 0%). We downgraded the evidence by one level for high risk of bias and two levels for imprecision. None of the four trials reported any adverse outcomes such as death or rabies but they were, in any case, unlikely to have been large enough to have satisfactory power to provide precise estimates for these. Important outcomes like time to complete wound healing, proportion of wounds healed, and length of hospital stay were not evaluated. Authors' conclusions All the studies we identified concerned dog bites. There is no highÃƒÂ¢Ã¢â€šÂ¬Ã‚Âcertainty evidence to support or refute existing recommendations concerning primary closure for dog bites. The potential benefits and harms of primary closure compared with delayed or no closure for mammalian bites remain uncertain and more robust trials are needed. Plain language summary Primary closure (immediate stitches) versus delayed closure (delayed stitches) or no closure (no stitches) for traumatic wounds due to mammalian bite What is the aim of this review? The aim of this review was to find out whether animal bite wounds heal better when they are closed with stitches straight away (primary closure), or if th wounds are left open to heal for a short time before closure (delayed closure) or not stitched at all (no closure). We wanted to find out which wounds healed fastest, and if the method of closure affected the likelihood of wound infection, the appearance of the scar, the length of time patients were in hospital, and more serious side effects such as death. To answer this question, we collected and analysed all relevant studies (randomised controlled trials). Randomised controlled trials are medical studies where people are chosen at random to receive different treatments. This type of trial provides the most reliable health evidence. We found four relevant studies. Key messages All the studies we found concerned dog bites. In terms of wound infection, we cannot be certain whether it is better to close dog bite wounds straight away, or wait a while before stitching, or leave them with no stitches. There was little difference in the appearance of the bite scar. Most of the evidence we found was of low certainty due to the size of the studies and the methods used. What was studied in the review? Mammalian bite wounds from animals such as dogs, cats and monkeys are a common problem throughout the world. In developed countries, many bite wounds are caused by domestic pets. In lowerÃƒÂ¢Ã¢â€šÂ¬Ã‚Âincome countries bites can also be caused by wild animals. Dogs are generally responsible for the majority of bites. Bite wounds are at high risk of infection as microbes are transmitted into the wound from the animal's mouth. In lowerÃƒÂ¢Ã¢â€šÂ¬Ã‚Âincome countries these wound infections can lead to serious complications and in some cases death. The first priorities when treating an animal bite are to stop the flow of blood from the wound, provide pain relief, and prevent infection. This can include appropriate vaccination against tetanus and rabies. It is often recommended that bite wounds are not stitched straight away if infection is suspected, as closing an infected wound could delay healing and be potentially fatal. What are the main results of the review? In July 2019 we searched for randomised controlled trials comparing primary closure versus delayed or no closure for mammalian bite wounds. We found four relevant studies on dog bites. They were carried out in the UK, Greece and China. No other mammalian bite studies were identified. Three of the studies we included compared primary closure with sutures (immediate stitches) with no closure for dog bite wounds. One study compared primary closure with delayed closure for dog bites. The people in the studies were followed, where stated, from 14 days to three months. Overall, participants from both sexes and all age groups were represented. We are uncertain whether primary closure of dog bite wounds increases the proportion of wounds which are infectionÃƒÂ¢Ã¢â€šÂ¬Ã‚Âfree compared with no closure (very lowÃƒÂ¢Ã¢â€šÂ¬Ã‚Âcertainty evidence from two studies including a total of 782 people) and compared with delayed closure (very lowÃƒÂ¢Ã¢â€šÂ¬Ã‚Âcertainty evidence from one study with a total of 120 people). There is little difference in the appearance of dog bite wounds when primary closure is compared with no closure (moderateÃƒÂ¢Ã¢â€šÂ¬Ã‚Âcertainty evidence from one study with a total of 182 participants). None of the included studies reported proportion of wounds healed, the time to complete wound healing, length of hospital stay or adverse events. The number of people in the included studies was small, and the people who assessed the outcomes were aware of which treatment had been given. Both of these are reasons why the results are uncertain. How up to date is this review? We searched for studies that had been published up to July 2019. | E13: FALSE | F13: Focuses on wound closure methods, not NHS shifts. | G13: None | I13: 1
A14: J515 | B14: 2019 | C14: What evidence is available to support the development of a regional specialist neurorehabilitation outreach service | D14: Background The WHO recognises several specialist rehabilitation provision models; in-patient, outpatient and outreach. Intensive early neurorehabilitation is required after severe Acquired Brain Injury (ABI), usually necessitating in-patient care. In the UK, children receiving specialist neurorehabilitation often remain in-patients for long periods because of the lack of appropriate out-of-hospital provision. Aims To explore feasibility and funding implications of developing a regional specialist neurorehabilitation outreach service to facilitate earlier discharge. Methods Analysis of data on children receiving in-patient neurorehabilitation at a paediatric Regional Neuroscience Centre (RNSC), 2014-2018. Information concerning therapy provision was obtained from Trust Clinical Information System Suite (CISS). Patient dependency and rehabilitation complexity was assessed by Rehabilitation Complexity Scale-Extended (RCS-E), scored by multi-disciplinary team (MDT) at weekly meetings over 15 months. For modelling purposes, a specialist neurorehabilitation outreach tariff equating to 50% in-patient tariff was assumed. Data analysis was undertaken by linear programming model (XpressIveÃƒâ€šÃ‚Â©) and Discrete-Even Simulation (Simul8 Ãƒâ€šÃ‚Â©).Various eligibility criteria for outreach provision were modelled: 1) needing >=1 therapies<3 times/week; 2) Total RCS-E score <9,<11 or<13; 3) Therapy Dependency (TD) +Therapy Intensity (TI) components of RCS-E <5. Results 156 children received neurorehabilitation as in-patients over 4 years. Mean age=7.34 years (range 0.1-17). 66 (55%) were male, 53 (45%) female. 84% had ABI, others acquired spinal injury, acute polyneuropathy or somatisation disorders. 52% lived >40 miles from RNSC, 47%>60 min' drive away. 49% were inpatients 1-28 days; 34%, 29-84 days; 18, 85-168 days; 6,>168 days. Patients showed significant functional improvements between admission to neurorehabilitation and discharge (p<0.001). Modelling suggests 14 outreach centres, including RNSC, would be required to permit 78% patients to access specialist neurorehabilitation <30 mins drive from home; 10 centres would permit 92% to access neurorehabilitation <45 min' drive away; 8 centres would permit 96% to access neurorehabilitation <60 min' drive away. Calculations assuming outreach tariff=50% in-patient tariff, and various RCS data models, suggest annual cost savings ranging from 53,424-166,950; calculations based on CISS data, suggest average savings of 1 05 596 per year (range 98,500-113,526). Conclusion Modelling supports the feasibility and affordability of specialist neurorehabilitation outreach provision, although efficacy remains uncertain. | E14: TRUE | F14: Proposes moving neurorehabilitation from hospital to community outreach services. | G14: Community | H14: Community | I14: 0.9
A15: J520 | B15: 2019 | C15: The budget impact of early dose optimisation with golimumab in ulcerative colitis in the UK | D15: Background: The PURSUIT study found that ulcerative colitis patients who were non-responders (based on full Mayo score) to subcutaneous golimumab treatment at Week 6 may benefit from receiving a dose of 100 mg golimumab from Week 6 onwards, with 28% of non-responders at Week 6 becoming responders by Week 14. The aim of this study was to assess the budget implications of optimising a patient's dose at Week 6 compared with other first-line therapies as per current clinical practice Methods: A decision tree model was designed to follow a patient's response to first-line treatment and to track a patient's progression through subsequent line of therapy. The budget impact model only considered drug costs from the perspective of the UK NHS. In total three lines of therapy were covered by the decision tree over a 1 year time horizon. Patients could have first-line treatment with one of the three treatment strategies; golimumab (current treatment practice), golimumab (dose optimisation based on the PURSUIT trial) and adalimumab. Within each of the comparator treatments dose escalation was considered, based on the median time to escalation and proportion of patients receiving dose escalation. Subsequent therapy for golimumab patients was adalimumab and patients who received adalimumab as a first-line therapy received golimumab as a second-line therapy. Response rates, time to loss of response and treatment costs were taken from published data sources. The cost of golimumab was equal between 50 mg pack and 100 mg pack. The model used assumption for second-line response rates; this has been tested in sensitivity analysis. Result(s): The use of dose optimisation for golimumab does not increase expenditure of drug costs compared with golimumab (single dose) with a cost saving of 42 per patient per year. When comparing dose optimisation for golimumab to adalimumab, golimumab was cost saving over 1 year of treatment with cost saving of 2138 per patient. The number of patients in a response health state was similar across all three treatments (47.7%, 47.6% and 45% for golimumab (single dose), golimumab (dose optimisation) and adalimumab, respectively. Conclusion(s): The implementation of dose optimisation at Week 6 for golimumab was cost saving compared with golimumab (current treatment practice) or adalimumab. The analysis highlights the need for immediate implementation of the updated GLM label in clinical practice for potentially more cost savings. | E15: FALSE | F15: Focuses on cost optimisation, not NHS Three Shifts. | G15: None | I15: 0.9
A16: J521 | B16: 2019 | C16: Pcv98 Pcsk9 Inhibitors: An Analysis of Current Uptake and Potential Opportunities in England | D16: Objectives: Cardiovascular disease (CVD) affects approximately 6 million people in England and costs the NHS an estimated 7 billion a year. A key risk factor for CVD is hypercholesterolaemia. PCSK9 inhibitors, such as alirocumab and evolocumab, are a treatment option for patients who, despite taking the maximum tolerated dose of statins, still have cholesterol higher than recommended levels. This study compares actual prescription of PCSK9 inhibitors with expected use and considers opportunities for improved access to these drugs. Method(s): An analysis of the initial uptake estimates from the NICE resource impact report for alirocumab and evolocumab and actual daily dose (ADD) prescribing data from the NICE innovation scorecard for the same drugs in 2018. The study included a review of the NICE technology appraisal guidance (TAG) for alirocumab (TA393) and evolocumab (TA394), and publications from 2016-2019 relating to uptake of, and guidance and initiatives associated with, PCSK9 inhibitors in England. Result(s): On publication of the TAG for alirocumab and evolocumab in 2016, NICE estimated that there would be 11,542 people receiving PCSK9 inhibitors by 2018. However, analysis of data from the NICE innovation scorecard for 2018 shows that 755,806 ADDs of alirocumab and evolocumab were actually prescribed. This is equivalent to approximately 2,069 people receiving treatment and indicates that uptake of PCSK9 inhibitors was 82% lower than expected in 2018. Conclusion(s): While there is considerable potential for PCSK9 inhibitors to alleviate some of the burden of CVD, prescription of these drugs is considerably lower than expected. Despite price reduction, the cost of PCSK9 inhibitors may remain the main barrier to access to these drugs. Further barriers could include a lack of clear guidance for clinicians, patient identification and, until recently, limited clinical trial data regarding CVD outcomes. New initiatives, such as the Accelerated Access Collaborative, may ultimately lead to improved access to PCSK9 inhibitors. Copyright Ãƒâ€šÃ‚Â© 2019 | E16: FALSE | F16: Focuses on drug uptake, not NHS Three Shifts. | G16: None | I16: 0.9
A17: J522 | B17: 2019 | C17: Continuous subcutaneous insulin infusion versus multiple daily injection regimens in children and young people at diagnosis of type 1 diabetes: Pragmatic randomised controlled trial and economic evaluation | D17: Objective To compare the efficacy, safety, and cost utility of continuous subcutaneous insulin infusion (CSII) with multiple daily injection (MDI) regimens during the first year following diagnosis of type 1 diabetes in children and young people. Design Pragmatic, multicentre, open label, parallel group, randomised controlled trial and economic evaluation. Setting 15 paediatric National Health Service (NHS) diabetes services in England and Wales. The study opened to recruitment in May 2011 and closed in January 2017. Participants Patients aged between 7 months and 15 years, with a new diagnosis of type 1 diabetes were eligible to participate. Patients who had a sibling with the disease, and those who took drug treatments or had additional diagnoses that could have affected glycaemic control were ineligible. Interventions Participants were randomised, stratified by age and treating centre, to start treatment with CSII or MDI within 14 days of diagnosis. Starting doses of aspart (CSII and MDI) and glargine or detemir (MDI) were calculated according to weight and age, and titrated according to blood glucose measurements and according to local clinical practice. Main outcome measures Primary outcome was glycaemic control (as measured by glycated haemoglobin; HbA1c) at 12 months. Secondary outcomes were percentage of patients in each treatment arm with HbA1c within the national target range, incidence of severe hypoglycaemia and diabetic ketoacidosis, change in height and body mass index (as measured by standard deviation scores), insulin requirements (units/kg/day), partial remission rate (insulin dose adjusted HbA1c <9), paediatric quality of life inventory score, and cost utility based on the incremental cost per quality adjusted life year (QALY) gained from an NHS costing perspective. Results 294 participants were randomised and 293 included in intention to treat analyses (CSI, n=144; MDI, n=149). At 12 months, mean HbA1c was comparable with clinically unimportant differences between CSII and MDI participants (60.9 mmol/mol v 58.5 mmol/mol, mean difference 2.4 mmol/mol (95% confidence interval -0.4 to 5.3), P=0.09). Achievement of HbA1c lower than 58 mmol/mol was low among the two groups (66/143 (46%) CSII participants v 78/142 (55%) MDI participants; relative risk 0.84 (95% confidence interval 0.67 to 1.06)). Incidence of severe hypoglycaemia and diabetic ketoacidosis were low in both groups. Fifty four non-serious and 14 serious adverse events were reported during CSII treatment, and 17 non-serious and eight serious adverse events during MDI treatment. Parents (but not children) reported superior PedsQL scores for those patients treated with CSII compared to those treated with MDI. CSII was more expensive than MDI by 1863 (2179; $2474; 95% confidence interval 1620 to 2137) per patient, with no additional QALY gains (difference -0.006 (95% confidence interval -0.031 to 0.018)). Conclusion During the first year following type 1 diabetes diagnosis, no clinical benefit of CSII over MDI was identified in children and young people in the UK setting, and treatment with either regimen was suboptimal in achieving HbA1c thresholds. CSII was not cost effective. Trial registration Current Controlled Trials ISRCTN29255275; European Clinical Trials Database 2010-023792-25. Copyright Ãƒâ€šÃ‚Â© Published by the BMJ Publishing Group Limited. | E17: FALSE | F17: Focuses on treatment efficacy, not NHS shifts. | G17: None | I17: 0.95
A18: J523 | B18: 2019 | C18: Perioperative betaÃƒÂ¢Ã¢â€šÂ¬Ã‚Âblockers for preventing surgeryÃƒÂ¢Ã¢â€šÂ¬Ã‚Ârelated mortality and morbidity in adults undergoing nonÃƒÂ¢Ã¢â€šÂ¬Ã‚Âcardiac surgery | D18: - Background Randomized controlled trials (RCTs) have yielded conflicting results regarding the ability of betaÃƒÂ¢Ã¢â€šÂ¬Ã‚Âblockers to influence perioperative cardiovascular morbidity and mortality. Thus routine prescription of these drugs in an unselected population remains a controversial issue. A previous version of this review assessing the effectiveness of perioperative betaÃƒÂ¢Ã¢â€šÂ¬Ã‚Âblockers in cardiac and nonÃƒÂ¢Ã¢â€šÂ¬Ã‚Âcardiac surgery was last published in 2018. The previous review has now been split into two reviews according to type of surgery. This is an update, and assesses the evidence in nonÃƒÂ¢Ã¢â€šÂ¬Ã‚Âcardiac surgery only. Objectives To assess the effectiveness of perioperatively administered betaÃƒÂ¢Ã¢â€šÂ¬Ã‚Âblockers for the prevention of surgeryÃƒÂ¢Ã¢â€šÂ¬Ã‚Ârelated mortality and morbidity in adults undergoing nonÃƒÂ¢Ã¢â€šÂ¬Ã‚Âcardiac surgery. Search methods We searched CENTRAL, MEDLINE, Embase, CINAHL, Biosis Previews and Conference Proceedings Citation IndexÃƒÂ¢Ã¢â€šÂ¬Ã‚ÂScience on 28 June 2019. We searched clinical trials registers and grey literature, and conducted backwardÃƒÂ¢Ã¢â€šÂ¬Ã‚Â and forwardÃƒÂ¢Ã¢â€šÂ¬Ã‚Âcitation searching of relevant articles. Selection criteria We included RCTs and quasiÃƒÂ¢Ã¢â€šÂ¬Ã‚Ârandomized studies comparing betaÃƒÂ¢Ã¢â€šÂ¬Ã‚Âblockers with a control (placebo or standard care) administered during the perioperative period to adults undergoing nonÃƒÂ¢Ã¢â€šÂ¬Ã‚Âcardiac surgery. If studies included surgery with different types of anaesthesia, we included them if 70% participants, or at least 100 participants, received general anaesthesia. We excluded studies in which all participants in the standard care control group were given a pharmacological agent that was not given to participants in the intervention group, studies in which all participants in the control group were given a betaÃƒÂ¢Ã¢â€šÂ¬Ã‚Âblocker, and studies in which betaÃƒÂ¢Ã¢â€šÂ¬Ã‚Âblockers were given with an additional agent (e.g. magnesium). We excluded studies that did not measure or report review outcomes. Data collection and analysis Two review authors independently assessed studies for inclusion, extracted data, and assessed risks of bias. We assessed the certainty of evidence with GRADE. Main results We included 83 RCTs with 14,967 participants; we found no quasiÃƒÂ¢Ã¢â€šÂ¬Ã‚Ârandomized studies. All participants were undergoing nonÃƒÂ¢Ã¢â€šÂ¬Ã‚Âcardiac surgery, and types of surgery ranged from low to high risk. Types of betaÃƒÂ¢Ã¢â€šÂ¬Ã‚Âblockers were: propranolol, metoprolol, esmolol, landiolol, nadolol, atenolol, labetalol, oxprenolol, and pindolol. In nine studies, betaÃƒÂ¢Ã¢â€šÂ¬Ã‚Âblockers were titrated according to heart rate or blood pressure. Duration of administration varied between studies, as did the time at which drugs were administered; in most studies, it was intraoperatively, but in 18 studies it was before surgery, in six postoperatively, one multiÃƒÂ¢Ã¢â€šÂ¬Ã‚Âarm study included groups of different timings, and one study did not report timing of drug administration. Overall, we found that more than half of the studies did not sufficiently report methods used for randomization. All studies in which the control was standard care were at high risk of performance bias because of the openÃƒÂ¢Ã¢â€šÂ¬Ã‚Âlabel study design. Only two studies were prospectively registered with clinical trials registers, which limited the assessment of reporting bias. In six studies, participants in the control group were given betaÃƒÂ¢Ã¢â€šÂ¬Ã‚Âblockers as rescue therapy during the study period. The evidence for allÃƒÂ¢Ã¢â€šÂ¬Ã‚Âcause mortality at 30 days was uncertain; based on the risk of death in the control group of 25 per 1000, the effect with betaÃƒÂ¢Ã¢â€šÂ¬Ã‚Âblockers was between two fewer and 13 more per 1000 (risk ratio (RR) 1.17, 95% confidence interval (CI) 0.89 to 1.54; 16 studies, 11,446 participants; lowÃƒÂ¢Ã¢â€šÂ¬Ã‚Âcertainty evidence). BetaÃƒÂ¢Ã¢â€šÂ¬Ã‚Âblockers may reduce the incidence of myocardial infarction by 13 fewer incidences per 1000 (RR 0.72, 95% CI 0.60 to 0.87; 12 studies, 10,520 participants; lowÃƒÂ¢Ã¢â€šÂ¬Ã‚Âcertainty evidence). We found no evidence of a difference in cerebrovascular events (RR 1.65, 95% CI 0.97 to 2.81; 6 studies, 9460 participants; lowÃƒÂ¢Ã¢â€šÂ¬Ã‚Âcertainty evidence), or in ventricular arrhythmias (RR 0.72, 95% CI 0.35 to 1.47; 5 studies, 47 participants; very lowÃƒÂ¢Ã¢â€šÂ¬Ã‚Âcertainty evidence). BetaÃƒÂ¢Ã¢â€šÂ¬Ã‚Âblockers may reduce atrial fibrillation or flutter by 26 fewer incidences per 1000 (RR 0.41, 95% CI 0.21 to 0.79; 9 studies, 9080 participants; lowÃƒÂ¢Ã¢â€šÂ¬Ã‚Âcertainty evidence). However, betaÃƒÂ¢Ã¢â€šÂ¬Ã‚Âblockers may increase bradycardia by 55 more incidences per 1000 (RR 2.49, 95% CI 1.74 to 3.56; 49 studies, 12,239 participants; lowÃƒÂ¢Ã¢â€šÂ¬Ã‚Âcertainty evidence), and hypotension by 44 more per 1000 (RR 1.40, 95% CI 1.29 to 1.51; 49 studies, 12,304 participants; moderateÃƒÂ¢Ã¢â€šÂ¬Ã‚Âcertainty evidence). We downgraded the certainty of the evidence owing to study limitations; some studies had high risks of bias, and the effects were sometimes altered when we excluded studies with a standard care control group (including only placeboÃƒÂ¢Ã¢â€šÂ¬Ã‚Âcontrolled trials showed an increase in early mortality and cerebrovascular events with betaÃƒÂ¢Ã¢â€šÂ¬Ã‚Âblockers). We also downgraded for inconsistency; one large, wellÃƒÂ¢Ã¢â€šÂ¬Ã‚Âconducted, international study found a reduction in myocardial infarction, and an increase in cerebrovascular events and allÃƒÂ¢Ã¢â€šÂ¬Ã‚Âcause mortality, when betaÃƒÂ¢Ã¢â€šÂ¬Ã‚Âblockers were used, but other studies showed no evidence of a difference. We could not explain the reason for the inconsistency in the evidence for ventricular arrhythmias, and we also downgraded this outcome for imprecision because we found few studies with few participants. Authors' conclusions The evidence for early allÃƒÂ¢Ã¢â€šÂ¬Ã‚Âcause mortality with perioperative betaÃƒÂ¢Ã¢â€šÂ¬Ã‚Âblockers was uncertain. We found no evidence of a difference in cerebrovascular events or ventricular arrhythmias, and the certainty of the evidence for these outcomes was low and very low. We found lowÃƒÂ¢Ã¢â€šÂ¬Ã‚Âcertainty evidence that betaÃƒÂ¢Ã¢â€šÂ¬Ã‚Âblockers may reduce atrial fibrillation and myocardial infarctions. However, betaÃƒÂ¢Ã¢â€šÂ¬Ã‚Âblockers may increase bradycardia (lowÃƒÂ¢Ã¢â€šÂ¬Ã‚Âcertainty evidence) and probably increase hypotension (moderateÃƒÂ¢Ã¢â€šÂ¬Ã‚Âcertainty evidence). Further evidence from large placeboÃƒÂ¢Ã¢â€šÂ¬Ã‚Âcontrolled trials is likely to increase the certainty of these findings, and we recommend the assessment of impact on quality of life. We found 18 studies awaiting classification; inclusion of these studies in future updates may also increase the certainty of the evidence. Plain language summary BetaÃƒÂ¢Ã¢â€šÂ¬Ã‚Âblockers to prevent death or serious events after surgery not involving the heart This review assessed evidence from randomized controlled trials (RCTs) on whether betaÃƒÂ¢Ã¢â€šÂ¬Ã‚Âblockers reduce deaths or other serious events when given to people undergoing surgery other than heart surgery. The findings for heart surgery are covered in another review. Background Surgery increases stress in the body, which responds by releasing the hormones adrenaline and noradrenaline. Stress from surgery can lead to death or other serious events such as heart attacks, stroke, or an irregular heartbeat. For surgery that does not involve the heart, an estimated 8% of people may have injury to their heart around the time of surgery. BetaÃƒÂ¢Ã¢â€šÂ¬Ã‚Âblockers are drugs that block the action of adrenaline and noradrenaline on the heart. BetaÃƒÂ¢Ã¢â€šÂ¬Ã‚Âblockers can slow down the heart, and reduce blood pressure, and this may reduce the risk of serious events. However, betaÃƒÂ¢Ã¢â€šÂ¬Ã‚Âblockers may lead to a very low heart rate or very low blood pressure which could increase the risk of death or a stroke. Prevention of early complications after surgery is important, but using betaÃƒÂ¢Ã¢â€šÂ¬Ã‚Âblockers to prevent these complications is controversial. Study characteristics The evidence is current to 28 June 2019. We included 83 RCTs with 14,967 adults who were undergoing different types of surgery other than heart surgery. Eighteen studies are awaiting classification (because we did not have enough details to assess them), and three studies are ongoing. The types of betaÃƒÂ¢Ã¢â€šÂ¬Ã‚Âblockers used in the studies were: propranolol, metoprolol, esmolol, landiolol, nadolol, atenolol, labetalol, oxprenolol, and pindolol. Studies compared these betaÃƒÂ¢Ã¢â€šÂ¬Ã‚Âblockers with either a placebo (disguised to look like a betaÃƒÂ¢Ã¢â€šÂ¬Ã‚Âblocker but containing no medicine) or with standard care. Key results BetaÃƒÂ¢Ã¢â€šÂ¬Ã‚Âblockers may make l ttle or no difference to the number of people who die within 30 days of surgery (16 studies, 11,446 participants; lowÃƒÂ¢Ã¢â€šÂ¬Ã‚Âcertainty evidence), have a stroke (6 studies, 9460 participants; lowÃƒÂ¢Ã¢â€šÂ¬Ã‚Âcertainty evidence), or experience ventricular arrhythmias (irregular heartbeat rhythms, starting in the main chambers of the heart, that are potentially lifeÃƒÂ¢Ã¢â€šÂ¬Ã‚Âthreatening and may need immediate medical treatment; 5 studies, 476 participants; very lowÃƒÂ¢Ã¢â€šÂ¬Ã‚Âcertainty evidence). We found that betaÃƒÂ¢Ã¢â€šÂ¬Ã‚Âblockers may reduce atrial fibrillation (an irregular heartbeat, starting in the atrial chambers of the heart, that increases the risk of stroke if untreated; 9 studies, 9080 participants; low certaintyÃƒÂ¢Ã¢â€šÂ¬Ã‚Âevidence), and the number of people who have a heart attack (12 studies, 10,520 participants; lowÃƒÂ¢Ã¢â€šÂ¬Ã‚Âcertainty evidence). However, taking betaÃƒÂ¢Ã¢â€šÂ¬Ã‚Âblockers may increase the number of people who experience a very low heart rate (49 studies, 12,239 participants; lowÃƒÂ¢Ã¢â€šÂ¬Ã‚Âcertainty evidence), or very low blood pressure (49 studies, 12,304 participants; moderateÃƒÂ¢Ã¢â€šÂ¬Ã‚Âcertainty evidence), around the time of surgery. In a few studies, we also found little or no difference in the number of people who died after 30 days, who died because of a heart problem, or had heart failure. We found no evidence of whether betaÃƒÂ¢Ã¢â€šÂ¬Ã‚Âblockers alter the length of time in hospital. No studies assessed whether people who were given betaÃƒÂ¢Ã¢â€šÂ¬Ã‚Âblockers had a better quality of life after heart surgery. Certainty of the evidence The certainty of the evidence in this review was limited by including some studies that were at high risk of bias, and we noticed that some of our findings were different if we only included placeboÃƒÂ¢Ã¢â€šÂ¬Ã‚Âcontrolled studies or studies that reported how participants were randomized. We also found one large, wellÃƒÂ¢Ã¢â€šÂ¬Ã‚Âconducted, international study that had different findings to the smaller studies. It showed a reduction in heart attacks and an increase in stroke and allÃƒÂ¢Ã¢â€šÂ¬Ã‚Âcause mortality when betaÃƒÂ¢Ã¢â€šÂ¬Ã‚Âblockers were used, whilst the other studies did not show a clear effect. We were also less certain of the findings for outcomes with few studies, such as for ventricular arrhythmias. Conclusion Although betaÃƒÂ¢Ã¢â€šÂ¬Ã‚Âblockers may make little or no difference to the number of people who die within 30 days, have a stroke, or have ventricular arrhythmias, they may reduce atrial fibrillation and heart attacks. Taking betaÃƒÂ¢Ã¢â€šÂ¬Ã‚Âblockers may increase the number of people with a very low heart rate or very low blood pressure around the time of surgery. Further evidence from large, placeboÃƒÂ¢Ã¢â€šÂ¬Ã‚Âcontrolled trials is likely to increase the certainty of these findings, and we recommend the assessment of impact on quality of life. | E18: FALSE | F18: Focuses on perioperative beta-blockers, not NHS shifts. | G18: None | I18: 0.9
A19: J524 | B19: 2019 | C19: Perioperative betaÃƒÂ¢Ã¢â€šÂ¬Ã‚Âblockers for preventing surgeryÃƒÂ¢Ã¢â€šÂ¬Ã‚Ârelated mortality and morbidity in adults undergoing cardiac surgery | D19: - Background Randomized controlled trials (RCTs) have yielded conflicting results regarding the ability of betaÃƒÂ¢Ã¢â€šÂ¬Ã‚Âblockers to influence perioperative cardiovascular morbidity and mortality. Thus routine prescription of these drugs in unselected patients remains a controversial issue. A previous version of this review assessing the effectiveness of perioperative betaÃƒÂ¢Ã¢â€šÂ¬Ã‚Âblockers in cardiac and nonÃƒÂ¢Ã¢â€šÂ¬Ã‚Âcardiac surgery was last published in 2018. The previous review has now been split into two reviews according to type of surgery. This is an update and assesses the evidence in cardiac surgery only. Objectives To assess the effectiveness of perioperatively administered betaÃƒÂ¢Ã¢â€šÂ¬Ã‚Âblockers for the prevention of surgeryÃƒÂ¢Ã¢â€šÂ¬Ã‚Ârelated mortality and morbidity in adults undergoing cardiac surgery. Search methods We searched CENTRAL, MEDLINE, Embase, CINAHL, Biosis Previews and Conference Proceedings Citation IndexÃƒÂ¢Ã¢â€šÂ¬Ã‚ÂScience on 28 June 2019. We searched clinical trials registers and grey literature, and conducted backwardÃƒÂ¢Ã¢â€šÂ¬Ã‚Â and forwardÃƒÂ¢Ã¢â€šÂ¬Ã‚Âcitation searching of relevant articles. Selection criteria We included RCTs and quasiÃƒÂ¢Ã¢â€šÂ¬Ã‚Ârandomized studies comparing betaÃƒÂ¢Ã¢â€šÂ¬Ã‚Âblockers with a control (placebo or standard care) administered during the perioperative period to adults undergoing cardiac surgery. We excluded studies in which all participants in the standard care control group were given a pharmacological agent that was not given to participants in the intervention group, studies in which all participants in the control group were given a betaÃƒÂ¢Ã¢â€šÂ¬Ã‚Âblocker, and studies in which betaÃƒÂ¢Ã¢â€šÂ¬Ã‚Âblockers were given with an additional agent (e.g. magnesium). We excluded studies that did not measure or report review outcomes. Data collection and analysis Two review authors independently assessed studies for inclusion, extracted data, and assessed risks of bias. We assessed the certainty of evidence with GRADE. Main results We included 63 studies with 7768 participants; six studies were quasiÃƒÂ¢Ã¢â€šÂ¬Ã‚Ârandomized and the remaining were RCTs. All participants were undergoing cardiac surgery, and in most studies, at least some of the participants were previously taking betaÃƒÂ¢Ã¢â€šÂ¬Ã‚Âblockers. Types of betaÃƒÂ¢Ã¢â€šÂ¬Ã‚Âblockers were: propranolol, metoprolol, sotalol, esmolol, landiolol, acebutolol, timolol, carvedilol, nadolol, and atenolol. In twelve studies, betaÃƒÂ¢Ã¢â€šÂ¬Ã‚Âblockers were titrated according to heart rate or blood pressure. Duration of administration varied between studies, as did the time at which drugs were administered; in nine studies this was before surgery, in 20 studies during surgery, and in the remaining studies betaÃƒÂ¢Ã¢â€šÂ¬Ã‚Âblockers were started postoperatively. Overall, we found that most studies did not report sufficient details for us to adequately assess risk of bias. In particular, few studies reported methods used to randomize participants to groups. In some studies, participants in the control group were given betaÃƒÂ¢Ã¢â€šÂ¬Ã‚Âblockers as rescue therapy during the study period, and all studies in which the control was standard care were at high risk of performance bias because of the openÃƒÂ¢Ã¢â€šÂ¬Ã‚Âlabel study design. No studies were prospectively registered with clinical trials registers, which limited the assessment of reporting bias. We judged 68% studies to be at high risk of bias in at least one domain. Study authors reported few deaths (7 per 1000 in both the intervention and control groups), and we found lowÃƒÂ¢Ã¢â€šÂ¬Ã‚Âcertainty evidence that betaÃƒÂ¢Ã¢â€šÂ¬Ã‚Âblockers may make little or no difference to allÃƒÂ¢Ã¢â€šÂ¬Ã‚Âcause mortality at 30 days (risk ratio (RR) 0.95, 95% confidence interval (CI) 0.47 to 1.90; 29 studies, 4099 participants). For myocardial infarctions, we found no evidence of a difference in events (RR 1.05, 95% CI 0.72 to 1.52; 25 studies, 3946 participants; lowÃƒÂ¢Ã¢â€šÂ¬Ã‚Âcertainty evidence). Few study authors reported cerebrovascular events, and the evidence was uncertain (RR 1.37, 95% CI 0.51 to 3.67; 5 studies, 1471 participants; very lowÃƒÂ¢Ã¢â€šÂ¬Ã‚Âcertainty evidence). Based on a control risk of 54 per 1000, we found lowÃƒÂ¢Ã¢â€šÂ¬Ã‚Âcertainty evidence that betaÃƒÂ¢Ã¢â€šÂ¬Ã‚Âblockers may reduce episodes of ventr cular arrhythmias by 32 episodes per 1000 (RR 0.40, 95% CI 0.25 to 0.63; 12 studies, 2296 participants). For atrial fibrillation or flutter, there may be 163 fewer incidences with betaÃƒÂ¢Ã¢â€šÂ¬Ã‚Âblockers, based on a control risk of 327 incidences per 1000 (RR 0.50, 95% CI 0.42 to 0.59; 40 studies, 5650 participants; lowÃƒÂ¢Ã¢â€šÂ¬Ã‚Âcertainty evidence). However, the evidence for bradycardia and hypotension was less certain. We found that betaÃƒÂ¢Ã¢â€šÂ¬Ã‚Âblockers may make little or no difference to bradycardia (RR 1.63, 95% CI 0.92 to 2.91; 12 studies, 1640 participants; lowÃƒÂ¢Ã¢â€šÂ¬Ã‚Âcertainty evidence), or hypotension (RR 1.84, 95% CI 0.89 to 3.80; 10 studies, 1538 participants; lowÃƒÂ¢Ã¢â€šÂ¬Ã‚Âcertainty evidence). We used GRADE to downgrade the certainty of evidence. Owing to studies at high risk of bias in at least one domain, we downgraded each outcome for study limitations. Based on effect size calculations in the previous review, we found an insufficient number of participants in all outcomes (except atrial fibrillation) and, for some outcomes, we noted a wide confidence interval; therefore, we also downgraded outcomes owing to imprecision. The evidence for atrial fibrillation and length of hospital stay had a moderate level of statistical heterogeneity which we could not explain, and we, therefore, downgraded these outcomes for inconsistency. Authors' conclusions We found no evidence of a difference in early allÃƒÂ¢Ã¢â€šÂ¬Ã‚Âcause mortality, myocardial infarction, cerebrovascular events, hypotension and bradycardia. However, there may be a reduction in atrial fibrillation and ventricular arrhythmias when betaÃƒÂ¢Ã¢â€šÂ¬Ã‚Âblockers are used. A larger sample size is likely to increase the certainty of this evidence. Four studies awaiting classification may alter the conclusions of this review. Plain language summary BetaÃƒÂ¢Ã¢â€šÂ¬Ã‚Âblockers to prevent death or serious events after heart surgery This review assessed evidence of whether betaÃƒÂ¢Ã¢â€šÂ¬Ã‚Âblockers given around the time of surgery can reduce death or other serious events for people undergoing heart surgery. Background People undergoing heart surgery are at greater risk of complications and death. Heart surgery increases the amount of stress in the body, causing the release of the hormones adrenaline and noradrenaline. This stress can lead to serious events including death, heart attacks, stroke, or an irregular heartbeat. BetaÃƒÂ¢Ã¢â€šÂ¬Ã‚Âblockers are drugs that block the action of adrenaline and noradrenaline on the heart. BetaÃƒÂ¢Ã¢â€šÂ¬Ã‚Âblockers can slow down the heart and reduce blood pressure, and this effect may reduce the risk of serious events. However, they can also lead to a very low heart rate or very low blood pressure, and this effect may increase the risk of death or a stroke. Prevention of complications around the time of surgery is an important safety consideration for people undergoing heart surgery. Study characteristics The evidence is current to 28 June 2019. We included 63 studies with 7768 adults who were undergoing heart surgery, including coronary artery bypass graft and valve replacement surgery. Studies were mostly randomized controlled studies, and six were quasiÃƒÂ¢Ã¢â€šÂ¬Ã‚Ârandomized (participants were allocated to groups by methods such as using hospital record numbers or dates of birth). The types of betaÃƒÂ¢Ã¢â€šÂ¬Ã‚Âblockers were: propranolol, metoprolol, sotalol, esmolol, landiolol, acebutolol, timolol, carvedilol, nadolol, and atenolol. These betaÃƒÂ¢Ã¢â€šÂ¬Ã‚Âblockers were compared with either a placebo (disguised to look like a betaÃƒÂ¢Ã¢â€šÂ¬Ã‚Âblocker but containing no medicine) or with standard care. BetaÃƒÂ¢Ã¢â€šÂ¬Ã‚Âblockers were started before surgery, during surgery or at the latest by the end of the first day after surgery. The length of time betaÃƒÂ¢Ã¢â€šÂ¬Ã‚Âblockers were given varied between studies. In most studies, at least some of the people were already taking betaÃƒÂ¢Ã¢â€šÂ¬Ã‚Âblockers, which would be expected for people who had conditions that needed heart surgery. Key results BetaÃƒÂ¢Ã¢â€šÂ¬Ã‚Âblockers probably make little or no difference to the number of people who die (29 studies, 4099 participants) or have a heart attack (25 studies, 3946 participants) within 30 days of surgery. This w s supported by lowÃƒÂ¢Ã¢â€šÂ¬Ã‚Âcertainty evidence. Few studies reported on people who had a stroke, and we were uncertain whether or not betaÃƒÂ¢Ã¢â€šÂ¬Ã‚Âblockers reduced strokes because the certainty of the evidence was very low (5 studies, 1471 participants). BetaÃƒÂ¢Ã¢â€šÂ¬Ã‚Âblockers may reduce atrial fibrillation, which is an irregular heartbeat starting in the atrial chambers of the heart that increases the risk of stroke if untreated (40 studies, 5650 participants; lowÃƒÂ¢Ã¢â€šÂ¬Ã‚Âcertainty evidence). BetaÃƒÂ¢Ã¢â€šÂ¬Ã‚Âblockers may also reduce ventricular arrhythmias, which are potentially lifeÃƒÂ¢Ã¢â€šÂ¬Ã‚Âthreatening irregular heartbeat rhythms originating in the main chambers of the heart, and which may need immediate medical treatment (12 studies, 2296 participants). We found that betaÃƒÂ¢Ã¢â€šÂ¬Ã‚Âblockers may make little or no difference to whether people experience a very low heart rate or very low blood pressure. We were uncertain whether betaÃƒÂ¢Ã¢â€šÂ¬Ã‚Âblockers made a difference to the number of deaths up to a year after surgery (3 studies, 511 participants), to death because of the heart (4 studies, 320 participants), or to people who had heart failure (3 studies, 311 participants). The certainty of this evidence was very low. People who took betaÃƒÂ¢Ã¢â€šÂ¬Ã‚Âblockers had a shorter hospital stay by about half a day (14 studies, 2450 participants; lowÃƒÂ¢Ã¢â€šÂ¬Ã‚Âcertainty evidence). No studies assessed whether people on betaÃƒÂ¢Ã¢â€šÂ¬Ã‚Âblockers had a better quality of life after heart surgery. Certainty of the evidence The certainty of the evidence in this review was mostly low. We found that many studies reported methods that we believed could influence the results. For example, many studies did not use a placeboÃƒÂ¢Ã¢â€šÂ¬Ã‚Âcontrol and the doctors might, therefore, have treated people differently in each group. We were unable to explain some of the differences that we found in the data for atrial fibrillation. We also needed to have evidence from a larger number of participants to be very confident in our findings. Conclusion BetaÃƒÂ¢Ã¢â€šÂ¬Ã‚Âblockers may be beneficial for people who are undergoing cardiac surgery because they may reduce the number of people who experience atrial fibrillation and ventricular arrhythmias. BetaÃƒÂ¢Ã¢â€šÂ¬Ã‚Âblockers may make little or no difference to the other outcomes in this review, including death, heart attacks or stroke. | E19: FALSE | F19: Focuses on perioperative beta-blockers, not NHS shifts. | G19: None | I19: 0.95
A20: J527 | B20: 2019 | C20: Botulinum toxin type A in the treatment of lower limb spasticity in children with cerebral palsy | D20: - Background Cerebral palsy (CP) is the most common cause of physical disabilities in children in highÃƒÂ¢Ã¢â€šÂ¬Ã‚Âincome countries. Spasticity is the most common motor disturbance in CP. Botulinum toxin type A (BoNTÃƒÂ¢Ã¢â€šÂ¬Ã‚ÂA) is considered the firstÃƒÂ¢Ã¢â€šÂ¬Ã‚Âline treatment for focal spasticity in people with CP. Objectives To evaluate the effectiveness and safety of BoNTÃƒÂ¢Ã¢â€šÂ¬Ã‚ÂA compared to other treatments used in the management of lower limb spasticity in children with CP. Search methods We searched CENTRAL, PubMed, four other databases, and two trial registers in October 2018. We also searched the reference lists of relevant studies and reviews and contacted experts in the field. We did not apply any date or language restrictions. Selection criteria Randomised controlled trials of children with CP, aged between birth and 19 years, treated with BoNTÃƒÂ¢Ã¢â€šÂ¬Ã‚ÂA injections in the lower limb muscles compared to other interventions. The primary outcomes were gait analysis and function. The secondary outcomes were joint range of motion, quality of life, satisfaction, spasticity, and adverse events. Data collection and analysis Two review authors independently selected studies, extracted data, assessed risk of bias, and rated the quality of the evidence using GRADE. A third review author arbitrated in case of disagreements. We conducted metaÃƒÂ¢Ã¢â€šÂ¬Ã‚Âanalyses of available data whenever possible, analysing dichotomous data with risk ratios (RR), and continuous data with mean differences (MD) or standardised mean differences (SMD), with 95% confidence intervals (CI). We considered a 5% significance level for all analyses. Whenever possible, we analysed outcomes at the time points at which they were assessed: short term (2 to 8 weeks); medium term (12 to 16 weeks); and long term (> 24 weeks). Main results We included 31 randomised controlled trials assessing 1508 participants. Most studies included ambulatory patients with more than one motor type of CP, and with a mean age of between three and seven years. There was a slight predominance of males. Studies compared BoNTÃƒÂ¢Ã¢â€šÂ¬Ã‚ÂA in the lower limb muscles to usual care or physiotherapy (14 studies), placebo or sham (12 studies), serial casting (4 studies), or orthoses (1 study). We rated studies as at high or unclear risk of bias mainly due to random sequence generation, allocation concealment, blinding of participants and personnel, and blinding of outcome assessment. BoNTÃƒÂ¢Ã¢â€šÂ¬Ã‚ÂA versus usual care or physiotherapy BoNTÃƒÂ¢Ã¢â€šÂ¬Ã‚ÂA might improve overall gait scores at mediumÃƒÂ¢Ã¢â€šÂ¬Ã‚Âterm followÃƒÂ¢Ã¢â€šÂ¬Ã‚Âup (MD 2.80, 95% CI 1.55 to 4.05; 1 study, 40 children; very lowÃƒÂ¢Ã¢â€šÂ¬Ã‚Âquality evidence) and is moderately effective at improving function at shortÃƒÂ¢Ã¢â€šÂ¬Ã‚Âterm (SMD 0.59, 95% CI 0.23 to 0.95; 2 studies, 123 children) and mediumÃƒÂ¢Ã¢â€šÂ¬Ã‚Âterm (SMD 1.04, 95% CI 0.16 to 1.91; 4 studies, 191 children) followÃƒÂ¢Ã¢â€šÂ¬Ã‚Âup (all very lowÃƒÂ¢Ã¢â€šÂ¬Ã‚Âquality evidence). BoNTÃƒÂ¢Ã¢â€šÂ¬Ã‚ÂA improves ankle range of motion, satisfaction, and ankle plantarflexors spasticity at one or more time points (very lowÃƒÂ¢Ã¢â€šÂ¬Ã‚Âquality evidence). The proportion of adverse events in the BoNTÃƒÂ¢Ã¢â€šÂ¬Ã‚ÂA group was 0.37 (95% CI 0.08 to 0.66; I 2 = 95%; very lowÃƒÂ¢Ã¢â€šÂ¬Ã‚Âquality evidence). No adverse events were reported in the control group. BoNTÃƒÂ¢Ã¢â€šÂ¬Ã‚ÂA versus placebo or sham BoNTÃƒÂ¢Ã¢â€šÂ¬Ã‚ÂA improves overall gait scores at shortÃƒÂ¢Ã¢â€šÂ¬Ã‚Âterm (RR 1.66, 95% CI 1.16 to 2.37, P = 0.006; 4 studies, 261 assessments) and mediumÃƒÂ¢Ã¢â€šÂ¬Ã‚Âterm (RR 1.90, 95% CI 1.32 to 2.74, P < 0.001; 3 studies, 248 assessments) followÃƒÂ¢Ã¢â€šÂ¬Ã‚Âup, and may improve peak ankle dorsiflexion in stance (MD 15.90 degrees, 95% CI 4.87 to 26.93, P = 0.005; 1 study, 19 children) and in swing (MD 10.20 degrees, 95% CI 4.01 to 16.39, P = 0.001; 1 study, 19 children) at shortÃƒÂ¢Ã¢â€šÂ¬Ã‚Âterm followÃƒÂ¢Ã¢â€šÂ¬Ã‚Âup (all moderateÃƒÂ¢Ã¢â€šÂ¬Ã‚Âquality evidence). BoNTÃƒÂ¢Ã¢â€šÂ¬Ã‚ÂA is not more effective than placebo or sham at improving function at shortÃƒÂ¢Ã¢â€šÂ¬Ã‚Âterm (SMD 0.24, 95% CI ÃƒÂ¢Ã‹â€ Ã¢â‚¬â„¢0.35 to 0.83, P = 0.42; 4 studies, 305 children) or longÃƒÂ¢Ã¢â€šÂ¬Ã‚Âterm (SMD ÃƒÂ¢Ã‹â€ Ã¢â‚¬â„¢0.07, 95% CI ÃƒÂ¢Ã‹â€ Ã¢â‚¬â„¢0.48 to 0.35, P = 0.76; 2 studies, 91 children) followÃƒÂ¢Ã¢â€šÂ¬Ã‚Âup, but has a small positive effect at mediumÃƒÂ¢Ã¢â€šÂ¬Ã‚Âterm followÃƒÂ¢Ã¢â€šÂ¬Ã‚Âup (SMD 0.28, 95% CI 0.06 to 0.49, P = 0.01; 5 studies, 327 children) (all moderateÃƒÂ¢Ã¢â€šÂ¬Ã‚Âquality evidence). BoNTÃƒÂ¢Ã¢â€šÂ¬Ã‚ÂA improves passive ankle range of motion, satisfaction, and ankle plantarflexors spasticity at one or more time points (moderateÃƒÂ¢Ã¢â€šÂ¬Ã‚Âquality evidence). There was no difference between groups in the rate of adverse events at shortÃƒÂ¢Ã¢â€šÂ¬Ã‚Âterm followÃƒÂ¢Ã¢â€šÂ¬Ã‚Âup (RR 1.29, 95% CI 0.87 to 1.93, P = 0.21; 12 studies, 918 children; moderateÃƒÂ¢Ã¢â€šÂ¬Ã‚Âquality evidence). BoNTÃƒÂ¢Ã¢â€šÂ¬Ã‚ÂA versus serial casting There was no difference between groups for overall gait scores at shortÃƒÂ¢Ã¢â€šÂ¬Ã‚Âterm (MD 0.00, 95% CI ÃƒÂ¢Ã‹â€ Ã¢â‚¬â„¢1.66 to 1.66); mediumÃƒÂ¢Ã¢â€šÂ¬Ã‚Âterm (MD 0.65, 95% CI ÃƒÂ¢Ã‹â€ Ã¢â‚¬â„¢1.21 to 2.51); or longÃƒÂ¢Ã¢â€šÂ¬Ã‚Âterm (MD 0.46, 95% CI ÃƒÂ¢Ã‹â€ Ã¢â‚¬â„¢1.33 to 2.25) followÃƒÂ¢Ã¢â€šÂ¬Ã‚Âup in one study with 18 children (moderateÃƒÂ¢Ã¢â€šÂ¬Ã‚Âquality evidence). BoNTÃƒÂ¢Ã¢â€šÂ¬Ã‚ÂA improved instrumented gait analysis only in terms of ankle dorsiflexion at initial contact (MD 6.59 degrees, 95% CI 1.39 to 11.78, P = 0.01; 2 studies, 47 children). There was no difference between groups for peak ankle dorsiflexion in stance and swing, and gait speed at any time point (moderateÃƒÂ¢Ã¢â€šÂ¬Ã‚Â and lowÃƒÂ¢Ã¢â€šÂ¬Ã‚Âquality evidence). BoNTÃƒÂ¢Ã¢â€šÂ¬Ã‚ÂA is not more effective than serial casting at improving function, ankle range of motion, and spasticity at any time point (moderateÃƒÂ¢Ã¢â€šÂ¬Ã‚Â and lowÃƒÂ¢Ã¢â€šÂ¬Ã‚Âquality evidence). BoNTÃƒÂ¢Ã¢â€šÂ¬Ã‚ÂA is not associated with a higher risk of adverse events than serial casting (RR 0.59, 95% CI 0.03 to 11.03; 3 studies, 64 children; lowÃƒÂ¢Ã¢â€šÂ¬Ã‚Âquality evidence). BoNTÃƒÂ¢Ã¢â€šÂ¬Ã‚ÂA versus orthoses There was no difference between groups for function at mediumÃƒÂ¢Ã¢â€šÂ¬Ã‚Âterm followÃƒÂ¢Ã¢â€šÂ¬Ã‚Âup (MD 11.14, 95% CI ÃƒÂ¢Ã‹â€ Ã¢â‚¬â„¢0.05 to 22.33; 1 study, 43 children), but BoNTÃƒÂ¢Ã¢â€šÂ¬Ã‚ÂA is more effective than orthoses at improving hip range of motion and hip adductors spasticity (all very lowÃƒÂ¢Ã¢â€šÂ¬Ã‚Âquality evidence). Authors' conclusions The quality of the evidence was low or very low for most of the outcomes analysed. We found limited evidence that BoNTÃƒÂ¢Ã¢â€šÂ¬Ã‚ÂA is more effective than placebo or a nonÃƒÂ¢Ã¢â€šÂ¬Ã‚Âplacebo control at improving gait, joint range of motion, satisfaction, and lower limb spasticity in children with CP, whereas the results for function were contradictory. The rate of adverse events with BoNTÃƒÂ¢Ã¢â€šÂ¬Ã‚ÂA is similar to placebo. BoNTÃƒÂ¢Ã¢â€šÂ¬Ã‚ÂA is not more effective than ankle serial casting to treat ankle contractures for any of the assessed outcomes, but is more effective than orthotics at improving range of motion and spasticity. Plain language summary Botulinum toxin type A injections for the treatment of lower limb spasticity in cerebral palsy Background Cerebral palsy (CP) is a nonÃƒÂ¢Ã¢â€šÂ¬Ã‚Âprogressive, lifelong condition resulting from damage to the developing brain. Over time, most children with CP will develop abnormal muscle activity and stiffness/overactivity (spasticity) that affects at least one limb and interferes with their normal movement. Treatments for spasticity include physiotherapy, oral antispasticity drugs (a type of medication that works to relax the muscles and relieve spasticity), casts, splints, orthopaedic surgery, and botulinum toxin A (BoNTÃƒÂ¢Ã¢â€šÂ¬Ã‚ÂA; a poisonous biological substance that is thought to relieve spasticity by reducing muscle overactivity when injected into the muscle). This review looked at the effects of BoNTÃƒÂ¢Ã¢â€šÂ¬Ã‚ÂA. Review question The aim of this review was to assess and summarise scientific studies comparing BoNTÃƒÂ¢Ã¢â€šÂ¬Ã‚ÂA injections to other treatments for lower limb spasticity in children with CP. Study characteristics We found 31 studies assessing 1508 participants. The use of BoNTÃƒÂ¢Ã¢â€šÂ¬Ã‚ÂA in the lower limb muscles was compared to: (1) children's regular care or physiotherapy, (2) placebo (fake injections), (3) a series of belowÃƒÂ¢Ã¢â€šÂ¬Ã‚Âknee plaster casts, and (4) leg splints. Key results Children receiving BoNTÃƒÂ¢Ã¢â€šÂ¬Ã‚ÂA injections tended to have improved walking pattern (gait), joint range of motion, satisfaction with outcome of treatment, and muscle spasms compared with their usual programme of care or physiotherapy, or placebo. Measures of function tended to show only modest improvements in children receiving BoNTÃƒÂ¢Ã¢â€šÂ¬Ã‚ÂA injections. The rate of side effects was similar when comparing BoNTÃƒÂ¢Ã¢â€šÂ¬Ã‚ÂA injections to placebo. BoNTÃƒÂ¢Ã¢â€šÂ¬Ã‚ÂA injections and plaster cas s below the knee produced similar benefits in walking and joint motion and relieving spasms. In addition, BoNTÃƒÂ¢Ã¢â€šÂ¬Ã‚ÂA provided better results in terms of joint range of motion compared to a specific type of splinting (Johnstone pressure splints). Quality of the evidence We considered the quality of the evidence as very low for the comparison BoNTÃƒÂ¢Ã¢â€šÂ¬Ã‚ÂA versus usual care or physiotherapy; moderate for the comparison BoNTÃƒÂ¢Ã¢â€šÂ¬Ã‚ÂA versus placebo; moderate and low for the comparison BoNTÃƒÂ¢Ã¢â€šÂ¬Ã‚ÂA versus plaster casts; and very low for the comparison BoNTÃƒÂ¢Ã¢â€šÂ¬Ã‚ÂA versus splints. Conclusion There is limited evidence that, compared to placebo or regular care, BoNTÃƒÂ¢Ã¢â€šÂ¬Ã‚ÂA improves walking, joint motion, satisfaction with the outcome of treatment, and muscle spasticity in children with CP. The rate of side effects with BoNTÃƒÂ¢Ã¢â€šÂ¬Ã‚ÂA was similar to placebo. BoNTÃƒÂ¢Ã¢â€šÂ¬Ã‚ÂA was no better than plaster casts in any of our analyses, but was better than splints at improving range of motion and spasticity. | E20: FALSE | F20: Focuses on treatment efficacy, not NHS shifts. | G20: None | I20: 0.9
A21: J529 | B21: 2019 | C21: Endometrial resection and ablation techniques for heavy menstrual bleeding | D21: - Background Heavy menstrual bleeding (HMB) is a significant health problem in premenopausal women; it can reduce their quality of life and can cause social disruption and physical problems such as iron deficiency anaemia. FirstÃƒÂ¢Ã¢â€šÂ¬Ã‚Âline treatment has traditionally consisted of medical therapy (hormonal and nonÃƒÂ¢Ã¢â€šÂ¬Ã‚Âhormonal), but this is not always successful in reducing menstrual bleeding to acceptable levels. Hysterectomy is a definitive treatment, but it is more costly and carries some risk. Endometrial ablation may be an alternative to hysterectomy that preserves the uterus. Many techniques have been developed to 'ablate' (remove) the lining of the endometrium. FirstÃƒÂ¢Ã¢â€šÂ¬Ã‚Âgeneration techniques require visualisation of the uterus with a hysteroscope during the procedure; although it is safe, this procedure requires specific technical skills. Newer techniques for endometrial ablation (secondÃƒÂ¢Ã¢â€šÂ¬Ã‚Â and thirdÃƒÂ¢Ã¢â€šÂ¬Ã‚Âgeneration techniques) have been developed that are quicker than previous approaches because they do not require hysteroscopic visualisation during the procedure. Objectives To compare the efficacy, safety, and acceptability of endometrial destruction techniques to reduce heavy menstrual bleeding (HMB) in premenopausal women. Search methods We searched the Cochrane Gynaecology and Fertility Group Specialised Register of controlled trials, the Cochrane Central Register of Controlled Trials (CENTRAL) in the Cochrane Library, MEDLINE, Embase, CINAHL, and PsycInfo (from inception to May 2018). We also searched trials registers, other sources of unpublished or grey literature, and reference lists of retrieved studies, and we made contact with experts in the field and with pharmaceutical companies that manufacture ablation devices. Selection criteria Randomised controlled trials (RCTs) comparing different endometrial ablation or resection techniques for women reporting HMB without known uterine pathology, other than fibroids outside the uterine cavity and smaller than 3 centimetres, were eligible. Outcomes included improvement in HMB and in quality of life, patient satisfaction, operative outcomes, complications, and the need for further surgery, including hysterectomy. Data collection and analysis Two review authors independently selected trials for inclusion, assessed trials for risk of bias, and extracted data. We contacted study authors for clarification of methods or for additional data. We assessed adverse events only if they were separately measured in the included trials. We undertook comparisons with individual techniques as well as an overall comparison of firstÃƒÂ¢Ã¢â€šÂ¬Ã‚Â and secondÃƒÂ¢Ã¢â€šÂ¬Ã‚Âgeneration ablation methods. Main results We included in this update 28 studies (4287 women) with sample sizes ranging from 20 to 372. Most studies had low risk of bias for randomisation, attrition, and selective reporting. Less than half of these studies had adequate allocation concealment, and most were unblinded. Using GRADE, we determined that the quality of evidence ranged from moderate to very low. We downgraded evidence for risk of bias, imprecision, and inconsistency. Overall comparison of secondÃƒÂ¢Ã¢â€šÂ¬Ã‚Âgeneration versus firstÃƒÂ¢Ã¢â€šÂ¬Ã‚Âgeneration (i.e. gold standard hysteroscopic ablative) techniques revealed no evidence of differences in amenorrhoea at 1 year and 2 to 5 years' followÃƒÂ¢Ã¢â€šÂ¬Ã‚Âup (risk ratio (RR) 0.99, 95% confidence interval (CI) 0.78 to 1.27; 12 studies; 2145 women; IÃƒâ€šÃ‚Â² = 77%; and RR 1.16, 95% CI 0.78 to 1.72; 672 women; 4 studies; IÃƒâ€šÃ‚Â² = 80%; very lowÃƒÂ¢Ã¢â€šÂ¬Ã‚Âquality evidence) and showed subjective improvement at 1 year followÃƒÂ¢Ã¢â€šÂ¬Ã‚Âup based on a Pictorial Blood Assessment Chart (PBAC) (< 75 or acceptable improvement) (RR 1.03, 95% CI 0.98 to 1.09; 5 studies; 1282 women; IÃƒâ€šÃ‚Â² = 0%; and RR 1.12, 95% CI 0.97 to 1.28; 236 women; 1 study; lowÃƒÂ¢Ã¢â€šÂ¬Ã‚Âquality evidence). Study results showed no difference in patient satisfaction between secondÃƒÂ¢Ã¢â€šÂ¬Ã‚Â and firstÃƒÂ¢Ã¢â€šÂ¬Ã‚Âgeneration techniques at 1 year followÃƒÂ¢Ã¢â€šÂ¬Ã‚Âup (RR 1.01, 95% CI 0.98 to 1.04; 11 studies; 1750 women; IÃƒâ€šÃ‚Â² = 36%; lowÃƒÂ¢Ã¢â€šÂ¬Ã‚Âquality evidence) nor at 2 to 5 years' followÃƒÂ¢Ã¢â€šÂ¬Ã‚Âup (RR 1.02, 95% CI 0.93 t 1.13; 672 women; 4 studies; IÃƒâ€šÃ‚Â² = 81%). Compared with firstÃƒÂ¢Ã¢â€šÂ¬Ã‚Âgeneration techniques, secondÃƒÂ¢Ã¢â€šÂ¬Ã‚Âgeneration endometrial ablation techniques were associated with shorter operating times (mean difference (MD) ÃƒÂ¢Ã¢â€šÂ¬Ã‚Â13.52 minutes, 95% CI ÃƒÂ¢Ã¢â€šÂ¬Ã‚Â16.90 to ÃƒÂ¢Ã¢â€šÂ¬Ã‚Â10.13; 9 studies; 1822 women; lowÃƒÂ¢Ã¢â€šÂ¬Ã‚Âquality evidence) and more often were performed under local rather than general anaesthesia (RR 2.8, 95% CI 1.8 to 4.4; 6 studies; 1434 women; lowÃƒÂ¢Ã¢â€šÂ¬Ã‚Âquality evidence). We are uncertain whether perforation rates differed between secondÃƒÂ¢Ã¢â€šÂ¬Ã‚Â and firstÃƒÂ¢Ã¢â€šÂ¬Ã‚Âgeneration techniques (RR 0.32, 95% CI 0.10 to 1.01; 1885 women; 8 studies; IÃƒâ€šÃ‚Â² = 0%). Trials reported little or no difference between secondÃƒÂ¢Ã¢â€šÂ¬Ã‚Â and firstÃƒÂ¢Ã¢â€šÂ¬Ã‚Âgeneration techniques in requirement for additional surgery (ablation or hysterectomy) at 1 year followÃƒÂ¢Ã¢â€šÂ¬Ã‚Âup (RR 0.72, 95% CI 0.41 to 1.26; 6 studies: 935 women; lowÃƒÂ¢Ã¢â€šÂ¬Ã‚Âquality evidence). At 5 years, results showed probably little or no difference between groups in the requirement for hysterectomy (RR 0.85, 95% CI 0.59 to 1.22; 4 studies; 758 women; moderateÃƒÂ¢Ã¢â€šÂ¬Ã‚Âquality evidence). Authors' conclusions Approaches to endometrial ablation have evolved from firstÃƒÂ¢Ã¢â€šÂ¬Ã‚Âgeneration techniques to newer secondÃƒÂ¢Ã¢â€šÂ¬Ã‚Â and thirdÃƒÂ¢Ã¢â€šÂ¬Ã‚Âgeneration approaches. Current evidence suggests that compared to firstÃƒÂ¢Ã¢â€šÂ¬Ã‚Âgeneration techniques (endometrial laser ablation, transcervical resection of the endometrium, rollerball endometrial ablation), secondÃƒÂ¢Ã¢â€šÂ¬Ã‚Âgeneration approaches (thermal balloon endometrial ablation, microwave endometrial ablation, hydrothermal ablation, bipolar radiofrequency endometrial ablation, endometrial cryotherapy) are of equivalent efficacy for heavy menstrual bleeding, with comparable rates of amenorrhoea and improvement on the PBAC. SecondÃƒÂ¢Ã¢â€šÂ¬Ã‚Âgeneration techniques are associated with shorter operating times and are performed more often under local rather than general anaesthesia. It is uncertain whether perforation rates differed between secondÃƒÂ¢Ã¢â€šÂ¬Ã‚Â and firstÃƒÂ¢Ã¢â€šÂ¬Ã‚Âgeneration techniques. Evidence was insufficient to show which secondÃƒÂ¢Ã¢â€šÂ¬Ã‚Âgeneration approaches were superior to others and to reveal the efficacy and safety of thirdÃƒÂ¢Ã¢â€šÂ¬Ã‚Âgeneration approaches versus firstÃƒÂ¢Ã¢â€šÂ¬Ã‚Â and secondÃƒÂ¢Ã¢â€šÂ¬Ã‚Âgeneration techniques. Plain language summary Are newer methods for destroying the lining of the uterus (endometrial ablation) more effective and safer compared to established methods? Review question This review compared the effectiveness, safety, acceptability, and complication rates of firstÃƒÂ¢Ã¢â€šÂ¬Ã‚Â, secondÃƒÂ¢Ã¢â€šÂ¬Ã‚Â and thirdÃƒÂ¢Ã¢â€šÂ¬Ã‚Âgeneration methods available to destroy the endometrium (lining of the uterus) for treatment of heavy menstrual bleeding (heavy periods) in premenopausal women. Background Medication and hysterectomy (surgery to remove the womb) used to be the main treatment options for heavy menstrual bleeding. Both are still effective and safe options, but available new treatments focus on removing the lining of the womb (endometrium) from which the bleeding comes. These procedures involve either removing the endometrium (resection) or destroying it with thermal (heat) energy from a laser, electrical instruments, or other devices (ablation). These treatments can stop or reduce menstrual bleeding. Study characteristics This review identified 28 randomised controlled trials undertaken in 4287 women. Most of the women knew which treatment they were receiving, which may have influenced their judgements about menstrual blood loss and satisfaction. Other aspects of study quality varied among trials. Evidence is current to May 2018. Nineteen of the 28 trials acknowledged that they received funding, supplies of equipment, or technical assistance from the pharmaceutical industry and from equipment manufacturers. Key results ModerateÃƒÂ¢Ã¢â€šÂ¬Ã‚Â to very lowÃƒÂ¢Ã¢â€šÂ¬Ã‚Âquality evidence suggests that firstÃƒÂ¢Ã¢â€šÂ¬Ã‚Â and secondÃƒÂ¢Ã¢â€šÂ¬Ã‚Âgeneration approaches were equally effective in the treatment of HMB. Newer (secondÃƒÂ¢Ã¢â€šÂ¬Ã‚Âgeneration) treatment approaches were safer in terms of rate of fluid overload, cervical lacerations, and haematometra, with similar rates of uterine perforation. The newer approaches (secondÃƒÂ¢Ã¢â€šÂ¬Ã‚Âgeneration ablation) w re quicker and were more likely to be done under local (rather than general) anaesthesia compared with firstÃƒÂ¢Ã¢â€šÂ¬Ã‚Âgeneration approaches. Most women in both groups were satisfied with results of the procedure. Not enough evidence is available to show which secondÃƒÂ¢Ã¢â€šÂ¬Ã‚Âgeneration approaches are superior to others, and information about thirdÃƒÂ¢Ã¢â€šÂ¬Ã‚Âgeneration approaches is not available for comparison. Quality of the evidence Evidence ranged from moderate to very low quality. Few studies were blinded, data were limited, and heterogeneity was substantial for some outcomes, leading to downgrading of the quality of evidence. | E21: FALSE | F21: Focuses on surgical techniques, not NHS shifts. | G21: None | I21: 0.9
A22: J530 | B22: 2019 | C22: Cyclical progestogens for heavy menstrual bleeding | D22: - Background Heavy menstrual bleeding (HMB) is a menstrual blood loss perceived by women as excessive that affects the health of women of reproductive age, interfering with their physical, emotional, social and material quality of life. Whilst abnormal menstrual bleeding may be associated with underlying pathology, in the present context, HMB is defined as excessive menstrual bleeding in the absence of other systemic or gynaecological disease. The firstÃƒÂ¢Ã¢â€šÂ¬Ã‚Âline therapy is usually medical, avoiding possibly unnecessary surgery. Of the wide variety of medications used to reduce HMB, oral progestogens were originally the most commonly prescribed agents. This review assesses the effectiveness of two different types and regimens of oral progestogens in reducing ovulatory HMB. This is the update of a Cochrane review last updated in 2007, and originally named Effectiveness of cyclical progestagen therapy in reducing heavy menstrual bleeding" (1998). Objectives To determine the effectiveness, safety and tolerability of oral progestogen therapy taken either during the luteal phase (short cycle) or for a longer course of 21 days per cycle (long cycle), in achieving a reduction in menstrual blood loss in women of reproductive age with HMB. Search methods In January 2019 we searched Cochrane Gynaecology and Fertility's specialized register, CENTRAL, MEDLINE, Embase, CINAHL and PsycInfo. We also searched trials registers, other sources of unpublished or grey literature and reference lists of retrieved trials. We also checked citation lists of review articles to identify trials. Selection criteria Randomized controlled trials (RCTs) comparing different treatments for HMB that included cyclical oral progestogens were eligible. Data collection and analysis Two review authors independently selected trials for inclusion, assessed trials for risk of bias and extracted data. We contacted trial authors for clarification of methods or additional data when necessary. We only assessed adverse events if they were separately measured in the included trials. We compared cyclical oral progestogen in different regimens and placebo or other treatments. Our primary outcomes were menstrual blood loss and satisfaction with treatment; the secondary outcomes were number of days of bleeding, quality of life, compliance and acceptability of treatment, adverse events and costs. Main results This review identified 15 randomized controlled trials (RCTs) with 1071 women in total. Most of the women knew which treatment they were receiving, which may have influenced their judgements about menstrual blood loss and satisfaction. Other aspects of trial quality varied among trials. We did not identify any RCTs comparing progestogen treatment with placebo . We assessed comparisons between oral progestogens and other medical therapies separately according to different regimens. ShortÃƒÂ¢Ã¢â€šÂ¬Ã‚Âcycle progestogen therapy during the luteal phase (medroxyprogesterone acetate or norethisterone for 7 to 10 days, from day 15 to 19) was inferior to other medical therapy, including tranexamic acid, danazol and the progestogenÃƒÂ¢Ã¢â€šÂ¬Ã‚Âreleasing intrauterine system (PgÃƒÂ¢Ã¢â€šÂ¬Ã‚ÂIUS (off the market since 2001)), releasing 60 mcg of progesterone daily, with respect to reduction of menstrual blood loss (mean difference (MD) 37.29, 95% confidence interval (CI) 17.67 to 56.91; I 2 = 50%; 6 trials, 145 women, lowÃƒÂ¢Ã¢â€šÂ¬Ã‚Âquality evidence). The rate of satisfaction and the quality of life with treatment was similar in both groups. The number of bleeding days was greater on the short cycle progestogen group compared to other medical treatments. Adverse events (such as gastrointestinal symptoms and weight gain) were more likely with danazol when compared with progestogen treatment. We note that danazol is no longer in general use for treating HMB. LongÃƒÂ¢Ã¢â€šÂ¬Ã‚Âcycle progestogen therapy (medroxyprogesterone acetate or norethisterone), from day 5 to day 26 of the menstrual cycle, is also inferior compared to the levonorgestrelÃƒÂ¢Ã¢â€šÂ¬Ã‚Âreleasing intrauterine system (LNGÃƒÂ¢Ã¢â€šÂ¬Ã‚ÂIUS), tranexamic acid and ormeloxifene, ut may be similar to the combined vaginal ring with respect to reduction of menstrual blood loss (MD 16.88, 95% CI 10.93 to 22.84; I 2 = 87%; 4 trials, 355 women, very lowÃƒÂ¢Ã¢â€šÂ¬Ã‚Âquality evidence). There was no clear evidence of a difference between progestogen therapy long cycle and other medical therapy in terms of headache (OR 1.45, 95% CI 0.40 to 5.31; I 2 = 0%; 2 trials, 189 women; lowÃƒÂ¢Ã¢â€šÂ¬Ã‚Âquality evidence). Breakthrough bleeding or spotting was more likely in women with the LNGÃƒÂ¢Ã¢â€šÂ¬Ã‚ÂIUS (OR 0.18, 95% CI 0.06 to 0.55; I 2 = 0%; 3 trials, 220 women; lowÃƒÂ¢Ã¢â€šÂ¬Ã‚Âquality evidence). No trials reported on days of bleeding or quality of life for this comparison. The evidence supporting these findings was limited by low or very low gradings of quality; thus, we are uncertain about the findings and there is a potential that they may change if we identify other trials. Authors' conclusions LowÃƒÂ¢Ã¢â€šÂ¬Ã‚Â or very lowÃƒÂ¢Ã¢â€šÂ¬Ã‚Âquality evidence suggests that shortÃƒÂ¢Ã¢â€šÂ¬Ã‚Âcourse progestogen was inferior to other medical therapy, including tranexamic acid, danazol and the PgÃƒÂ¢Ã¢â€šÂ¬Ã‚ÂIUS with respect to reduction of menstrual blood loss. Long cycle progestogen therapy (medroxyprogesterone acetate or norethisterone) was also inferior to the LNGÃƒÂ¢Ã¢â€šÂ¬Ã‚ÂIUS, tranexamic acid and ormeloxifene, but may be similar to the combined vaginal ring with respect to reduction of menstrual blood loss. Plain language summary Are cyclical progestogens an effective and safe treatment for heavy menstrual bleeding compared to other medical treatments? Background Heavy menstrual bleeding (HMB) is menstrual bleeding (periods) that interferes with a woman's quality of life, either physical, emotional, social or material, independently of the actual amount of blood loss. Most women with HMB do not have any associated physical cause, such as fibroids, so getting help that does not involve surgery is an attractive alternative. A cyclical progestogen is a hormone tablet that can be taken by mouth for either 10 days or 3 to 4 weeks per month for the treatment of HMB (short or long course cyclical progestogen). Trial characteristics This review identified 15 randomized controlled trials (clinical studies where people are randomly put into one of two or more treatment groups) with 1071 women in total comparing oral progestogens to other medical treatment for HMB (other oral treatments, intrauterine device and vaginal ring). Our primary outcomes were menstrual blood loss and satisfaction with treatment; the secondary outcomes were number of days of bleeding, quality of life, compliance and acceptability of treatment, adverse events and costs. Evidence is current to January 2019. Key results This review of trials found that progestogen hormone tablets taken by mouth for 10 days per month (short course) were less effective at reducing menstrual blood loss when compared to other medical treatments. We are uncertain whether they improved satisfaction or quality of life in women with HMB, or were associated with any difference in adverse effects when compared to other medical treatments. Even though it was less effective at reducing menstrual blood loss, satisfaction with treatment was similar to other medical treatments such as tranexamic acid and PgÃƒÂ¢Ã¢â€šÂ¬Ã‚ÂIUS. We found that progestogen hormone tablets, taken by mouth for three to four weeks from day 5 to 26 of the menstrual cycle (long course), reduced menstrual blood loss but this treatment may be less effective than tranexamic acid, combined hormonal contraceptives and the levonorgestrelÃƒÂ¢Ã¢â€šÂ¬Ã‚Âreleasing intrauterine device. No studies in this comparison reported on quality of life. Satisfaction with treatment was similar to women using the combined vaginal ring, but there were no data to compare satisfaction between long cycle and LNGÃƒÂ¢Ã¢â€šÂ¬Ã‚ÂIUS or tranexamic acid. There was no evidence of a difference in the occurrence of headache, but long course oral progestogens were associated with a significantly lower incidence of breakthrough bleeding compared with other medical treatment. Quality of the evidence The quality of the evidence that compared oral progestogens (shor and long course) to other medical treatments for HMB was either low or very low which means that we are very uncertain of the findings of the review. The main limitations were risk of bias (women and researchers were aware of the treatment they were receiving which was likely to interfere with the responses, and there was a high number of dropouts from studies) and inconsistency (the results varied among studies)." | E22: FALSE | F22: Focuses on medical treatment, not NHS shifts. | G22: None | I22: 0.9
A23: J535 | B23: 2019 | C23: Interventions for prodromal stage of psychosis | D23: - Background Psychosis is a serious mental condition characterised by a loss of contact with reality. There may be a prodromal period or stage of psychosis, where early signs of symptoms indicating onset of first episode psychosis (FEP) occur. A number of services, incorporating multimodal treatment approaches (pharmacotherapy, psychotherapy and psychosocial interventions), developed worldwide, now focus on this prodromal period with the aim of preventing psychosis in people at risk of developing FEP. Objectives The primary objective is to assess the safety and efficacy of early interventions for people in the prodromal stage of psychosis. The secondary objective is, if possible, to compare the effectiveness of the various different interventions. Search methods We searched Cochrane Schizophrenia's studyÃƒÂ¢Ã¢â€šÂ¬Ã‚Âbased Register of studies (including trials registers) on 8 June 2016 and 4 August 2017. Selection criteria All randomised controlled trials (RCTs) evaluating interventions for participants older than 12 years, who had developed a prodromal stage of psychosis. Data collection and analysis Review authors independently inspected citations, selected studies, extracted data, and assessed study quality. Main results We included 20 studies with 2151 participants. The studies analysed 13 different comparisons. Group A comparisons explored the absolute effects of the experimental intervention. Group B were comparisons within which we could not be clear whether differential interactive effects were also ongoing. Group C comparisons explored differential effects between clearly distinct treatments. A key outcome for this review was ÃƒÂ¢Ã¢â€šÂ¬Ã‹Å“transition to psychosisÃƒÂ¢Ã¢â€šÂ¬Ã¢â€žÂ¢. For details of other main outcomes please see 'Summary of findings' tables. In Group A (comparisons of absolute effects) we found no clear difference between amino acids and placebo (risk ratio (RR) 0.48 95% confidence interval (CI) 0.08 to 2.98; 2 RCTs, 52 participants; very lowÃƒÂ¢Ã¢â€šÂ¬Ã‚Âquality evidence). When omegaÃƒÂ¢Ã¢â€šÂ¬Ã‚Â3 fatty acids were compared to placebo, fewer participants given the omegaÃƒÂ¢Ã¢â€šÂ¬Ã‚Â3 (10%) transitioned to psychosis compared to the placebo group (33%) during longÃƒÂ¢Ã¢â€šÂ¬Ã‚Âterm followÃƒÂ¢Ã¢â€šÂ¬Ã‚Âup of seven years (RR 0.24 95% CI 0.09 to 0.67; 1 RCT, 81 participants; lowÃƒÂ¢Ã¢â€šÂ¬Ã‚Âquality evidence). In Group B (comparisons where complex interactions are probable) and in the subgroup focusing on antipsychotic drugs added to specific care packages, the amisulpiride + needsÃƒÂ¢Ã¢â€šÂ¬Ã‚Âfocused intervention (NFI) compared to NFI comparison (no reporting of transition to psychosis; 1 RCT, 102 participants; very lowÃƒÂ¢Ã¢â€šÂ¬Ã‚Âquality evidence) and the olanzapine + supportive intervention compared to supportive intervention alone comparison (RR 0.58 95% CI 0.28 to 1.18; 1 RCT, 60 participants; very lowÃƒÂ¢Ã¢â€šÂ¬Ã‚Âquality evidence) showed no clear differences between groups. In the second Group B subgroup (cognitive behavioural therapies (CBT)), when CBT + supportive therapy was compared with supportive therapy alone around 8% of participants allocated to the combination of CBT and supportive therapy group transitioned to psychosis during followÃƒÂ¢Ã¢â€šÂ¬Ã‚Âup by 18 months, compared with double that percentage in the supportive therapy alone group (RR 0.45 95% CI 0.23 to 0.89; 2 RCTs, 252 participants; very lowÃƒÂ¢Ã¢â€šÂ¬Ã‚Âquality evidence). The CBT + risperidone versus CBT + placebo comparison identified no clear difference between treatments (RR 1.02 95% CI 0.39 to 2.67; 1 RCT, 87 participants; very lowÃƒÂ¢Ã¢â€šÂ¬Ã‚Âquality evidence) and this also applies to the CBT + needsÃƒÂ¢Ã¢â€šÂ¬Ã‚Âbased intervention (NBI) + risperidone versus NBI comparison (RR 0.75 95% CI 0.39 to 1.46; 1 RCT, 59 participants; very lowÃƒÂ¢Ã¢â€šÂ¬Ã‚Âquality evidence). Group C (differential effects) also involved six comparisons. The first compared CBT with supportive therapy. No clear difference was found for the ÃƒÂ¢Ã¢â€šÂ¬Ã‹Å“transition to psychosisÃƒÂ¢Ã¢â€šÂ¬Ã¢â€žÂ¢ outcome (RR 0.74 95% CI 0.28 to 1.98; 1 RCT, 72 participants; very lowÃƒÂ¢Ã¢â€šÂ¬Ã‚Âquality evidence). The second subgroup compared CBT + supportive intervention was compared with a NBI + supportive intervention, again, data were equivocal, few and of very low quality (RR 6.32 95% CI 0.34 to 117.09; 1 RCT, 57 participants). In the CBT + risperidone versus supportive therapy comparison, again there was no clear difference between groups (RR 0.76 95% CI 0.28 to 2.03; 1 RCT, 71 participants; very lowÃƒÂ¢Ã¢â€šÂ¬Ã‚Âquality evidence). The three other comparisons in Group C demonstrated no clear differences between treatment groups. When cognitive training was compared to active control (tablet games) (no reporting of transition to psychosis; 1 RCT, 62 participants; very low quality data), family treatment compared with enhanced care comparison (RR 0.54 95% CI 0.18 to 1.59; 2 RCTs, 229 participants; very lowÃƒÂ¢Ã¢â€šÂ¬Ã‚Âquality evidence) and integrated treatment compared to standard treatment comparison (RR 0.57 95% CI 0.28 to 1.15; 1 RCT, 79 participants; very lowÃƒÂ¢Ã¢â€šÂ¬Ã‚Âquality evidence) no effects of any of these approaches was evident. Authors' conclusions There has been considerable research effort in this area and several interventions have been trialled. The evidence available suggests that omegaÃƒÂ¢Ã¢â€šÂ¬Ã‚Â3 fatty acids may prevent transition to psychosis but this evidence is low quality and more research is needed to confirm this finding. Other comparisons did not show any clear differences in effect for preventing transition to psychosis but again, the quality of this evidence is very low or low and not strong enough to make firm conclusions. Plain language summary Early interventions for people at risk of developing psychosis Review question Is there highÃƒÂ¢Ã¢â€šÂ¬Ã‚Âquality evidence indicating that interventions for people at risk of developing psychosis are effective? Background Psychoses are serious mental conditions characterised by a loss of contact with reality. The first clear episode of psychosis can be preceded by a 'prodromal' period of at least six months, where a person experiences gradual nonÃƒÂ¢Ã¢â€šÂ¬Ã‚Âspecific changes in thoughts, perceptions, behaviours and functioning. Although an individual is experiencing changes, they have not yet started to experience the more obvious psychotic symptoms such as delusions (fixed false beliefs) or hallucinations (perceptions without a cause). A number of services with treatment approaches that combine pharmacotherapy, psychotherapy and psychosocial treatments, developed worldwide, are now focusing on prevention of psychosis in people at risk by giving treatments during this prodromal period. This review assesses the evidence available concerning the effects of different treatment approaches for people not yet diagnosed with a non affective psychosis but who are in the prodromal stage of psychosis. Searching for evidence On 8 June 2016 and 4 August 2017 we ran electronic searches of the Cochrane Schizophrenia's specialised register of studies in order to find clinical studies that randomly allocated individuals at risk of developing psychosis to receive various treatments for preventing development of psychosis. Evidence found We were able to include 20 studies with 2151 participants. These studies analysed a wide range of treatments. All the review findings are of, at very best, low quality. There is some suggestion from one small study that people at risk of psychosis may benefit from taking omegaÃƒÂ¢Ã¢â€šÂ¬Ã‚Â3 fatty acids in terms of reduced transition to psychosis. Other studies found adding antipsychotic drugs to supportiveÃƒÂ¢Ã¢â€šÂ¬Ã‚Âcare packages did not seem to make much difference in terms of transition to full illness. When cognitive behavioural therapy (CBT) + supportive therapy was compared with supportive therapy alone around 8% of participants treated allocated to the combination of CBT and supportive therapy transitioned to psychosis during followÃƒÂ¢Ã¢â€šÂ¬Ã‚Âup by 18 months, compared with double that percentage in people who just received supportive therapy. This could be important but these data are of very low quality. All other testing of CBT and other packages of care found no clear difference between treatments for transition to psychosis. Conclusions There has been considerable effort and expense invested testing treatment approaches for prevention of the first episode of schizophr nia. Currently, there is some lowÃƒÂ¢Ã¢â€šÂ¬Ã‚Âquality evidence suggesting that omegaÃƒÂ¢Ã¢â€šÂ¬Ã‚Â3 fatty acids may be effective, but there is no highÃƒÂ¢Ã¢â€šÂ¬Ã‚Âquality evidence to suggest that any type of treatment is effective, and no firm conclusions can be made. | E23: TRUE | F23: Focus on preventing psychosis aligns with prevention shift. | G23: Prevention | H23: Prevention | I23: 0.9
A24: J536 | B24: 2019 | C24: Context-Specific Economic Evaluation for Molecular Pathology Tests: An Application in Colorectal Cancer in the West of Scotland | D24: Objectives The cost-effectiveness of molecular pathology testing is highly context dependent. The field is fast-moving, and national health technology assessment may not be relevant or timely for local decision makers. This study illustrates a method of context-specific economic evaluation that can be carried out in a limited timescale without extensive resources.Methods We established a multi-disciplinary group including an oncologist, pathologists and a health economist. We set out diagnostic and treatment pathways and costs using registry data, health technology assessments, guidelines, audit data, and estimates from the group. Sensitivity analysis varied input parameters across plausible ranges. The evaluation setting was the West of Scotland and UK NHS perspective was adopted. The evaluation was assessed against the AdHopHTA checklist for hospital-based health technology assessment.Results A context-specific economic evaluation could be carried out on a timely basis using limited resources. The evaluation met all relevant criteria in the AdHopHTA checklist. Health outcomes were expected to be at least equal to the current strategy. Annual cost savings of 637,000 were estimated resulting primarily from a reduction in the proportion of patients receiving intravenous infusional chemotherapy regimens. The result was not sensitive to any parameter. The data driving the main cost saving came from a small clinical audit. We recommended this finding was confirmed in a larger population.Conclusions The method could be used to evaluate testing changes elsewhere. The results of the case study may be transferable to other jurisdictions where the organization of cancer services is fragmented. Copyright Ãƒâ€šÃ‚Â© 2019 Cambridge University Press. | E24: FALSE | F24: Focus on economic evaluation, not aligned with NHS shifts. | G24: None | I24: 0.9
A25: J537 | B25: 2019 | C25: Screening Women for Abdominal Aortic Aneurysms: Clinical and Economic Effectiveness Results from a Discrete Event Simulation Model | D25: Introduction - Abdominal aortic aneurysm (AAA) screening programmes have been established for men in several countries. Whether screening should be extended to women is uncertain. The objective of this study was to evaluate the cost-effectiveness of population screening for AAA in women, and compare a range of screening options. Methods - A discrete event simulation model was developed to provide a clinically realistic model of screening, surveillance, and elective and emergency AAA repair in women. Input parameters specifically for women were obtained from surgical registries, published literature and national administrative datasets. Screening was modelled for women aged 65 years or over. The model was run for 10-million women, with parameter uncertainty addressed by probabilistic and deterministic sensitivity analyses. UK costs in pounds sterling were converted to Euros based on 2016 average OECD purchasing power parity. Results - The prevalence of AAA (aortic diameter 33.0cm) was estimated as 0.43% in women aged 65 years and 1.15% at age 75. The corresponding attendance rates following invitation to screening were estimated as 73% and 62%. The base-case model adopted the same age at screening (65 years), definition of AAA (33.0cm), surveillance intervals (1 year for 3.0-4.4cm AAAs, 3 months for 4.5-5.4cm) and AAA diameter for consideration of surgery (5.5cm) as in the UK NHS AAA screening programmes. For screening at age 65, per woman invited to screening, the estimated gain in QALYs was 0.00075 (just under one day of life per woman screened), and the incremental cost was 33.51 (36.33) (all values discounted). This gave an incremental cost-effectiveness ratio (ICER) of 45,000 (48,782) per quality-adjusted life-year (QALY) gained (current UK threshold for implementation approximately 20,000 (21,681)). Under the base-case model around 2800 women would need to be invited to screening to prevent one death from AAA and screening would cost 100,000 (108,406) per death from AAA prevented (non-discounted). Sensitivity analyses did not bring the ICER below 20,000 per QALY gained, with the exception of doubling the AAA prevalence to 0.86% where the ICER was 18,000 (19,513). Alternative screening options (increasing the screening age to 70 years, lowering the threshold for considering surgery to 5.0 or 4.5cm, lowering the diameter defining an AAA in women to 2.5cm, and lengthening the surveillance intervals for the smallest AAAs) did not bring the ICER below 30,000 (32,522) per QALY gained when considered either singly or in combination. Conclusion - The current UK cost-effectiveness criteria for a population-based AAA screening programme in women are not currently met. Copyright Ãƒâ€šÃ‚Â© 2019 | E25: FALSE | F25: Focuses on screening effectiveness, not NHS Three Shifts. | G25: None | I25: 0.9
A26: J540 | B26: 2019 | C26: Conservative management following closed reduction of traumatic anterior dislocation of the shoulder | D26: - Background Acute anterior shoulder dislocation, which is the most common type of dislocation, usually results from an injury. Subsequently, the shoulder is less stable and is more susceptible to reÃƒÂ¢Ã¢â€šÂ¬Ã‚Âdislocation or recurrent instability (e.g. subluxation), especially in active young adults. After closed reduction, most of these injuries are treated with immobilisation of the injured arm in a sling or brace for a few weeks, followed by exercises. This is an update of a Cochrane Review first published in 2006 and last updated in 2014. Objectives To assess the effects (benefits and harms) of conservative interventions after closed reduction of traumatic anterior dislocation of the shoulder. These might include immobilisation, rehabilitative interventions or both. Search methods We searched the Cochrane Bone, Joint and Muscle Trauma Group Specialised Register, the Cochrane Central Register of Controlled Trials, MEDLINE, Embase, CINAHL, PEDro and trial registries. We also searched conference proceedings and reference lists of included studies. Date of last search: May 2018. Selection criteria We included randomised or quasiÃƒÂ¢Ã¢â€šÂ¬Ã‚Ârandomised controlled trials comparing conservative interventions with no treatment, a different intervention or a variant of the intervention (e.g. a different duration) for treating people after closed reduction of a primary traumatic anterior shoulder dislocation. Inclusion was regardless of age, sex or mechanism of injury. Primary outcomes were reÃƒÂ¢Ã¢â€šÂ¬Ã‚Âdislocation, patientÃƒÂ¢Ã¢â€šÂ¬Ã‚Âreported shoulder instability measures and return to preÃƒÂ¢Ã¢â€šÂ¬Ã‚Âinjury activities. Secondary outcomes included participant satisfaction, healthÃƒÂ¢Ã¢â€šÂ¬Ã‚Ârelated quality of life, any instability and adverse events. Data collection and analysis Both review authors independently selected studies, assessed risk of bias and extracted data. We contacted study authors for additional information. We pooled results of comparable groups of studies. We assessed risk of bias with the Cochrane 'Risk of bias' tool and the quality of the evidence with the GRADE approach. Main results We included seven trials (six randomised controlled trials and one quasiÃƒÂ¢Ã¢â€šÂ¬Ã‚Ârandomised controlled trial) with 704 participants; three of these trials (234 participants) are new to this update. The mean age across the trials was 29 years (range 12 to 90 years), and 82% of the participants were male. All trials compared immobilisation in external rotation (with or without an additional abduction component) versus internal rotation (the traditional method) following closed reduction. No trial evaluated any other interventions or comparisons, such as rehabilitation. All trials provided data for a followÃƒÂ¢Ã¢â€šÂ¬Ã‚Âup of one year or longer; the commonest length was two years or longer. All trials were at some risk of bias, commonly performance and detection biases given the lack of blinding. Two trials were at high risk of selection bias and some trials were affected by attrition bias for some outcomes. We rated the certainty of the evidence as very low for all outcomes. We are uncertain whether immobilisation in external rotation makes a difference to the risk of reÃƒÂ¢Ã¢â€šÂ¬Ã‚Âdislocation after 12 months' or longer followÃƒÂ¢Ã¢â€šÂ¬Ã‚Âup compared with immobilisation in internal rotation (55/245 versus 73/243; risk ratio (RR) 0.67, 95% confidence interval (CI) 0.38 to 1.19; 488 participants; 6 studies; IÃƒâ€šÃ‚Â² = 61%; very low certainty evidence). In a moderateÃƒÂ¢Ã¢â€šÂ¬Ã‚Ârisk population with an illustrative risk of 312 per 1000 people experiencing a dislocation in the internal rotation group, this equates to 103 fewer (95% CI 194 fewer to 60 more) reÃƒÂ¢Ã¢â€šÂ¬Ã‚Âdislocations after immobilisation in external rotation. Thus this result covers the possibility of a benefit for each intervention. Individually, the four studies (380 participants) reporting on validated patientÃƒÂ¢Ã¢â€šÂ¬Ã‚Âreported outcome measures for shoulder instability at a minimum of 12 months' followÃƒÂ¢Ã¢â€šÂ¬Ã‚Âup found no evidence of a clinically important difference between the two interventions. We are uncertain of the relative effects of the two methods of immobilisat on on resumption of preÃƒÂ¢Ã¢â€šÂ¬Ã‚Âinjury activities or sports. One study (169 participants) found no evidence of a difference between interventions in the return to preÃƒÂ¢Ã¢â€šÂ¬Ã‚Âinjury activity of the affected arm. Two studies (135 participants) found greater return to sports in the external rotation group in a subgroup of participants who had sustained their injury during sports activities. None of the trials reported on participant satisfaction or healthÃƒÂ¢Ã¢â€šÂ¬Ã‚Ârelated quality of life. We are uncertain whether there is a difference between the two interventions in the number of participants experiencing instability, defined as either reÃƒÂ¢Ã¢â€šÂ¬Ã‚Âdislocation or subluxation (RR 0.84, 95% CI 0.62 to 1.14; 395 participants, 3 studies; very low certainty evidence). Data on adverse events were collected only in an ad hoc way in the seven studies. Reported transient and resolved adverse events" were nine cases of shoulder stiffness or rigidity in the external rotation group and two cases of axillary rash in the internal rotation group. There were three "important" adverse events: hyperaesthesia and moderate hand pain; eighth cervical dermatome paraesthesia; and major movement restriction between 6 and 12 months. It was unclear to what extent these three events could be attributed to the treatment. Authors' conclusions The available evidence from randomised trials is limited to that comparing immobilisation in external versus internal rotation. Overall, the evidence is insufficient to draw firm conclusions about whether immobilisation in external rotation confers any benefit over immobilisation in internal rotation. Considering that there are several unpublished and ongoing trials evaluating immobilisation in external versus internal rotation, the main priority for research on this question consists of the publication of completed trials and the completion and publication of ongoing trials. Meanwhile, evaluation of other interventions, including rehabilitation, is warranted. There is a need for sufficiently large, goodÃƒÂ¢Ã¢â€šÂ¬Ã‚Âquality, wellÃƒÂ¢Ã¢â€šÂ¬Ã‚Âreported randomised controlled trials with longÃƒÂ¢Ã¢â€šÂ¬Ã‚Âterm followÃƒÂ¢Ã¢â€šÂ¬Ã‚Âup. Future research should aim to determine the optimal immobilisation duration, precise indications for immobilisation, optimal rehabilitation interventions, and the acceptability of these different interventions. Plain language summary NonÃƒÂ¢Ã¢â€šÂ¬Ã‚Âsurgical management after nonÃƒÂ¢Ã¢â€šÂ¬Ã‚Âsurgical repositioning of traumatic anterior dislocation of the shoulder Background Acute anterior shoulder dislocation is an injury in which the top end of the upper arm bone is pushed out of the joint socket in a forward direction. Afterwards, the shoulder is less stable, and prone to either partial or complete reÃƒÂ¢Ã¢â€šÂ¬Ã‚Âdislocation, especially in active young adults. Initial treatment involves putting the joint back in place. This is called ÃƒÂ¢Ã¢â€šÂ¬Ã‹Å“closed reductionÃƒÂ¢Ã¢â€šÂ¬Ã¢â€žÂ¢ when it is done without surgery. Subsequent treatment is often conservative (nonÃƒÂ¢Ã¢â€šÂ¬Ã‚Âsurgical) and usually involves a period of immobilisation of the injured arm in a sling or brace, followed by exercises. Review question What are the benefits and harms of different conservative interventions for treating people after closed reduction of a primary traumatic anterior shoulder dislocation? This is an update of a review that was first published in 2006 and last updated in 2014. We reviewed the evidence from clinical studies comparing any conservative intervention (e.g. immobilisation, rehabilitation) versus no treatment or a different intervention, or comparing different variants of an intervention (e.g. different duration). The primary outcomes of interest were reÃƒÂ¢Ã¢â€šÂ¬Ã‚Âdislocation, patientÃƒÂ¢Ã¢â€šÂ¬Ã‚Âreported shoulder instability measures (usually questionnaires) and return to preÃƒÂ¢Ã¢â€šÂ¬Ã‚Âinjury activities. Further outcomes of interest included patientsÃƒÂ¢Ã¢â€šÂ¬Ã¢â€žÂ¢ satisfaction with the intervention, healthÃƒÂ¢Ã¢â€šÂ¬Ã‚Ârelated quality of life and adverse events. Search date We conducted the searches of healthcare literature for this review in May 2018. Study characteristics We identified three new relevant studies in this update. In total, this review now includes seven studies with 704 participants. Most of the participants (82%) were male; the average age across the studies was 29 years (range 12 to 90 years). All of the studies investigated just one comparison: immobilisation in external rotation (when the arm is orientated outwards with the forearm away from the chest) versus immobilisation in internal rotation (the usual sling position, where the arm rests against the chest) following closed reduction. Participants were followed over different lengths of time; the most common duration was two years or longer. Key results We are uncertain whether immobilisation in external rotation makes a difference to the risk of reÃƒÂ¢Ã¢â€šÂ¬Ã‚Âdislocation at oneÃƒÂ¢Ã¢â€šÂ¬Ã‚Âyear or more followÃƒÂ¢Ã¢â€šÂ¬Ã‚Âup compared with immobilisation in internal rotation. None of the four studies reporting on patientÃƒÂ¢Ã¢â€šÂ¬Ã‚Âreported outcome measures for shoulder instability at a minimum of oneÃƒÂ¢Ã¢â€šÂ¬Ã‚Âyear followÃƒÂ¢Ã¢â€šÂ¬Ã‚Âup found evidence of any important difference between the two interventions. We are uncertain of the relative effects of the two methods of immobilisation on resumption of preÃƒÂ¢Ã¢â€šÂ¬Ã‚Âinjury activities or sports. One study found no evidence of a difference between interventions in the return to preÃƒÂ¢Ã¢â€šÂ¬Ã‚Âinjury activity of the affected arm. Two other studies found greater return to sports in the external rotation group in a small group of participants who had sustained their injury during sports activities. None of the trials reported on participant satisfaction or healthÃƒÂ¢Ã¢â€šÂ¬Ã‚Ârelated quality of life. We are uncertain whether there is a difference between the two interventions in the number of participants experiencing instability, defined as either reÃƒÂ¢Ã¢â€šÂ¬Ã‚Âdislocation or subluxation (a partial dislocation). The reporting of adverse events (complications) was unsatisfactory. There were reports of nine cases of shortÃƒÂ¢Ã¢â€šÂ¬Ã‚Âterm shoulder stiffness in the external rotation group and two cases of underÃƒÂ¢Ã¢â€šÂ¬Ã‚Âarm rash in the internal fixation group. There were three more serious adverse events: abnormal sensitivity and hand pain; abnormal sensation such as tingling in the little finger and along to the elbow; and major movement restriction. It was unclear to what extent these three adverse events could be attributed to the treatment. Certainty of the evidence We rated the certainty of the evidence as very low for all outcomes. This was mainly because there were not enough data and we were unsure how reliable the results were from the individual studies. Thus we are uncertain about the estimates of effect. Conclusions Overall, the current evidence is insufficient to inform the choice of immobilisation in external versus internal rotation. There is no evidence to inform on any other conservative interventions following closed reduction of traumatic anterior dislocation of the shoulder." | E26: FALSE | F26: Focuses on treatment post-injury, not on NHS shifts. | G26: None | I26: 1
A27: J541 | B27: 2019 | C27: Surgical treatments for women with stress urinary incontinence: the ESTER systematic review and economic evaluation | D27: <b>BACKGROUND</b>: Urinary incontinence in women is a distressing condition that restricts quality of life and results in a large economic burden to both the NHS and women themselves._x000D_ <b>OBJECTIVE</b>: To evaluate the clinical effectiveness, safety and cost-effectiveness of surgical treatment for stress urinary incontinence (SUI) in women and explore women's preferences._x000D_ <b>DESIGN</b>: An evidence synthesis, a discrete choice experiment (DCE) and an economic decision model, with a value-of-information (VOI) analysis. Nine surgical interventions were compared. Previous Cochrane reviews for each were identified and updated to include additional studies. Systematic review methods were applied. The outcomes of interest were 'cure' and 'improvement'. Both a pairwise and a network meta-analysis (NMA) were conducted for all available surgical comparisons. A DCE was undertaken to assess the preferences of women for treatment outcomes. An economic model assessed the cost-effectiveness of alternative surgeries and a VOI analysis was undertaken._x000D_ <b>RESULTS</b>: Data from 175 studies were included in the effectiveness review. The majority of included studies were rated as being at high or unclear risk of bias across all risk-of-bias domains. The NMA, which included 120 studies that reported data on 'cure' or 'improvement', showed that retropubic mid-urethral sling (MUS), transobturator MUS, traditional sling and open colposuspension were more effective than other surgical procedures for both primary outcomes. The results for other interventions were variable. In general, rate of tape and mesh exposure was higher after transobturator MUS than after retropubic MUS or single-incision sling, whereas the rate of tape or mesh erosion/extrusion was similar between transobturator MUS and retropubic MUS. The results of the DCE, in which 789 women completed an anonymous online questionnaire, indicate that women tend to prefer surgical treatments associated with no pain or mild chronic pain and shorter length of hospital stay as well as those treatments that have a smaller risk for urinary symptoms to reoccur after surgery. The cost-effectiveness results suggest that, over a lifetime, retropubic MUS is, on average, the least costly and most effective surgery. However, the high level of uncertainty makes robust estimates difficult to ascertain. The VOI analysis highlighted that further research around the incidence rates of complications would be of most value._x000D_ <b>LIMITATIONS</b>: Overall, the quality of the clinical evidence was low, with limited data available for the assessment of complications. Furthermore, there is a lack of robust evidence and significant uncertainty around some parameters in the economic modelling._x000D_ <b>CONCLUSIONS</b>: To our knowledge, this is the most comprehensive assessment of published evidence for the treatment of SUI. There is some evidence that retropubic MUS, transobturator MUS and traditional sling are effective in the short to medium term and that retropubic MUS is cost-effective in the medium to long term. The VOI analysis highlights the value of further research to reduce the uncertainty around the incidence rates of complications. There is a need to obtain robust clinical data in future work, particularly around long-term complication rates._x000D_ <b>STUDY REGISTRATION</b>: This study is registered as PROSPERO CRD42016049339._x000D_ <b>FUNDING</b>: The National Institute for Health Research Health Technology Assessment programme. | E27: FALSE | F27: Focuses on surgical treatment evaluation, not aligned with NHS shifts. | G27: None | I27: 0.9
A28: J544 | B28: 2019 | C28: PRIMEtime CE: a multistate life table model for estimating the cost-effectiveness of interventions affecting diet and physical activity | D28: BACKGROUND: Non-communicable diseases are the leading cause of death in England, and poor diet and physical inactivity are two of the principle behavioural risk factors. In the context of increasingly constrained financial resources, decision makers in England need to be able to compare the potential costs and health outcomes of different public health policies aimed at improving these risk factors in order to know where to invest so that they can maximise population health. This paper describes PRIMEtime CE, a multistate life table cost-effectiveness model that can directly compare interventions affecting multiple disease outcomes. METHOD(S): The multistate life table model, PRIMEtime Cost Effectiveness (PRIMEtime CE), is developed from the Preventable Risk Integrated ModEl (PRIME) and the PRIMEtime model. PRIMEtime CE uses routinely available data to estimate how changing diet and physical activity in England affects morbidity and mortality from heart disease, stroke, diabetes, liver disease, and cancers either directly or via raised blood pressure, cholesterol, and body weight. RESULT(S): Model outcomes are change in quality adjusted life years, and change in English National Health Service and social care costs. CONCLUSION(S): This paper describes PRIMEtime CE and highlights its main strengths and limitations. The model can be used to compare any number of public policies affecting diet and physical activity, allowing decision makers to understand how they can maximise population health with limited financial resources. | E28: TRUE | F28: Focus on preventive models for diet and physical activity. | G28: Prevention | H28: Prevention | I28: 0.9
A29: J545 | B29: 2019 | C29: Estimating the cost-effectiveness of salt reformulation and increasing access to leisure centres in England, with PRIMEtime CE model validation using the AdViSHE tool | D29: BACKGROUND: PRIMEtime CE is a multistate life table model that can directly compare the cost effectiveness of public health interventions affecting diet and physical activity levels, helping to inform decisions about how to spend finite resources. This paper estimates the costs and health outcomes in England of two scenarios: reformulating salt and expanding subsidised access to leisure centres. The results are used to help validate PRIMEtime CE, following the steps outlined in the Assessment of the Validation Status of Health-Economic decision models (AdViSHE) tool. METHOD(S): The PRIMEtime CE model estimates the difference in quality adjusted life years (QALYs) and difference in NHS and social care costs of modelled interventions compared with doing nothing. The salt reformulation scenario models how salt consumption would change if food producers met the 2017 UK Food Standards Agency salt reformulation targets. The leisure centre scenario models change in physical activity levels if the Birmingham Be Active scheme (where swimming pools and gym access is free to residents during defined periods) was rolled out across England. The AdViSHE tool was developed by health economic modellers and divides model validation into five parts: validation of the conceptual model, input data validation, validation of computerised model, operational validation, and other validation techniques. PRIMEtime CE is discussed in relation to each part. RESULT(S): Salt reformulation was dominant compared with doing nothing, and had a 10-year return on investment of 1.44 (0.50 to 2.94) for every 1 spent. By contrast, over 10 years the Be Active expansion would cost 727,000 (514,000 to 1,064,000) per QALY. PRIMEtime CE has good face validity of its conceptual model and has robust input data. Cross-validation produces mixed results and shows the impact of model scope, input parameters, and model structure on cost-per-QALY estimates. CONCLUSION(S): This paper illustrates how PRIMEtime CE can be used to compare the cost-effectiveness of two different public health measures affecting diet and physical activity levels. The AdViSHE tool helps to validate PRIMEtime CE, identifies some of the key drivers of model estimates, and highlights the challenges of externally validating public health economic models against independent data. | E29: TRUE | F29: Focus on prevention through diet and physical activity interventions. | G29: Prevention | H29: Prevention | I29: 0.9
A30: J547 | B30: 2019 | C30: Individualised screening for diabetic retinopathy: The ISDR study-a randomised controlled trial of safety, efficacy, and cost-effectiveness | D30: Background: Varying the intervals in retinopathy screening informed by personal risk offers reallocation of resources to better target high risk groups and address the increasing prevalence of diabetes. However, safety data especially on extended intervals is minimal. Aim(s): To evaluate the safety, efficacy and cost effectiveness (CE) of individualized variable-interval risk-based screening in a population setting compared to usual care. Method(s): Masked 2 arm, parallel assignment, equivalence RCT (largest to date in screening) with independent trials unit monitoring in people with diabetes aged >=12 years attending screening in a single English program. Randomization was 1:1 to individualized screening (active group; 6, 12 or 24 months for high, medium and low risk) determined by a risk calculation engine using real-time local demographic, retinal and clinical data, compared with annual screening (control). CE analysis measuring NHS and societal costs took a 2-year time horizon. Finding(s): 4534 participants entered the study-after withdrawals/loss to follow-up: active 2097; control 2224. Attendance rates at first follow-up visit (primary outcome, safety) were equivalent (per protocol analysis, 5% margin): active 83.6% control 84.7% (difference 1.0, 90% CI-0.8, 2.9). STDR detection rates were non-inferior (1.5% margin): active 1.43% control 1.71% (difference-0.28, CI-0.93, 0.36). Quality of life (EQ5D5L, HUI3) was not significantly different between the groups. Incremental cost saving per person was 18.75 (NHS cost) rising to 49.96 with societal costs. A 39.3% reduction in number of appointments was seen. Conclusion(s): All parties involved in diabetes care can be reassured that extended and personalized screening intervals can safely be introduced in established screening program. Scale-up with further validation outside a research setting is recommended. Views expressed are solely those of the authors. | E30: TRUE | F30: Personalised screening intervals focus on prevention by targeting high-risk groups. | G30: Prevention | H30: Prevention | I30: 0.9
A31: J549 | B31: 2019 | C31: Assessing the early impact of enhanced NHS england (NHSE) funding on footcare services | D31: Background: A key aim of the National Diabetes Treatment and Care Programme is to improve footcare services. In Sheffield, this investment was used primarily to expand the foot protection team (FPT) and in prevention strategies. Aim(s): To assess if there has been a benefit for patients and if the spending has been cost-effective. Method(s): Ulcer severity in patients presenting to the Multi-Disciplinary Foot Team (MDFT) (SINBAD score >3 = severe, <3 = mild) was tracked between 2013 and 2018, to determine whether the proportion of severe ulcers had declined. Cost calculations were based on the 'Economic Case for Change' paper (Marion Kerr, 2017); weekly cost of a mild ulcer-77, severe ulcer-359. Result(s): The percentage of ulcers presenting as severe from 2013-2017 (prior to additional investment) was 27%, 32%, 43%, 47% and 46% respectively. In 2018, to date, this has fallen to 36%. Our mean healing time for a mild ulcer is 12.6 weeks (974) vs a severe ulcer at 16.3 weeks (5,847). This represents an approximate reduction in the costs of managing foot ulcers from 326,000/100 patients (pre-investment) to 273,000/100 patients (post-investment), a saving of 53,000/100 patients. Approximately 500 patients with new ulcers are seen by our MDFT each year, giving a total estimated saving of 268,000. If the percentage of severe ulcers returned to the baseline of 2013 (27%), savings would total around 487,000/100 patients. Conclusion(s): These data show that, within a very short timescale, the enhanced NHSE funding and added investment in prevention strategies reduced severe ulcers, giving patients' better quality of life, shorter healing times, and is cost-effective. | E31: TRUE | F31: Focus on prevention strategies for foot ulcers. | G31: Prevention | H31: Prevention | I31: 0.9
A32: J551 | B32: 2019 | C32: Cost effectiveness of letermovir as prophylaxis of clinically significant cytomegalovirus reactivation and disease in adult CMV-seropositive allogeneic haematopoietic stem cell transplant: A Scottish payer perspective | D32: Background: Data from a recent phase III clinical trial has demonstrated the efficacy of letermovir as prophylaxis against CMV reactivation in adult CMV-seropositive recipients of an allogeneic haematopoietic stem-cell transplant (HSCT). The objective of this cost-effectiveness analysis is to evaluate the clinical and economic value of letermovir when compared to pre-emptive treatment from the payer perspective in Scotland. Method(s): A decision-analytic model evaluated total costs and lifetime quality-adjusted life-years (QALY's) from the perspective of the National Health Service (NHS) and social work in Scotland. Efficacy data, including rates of preemptive therapy for CMV infection, CMV disease, rehospitalization, mortality, and quality of life were incorporated from clinical trial data at 24 weeks posttransplant. The primary endpoint of the trial was clinically significant CMV-infection at week 24 post-transplant. Costs of preemptive treatment, CMV disease, and other trial outcomes were obtained from published sources. Life-years during the first 24 weeks were estimated from the mortality observed in the clinical trial. Life-years post 24 weeks were estimated for the week 24 survivors by applying a relative risk of death for HSCT to the general mortality risk from the life tables for Scotland (2014-16). Utility values were applied based on EQ-5D data collected in the clinical trial and longer-term data from published sources. The annual cost to treat 1-year survivors was based on a proportion of patients receiving 2 years of immunosuppressive agent treatment for chronic graft-versus-host disease (onset 100 days after transplant). Sensitivity analysis explored the impact of including data from the extended follow-up period, where various endpoints were collected through 48 weeks post-transplant. The model used an annual discount rate of 3.5%. Result(s): In the base-case analysis, letermovir reduced the number CMV infections requiring pre-emptive treatment vs standard of care (SoC) (20.0% vs 49.3%) at 24 weeks posttransplant. Prophylaxis with letermovir resulted in lower allcause mortality at week 24 in comparison to SoC (10.2% vs. 15.9%), and a mean increase in life-years (+0.46), QALY's (+0.41) and total costs up to week 24 post-HSCT per patient. This resulted in an incremental costeffectiveness ratio (ICER) of 12,659 per QALY gained. The sensitivity analysis using data from 48 weeks posttransplant did not have a significant effect on the results. Results of a probabilistic sensitivity analysis indicated that letermovir was cost effective in 77.4% of iterations at 20,000 per QALY gained and 87.6% of iterations at 30,000 per QALY gained. Conclusion(s): The results of this model would suggest that the prophylaxis use of letermovir is a cost-effective treatment strategy at commonly accepted ICER thresholds. The model inputs with a greatest impact on the results were a reduction in the rate of mortality, increasing the age of patients treated with letermovir, and an increase in the cost of prophylaxis for letermovir. | E32: FALSE | F32: Focuses on cost-effectiveness of a drug, not NHS shifts. | G32: None | I32: 0.9
A33: J552 | B33: 2019 | C33: PharmacyÃƒÂ¢Ã¢â€šÂ¬Ã‚Âbased management for depression in adults | D33: - Background It is common for people not to take antidepressant medication as prescribed, with around 50% of people likely to prematurely discontinue taking their medication after six months. Community pharmacists may be well placed to have a role in antidepressant management because of their unique pharmacotherapeutic knowledge and ease of access for people. Pharmacists are in an ideal position to offer proactive interventions to people with depression or depressive symptoms. However, the effectiveness and acceptability of existing pharmacistÃƒÂ¢Ã¢â€šÂ¬Ã‚Âbased interventions is not yet well understood. The degree to which a pharmacyÃƒÂ¢Ã¢â€šÂ¬Ã‚Âbased management approach might be beneficial, acceptable to people, and effective as part of the overall management for those with depression is, to date, unclear. A systematic review of randomised controlled trials (RCTs) will help answer these questions and add important knowledge to the currently sparse evidence base. Objectives To examine the effects of pharmacyÃƒÂ¢Ã¢â€šÂ¬Ã‚Âbased management interventions compared with active control (e.g. patient information materials or any other active intervention delivered by someone other than the pharmacist or the pharmacy team), waiting list, or treatment as usual (e.g. standard pharmacist advice or antidepressant education, signposting to support available in primary care services, brief medication counselling, and/or (selfÃƒÂ¢Ã¢â€šÂ¬Ã‚Â)monitoring of medication adherence offered by a healthcare professional outside the pharmacy team) at improving depression outcomes in adults. Search methods We searched the Cochrane Common Mental Disorders Controlled Trials Register (CCMDÃƒÂ¢Ã¢â€šÂ¬Ã‚ÂCTR) to June 2016; the Cochrane Library (Issue 11, 2018); and Ovid MEDLINE, Embase, and PsycINFO to December 2018. We searched theses and dissertation databases and international trial registers for unpublished/ongoing trials. We applied no restrictions on date, language, or publication status to the searches. Selection criteria We included all RCTs and clusterÃƒÂ¢Ã¢â€šÂ¬Ã‚ÂRCTs where a pharmacyÃƒÂ¢Ã¢â€šÂ¬Ã‚Âbased intervention was compared with treatment as usual, waiting list, or an alternative intervention in the management of depression in adults over 16 years of age. Eligible studies had to report at least one of the following outcomes at any time point: depression symptom change, acceptability of the intervention, diagnosis of depression, nonÃƒÂ¢Ã¢â€šÂ¬Ã‚Âadherence to medication, frequency of primary care appointments, quality of life, social functioning, or adverse events. Data collection and analysis Two authors independently, and in duplicate, conducted all stages of study selection, data extraction, and quality assessment (including GRADE). We discussed disagreements within the team until we reached consensus. Where data did not allow metaÃƒÂ¢Ã¢â€šÂ¬Ã‚Âanalyses, we synthesised results narratively. Main results Twelve studies (2215 participants) met the inclusion criteria and compared pharmacyÃƒÂ¢Ã¢â€šÂ¬Ã‚Âbased management with treatment as usual. Two studies (291 participants) also included an active control (both used patient information leaflets providing information about the prescribed antidepressant). Neither of these studies reported depression symptom change. A narrative synthesis of results on acceptability of the intervention was inconclusive, with one study reporting better acceptability of pharmacyÃƒÂ¢Ã¢â€šÂ¬Ã‚Âbased management and the other better acceptability of the active control. One study reported that participants in the pharmacyÃƒÂ¢Ã¢â€šÂ¬Ã‚Âbased management group had better medication adherence than the control participants. One study reported adverse events with no difference between groups. The studies reported no other outcomes. MetaÃƒÂ¢Ã¢â€šÂ¬Ã‚Âanalyses comparing pharmacyÃƒÂ¢Ã¢â€šÂ¬Ã‚Âbased management with treatment as usual showed no evidence of a difference in the effect of the intervention on depression symptom change (dichotomous data; improvement in symptoms yes/no: risk ratio (RR), 0.95, 95% confidence interval (CI) 0.86 to 1.05; 4 RCTs, 475 participants; moderateÃƒÂ¢Ã¢â€šÂ¬Ã‚Âquality evidence; continuous data: standard mean difference (SMD) ÃƒÂ¢Ã¢â€šÂ¬Ã‚Â0.04, 95% | E33: TRUE | F33: Community pharmacy managing depression aligns with Community shift. | G33: Community | H33: Community | I33: 0.9
A34: J554 | B34: 2019 | C34: Early supported discharge for patients with febrile neutropenia - experience at a large district hospital in the UK | D34: Neutropenic sepsis can be life threatening, with mortality 2-21%. The heterogeneity of patients referred with suspected neutropenic sepsis" has led to strategies being developed to risk-stratify patients and identify those with a low risk of septic complications that could be managed in the outpatient setting, such as The Multinational Association for Supportive Care in Cancer score (MASCC). Outcomes for patients referred with suspected neutropenic sepsis were assessed before and after use of MASCC guided early-supported discharge. 50/123 (41%) patients over 24 months were eligible for early-supported discharge. 26/50 patients had same-day discharge, 14 had overnight admission, 8 stayed 2 nights and 2 stayed 3 nights. Patients received on average 2 follow-up telephone consultations. There were 5 readmissions (10%) and no adverse events. In comparison group; 8 patients over 3-months would have been suitable, potentially saving 40 bed-days. This shows MASCC guided early-supported discharge is safe and cost-effective. Copyright Ãƒâ€šÃ‚Â© 2019 Rila Publications Ltd." | E34: TRUE | F34: Early-supported discharge shifts care from hospital to community. | G34: Community | H34: Community | I34: 0.9
A35: J555 | B35: 2019 | C35: Should we all be looking for marginal gains in endoscopy efficiency? | D35: Introduction Demand for endoscopy in the UK has doubled in the last 5 years. In 2017, 64% of units failed to meet suspected cancer targets despite 66% of units having weekend lists and 27% outsourcing to external providers1. UCL Cancer Collaborative (UCLCC) data showed demand can be met by improving efficiency. This is important in a resource-limited setting. Our Quality Improvement (QI) Project aimed to improve efficiency by improving turnaround time, non-attendance and on-the-day cancellations. Methods The Endoscopy QI fellow, endoscopy unit manager and Gastroenterology service manager participated in the UCLCC Improvement Programme, and utilised QI methodology. We collected data from electronic patient records and scheduling system. At baseline, we identified that underutilisation of lists was multifactorial. We introduced a turnaround nurse role to consent patients. Healthcare assistants (HCAS) and nurses were trained in cannulation. As poor bowel preparation contributed to cancellations, we introduced telephone pre-assessment to educate patients. Finally, the administrative team sent text reminders before appointments. Results At baseline, our unit performed an average of 7.9 points per list, out of a planned 10. On average, 28.5 patients per month had procedures cancelled on the day due to poor bowel prep or inadequate fasting. After the introduction of pre-assessment, it improved to 23.5 per month, saving 5 procedures which would have had to be rearranged. The average points performed improved to 9.3 points per list. The average DNA rate has improved from 9% to 7% after the introduction of text reminders. After the introduction of the turnaround nurse and HCA cannulation, turnaround time reduced from an average of 18 to 9 minutes between procedures. This could save 90 minutes over a 12-point list. Despite these improvements, only 41.6% of lists are booked for 1-2 points. Inadequate staffing numbers and late start times are contributing factors. A start time audit showed that only 5 out of 27 lists in a week started within 10 minutes of supposed start times, a target for further cycles of this QI project. Conclusions Multiple small improvements in efficiency can achieve significant impact on productivity. Interventions focused on turnaround time can reduce underuse of list time. Patient-centred approaches to procedural preparation may reduce squandered appointments. Sustainability of these improvements is difficult to assess in the short term but will be promoted by the continuing QI fellow role and implementation of endoscopy QI champions from the administrative and nursing team. | E35: FALSE | F35: Focuses on efficiency, not on NHS Three Shifts. | G35: None | I35: 0.9
A36: J556 | B36: 2019 | C36: Low Back and Radicular Pain Including Symptomatic Spinal Stenosis | D36: Back pain is the largest single cause of disability in the UK, with lower back pain alone accounting for 11% of the total disability of the UK population. Currently there is enormous geographical variation in the pathways, costs and outcomes of patients with back pain. Despite existing evidence there are a significant number of treatments with low clinical value still in use. The NHS England Trauma Programme of Care Board selected Low Back Pain and Radicular Pain as a pathfinder project in 2013. A clinical group of 30 stakeholder representatives worked collaboratively to produce an agreed, seamless pathway, extending from first contact in primary care through to secondary care and specialist services. This pathway was updated in 2017 following the publication of NICE NG59 and is endorsed in the 2019 GIRFT report. The National Back and Radicular Pain Pathway (NBRPP) is recognised as the commissioning pathway of choice for CCG's. Implementation of the NBRPP is currently being driven through Right Care and GIRFT. National Back and Radicular Pain Pathway. Where implemented, evaluation of the pathway provides evidence that the NBRPP results in substantial cost saving through reducing; admissions for back pain (with or without radicular pain), therapeutic injections for back pain, readmissions and spinal fusions for back pain. This session will use case studies to explore the recommended pathway of care for people with: * Back pain who are at risk of persisting disability * Severe radicular pain, best managed with injection or surgery * Symptomatic spinal stenosis which can be managed conservatively.. | E36: TRUE | F36: Pathway integrates primary and secondary care, reducing hospital admissions. | G36: Community | H36: Community | I36: 0.9
A37: J557 | B37: 2019 | C37: Pns408 How Is the English Nhs Prescription Drugs Budget Spent | D37: Objectives: In Financial Year (FY) 2018/19, NHS England (NHSE) spent 7.9 billion on prescription drugs prescribed by GPs to their patients. This is 2.7% less than FY 2017/18. This study investigated drivers of this trend at regional and drug-class levels on a risk-adjusted basis and projected the results over a five year time period. Method(s): Publicly available data was used. Prescription drug and population data published by the NHS were used to derive the per person per month costs. The prescription drug risk-adjustment factors were based on those used in the NHS funding allocation formula. Prescription drug cost and activity trends were analysed at a drug-class (BNF chapter) and regional level. Regions were defined by sustainability and transformation plan (STP) area. Risk-adjustment helped determine what cost we would 'expect' based on each STP's risk profile compared to the English average. Costs were projected over a five-year period under various scenarios, using expected changes in population size and structure published by the NHS. Result(s): The reduction in expenditure is driven by a combination of lower average costs (3.83% decrease) and lower levels of activity (0.92% decrease). These decreases in total cost are slightly offset by the 1.19% increase in the English population size. The research highlights particular BNF chapters and STP regions that are driving these trends as well as how STP regions' experience compares to the English average on a risk-adjusted basis. The projection model shows that prescription drug costs can be expected to decrease by 3.6% p.a. over the next five years if historical trends persist. Conclusion(s): The insights provided by this research can help stakeholders with experience analysis and planning by identifying cost and activity drivers on a population risk-adjusted basis as well as having a view of how demand may develop over the projection period. Copyright Ãƒâ€šÃ‚Â© 2019 | E37: FALSE | F37: Focuses on prescription drug spending trends, not NHS Three Shifts. | G37: None | I37: 0.9
A38: J558 | B38: 2019 | C38: Conservative interventions for treating functional daytime urinary incontinence in children | D38: - Background In children, functional daytime urinary incontinence is the term used to describe any leakage of urine while awake that is not the result of a known underlying neurological or congenital anatomic cause (such as conditions or injuries that affect the nerves that control the bladder or problems with the way the urinary system is formed). It can result in practical difficulties for both the child and their family and can have detrimental effects on a childÃƒÂ¢Ã¢â€šÂ¬Ã¢â€žÂ¢s wellÃƒÂ¢Ã¢â€šÂ¬Ã‚Âbeing, education and social engagement. Objectives To assess the effects of conservative interventions for treating functional daytime urinary incontinence in children. Search methods We searched the Cochrane Incontinence Specialised Register, which contains studies identified from CENTRAL, MEDLINE, MEDLINE InÃƒÂ¢Ã¢â€šÂ¬Ã‚ÂProcess, MEDLINE Epub Ahead of Print, CINAHL, ClinicalTrials.gov, WHO ICTRP and handsearching of journals and conference proceedings (searched 11 September 2018). We also searched Chinese language bibliographic databases: Chinese Biomedical Literature Database (CBM), China National Knowledge Infrastructure (CNKI), and Wanfang. No language restrictions were imposed. Selection criteria We included randomised controlled trials (RCTs), quasiÃƒÂ¢Ã¢â€šÂ¬Ã‚Ârandomised, multiÃƒÂ¢Ã¢â€šÂ¬Ã‚Âarm studies, crossÃƒÂ¢Ã¢â€šÂ¬Ã‚Âover studies and clusterÃƒÂ¢Ã¢â€šÂ¬Ã‚Ârandomised studies that included children aged between 5 and 18 years with functional daytime urinary incontinence. Data collection and analysis Two review authors independently screened records and determined the eligibility of studies for inclusion according to predefined criteria. Where data from the study were not provided, we contacted the study authors to request further information. Two review authors assessed risk of bias and processed included study data as described in the Cochrane Handbook for Systematic Reviews of Interventions . Where metaÃƒÂ¢Ã¢â€šÂ¬Ã‚Âanalysis was possible, we applied randomÃƒÂ¢Ã¢â€šÂ¬Ã‚Âeffects metaÃƒÂ¢Ã¢â€šÂ¬Ã‚Âanalysis using the MantelÃƒÂ¢Ã¢â€šÂ¬Ã‚ÂHaenszel method for dichotomous outcomes. Main results The review included 27 RCTs involving 1803 children. Of these, six were multiÃƒÂ¢Ã¢â€šÂ¬Ã‚Âarm and one was also a crossÃƒÂ¢Ã¢â€šÂ¬Ã‚Âover study. Most studies were small, with numbers randomised ranging from 16 to 202. A total of 19 studies were at high risk of bias for at least one domain. Few studies reported data suitable for pooling due to heterogeneity in interventions, outcomes and measurements. Individual conservative interventions (lifestyle, behavioural or physical) versus no treatment Transcutaneous electrical nerve stimulation (TENS) versus sham (placebo) TENS. M ore children receiving active TENS may achieve continence (risk ratio (RR) 4.89, 95% confidence interval (CI) 1.68 to 14.21; 3 studies; n = 93; lowÃƒÂ¢Ã¢â€šÂ¬Ã‚Âcertainty evidence). One individual conservative intervention versus another individual or combined conservative intervention Pelvic floor muscle training (PFMT) with urotherapy versus urotherapy alone. We are uncertain whether more children receiving PFMT with urotherapy achieve continence (RR 2.36, 95% CI 0.65 to 8.53, 95% CI 25 to 100; 3 studies; n = 91; very lowÃƒÂ¢Ã¢â€šÂ¬Ã‚Âcertainty evidence). Voiding education with uroflowmetry feedback and urotherapy versus urotherapy alone. Slightly more children receiving voiding education with uroflow feedback and urotherapy may achieve continence (RR 1.13, 95% CI 0.87 to 1.45; 3 studies; n = 151; lowÃƒÂ¢Ã¢â€šÂ¬Ã‚Âcertainty evidence). Urotherapy with timer watch versus urotherapy alone. We are uncertain whether urotherapy plus timer watch increases the number of children achieving continence compared to urotherapy alone (RR 1.42, 95% CI 1.12 to 1.80; 1 study; n = 58; very lowÃƒÂ¢Ã¢â€šÂ¬Ã‚Âcertainty evidence). Combined conservative interventions versus other combined conservative interventions TENS and standard urotherapy versus PFMT with electromyographic biofeedback and standard urotherapy. We are uncertain whether there is any evidence of a difference between treatment groups in the proportions of children achieving continence (RR 1.11, 95% CI 0.73 to 1.68; 1 study; n = 78; very lowÃƒÂ¢Ã¢â€šÂ¬Ã‚Âcertainty evidence). PFMT with electr myography biofeedback and standard urotherapy versus PFMT without feedback but with standard urotherapy. We are uncertain whether there is any evidence of a difference between treatment groups in the proportions of children achieving continence (RR 1.05, 95% CI 0.72 to 1.52; 1 study; n = 41; very lowÃƒÂ¢Ã¢â€šÂ¬Ã‚Âcertainty evidence). Individual conservative interventions versus nonÃƒÂ¢Ã¢â€šÂ¬Ã‚Âconservative interventions (pharmacological or invasive, combined or not with any conservative interventions) PFMT versus anticholinergics. We are uncertain whether more children receiving PFMT than anticholinergics achieve continence (RR 1.92, 95% CI 1.17 to 3.15; equivalent to an increase from 33 to 64 per 100 children; 2 studies; n = 86; very lowÃƒÂ¢Ã¢â€šÂ¬Ã‚Âcertainty evidence). TENS versus anticholinergics. We are uncertain whether there was any evidence of a difference between treatment groups in the proportions of children achieving continence (RR 0.81, 95% CI 0.05 to 12.50; 2 studies; n = 72; very lowÃƒÂ¢Ã¢â€šÂ¬Ã‚Âcertainty evidence). Combined conservative interventions versus nonÃƒÂ¢Ã¢â€šÂ¬Ã‚Âconservative interventions (pharmacological or invasive, combined or not with any conservative interventions) Voiding education with uroflowmetry feedback versus anticholinergics. We are uncertain whether there was any evidence of a difference between treatment groups in the proportion of children achieving continence (RR 1.02, 95% CI 0.58 to 1.78; 1 study; n = 64; very lowÃƒÂ¢Ã¢â€šÂ¬Ã‚Âcertainty evidence). Authors' conclusions The review found little reliable evidence that can help affected children, their carers and the clinicians working with them to make evidenceÃƒÂ¢Ã¢â€šÂ¬Ã‚Âbased treatment decisions. In this scenario, the clinical experience of individual clinicians and the support of carers may be the most valuable resources. More wellÃƒÂ¢Ã¢â€šÂ¬Ã‚Âdesigned research, with wellÃƒÂ¢Ã¢â€šÂ¬Ã‚Âdefined interventions and consistent outcome measurement, is needed. Plain language summary Conservative (nonÃƒÂ¢Ã¢â€šÂ¬Ã‚Âpharmaceutical and nonÃƒÂ¢Ã¢â€šÂ¬Ã‚Âsurgical) treatments for children who have daytime urinary incontinence Background Many children continue to have daytime wetting accidents (urinary incontinence) long after most become dry, some into teenage years. When there is no known cause, it is referred to as functional daytime urinary incontinence. Daytime wetting can be a practical problem for the child and their carers, leading to additional laundry, expenses on absorbent pads or underwear, wet or stained furnishings and difficulties attending school or travelling. It can also lead to emotional stress, poor school attendance and performance, difficulties with social activities and making friends, and even depression and behaviour problems. Finding an effective treatment can improve the quality of life of children and their carers. Review question Children, their carers, doctors and nurses may want to avoid treatments that involve drugs or surgery, at least until they have tried treatments that do not involve these. In this review researchers brought together the results of studies conducted around the world to combine the evidence and assess which treatment(s) are most effective for managing daytime urinary incontinence in children. How upÃƒÂ¢Ã¢â€šÂ¬Ã‚ÂtoÃƒÂ¢Ã¢â€šÂ¬Ã‚Âdate is this review? The evidence is current to 11 September 2018. Study characteristics and funding sources The review identified 27 studies involving 1803 children. Twelve studies declared funding from outside sources. One of these was funded by Astellas Pharma, while another study was provided with special batches of placebo and medication free of charge, as well as materials for pad tests free of charge from another company. Certainty of evidence Cochrane Reviews assess the 'certainty' or reliability of the evidence using standardised methods that consider the way studies were designed, conducted and reported, differences between studies or populations, and the combined results of studies. Most of the studies identified for this review were small and many were poorly designed and not reported clearly. Most of the evidence was considered to be of very low certainty, meaning that little can be sa d with any certainty about the effectiveness of treatments. Key results Transcutaneous electrical nerve stimulation (TENS) may be more effective than no treatment for ending or reducing daytime wetting. We are uncertain whether urotherapy (behavioural programmes in which children ÃƒÂ¢Ã¢â€šÂ¬Ã‚Â and sometimes carers ÃƒÂ¢Ã¢â€šÂ¬Ã‚Â are taught about how the bladder works, proper toileting postures and methods, scheduled toileting, and planning what and how much to drink) is more effective when supplemented with PFMT, voiding education with feedback, or watches with alarms set to remind children when to go to the toilet. We are uncertain whether feedback that shows children how their muscles are working or how their bladder is emptying improves the effectiveness of TENS with urotherapy compared to PFMT plus feedback and urotherapy. We are also uncertain whether PFMT and urotherapy plus feedback improves the effectiveness of PFMT and urotherapy alone. We are uncertain whether pelvic floor muscle training (PFMT) or TENS are more effective than anticholinergics (drugs that can reduce signals from the brain that cause the bladder to contract and empty). We are uncertain whether voiding education plus uroflowmetry (a test to measure the volume of urine) and feedback increases the number of continent children compared to anticholinergics. No serious adverse events were reported that were considered to be related to study treatments. Most nonÃƒÂ¢Ã¢â€šÂ¬Ã‚Âserious adverse events and side effects were mild or moderate in severity and were in children receiving pharmaceutical interventions. These included common pharmaceutical side effects such as nausea, abdominal pain, dry mouth, drowsiness and headache. Authors' conclusions There is a lack of goodÃƒÂ¢Ã¢â€šÂ¬Ã‚Âquality research evidence that can help children, their carers and doctors and nurses to make decisions about treatments. More wellÃƒÂ¢Ã¢â€šÂ¬Ã‚Âdesigned research may provide much needed evidence about the effectiveness of promising interventions in children with daytime urinary incontinence, such as TENS, PFMT and timers on watches (or mobile phones) to remind children about toileting schedules. However, it is hoped that this review will draw attention to the need for research into effective treatments for daytime wetting in children. | E38: FALSE | F38: Focuses on treatment, not aligned with NHS shifts. | G38: None | I38: 0.9
