Workbook

Sheet Stage_6_API_50
A1: id | B1: Year | C1: Title | D1: Abstract | E1: include_stage6 | F1: reason_stage6 | G1: main_shift | H1: shifts_detected | I1: confidence_stage6
A2: J502 | B2: 2019 | C2: Pdb16 Assessment of Cost-Effectiveness of a 0.2 Mcg/Day Fluocinolone Acetonide (Fac) Implant in Patients with Chronic Diabetic Macular Oedema (Dmo) in an Eye with Cataract | D2: Objectives: The fluocinolone acetonide 0.2 mug/day implant (FAc) is effective in improving visual acuity in patients with chronic diabetic macular oedema (cDMO) but is associated with worsening of cataract. A model previously suggested that FAc is cost-effective in patients with cDMO, who have undergone cataract surgery or not. The aim of this study was to update this model and assess the cost-effectiveness of FAc in the subgroup of patients with symptomatic cataract. Method(s): The existing Markov model was designed to assess costs and QALYs over lifetime in patients treated with FAc implant, compared to usual care (UC), consisting of laser photocoagulation and anti-VEGFs from the UK NHS perspective. Unit costs and health state utility values (HSUVs) were updated. The FAc price was NHS list price. HSUVs were obtained from the FAME trial using the VFQ-UI utility index. Best-Corrected Visual Acuity (BCVA) with UC was supposed to be stable. Additional scenarios were considered, with BCVA decreasing over time in UC arm, according to real-world data, and with possibility of administering FAc after cataract surgery in the UC arm. Result(s): New HSUVs ranged from 0.48 for blind patients to 0.91 for patients with perfect vision in both eyes. The FAc strategy was more expensive compared to usual care, by 3,445 per patients over lifetime, and produced more QALYs (+0.247). The incremental cost-effectiveness ratio (ICER) was estimated at 13,932 per QALY gained. The ICER was sensitive to the baseline visual acuity, patients' age and the probability of cataract surgery. The probability of FAc being cost-effective was 66.1% at a threshold of 20,000 per QALY gained. Scenario analyses showed that the efficacy of UC had a strong influence on results, and ICER decreased to 1,686 per QALY gained when BCVA decreased under UC Conclusion(s): The FAc implant is a cost-effective treatment for cDMO in patients with symptomatic cataract. Copyright Ãƒâ€šÃ‚Â© 2019 | E2: FALSE | F2: Focuses on cost-effectiveness of a treatment, not NHS shifts. | G2: None | I2: 0.9
A3: J503 | B3: 2019 | C3: Fluorides for preventing early tooth decay (demineralised lesions) during fixed brace treatment | D3: - Background Early dental decay or demineralised lesions (DLs, also known as white spot lesions) can appear on teeth during fixed orthodontic (brace) treatment. Fluoride reduces decay in susceptible individuals, including orthodontic patients. This review compared various forms of topical fluoride to prevent the development of DLs during orthodontic treatment. This is the second update of the Cochrane Review first published in 2004 and previously updated in 2013. Objectives The primary objective was to evaluate whether topical fluoride reduces the proportion of orthodontic patients with new DLs after fixed appliances. The secondary objectives were to examine the effectiveness of different modes of topical fluoride delivery in reducing the proportions of orthodontic patients with new DLs, as well as the severity of lesions, in terms of number, size and colour. ParticipantÃƒÂ¢Ã¢â€šÂ¬Ã‚Âassessed outcomes, such as perception of DLs, and oral healthÃƒÂ¢Ã¢â€šÂ¬Ã‚Ârelated quality of life data were to be included, as would reports of adverse effects. Search methods Cochrane Oral Health's Information Specialist searched the following databases: Cochrane Oral Health's Trials Register (to 1 February 2019), the Cochrane Central Register of Controlled Trials (CENTRAL; 2019, Issue 1) in the Cochrane Library (searched 1 February 2019), MEDLINE Ovid (1946 to 1 February 2019), and Embase Ovid (1980 to 1 February 2019). The US National Institutes of Health Ongoing Trials Register (ClinicalTrials.gov) and the World Health Organization International Clinical Trials Registry Platform were searched for ongoing trials. No restrictions were placed on the language or date of publication when searching the electronic databases. Selection criteria ParallelÃƒÂ¢Ã¢â€šÂ¬Ã‚Âgroup, randomised controlled trials comparing the use of a fluorideÃƒÂ¢Ã¢â€šÂ¬Ã‚Âcontaining product versus a placebo, no treatment or a different type of fluoride treatment, in which the outcome of enamel demineralisation was assessed at the start and at the end of orthodontic treatment. Data collection and analysis At least two review authors independently, in duplicate, conducted risk of bias assessments and extracted data. Authors of trials were contacted to obtain missing data or to ask for clarification of aspects of trial methodology. Cochrane's statistical guidelines were followed. Main results This update includes 10 studies and contains data from nine studies, comparing eight interventions, involving 1798 randomised participants (1580 analysed). One report contained insufficient information and the authors have been contacted. We assessed two studies as at low risk of bias, six at unclear risk of bias, and two at high risk of bias. Two placebo (nonÃƒÂ¢Ã¢â€šÂ¬Ã‚Âfluoride) controlled studies, at low risk of bias, investigated the professional application of varnish (7700 or 10,000 parts per million (ppm) fluoride (F)), every six weeks and found insufficient evidence of a difference regarding its effectiveness in preventing new DLs (risk ratio (RR) 0.52, 95% confidence interval (CI) 0.14 to 1.93; 405 participants; lowÃƒÂ¢Ã¢â€šÂ¬Ã‚Âcertainty evidence). One placebo (nonÃƒÂ¢Ã¢â€šÂ¬Ã‚Âfluoride) controlled study, at unclear risk of bias, provides a low level of certainty that fluoride foam (12,300 ppm F), professionally applied every two months, may reduce the incidence of new DLs (12% versus 49%) after fixed orthodontic treatment (RR 0.26, 95% CI 0.11 to 0.57; 95 participants). One study, at unclear risk of bias, also provides a low level of certainty that use of a highÃƒÂ¢Ã¢â€šÂ¬Ã‚Âconcentration fluoride toothpaste (5000 ppm F) by patients may reduce the incidence of new DLs (18% versus 27%) compared with a conventional fluoride toothpaste (1450 ppm F) (RR 0.68, 95% CI 0.46 to 1.00; 380 participants). There was no evidence for a difference in the proportions of orthodontic patients with new DLs on the teeth after treatment with fixed orthodontic appliances for the following comparisons:ÃƒÂ¢Ã¢â€šÂ¬Ã‚Â¨ ÃƒÂ¢Ã¢â€šÂ¬Ã‚Â an amine fluoride and stannous fluoride toothpaste/mouthrinse combination versus a sodium fluoride toothpaste/mouthrinse,ÃƒÂ¢Ã¢â€šÂ¬Ã‚Â¨ ÃƒÂ¢Ã¢â€šÂ¬Ã‚Â an amine fluoride gel versus a nonÃƒÂ¢Ã¢â€šÂ¬Ã‚Âfluoride placebo applied by participants at home once a week and by professional application every three months,ÃƒÂ¢Ã¢â€šÂ¬Ã‚Â¨ ÃƒÂ¢Ã¢â€šÂ¬Ã‚Â resinÃƒÂ¢Ã¢â€šÂ¬Ã‚Âmodified glass ionomer cement versus lightÃƒÂ¢Ã¢â€šÂ¬Ã‚Âcured composite resin for bonding orthodontic brackets,ÃƒÂ¢Ã¢â€šÂ¬Ã‚Â¨ ÃƒÂ¢Ã¢â€šÂ¬Ã‚Â a 250 ppm F mouthrinse versus 0 ppm F placebo mouthrinse,ÃƒÂ¢Ã¢â€šÂ¬Ã‚Â¨ ÃƒÂ¢Ã¢â€šÂ¬Ã‚Â the use of an intraoral fluorideÃƒÂ¢Ã¢â€šÂ¬Ã‚Âreleasing glass bead device attached to the brace versus a daily fluoride mouthrinse. The last two comparisons involved studies that were assessed at high risk of bias, because a substantial number of participants were lost to followÃƒÂ¢Ã¢â€šÂ¬Ã‚Âup. Unfortunately, although the internal validity and hence the quality of the studies has improved since the first version of the review, they have compared different interventions; therefore, the findings are only considered to provide low level of certainty, because none has been replicated by followÃƒÂ¢Ã¢â€šÂ¬Ã‚Âup studies, in different settings, to confirm external validity. A patientÃƒÂ¢Ã¢â€šÂ¬Ã‚Âreported outcome, such as concern about the aesthetics of any DLs, was still not included as an outcome in any study. Reports of adverse effects from topical fluoride applications were rare and unlikely to be significant. One study involving fluorideÃƒÂ¢Ã¢â€šÂ¬Ã‚Âcontaining glass beads reported numerous breakages. Authors' conclusions This review found a low level of certainty that 12,300 ppm F foam applied by a professional every 6 to 8 weeks throughout fixed orthodontic treatment, might be effective in reducing the proportion of orthodontic patients with new DLs. In addition, there is a low level of certainty that the patient use of a high fluoride toothpaste (5000 ppm F) throughout orthodontic treatment, might be more effective than a conventional fluoride toothpaste. These two comparisons were based on single studies. There was insufficient evidence of a difference regarding the professional application of fluoride varnish (7700 or 10,000 ppm F). Further adequately powered, randomised controlled trials are required to increase the certainty of these findings and to determine the best means of preventing DLs in patients undergoing fixed orthodontic treatment. The most accurate means of assessing adherence with the use of fluoride products by patients and any possible adverse effects also need to be considered. Future studies should follow up participants beyond the end of orthodontic treatment to determine the effect of DLs on patient satisfaction with treatment. Plain language summary Fluorides for preventing early tooth decay (demineralised lesions) during fixed brace treatment Review question ÃƒÂ¢Ã¢â€šÂ¬Ã‚Â¨ Ugly white or brown marks sometimes appear on the teeth during treatment with braces to straighten teeth. These are due to early tooth decay and usually occur with fixed, gluedÃƒÂ¢Ã¢â€šÂ¬Ã‚Âon 'train track', braces, which make it more difficult to clean the teeth. We know that fluoride in toothpaste helps to prevent tooth decay and think that if extra fluoride is given to people wearing fixed braces, it will protect them from getting these marks. The aim of this Cochrane Oral Health's review was to look at how well fluorides help to prevent early tooth decay during fixed brace treatment and to find out the best way to get fluoride to the teeth. Background ÃƒÂ¢Ã¢â€šÂ¬Ã‚Â¨ Wearing a fixed brace makes it harder for people to keep their teeth clean and may also cause pain. Pain can make it more difficult for people to brush their teeth. This can lead to a buildÃƒÂ¢Ã¢â€šÂ¬Ã‚Âup of dental plaque around the brackets that attach the fixed brace to the teeth, and if the plaque stays on the tooth for long enough, it will cause early tooth decay, which looks like white or brown marks (demineralised lesions, also known as white spot lesions). People often wear braces for 18 months or longer and if the decay is left to progress, it can cause holes, which are sometimes bad enough to need fillings to be done in the teeth. Fluoride helps the tooth to heal, reducing tooth decay in people who are at risk of developing it. People receiving fixed brace treatment may be given different forms of fluoride treatment. It is important to think about how the fluoride gets to the teeth. Does the fluoride need to be placed by a dentist or dental nurse, or can people having treatment with braces apply the fluoride to their own teeth? Study characteristics ÃƒÂ¢Ã¢â€šÂ¬Ã‚Â¨ This review is upÃƒÂ¢Ã¢â€šÂ¬Ã‚ÂtoÃƒÂ¢Ã¢â€šÂ¬Ã‚Âdate as of 1 February 2019. The review includes 10 studies but we could only use the information from nine studies involving 1798 randomised people. We have asked for more information about one study. The review looks at eight different ways of applying fluoride to the teeth. People taking part in the studies were all having treatment with fixed braces. The number of people with new decay on the teeth at end of fixed brace treatment, as well as the amount of decay in each person, were measured and counted. We compared the following treatments:ÃƒÂ¢Ã¢â€šÂ¬Ã‚Â¨ ÃƒÂ¢Ã¢â€šÂ¬Ã‚Â dentist or nurseÃƒÂ¢Ã¢â€šÂ¬Ã‚Âapplied fluoride e.g. varnish, gel or foam,ÃƒÂ¢Ã¢â€šÂ¬Ã‚Â¨ ÃƒÂ¢Ã¢â€šÂ¬Ã‚Â patientÃƒÂ¢Ã¢â€šÂ¬Ã‚Âapplied/used fluoride e.g. toothpaste, mouthwash, gel or foam, andÃƒÂ¢Ã¢â€šÂ¬Ã‚Â¨ ÃƒÂ¢Ã¢â€šÂ¬Ã‚Â materials that release fluoride over time e.g. glues, elastic bands. Key results ÃƒÂ¢Ã¢â€šÂ¬Ã‚Â¨ One study showed that when the dentist applies a foam with a high level of fluoride in it onto the teeth every time the patient is seen, this might reduce the risk of new decay. Another study found that if patients use a toothpaste with a higher level of fluoride than normal, then this might also reduce the risk of new marks on their teeth. No studies have shown that other ways of giving the teeth extra fluoride reduced the number and/or size of new decay on teeth in people wearing fixed braces. Harmful effects of the different ways of giving the teeth more fluoride were not reported in any of the included studies. Certainty of the evidence ÃƒÂ¢Ã¢â€šÂ¬Ã‚Â¨ The level of belief we have in these findings is low, due to the lack of studies testing the same fluorides and showing the same results. We suggest that more, wellÃƒÂ¢Ã¢â€šÂ¬Ã‚Âconducted studies should be done in this area. | E3: FALSE | F3: Focuses on treatment efficacy, not NHS shifts. | G3: None | I3: 0.95
A4: J504 | B4: 2019 | C4: Pmh28 Assessing the Life-Cycle Value Added of Second-Generation Antipsychotics in Sweden and the Uk: The Case of Risperidone | D4: To estimate the life-cycle value of risperidone - representative of Second-Generation Antipsychotics- relative to First Generation Antipsychotics to balance the view that cost per Quality-Adjusted Life Year (QALY) at launch are enough to guide access decisions. Study aims to drive the discussion on access and price, through recognition of the dynamic nature of value added by pharmaceutical innovation over the long-run. We estimated the number of patients with schizophrenia treated with risperidone in Sweden and the UK (1994-2017). We collected cost-effectiveness data from the literature of risperidone and haloperidol - representative of First-Generation Antipsychotics. We modelled the life-cycle uptake of risperidone to estimate the life-cycle incremental cost, incremental QALYs and Net monetary Benefit (NMB). We also assessed the life-cycle distribution of the consumer (the payer) and the producer (innovator) surpluses. For the UK, the producer surplus represents around 28% of the total surplus before patent expiration and around 5% after patent expiration. Life-cycle NMB for the health system is estimated at 1,116m. During the life-cycle, the NMB significantly increased in response to two events: (i) the launch of Risperidone Long-Acting Injectable (RLAI); and (ii) generic entry. The ICER was negative (dominant) for the whole period. For Sweden, the producer surplus represents around 6% of the total surplus before patent expiration and around 1% after generic competition. Life-cycle NMB is estimated at 803m, and both NMB and ICER follow the same pattern as in the UK. Analysis shows that health systems appropriated most of the life-cycle value (surplus) generated. This suggests that, considering the entire life-cycle, the value added by SGAs to the system is higher than the value estimated using cost-effectiveness analysis at launch. Pricing and reimbursement decisions should take into account the dynamic nature of pharmaceutical markets and the value added by innovative medicines over the long-run. Copyright Ãƒâ€šÃ‚Â© 2019 | E4: FALSE | F4: Focuses on cost-effectiveness of antipsychotics, not NHS Three Shifts. | G4: None | I4: 0.9
A5: J505 | B5: 2019 | C5: Fetal fibronectin testing for reducing the risk of preterm birth | D5: - Background Fetal fibronectin (FFN) is an extracellular matrix glycoprotein localized at the maternalÃƒÂ¢Ã¢â€šÂ¬Ã‚Âfetal interface of the amniotic membranes, between chorion and decidua, where it is concentrated in this area between decidua and trophoblast. In normal conditions, FFN is found at very low levels in cervicovaginal secretions. Levels greater than or equal to 50 ng/mL at or after 22 weeks have been associated with an increased risk of spontaneous preterm birth. In fact, FFN is one of the best predictors of preterm birth in all populations studied so far, and can help in selecting which women are at significant risk for preterm birth. This is an update of a review first published in 2008. Objectives To assess the effectiveness of management based on knowledge of FFN testing results for preventing preterm birth. Search methods For this update, we searched Cochrane Pregnancy and ChildbirthÃƒÂ¢Ã¢â€šÂ¬Ã¢â€žÂ¢s Trials Register (7 September 2018), ClinicalTrials.gov , the WHO International Clinical Trials Registry Platform ( ICTRP ) (7 September 2018), and reference lists of retrieved studies. Selection criteria Randomized controlled trials of pregnant women screened with FFN for risk of preterm birth. Studies included are based exclusively on knowledge of FFN results versus no such knowledge, and we have excluded studies including women with only positive or only negative FFN results. Data collection and analysis Two review authors independently assessed trials for inclusion and risk of bias, extracted data, and checked them for accuracy. The quality of the evidence was assessed using the GRADE approach. Main results We identified 16 trials, of which six were eligible for inclusion. The six included studies randomized 546 women with singleton gestations and threatened preterm labor (PTL) at 23 0/7 to 34 6/7 weeks. A total of 277 women were randomized to knowledge and 269 to no knowledge of FFN. No trials were identified on asymptomatic women or multiple gestations. The risk of bias of included studies was mixed. For selected important outcomes, preterm birth before 37, 34, and 32 weeks, and maternal hospitalization, we graded the quality of the evidence and created a 'Summary of findings' table. For these outcomes, the evidence was graded as mainly low quality due to the imprecision of effect estimates. Management based on knowledge of FFN results may reduce preterm birth before 37 weeks (20.7%) versus controls without such knowledge (29.2%) (risk ratio (RR) 0.72, 95% confidence interval (CI) 0.52 to 1.01; 5 trials; 434 women; lowÃƒÂ¢Ã¢â€šÂ¬Ã‚Âquality evidence). However, management based on knowledge of FFN results may make little or no difference to preterm birth before 34 (RR 1.09, 95% CI 0.54 to 2.18; 4 trials; 357 women; lowÃƒÂ¢Ã¢â€šÂ¬Ã‚Âquality evidence) or maternal hospitalization (RR 1.06, 95% CI 0.79 to 1.43; 5 trials; 441 women; lowÃƒÂ¢Ã¢â€šÂ¬Ã‚Âquality evidence). The evidence for preterm birth before 32 weeks is uncertain because the quality was found to be very low (average RR 0.79, 95% CI 0.16 to 3.96; 4 trials; 357 women; very lowÃƒÂ¢Ã¢â€šÂ¬Ã‚Âquality evidence). For all other outcomes, for which there were available data (preterm birth less than 28 weeks; gestational age at delivery (weeks); birthweight less than 2500 g; perinatal death; tocolysis; steroids for fetal lung maturity; time to evaluate; respiratory distress syndrome; neonatal intensive care unit (NICU) admission; and NICU days), knowledge of FFN results may make little or no difference to the outcomes. Authors' conclusions The evidence from this review suggests that management based on knowledge of FFN results may reduce preterm birth before 37 weeks. However, our confidence in this result is limited as the evidence was found to be of low quality. Effects on other substantive outcomes are uncertain due to serious concerns in study design, inconsistency, and imprecision of effect estimates. No trials were identified on asymptomatic women, or multiple gestations. Future studies are needed that include specific populations (e.g. singleton gestations with symptoms of preterm labor), a study gro p managed with a protocol based on the FFN results, and that report not only maternal but also important perinatal outcomes. CostÃƒÂ¢Ã¢â€šÂ¬Ã‚Âeffectiveness analyses are also needed. Plain language summary Fetal fibronectin testing for reducing the risk of preterm birth What is the issue? To assess the effectiveness of management of pregnant women based on a knowledge of fetal fibronectin test results for preventing preterm birth, compared with not having that knowledge. Fetal fibronectin (FFN) acts as a ÃƒÂ¢Ã¢â€šÂ¬Ã‹Å“glueÃƒÂ¢Ã¢â€šÂ¬Ã¢â€žÂ¢ between the pregnancy and the uterus. Normally very low levels of FFN can be found in secretions of the vagina and cervix. Raised levels at or after 22 weeks have been associated with an increased risk of spontaneous preterm birth. Why is this important? Preterm birth before 37 weeks is the main cause of sickness and death for newborn infants. Most women who give birth preterm have preterm labor symptoms such as contractions but many of the women with symptoms go on to deliver at term (37 weeks or more). Fetal fibronectin (FFN) is a test that can identify the women with symptoms of preterm labor who are most at risk for preterm birth. The level of FFN is measured in secretions from the vagina or cervix. What evidence did we find? We found six randomised controlled studies involving 546 women who were pregnant with one baby and were showing signs of preterm labor at between 23 to 34 weeks' gestation. We graded the following evidence as mainly low quality because of the low number of women in the studies and a wide variation in findings. We found that the number of births before 37 weeks may be slightly reduced when women and their doctors know the results of the FFN test (20.7% versus 29.2%; 5 trials; 434 women). However, knowledge of FFN results may make little or no difference for the other outcomes with available data, including: maternal hospitalization (5 trials; 441 women); use of uterine relaxants (tocolysis) to try to prevent labor; earlier preterm births; womenÃƒÂ¢Ã¢â€šÂ¬Ã¢â€žÂ¢s gestational age at delivery; babies with a birthweight less than 2500 g; newborn deaths; the number of babies with respiratory distress syndrome; giving steroids to mature the unborn babiesÃƒÂ¢Ã¢â€šÂ¬Ã¢â€žÂ¢ lungs; and number of days in a neonatal intensive care unit (NICU). What does this mean? This review of six studies did not find enough evidence to say whether or not the FFN test should be used in the management of women showing signs of preterm labor. A screening test such as FFN can only be considered effective if interventions based on the screening results, such as giving drugs to relax the uterus, reduce the number of preterm births. Further research should be encouraged. | E5: TRUE | F5: Focuses on preventing preterm birth via predictive testing. | G5: Prevention | H5: Prevention | I5: 0.9
A6: J508 | B6: 2019 | C6: Adalimumab for non-infectious uveitis: Is it cost-effective? | D6: Background/Aims: Uveitis is inflammation inside the eye. Our objective was to assess the cost-effectiveness of adalimumab compared with current practice (immunosuppressants and systemic corticosteroids) in patients with non-infectious intermediate, posterior or panuveitis and to identify areas for future research. Method(s): A Markov model was built to estimate costs and benefits of the interventions. Systematic reviews were performed to identify the available relevant clinical and cost-effectiveness evidence. Data collected in two key randomised controlled trials (VISUAL I and VISUAL II) were used to estimate the interventions' effectiveness compared with the trials' comparator arms (placebo plus limited current practice (LCP)). The analysis was performed from the National Health Service and Personal Social Services perspective. Costs were calculated based on standard UK sources. Result(s): The estimated incremental cost-effectiveness ratios (ICERs) of adalimumab versus LCP for the base case are 92 600 and 318 075 per quality-adjusted life year (QALY) gained for active and inactive uveitis, respectively. In sensitivity analyses, the ICER varied from 15 579 to 120 653 and 35 642 to 800 775 per QALY for active and inactive uveitis. Conclusion(s): The estimated ICERs of adalimumab versus LCP are above generally accepted thresholds for cost-effectiveness in the UK. Adalimumab may be more cost-effective in patients with active uveitis at greater risk of blindness. However, there is an unmet need for additional primary data to provide more reliable estimates in several important areas, including effectiveness of adalimumab versus current practice (instead of LCP), incidence of long-term blindness, adalimumab effectiveness in avoiding blindness, and rates and time to remission while on adalimumab. Copyright Ãƒâ€šÃ‚Â© 2019 Author(s). | E6: FALSE | F6: Focus on cost-effectiveness of a drug, not NHS shifts. | G6: None | I6: 1
A7: J510 | B7: 2019 | C7: Treatment for hepatorenal syndrome in people with decompensated liver cirrhosis: a network metaÃƒÂ¢Ã¢â€šÂ¬Ã‚Âanalysis | D7: - Background Hepatorenal syndrome is defined as renal failure in people with cirrhosis in the absence of other causes. In addition to supportive treatment such as albumin to restore fluid balance, the other potential treatments include systemic vasoconstrictor drugs (such as vasopressin analogues or noradrenaline), renal vasodilator drugs (such as dopamine), transjugular intrahepatic portosystemic shunt (TIPS), and liver support with molecular adsorbent recirculating system (MARS). There is uncertainty over the best treatment regimen for hepatorenal syndrome. Objectives To compare the benefits and harms of different treatments for hepatorenal syndrome in people with decompensated liver cirrhosis. Search methods We searched CENTRAL, MEDLINE, Embase, Science Citation Index Expanded, World Health Organization International Clinical Trials Registry Platform, and trial registers until December 2018 to identify randomised clinical trials on hepatorenal syndrome in people with cirrhosis. Selection criteria We included only randomised clinical trials (irrespective of language, blinding, or publication status) in adults with cirrhosis and hepatorenal syndrome. We excluded randomised clinical trials in which participants had previously undergone liver transplantation. Data collection and analysis Two authors independently identified eligible trials and collected data. The outcomes for this review included mortality, serious adverse events, any adverse events, resolution of hepatorenal syndrome, liver transplantation, and other decompensation events. We performed a network metaÃƒÂ¢Ã¢â€šÂ¬Ã‚Âanalysis with OpenBUGS using Bayesian methods and calculated the odds ratio (OR), rate ratio, hazard ratio (HR), and mean difference (MD) with 95% credible intervals (CrI) based on an availableÃƒÂ¢Ã¢â€šÂ¬Ã‚Âcase analysis, according to National Institute of Health and Care Excellence Decision Support Unit guidance. Main results We included a total of 25 trials (1263 participants; 12 interventions) in the review. TwentyÃƒÂ¢Ã¢â€šÂ¬Ã‚Âthree trials (1185 participants) were included in one or more outcomes. All the trials but two were at high risk of bias, and all the evidence was of low or very low certainty. The trials included participants with liver cirrhosis of varied aetiologies as well as a mixture of type I hepatorenal syndrome only, type II hepatorenal syndrome only, or people with both type I and type II hepatorenal syndrome. Participant age ranged from 42 to 60 years, and the proportion of females ranged from 5.8% to 61.5% in the trials that reported this information. The followÃƒÂ¢Ã¢â€šÂ¬Ã‚Âup in the trials ranged from one week to six months. Overall, 59% of participants died during this period and about 35% of participants recovered from hepatorenal syndrome. The most common interventions compared were albumin plus terlipressin, albumin plus noradrenaline, and albumin alone. There was no evidence of a difference in mortality (22 trials; 1153 participants) at maximal followÃƒÂ¢Ã¢â€šÂ¬Ã‚Âup between the different interventions. None of the trials reported healthÃƒÂ¢Ã¢â€šÂ¬Ã‚Ârelated quality of life. There was no evidence of differences in the proportion of people with serious adverse events (three trials; 428 participants), number of participants with serious adverse events per participant (two trials; 166 participants), proportion of participants with any adverse events (four trials; 402 participants), the proportion of people who underwent liver transplantation at maximal followÃƒÂ¢Ã¢â€šÂ¬Ã‚Âup (four trials; 342 participants), or other features of decompensation at maximal followÃƒÂ¢Ã¢â€šÂ¬Ã‚Âup (one trial; 466 participants). Five trials (293 participants) reported number of any adverse events, and five trials (219 participants) reported treatment costs. Albumin plus noradrenaline had fewer numbers of adverse events per participant (rate ratio 0.51, 95% CrI 0.28 to 0.87). Eighteen trials (1047 participants) reported recovery from hepatorenal syndrome (as per definition of hepatorenal syndrome). In terms of recovery from hepatorenal syndrome, in the direct comparisons, albumin plus midodrine plus octreotide and albumin plus octreotide had lower recovery from hepatorenal syndrome than albumin plus terlipressin (HR 0.04; 95% CrI 0.00 to 0.25 and HR 0.26, 95% CrI 0.07 to 0.80 respectively). There was no evidence of differences between the groups in any of the other direct comparisons. In the network metaÃƒÂ¢Ã¢â€šÂ¬Ã‚Âanalysis, albumin and albumin plus midodrine plus octreotide had lower recovery from hepatorenal syndrome compared with albumin plus terlipressin. Funding: two trials were funded by pharmaceutical companies; five trials were funded by parties who had no vested interest in the results of the trial; and 18 trials did not report the source of funding. Authors' conclusions Based on very lowÃƒÂ¢Ã¢â€šÂ¬Ã‚Âcertainty evidence, there is no evidence of benefit or harm of any of the interventions for hepatorenal syndrome with regards to the following outcomes: allÃƒÂ¢Ã¢â€šÂ¬Ã‚Âcause mortality, serious adverse events (proportion), number of serious adverse events per participant, any adverse events (proportion), liver transplantation, or other decompensation events. LowÃƒÂ¢Ã¢â€šÂ¬Ã‚Âcertainty evidence suggests that albumin plus noradrenaline had fewer 'any adverse events per participant' than albumin plus terlipressin. LowÃƒÂ¢Ã¢â€šÂ¬Ã‚Â or very lowÃƒÂ¢Ã¢â€šÂ¬Ã‚Âcertainty evidence also found that albumin plus midodrine plus octreotide and albumin alone had lower recovery from hepatorenal syndrome compared with albumin plus terlipressin. Future randomised clinical trials should be adequately powered; employ blinding, avoid postÃƒÂ¢Ã¢â€šÂ¬Ã‚Ârandomisation dropouts or planned crossÃƒÂ¢Ã¢â€šÂ¬Ã‚Âovers (or perform an intentionÃƒÂ¢Ã¢â€šÂ¬Ã‚ÂtoÃƒÂ¢Ã¢â€šÂ¬Ã‚Âtreat analysis); and report clinically important outcomes such as mortality, healthÃƒÂ¢Ã¢â€šÂ¬Ã‚Ârelated quality of life, adverse events, and recovery from hepatorenal syndrome. Albumin plus noradrenaline and albumin plus terlipressin appear to be the interventions that should be compared in future trials. Plain language summary Treatment of hepatorenal syndrome What is the aim of this Cochrane review? To find out the best treatment for decreased kidney function (hepatorenal syndrome) in people with liver cirrhosis (a form of advanced liver disease with scarring of the liver) with complications. The authors collected and analysed all relevant studies to answer this question and found 25 randomised controlled trials (participants receive the treatment based on method similar to coin toss or lottery; this is to ensure that the people who receive the different treatments are similar in all aspects except the treatment, so that any differences in the results between the treatments can be attributed to the treatment rather than differences in the type of people who received the treatment). During analysis of data, authors used standard Cochrane techniques, which allows comparison of two treatments at a time. Authors also used advanced techniques, that allow comparison of many treatments at the same time (usually referred as 'network metaÃƒÂ¢Ã¢â€šÂ¬Ã‚Âanalysis' or 'multiple treatment comparisons'). The aim is to gather reliable evidence on the relative benefits and harms of the different treatments. Date of literature search ÃƒÂ¢Ã¢â€šÂ¬Ã‚Â¨ December 2018 Key messages ÃƒÂ¢Ã¢â€šÂ¬Ã‚Â¨ Only two studies were conducted well. The remaining studies had one or more flaws. Therefore, there is high uncertainty in the results of the analysis. The authors could not recommend one treatment over another on the basis of risk of death, serious complications, percentage of people who developed any complication, percentage of participants who underwent liver transplantation (replacement of a diseased liver with a healthy one), or the number of other liver failure events. HealthÃƒÂ¢Ã¢â€šÂ¬Ã‚Ârelated quality of life was not reported in any of the trials. The number of complications of any severity was lower with albumin plus noradrenaline than albumin plus terlipressin. Recovery from hepatorenal syndrome may be lower with albumin plus midodrine plus octreotide and albumin alone than albumin plus terlipressin and albumin plus noradrenaline. Funding source was unclear in 18 studies. Industrial organisations funded two studies and the remaining five studies did not receive any funding from industrial organisations. What was studied in the review? This review studied people of any sex, age, and origin, having advanced liver disease due to various causes, and who had developed hepatorenal syndrome. People were administered different treatments. The review authors excluded studies with liverÃƒÂ¢Ã¢â€šÂ¬Ã‚Âtransplanted participants. Participants age, when reported, ranged from 42 to 60 years. The number of females ranged from 6 to 62 out of 100 in the studies that reported this information. The main treatments compared were albumin alone, albumin plus terlipressin, and albumin plus noradrenaline. The authors gathered and analysed data on death, quality of life, serious and nonÃƒÂ¢Ã¢â€šÂ¬Ã‚Âserious complications, time to liver transplantation, recovery from hepatorenal syndrome, and disappearance of symptoms. What were the main results of the review? The 25 studies included a small number of participants (1263 participants). Study data were sparse. TwentyÃƒÂ¢Ã¢â€šÂ¬Ã‚Âthree studies with 1185 participants provided data for analyses. The followÃƒÂ¢Ã¢â€šÂ¬Ã‚Âup in the trials ranged from one week to six months. The review shows that: ÃƒÂ¢Ã¢â€šÂ¬Ã‚Â About 60 out of every 100 people died within three months, and 35 out of every 100 people recovered from hepatorenal syndrome. ÃƒÂ¢Ã¢â€šÂ¬Ã‚Â The provided treatment may make no difference to the percentage of people who died or developed serious complications, number of serious complications per person, percentage of people who developed complications of any severity, or the percentage of people undergoing liver transplantation. ÃƒÂ¢Ã¢â€šÂ¬Ã‚Â None of the trials reported healthÃƒÂ¢Ã¢â€šÂ¬Ã‚Ârelated quality of life. ÃƒÂ¢Ã¢â€šÂ¬Ã‚Â The number of complications of any severity was lower with albumin plus noradrenaline than albumin plus terlipressin. ÃƒÂ¢Ã¢â€šÂ¬Ã‚Â Recovery from hepatorenal syndrome may be lower with albumin plus midodrine plus octreotide and albumin alone than albumin plus terlipressin and albumin plus noradrenaline. ÃƒÂ¢Ã¢â€šÂ¬Ã‚Â We have very low confidence in the overall results. ÃƒÂ¢Ã¢â€šÂ¬Ã‚Â Future trials with proper design and quality are needed to clarify the best treatment for people with advanced liver disease having hepatorenal syndrome. | E7: FALSE | F7: Focuses on treatment comparison, not aligned with NHS shifts. | G7: None | I7: 0.95
A8: J520 | B8: 2019 | C8: The budget impact of early dose optimisation with golimumab in ulcerative colitis in the UK | D8: Background: The PURSUIT study found that ulcerative colitis patients who were non-responders (based on full Mayo score) to subcutaneous golimumab treatment at Week 6 may benefit from receiving a dose of 100 mg golimumab from Week 6 onwards, with 28% of non-responders at Week 6 becoming responders by Week 14. The aim of this study was to assess the budget implications of optimising a patient's dose at Week 6 compared with other first-line therapies as per current clinical practice Methods: A decision tree model was designed to follow a patient's response to first-line treatment and to track a patient's progression through subsequent line of therapy. The budget impact model only considered drug costs from the perspective of the UK NHS. In total three lines of therapy were covered by the decision tree over a 1 year time horizon. Patients could have first-line treatment with one of the three treatment strategies; golimumab (current treatment practice), golimumab (dose optimisation based on the PURSUIT trial) and adalimumab. Within each of the comparator treatments dose escalation was considered, based on the median time to escalation and proportion of patients receiving dose escalation. Subsequent therapy for golimumab patients was adalimumab and patients who received adalimumab as a first-line therapy received golimumab as a second-line therapy. Response rates, time to loss of response and treatment costs were taken from published data sources. The cost of golimumab was equal between 50 mg pack and 100 mg pack. The model used assumption for second-line response rates; this has been tested in sensitivity analysis. Result(s): The use of dose optimisation for golimumab does not increase expenditure of drug costs compared with golimumab (single dose) with a cost saving of 42 per patient per year. When comparing dose optimisation for golimumab to adalimumab, golimumab was cost saving over 1 year of treatment with cost saving of 2138 per patient. The number of patients in a response health state was similar across all three treatments (47.7%, 47.6% and 45% for golimumab (single dose), golimumab (dose optimisation) and adalimumab, respectively. Conclusion(s): The implementation of dose optimisation at Week 6 for golimumab was cost saving compared with golimumab (current treatment practice) or adalimumab. The analysis highlights the need for immediate implementation of the updated GLM label in clinical practice for potentially more cost savings. | E8: FALSE | F8: Focuses on drug cost optimisation, not NHS Three Shifts. | G8: None | I8: 0.9
A9: J522 | B9: 2019 | C9: Continuous subcutaneous insulin infusion versus multiple daily injection regimens in children and young people at diagnosis of type 1 diabetes: Pragmatic randomised controlled trial and economic evaluation | D9: Objective To compare the efficacy, safety, and cost utility of continuous subcutaneous insulin infusion (CSII) with multiple daily injection (MDI) regimens during the first year following diagnosis of type 1 diabetes in children and young people. Design Pragmatic, multicentre, open label, parallel group, randomised controlled trial and economic evaluation. Setting 15 paediatric National Health Service (NHS) diabetes services in England and Wales. The study opened to recruitment in May 2011 and closed in January 2017. Participants Patients aged between 7 months and 15 years, with a new diagnosis of type 1 diabetes were eligible to participate. Patients who had a sibling with the disease, and those who took drug treatments or had additional diagnoses that could have affected glycaemic control were ineligible. Interventions Participants were randomised, stratified by age and treating centre, to start treatment with CSII or MDI within 14 days of diagnosis. Starting doses of aspart (CSII and MDI) and glargine or detemir (MDI) were calculated according to weight and age, and titrated according to blood glucose measurements and according to local clinical practice. Main outcome measures Primary outcome was glycaemic control (as measured by glycated haemoglobin; HbA1c) at 12 months. Secondary outcomes were percentage of patients in each treatment arm with HbA1c within the national target range, incidence of severe hypoglycaemia and diabetic ketoacidosis, change in height and body mass index (as measured by standard deviation scores), insulin requirements (units/kg/day), partial remission rate (insulin dose adjusted HbA1c <9), paediatric quality of life inventory score, and cost utility based on the incremental cost per quality adjusted life year (QALY) gained from an NHS costing perspective. Results 294 participants were randomised and 293 included in intention to treat analyses (CSI, n=144; MDI, n=149). At 12 months, mean HbA1c was comparable with clinically unimportant differences between CSII and MDI participants (60.9 mmol/mol v 58.5 mmol/mol, mean difference 2.4 mmol/mol (95% confidence interval -0.4 to 5.3), P=0.09). Achievement of HbA1c lower than 58 mmol/mol was low among the two groups (66/143 (46%) CSII participants v 78/142 (55%) MDI participants; relative risk 0.84 (95% confidence interval 0.67 to 1.06)). Incidence of severe hypoglycaemia and diabetic ketoacidosis were low in both groups. Fifty four non-serious and 14 serious adverse events were reported during CSII treatment, and 17 non-serious and eight serious adverse events during MDI treatment. Parents (but not children) reported superior PedsQL scores for those patients treated with CSII compared to those treated with MDI. CSII was more expensive than MDI by 1863 (2179; $2474; 95% confidence interval 1620 to 2137) per patient, with no additional QALY gains (difference -0.006 (95% confidence interval -0.031 to 0.018)). Conclusion During the first year following type 1 diabetes diagnosis, no clinical benefit of CSII over MDI was identified in children and young people in the UK setting, and treatment with either regimen was suboptimal in achieving HbA1c thresholds. CSII was not cost effective. Trial registration Current Controlled Trials ISRCTN29255275; European Clinical Trials Database 2010-023792-25. Copyright Ãƒâ€šÃ‚Â© Published by the BMJ Publishing Group Limited. | E9: FALSE | F9: Focuses on treatment efficacy, not NHS shifts. | G9: None | I9: 0.9
A10: J523 | B10: 2019 | C10: Perioperative betaÃƒÂ¢Ã¢â€šÂ¬Ã‚Âblockers for preventing surgeryÃƒÂ¢Ã¢â€šÂ¬Ã‚Ârelated mortality and morbidity in adults undergoing nonÃƒÂ¢Ã¢â€šÂ¬Ã‚Âcardiac surgery | D10: - Background Randomized controlled trials (RCTs) have yielded conflicting results regarding the ability of betaÃƒÂ¢Ã¢â€šÂ¬Ã‚Âblockers to influence perioperative cardiovascular morbidity and mortality. Thus routine prescription of these drugs in an unselected population remains a controversial issue. A previous version of this review assessing the effectiveness of perioperative betaÃƒÂ¢Ã¢â€šÂ¬Ã‚Âblockers in cardiac and nonÃƒÂ¢Ã¢â€šÂ¬Ã‚Âcardiac surgery was last published in 2018. The previous review has now been split into two reviews according to type of surgery. This is an update, and assesses the evidence in nonÃƒÂ¢Ã¢â€šÂ¬Ã‚Âcardiac surgery only. Objectives To assess the effectiveness of perioperatively administered betaÃƒÂ¢Ã¢â€šÂ¬Ã‚Âblockers for the prevention of surgeryÃƒÂ¢Ã¢â€šÂ¬Ã‚Ârelated mortality and morbidity in adults undergoing nonÃƒÂ¢Ã¢â€šÂ¬Ã‚Âcardiac surgery. Search methods We searched CENTRAL, MEDLINE, Embase, CINAHL, Biosis Previews and Conference Proceedings Citation IndexÃƒÂ¢Ã¢â€šÂ¬Ã‚ÂScience on 28 June 2019. We searched clinical trials registers and grey literature, and conducted backwardÃƒÂ¢Ã¢â€šÂ¬Ã‚Â and forwardÃƒÂ¢Ã¢â€šÂ¬Ã‚Âcitation searching of relevant articles. Selection criteria We included RCTs and quasiÃƒÂ¢Ã¢â€šÂ¬Ã‚Ârandomized studies comparing betaÃƒÂ¢Ã¢â€šÂ¬Ã‚Âblockers with a control (placebo or standard care) administered during the perioperative period to adults undergoing nonÃƒÂ¢Ã¢â€šÂ¬Ã‚Âcardiac surgery. If studies included surgery with different types of anaesthesia, we included them if 70% participants, or at least 100 participants, received general anaesthesia. We excluded studies in which all participants in the standard care control group were given a pharmacological agent that was not given to participants in the intervention group, studies in which all participants in the control group were given a betaÃƒÂ¢Ã¢â€šÂ¬Ã‚Âblocker, and studies in which betaÃƒÂ¢Ã¢â€šÂ¬Ã‚Âblockers were given with an additional agent (e.g. magnesium). We excluded studies that did not measure or report review outcomes. Data collection and analysis Two review authors independently assessed studies for inclusion, extracted data, and assessed risks of bias. We assessed the certainty of evidence with GRADE. Main results We included 83 RCTs with 14,967 participants; we found no quasiÃƒÂ¢Ã¢â€šÂ¬Ã‚Ârandomized studies. All participants were undergoing nonÃƒÂ¢Ã¢â€šÂ¬Ã‚Âcardiac surgery, and types of surgery ranged from low to high risk. Types of betaÃƒÂ¢Ã¢â€šÂ¬Ã‚Âblockers were: propranolol, metoprolol, esmolol, landiolol, nadolol, atenolol, labetalol, oxprenolol, and pindolol. In nine studies, betaÃƒÂ¢Ã¢â€šÂ¬Ã‚Âblockers were titrated according to heart rate or blood pressure. Duration of administration varied between studies, as did the time at which drugs were administered; in most studies, it was intraoperatively, but in 18 studies it was before surgery, in six postoperatively, one multiÃƒÂ¢Ã¢â€šÂ¬Ã‚Âarm study included groups of different timings, and one study did not report timing of drug administration. Overall, we found that more than half of the studies did not sufficiently report methods used for randomization. All studies in which the control was standard care were at high risk of performance bias because of the openÃƒÂ¢Ã¢â€šÂ¬Ã‚Âlabel study design. Only two studies were prospectively registered with clinical trials registers, which limited the assessment of reporting bias. In six studies, participants in the control group were given betaÃƒÂ¢Ã¢â€šÂ¬Ã‚Âblockers as rescue therapy during the study period. The evidence for allÃƒÂ¢Ã¢â€šÂ¬Ã‚Âcause mortality at 30 days was uncertain; based on the risk of death in the control group of 25 per 1000, the effect with betaÃƒÂ¢Ã¢â€šÂ¬Ã‚Âblockers was between two fewer and 13 more per 1000 (risk ratio (RR) 1.17, 95% confidence interval (CI) 0.89 to 1.54; 16 studies, 11,446 participants; lowÃƒÂ¢Ã¢â€šÂ¬Ã‚Âcertainty evidence). BetaÃƒÂ¢Ã¢â€šÂ¬Ã‚Âblockers may reduce the incidence of myocardial infarction by 13 fewer incidences per 1000 (RR 0.72, 95% CI 0.60 to 0.87; 12 studies, 10,520 participants; lowÃƒÂ¢Ã¢â€šÂ¬Ã‚Âcertainty evidence). We found no evidence of a difference in cerebrovascular events (RR 1.65, 95% CI 0.97 to 2.81; 6 studies, 9460 participants; lowÃƒÂ¢Ã¢â€šÂ¬Ã‚Âcertainty evidence), or in ventricular arrhythmias (RR 0.72, 95% CI 0.35 to 1.47; 5 studies, 47 participants; very lowÃƒÂ¢Ã¢â€šÂ¬Ã‚Âcertainty evidence). BetaÃƒÂ¢Ã¢â€šÂ¬Ã‚Âblockers may reduce atrial fibrillation or flutter by 26 fewer incidences per 1000 (RR 0.41, 95% CI 0.21 to 0.79; 9 studies, 9080 participants; lowÃƒÂ¢Ã¢â€šÂ¬Ã‚Âcertainty evidence). However, betaÃƒÂ¢Ã¢â€šÂ¬Ã‚Âblockers may increase bradycardia by 55 more incidences per 1000 (RR 2.49, 95% CI 1.74 to 3.56; 49 studies, 12,239 participants; lowÃƒÂ¢Ã¢â€šÂ¬Ã‚Âcertainty evidence), and hypotension by 44 more per 1000 (RR 1.40, 95% CI 1.29 to 1.51; 49 studies, 12,304 participants; moderateÃƒÂ¢Ã¢â€šÂ¬Ã‚Âcertainty evidence). We downgraded the certainty of the evidence owing to study limitations; some studies had high risks of bias, and the effects were sometimes altered when we excluded studies with a standard care control group (including only placeboÃƒÂ¢Ã¢â€šÂ¬Ã‚Âcontrolled trials showed an increase in early mortality and cerebrovascular events with betaÃƒÂ¢Ã¢â€šÂ¬Ã‚Âblockers). We also downgraded for inconsistency; one large, wellÃƒÂ¢Ã¢â€šÂ¬Ã‚Âconducted, international study found a reduction in myocardial infarction, and an increase in cerebrovascular events and allÃƒÂ¢Ã¢â€šÂ¬Ã‚Âcause mortality, when betaÃƒÂ¢Ã¢â€šÂ¬Ã‚Âblockers were used, but other studies showed no evidence of a difference. We could not explain the reason for the inconsistency in the evidence for ventricular arrhythmias, and we also downgraded this outcome for imprecision because we found few studies with few participants. Authors' conclusions The evidence for early allÃƒÂ¢Ã¢â€šÂ¬Ã‚Âcause mortality with perioperative betaÃƒÂ¢Ã¢â€šÂ¬Ã‚Âblockers was uncertain. We found no evidence of a difference in cerebrovascular events or ventricular arrhythmias, and the certainty of the evidence for these outcomes was low and very low. We found lowÃƒÂ¢Ã¢â€šÂ¬Ã‚Âcertainty evidence that betaÃƒÂ¢Ã¢â€šÂ¬Ã‚Âblockers may reduce atrial fibrillation and myocardial infarctions. However, betaÃƒÂ¢Ã¢â€šÂ¬Ã‚Âblockers may increase bradycardia (lowÃƒÂ¢Ã¢â€šÂ¬Ã‚Âcertainty evidence) and probably increase hypotension (moderateÃƒÂ¢Ã¢â€šÂ¬Ã‚Âcertainty evidence). Further evidence from large placeboÃƒÂ¢Ã¢â€šÂ¬Ã‚Âcontrolled trials is likely to increase the certainty of these findings, and we recommend the assessment of impact on quality of life. We found 18 studies awaiting classification; inclusion of these studies in future updates may also increase the certainty of the evidence. Plain language summary BetaÃƒÂ¢Ã¢â€šÂ¬Ã‚Âblockers to prevent death or serious events after surgery not involving the heart This review assessed evidence from randomized controlled trials (RCTs) on whether betaÃƒÂ¢Ã¢â€šÂ¬Ã‚Âblockers reduce deaths or other serious events when given to people undergoing surgery other than heart surgery. The findings for heart surgery are covered in another review. Background Surgery increases stress in the body, which responds by releasing the hormones adrenaline and noradrenaline. Stress from surgery can lead to death or other serious events such as heart attacks, stroke, or an irregular heartbeat. For surgery that does not involve the heart, an estimated 8% of people may have injury to their heart around the time of surgery. BetaÃƒÂ¢Ã¢â€šÂ¬Ã‚Âblockers are drugs that block the action of adrenaline and noradrenaline on the heart. BetaÃƒÂ¢Ã¢â€šÂ¬Ã‚Âblockers can slow down the heart, and reduce blood pressure, and this may reduce the risk of serious events. However, betaÃƒÂ¢Ã¢â€šÂ¬Ã‚Âblockers may lead to a very low heart rate or very low blood pressure which could increase the risk of death or a stroke. Prevention of early complications after surgery is important, but using betaÃƒÂ¢Ã¢â€šÂ¬Ã‚Âblockers to prevent these complications is controversial. Study characteristics The evidence is current to 28 June 2019. We included 83 RCTs with 14,967 adults who were undergoing different types of surgery other than heart surgery. Eighteen studies are awaiting classification (because we did not have enough details to assess them), and three studies are ongoing. The types of betaÃƒÂ¢Ã¢â€šÂ¬Ã‚Âblockers used in the studies were: propranolol, metoprolol, esmolol, landiolol, nadolol, atenolol, labetalol, oxprenolol, and pindolol. Studies compared these betaÃƒÂ¢Ã¢â€šÂ¬Ã‚Âblockers with either a placebo (disguised to look like a betaÃƒÂ¢Ã¢â€šÂ¬Ã‚Âblocker but containing no medicine) or with standard care. Key results BetaÃƒÂ¢Ã¢â€šÂ¬Ã‚Âblockers may make l ttle or no difference to the number of people who die within 30 days of surgery (16 studies, 11,446 participants; lowÃƒÂ¢Ã¢â€šÂ¬Ã‚Âcertainty evidence), have a stroke (6 studies, 9460 participants; lowÃƒÂ¢Ã¢â€šÂ¬Ã‚Âcertainty evidence), or experience ventricular arrhythmias (irregular heartbeat rhythms, starting in the main chambers of the heart, that are potentially lifeÃƒÂ¢Ã¢â€šÂ¬Ã‚Âthreatening and may need immediate medical treatment; 5 studies, 476 participants; very lowÃƒÂ¢Ã¢â€šÂ¬Ã‚Âcertainty evidence). We found that betaÃƒÂ¢Ã¢â€šÂ¬Ã‚Âblockers may reduce atrial fibrillation (an irregular heartbeat, starting in the atrial chambers of the heart, that increases the risk of stroke if untreated; 9 studies, 9080 participants; low certaintyÃƒÂ¢Ã¢â€šÂ¬Ã‚Âevidence), and the number of people who have a heart attack (12 studies, 10,520 participants; lowÃƒÂ¢Ã¢â€šÂ¬Ã‚Âcertainty evidence). However, taking betaÃƒÂ¢Ã¢â€šÂ¬Ã‚Âblockers may increase the number of people who experience a very low heart rate (49 studies, 12,239 participants; lowÃƒÂ¢Ã¢â€šÂ¬Ã‚Âcertainty evidence), or very low blood pressure (49 studies, 12,304 participants; moderateÃƒÂ¢Ã¢â€šÂ¬Ã‚Âcertainty evidence), around the time of surgery. In a few studies, we also found little or no difference in the number of people who died after 30 days, who died because of a heart problem, or had heart failure. We found no evidence of whether betaÃƒÂ¢Ã¢â€šÂ¬Ã‚Âblockers alter the length of time in hospital. No studies assessed whether people who were given betaÃƒÂ¢Ã¢â€šÂ¬Ã‚Âblockers had a better quality of life after heart surgery. Certainty of the evidence The certainty of the evidence in this review was limited by including some studies that were at high risk of bias, and we noticed that some of our findings were different if we only included placeboÃƒÂ¢Ã¢â€šÂ¬Ã‚Âcontrolled studies or studies that reported how participants were randomized. We also found one large, wellÃƒÂ¢Ã¢â€šÂ¬Ã‚Âconducted, international study that had different findings to the smaller studies. It showed a reduction in heart attacks and an increase in stroke and allÃƒÂ¢Ã¢â€šÂ¬Ã‚Âcause mortality when betaÃƒÂ¢Ã¢â€šÂ¬Ã‚Âblockers were used, whilst the other studies did not show a clear effect. We were also less certain of the findings for outcomes with few studies, such as for ventricular arrhythmias. Conclusion Although betaÃƒÂ¢Ã¢â€šÂ¬Ã‚Âblockers may make little or no difference to the number of people who die within 30 days, have a stroke, or have ventricular arrhythmias, they may reduce atrial fibrillation and heart attacks. Taking betaÃƒÂ¢Ã¢â€šÂ¬Ã‚Âblockers may increase the number of people with a very low heart rate or very low blood pressure around the time of surgery. Further evidence from large, placeboÃƒÂ¢Ã¢â€šÂ¬Ã‚Âcontrolled trials is likely to increase the certainty of these findings, and we recommend the assessment of impact on quality of life. | E10: FALSE | F10: Focuses on perioperative beta-blockers, not NHS shifts. | G10: None | I10: 0.9
A11: J524 | B11: 2019 | C11: Perioperative betaÃƒÂ¢Ã¢â€šÂ¬Ã‚Âblockers for preventing surgeryÃƒÂ¢Ã¢â€šÂ¬Ã‚Ârelated mortality and morbidity in adults undergoing cardiac surgery | D11: - Background Randomized controlled trials (RCTs) have yielded conflicting results regarding the ability of betaÃƒÂ¢Ã¢â€šÂ¬Ã‚Âblockers to influence perioperative cardiovascular morbidity and mortality. Thus routine prescription of these drugs in unselected patients remains a controversial issue. A previous version of this review assessing the effectiveness of perioperative betaÃƒÂ¢Ã¢â€šÂ¬Ã‚Âblockers in cardiac and nonÃƒÂ¢Ã¢â€šÂ¬Ã‚Âcardiac surgery was last published in 2018. The previous review has now been split into two reviews according to type of surgery. This is an update and assesses the evidence in cardiac surgery only. Objectives To assess the effectiveness of perioperatively administered betaÃƒÂ¢Ã¢â€šÂ¬Ã‚Âblockers for the prevention of surgeryÃƒÂ¢Ã¢â€šÂ¬Ã‚Ârelated mortality and morbidity in adults undergoing cardiac surgery. Search methods We searched CENTRAL, MEDLINE, Embase, CINAHL, Biosis Previews and Conference Proceedings Citation IndexÃƒÂ¢Ã¢â€šÂ¬Ã‚ÂScience on 28 June 2019. We searched clinical trials registers and grey literature, and conducted backwardÃƒÂ¢Ã¢â€šÂ¬Ã‚Â and forwardÃƒÂ¢Ã¢â€šÂ¬Ã‚Âcitation searching of relevant articles. Selection criteria We included RCTs and quasiÃƒÂ¢Ã¢â€šÂ¬Ã‚Ârandomized studies comparing betaÃƒÂ¢Ã¢â€šÂ¬Ã‚Âblockers with a control (placebo or standard care) administered during the perioperative period to adults undergoing cardiac surgery. We excluded studies in which all participants in the standard care control group were given a pharmacological agent that was not given to participants in the intervention group, studies in which all participants in the control group were given a betaÃƒÂ¢Ã¢â€šÂ¬Ã‚Âblocker, and studies in which betaÃƒÂ¢Ã¢â€šÂ¬Ã‚Âblockers were given with an additional agent (e.g. magnesium). We excluded studies that did not measure or report review outcomes. Data collection and analysis Two review authors independently assessed studies for inclusion, extracted data, and assessed risks of bias. We assessed the certainty of evidence with GRADE. Main results We included 63 studies with 7768 participants; six studies were quasiÃƒÂ¢Ã¢â€šÂ¬Ã‚Ârandomized and the remaining were RCTs. All participants were undergoing cardiac surgery, and in most studies, at least some of the participants were previously taking betaÃƒÂ¢Ã¢â€šÂ¬Ã‚Âblockers. Types of betaÃƒÂ¢Ã¢â€šÂ¬Ã‚Âblockers were: propranolol, metoprolol, sotalol, esmolol, landiolol, acebutolol, timolol, carvedilol, nadolol, and atenolol. In twelve studies, betaÃƒÂ¢Ã¢â€šÂ¬Ã‚Âblockers were titrated according to heart rate or blood pressure. Duration of administration varied between studies, as did the time at which drugs were administered; in nine studies this was before surgery, in 20 studies during surgery, and in the remaining studies betaÃƒÂ¢Ã¢â€šÂ¬Ã‚Âblockers were started postoperatively. Overall, we found that most studies did not report sufficient details for us to adequately assess risk of bias. In particular, few studies reported methods used to randomize participants to groups. In some studies, participants in the control group were given betaÃƒÂ¢Ã¢â€šÂ¬Ã‚Âblockers as rescue therapy during the study period, and all studies in which the control was standard care were at high risk of performance bias because of the openÃƒÂ¢Ã¢â€šÂ¬Ã‚Âlabel study design. No studies were prospectively registered with clinical trials registers, which limited the assessment of reporting bias. We judged 68% studies to be at high risk of bias in at least one domain. Study authors reported few deaths (7 per 1000 in both the intervention and control groups), and we found lowÃƒÂ¢Ã¢â€šÂ¬Ã‚Âcertainty evidence that betaÃƒÂ¢Ã¢â€šÂ¬Ã‚Âblockers may make little or no difference to allÃƒÂ¢Ã¢â€šÂ¬Ã‚Âcause mortality at 30 days (risk ratio (RR) 0.95, 95% confidence interval (CI) 0.47 to 1.90; 29 studies, 4099 participants). For myocardial infarctions, we found no evidence of a difference in events (RR 1.05, 95% CI 0.72 to 1.52; 25 studies, 3946 participants; lowÃƒÂ¢Ã¢â€šÂ¬Ã‚Âcertainty evidence). Few study authors reported cerebrovascular events, and the evidence was uncertain (RR 1.37, 95% CI 0.51 to 3.67; 5 studies, 1471 participants; very lowÃƒÂ¢Ã¢â€šÂ¬Ã‚Âcertainty evidence). Based on a control risk of 54 per 1000, we found lowÃƒÂ¢Ã¢â€šÂ¬Ã‚Âcertainty evidence that betaÃƒÂ¢Ã¢â€šÂ¬Ã‚Âblockers may reduce episodes of ventr cular arrhythmias by 32 episodes per 1000 (RR 0.40, 95% CI 0.25 to 0.63; 12 studies, 2296 participants). For atrial fibrillation or flutter, there may be 163 fewer incidences with betaÃƒÂ¢Ã¢â€šÂ¬Ã‚Âblockers, based on a control risk of 327 incidences per 1000 (RR 0.50, 95% CI 0.42 to 0.59; 40 studies, 5650 participants; lowÃƒÂ¢Ã¢â€šÂ¬Ã‚Âcertainty evidence). However, the evidence for bradycardia and hypotension was less certain. We found that betaÃƒÂ¢Ã¢â€šÂ¬Ã‚Âblockers may make little or no difference to bradycardia (RR 1.63, 95% CI 0.92 to 2.91; 12 studies, 1640 participants; lowÃƒÂ¢Ã¢â€šÂ¬Ã‚Âcertainty evidence), or hypotension (RR 1.84, 95% CI 0.89 to 3.80; 10 studies, 1538 participants; lowÃƒÂ¢Ã¢â€šÂ¬Ã‚Âcertainty evidence). We used GRADE to downgrade the certainty of evidence. Owing to studies at high risk of bias in at least one domain, we downgraded each outcome for study limitations. Based on effect size calculations in the previous review, we found an insufficient number of participants in all outcomes (except atrial fibrillation) and, for some outcomes, we noted a wide confidence interval; therefore, we also downgraded outcomes owing to imprecision. The evidence for atrial fibrillation and length of hospital stay had a moderate level of statistical heterogeneity which we could not explain, and we, therefore, downgraded these outcomes for inconsistency. Authors' conclusions We found no evidence of a difference in early allÃƒÂ¢Ã¢â€šÂ¬Ã‚Âcause mortality, myocardial infarction, cerebrovascular events, hypotension and bradycardia. However, there may be a reduction in atrial fibrillation and ventricular arrhythmias when betaÃƒÂ¢Ã¢â€šÂ¬Ã‚Âblockers are used. A larger sample size is likely to increase the certainty of this evidence. Four studies awaiting classification may alter the conclusions of this review. Plain language summary BetaÃƒÂ¢Ã¢â€šÂ¬Ã‚Âblockers to prevent death or serious events after heart surgery This review assessed evidence of whether betaÃƒÂ¢Ã¢â€šÂ¬Ã‚Âblockers given around the time of surgery can reduce death or other serious events for people undergoing heart surgery. Background People undergoing heart surgery are at greater risk of complications and death. Heart surgery increases the amount of stress in the body, causing the release of the hormones adrenaline and noradrenaline. This stress can lead to serious events including death, heart attacks, stroke, or an irregular heartbeat. BetaÃƒÂ¢Ã¢â€šÂ¬Ã‚Âblockers are drugs that block the action of adrenaline and noradrenaline on the heart. BetaÃƒÂ¢Ã¢â€šÂ¬Ã‚Âblockers can slow down the heart and reduce blood pressure, and this effect may reduce the risk of serious events. However, they can also lead to a very low heart rate or very low blood pressure, and this effect may increase the risk of death or a stroke. Prevention of complications around the time of surgery is an important safety consideration for people undergoing heart surgery. Study characteristics The evidence is current to 28 June 2019. We included 63 studies with 7768 adults who were undergoing heart surgery, including coronary artery bypass graft and valve replacement surgery. Studies were mostly randomized controlled studies, and six were quasiÃƒÂ¢Ã¢â€šÂ¬Ã‚Ârandomized (participants were allocated to groups by methods such as using hospital record numbers or dates of birth). The types of betaÃƒÂ¢Ã¢â€šÂ¬Ã‚Âblockers were: propranolol, metoprolol, sotalol, esmolol, landiolol, acebutolol, timolol, carvedilol, nadolol, and atenolol. These betaÃƒÂ¢Ã¢â€šÂ¬Ã‚Âblockers were compared with either a placebo (disguised to look like a betaÃƒÂ¢Ã¢â€šÂ¬Ã‚Âblocker but containing no medicine) or with standard care. BetaÃƒÂ¢Ã¢â€šÂ¬Ã‚Âblockers were started before surgery, during surgery or at the latest by the end of the first day after surgery. The length of time betaÃƒÂ¢Ã¢â€šÂ¬Ã‚Âblockers were given varied between studies. In most studies, at least some of the people were already taking betaÃƒÂ¢Ã¢â€šÂ¬Ã‚Âblockers, which would be expected for people who had conditions that needed heart surgery. Key results BetaÃƒÂ¢Ã¢â€šÂ¬Ã‚Âblockers probably make little or no difference to the number of people who die (29 studies, 4099 participants) or have a heart attack (25 studies, 3946 participants) within 30 days of surgery. This w s supported by lowÃƒÂ¢Ã¢â€šÂ¬Ã‚Âcertainty evidence. Few studies reported on people who had a stroke, and we were uncertain whether or not betaÃƒÂ¢Ã¢â€šÂ¬Ã‚Âblockers reduced strokes because the certainty of the evidence was very low (5 studies, 1471 participants). BetaÃƒÂ¢Ã¢â€šÂ¬Ã‚Âblockers may reduce atrial fibrillation, which is an irregular heartbeat starting in the atrial chambers of the heart that increases the risk of stroke if untreated (40 studies, 5650 participants; lowÃƒÂ¢Ã¢â€šÂ¬Ã‚Âcertainty evidence). BetaÃƒÂ¢Ã¢â€šÂ¬Ã‚Âblockers may also reduce ventricular arrhythmias, which are potentially lifeÃƒÂ¢Ã¢â€šÂ¬Ã‚Âthreatening irregular heartbeat rhythms originating in the main chambers of the heart, and which may need immediate medical treatment (12 studies, 2296 participants). We found that betaÃƒÂ¢Ã¢â€šÂ¬Ã‚Âblockers may make little or no difference to whether people experience a very low heart rate or very low blood pressure. We were uncertain whether betaÃƒÂ¢Ã¢â€šÂ¬Ã‚Âblockers made a difference to the number of deaths up to a year after surgery (3 studies, 511 participants), to death because of the heart (4 studies, 320 participants), or to people who had heart failure (3 studies, 311 participants). The certainty of this evidence was very low. People who took betaÃƒÂ¢Ã¢â€šÂ¬Ã‚Âblockers had a shorter hospital stay by about half a day (14 studies, 2450 participants; lowÃƒÂ¢Ã¢â€šÂ¬Ã‚Âcertainty evidence). No studies assessed whether people on betaÃƒÂ¢Ã¢â€šÂ¬Ã‚Âblockers had a better quality of life after heart surgery. Certainty of the evidence The certainty of the evidence in this review was mostly low. We found that many studies reported methods that we believed could influence the results. For example, many studies did not use a placeboÃƒÂ¢Ã¢â€šÂ¬Ã‚Âcontrol and the doctors might, therefore, have treated people differently in each group. We were unable to explain some of the differences that we found in the data for atrial fibrillation. We also needed to have evidence from a larger number of participants to be very confident in our findings. Conclusion BetaÃƒÂ¢Ã¢â€šÂ¬Ã‚Âblockers may be beneficial for people who are undergoing cardiac surgery because they may reduce the number of people who experience atrial fibrillation and ventricular arrhythmias. BetaÃƒÂ¢Ã¢â€šÂ¬Ã‚Âblockers may make little or no difference to the other outcomes in this review, including death, heart attacks or stroke. | E11: FALSE | F11: Focuses on perioperative beta-blockers, not on NHS Three Shifts. | G11: None | I11: 1
A12: J527 | B12: 2019 | C12: Botulinum toxin type A in the treatment of lower limb spasticity in children with cerebral palsy | D12: - Background Cerebral palsy (CP) is the most common cause of physical disabilities in children in highÃƒÂ¢Ã¢â€šÂ¬Ã‚Âincome countries. Spasticity is the most common motor disturbance in CP. Botulinum toxin type A (BoNTÃƒÂ¢Ã¢â€šÂ¬Ã‚ÂA) is considered the firstÃƒÂ¢Ã¢â€šÂ¬Ã‚Âline treatment for focal spasticity in people with CP. Objectives To evaluate the effectiveness and safety of BoNTÃƒÂ¢Ã¢â€šÂ¬Ã‚ÂA compared to other treatments used in the management of lower limb spasticity in children with CP. Search methods We searched CENTRAL, PubMed, four other databases, and two trial registers in October 2018. We also searched the reference lists of relevant studies and reviews and contacted experts in the field. We did not apply any date or language restrictions. Selection criteria Randomised controlled trials of children with CP, aged between birth and 19 years, treated with BoNTÃƒÂ¢Ã¢â€šÂ¬Ã‚ÂA injections in the lower limb muscles compared to other interventions. The primary outcomes were gait analysis and function. The secondary outcomes were joint range of motion, quality of life, satisfaction, spasticity, and adverse events. Data collection and analysis Two review authors independently selected studies, extracted data, assessed risk of bias, and rated the quality of the evidence using GRADE. A third review author arbitrated in case of disagreements. We conducted metaÃƒÂ¢Ã¢â€šÂ¬Ã‚Âanalyses of available data whenever possible, analysing dichotomous data with risk ratios (RR), and continuous data with mean differences (MD) or standardised mean differences (SMD), with 95% confidence intervals (CI). We considered a 5% significance level for all analyses. Whenever possible, we analysed outcomes at the time points at which they were assessed: short term (2 to 8 weeks); medium term (12 to 16 weeks); and long term (> 24 weeks). Main results We included 31 randomised controlled trials assessing 1508 participants. Most studies included ambulatory patients with more than one motor type of CP, and with a mean age of between three and seven years. There was a slight predominance of males. Studies compared BoNTÃƒÂ¢Ã¢â€šÂ¬Ã‚ÂA in the lower limb muscles to usual care or physiotherapy (14 studies), placebo or sham (12 studies), serial casting (4 studies), or orthoses (1 study). We rated studies as at high or unclear risk of bias mainly due to random sequence generation, allocation concealment, blinding of participants and personnel, and blinding of outcome assessment. BoNTÃƒÂ¢Ã¢â€šÂ¬Ã‚ÂA versus usual care or physiotherapy BoNTÃƒÂ¢Ã¢â€šÂ¬Ã‚ÂA might improve overall gait scores at mediumÃƒÂ¢Ã¢â€šÂ¬Ã‚Âterm followÃƒÂ¢Ã¢â€šÂ¬Ã‚Âup (MD 2.80, 95% CI 1.55 to 4.05; 1 study, 40 children; very lowÃƒÂ¢Ã¢â€šÂ¬Ã‚Âquality evidence) and is moderately effective at improving function at shortÃƒÂ¢Ã¢â€šÂ¬Ã‚Âterm (SMD 0.59, 95% CI 0.23 to 0.95; 2 studies, 123 children) and mediumÃƒÂ¢Ã¢â€šÂ¬Ã‚Âterm (SMD 1.04, 95% CI 0.16 to 1.91; 4 studies, 191 children) followÃƒÂ¢Ã¢â€šÂ¬Ã‚Âup (all very lowÃƒÂ¢Ã¢â€šÂ¬Ã‚Âquality evidence). BoNTÃƒÂ¢Ã¢â€šÂ¬Ã‚ÂA improves ankle range of motion, satisfaction, and ankle plantarflexors spasticity at one or more time points (very lowÃƒÂ¢Ã¢â€šÂ¬Ã‚Âquality evidence). The proportion of adverse events in the BoNTÃƒÂ¢Ã¢â€šÂ¬Ã‚ÂA group was 0.37 (95% CI 0.08 to 0.66; I 2 = 95%; very lowÃƒÂ¢Ã¢â€šÂ¬Ã‚Âquality evidence). No adverse events were reported in the control group. BoNTÃƒÂ¢Ã¢â€šÂ¬Ã‚ÂA versus placebo or sham BoNTÃƒÂ¢Ã¢â€šÂ¬Ã‚ÂA improves overall gait scores at shortÃƒÂ¢Ã¢â€šÂ¬Ã‚Âterm (RR 1.66, 95% CI 1.16 to 2.37, P = 0.006; 4 studies, 261 assessments) and mediumÃƒÂ¢Ã¢â€šÂ¬Ã‚Âterm (RR 1.90, 95% CI 1.32 to 2.74, P < 0.001; 3 studies, 248 assessments) followÃƒÂ¢Ã¢â€šÂ¬Ã‚Âup, and may improve peak ankle dorsiflexion in stance (MD 15.90 degrees, 95% CI 4.87 to 26.93, P = 0.005; 1 study, 19 children) and in swing (MD 10.20 degrees, 95% CI 4.01 to 16.39, P = 0.001; 1 study, 19 children) at shortÃƒÂ¢Ã¢â€šÂ¬Ã‚Âterm followÃƒÂ¢Ã¢â€šÂ¬Ã‚Âup (all moderateÃƒÂ¢Ã¢â€šÂ¬Ã‚Âquality evidence). BoNTÃƒÂ¢Ã¢â€šÂ¬Ã‚ÂA is not more effective than placebo or sham at improving function at shortÃƒÂ¢Ã¢â€šÂ¬Ã‚Âterm (SMD 0.24, 95% CI ÃƒÂ¢Ã‹â€ Ã¢â‚¬â„¢0.35 to 0.83, P = 0.42; 4 studies, 305 children) or longÃƒÂ¢Ã¢â€šÂ¬Ã‚Âterm (SMD ÃƒÂ¢Ã‹â€ Ã¢â‚¬â„¢0.07, 95% CI ÃƒÂ¢Ã‹â€ Ã¢â‚¬â„¢0.48 to 0.35, P = 0.76; 2 studies, 91 children) followÃƒÂ¢Ã¢â€šÂ¬Ã‚Âup, but has a small positive effect at mediumÃƒÂ¢Ã¢â€šÂ¬Ã‚Âterm followÃƒÂ¢Ã¢â€šÂ¬Ã‚Âup (SMD 0.28, 95% CI 0.06 to 0.49, P = 0.01; 5 studies, 327 children) (all moderateÃƒÂ¢Ã¢â€šÂ¬Ã‚Âquality evidence). BoNTÃƒÂ¢Ã¢â€šÂ¬Ã‚ÂA improves passive ankle range of motion, satisfaction, and ankle plantarflexors spasticity at one or more time points (moderateÃƒÂ¢Ã¢â€šÂ¬Ã‚Âquality evidence). There was no difference between groups in the rate of adverse events at shortÃƒÂ¢Ã¢â€šÂ¬Ã‚Âterm followÃƒÂ¢Ã¢â€šÂ¬Ã‚Âup (RR 1.29, 95% CI 0.87 to 1.93, P = 0.21; 12 studies, 918 children; moderateÃƒÂ¢Ã¢â€šÂ¬Ã‚Âquality evidence). BoNTÃƒÂ¢Ã¢â€šÂ¬Ã‚ÂA versus serial casting There was no difference between groups for overall gait scores at shortÃƒÂ¢Ã¢â€šÂ¬Ã‚Âterm (MD 0.00, 95% CI ÃƒÂ¢Ã‹â€ Ã¢â‚¬â„¢1.66 to 1.66); mediumÃƒÂ¢Ã¢â€šÂ¬Ã‚Âterm (MD 0.65, 95% CI ÃƒÂ¢Ã‹â€ Ã¢â‚¬â„¢1.21 to 2.51); or longÃƒÂ¢Ã¢â€šÂ¬Ã‚Âterm (MD 0.46, 95% CI ÃƒÂ¢Ã‹â€ Ã¢â‚¬â„¢1.33 to 2.25) followÃƒÂ¢Ã¢â€šÂ¬Ã‚Âup in one study with 18 children (moderateÃƒÂ¢Ã¢â€šÂ¬Ã‚Âquality evidence). BoNTÃƒÂ¢Ã¢â€šÂ¬Ã‚ÂA improved instrumented gait analysis only in terms of ankle dorsiflexion at initial contact (MD 6.59 degrees, 95% CI 1.39 to 11.78, P = 0.01; 2 studies, 47 children). There was no difference between groups for peak ankle dorsiflexion in stance and swing, and gait speed at any time point (moderateÃƒÂ¢Ã¢â€šÂ¬Ã‚Â and lowÃƒÂ¢Ã¢â€šÂ¬Ã‚Âquality evidence). BoNTÃƒÂ¢Ã¢â€šÂ¬Ã‚ÂA is not more effective than serial casting at improving function, ankle range of motion, and spasticity at any time point (moderateÃƒÂ¢Ã¢â€šÂ¬Ã‚Â and lowÃƒÂ¢Ã¢â€šÂ¬Ã‚Âquality evidence). BoNTÃƒÂ¢Ã¢â€šÂ¬Ã‚ÂA is not associated with a higher risk of adverse events than serial casting (RR 0.59, 95% CI 0.03 to 11.03; 3 studies, 64 children; lowÃƒÂ¢Ã¢â€šÂ¬Ã‚Âquality evidence). BoNTÃƒÂ¢Ã¢â€šÂ¬Ã‚ÂA versus orthoses There was no difference between groups for function at mediumÃƒÂ¢Ã¢â€šÂ¬Ã‚Âterm followÃƒÂ¢Ã¢â€šÂ¬Ã‚Âup (MD 11.14, 95% CI ÃƒÂ¢Ã‹â€ Ã¢â‚¬â„¢0.05 to 22.33; 1 study, 43 children), but BoNTÃƒÂ¢Ã¢â€šÂ¬Ã‚ÂA is more effective than orthoses at improving hip range of motion and hip adductors spasticity (all very lowÃƒÂ¢Ã¢â€šÂ¬Ã‚Âquality evidence). Authors' conclusions The quality of the evidence was low or very low for most of the outcomes analysed. We found limited evidence that BoNTÃƒÂ¢Ã¢â€šÂ¬Ã‚ÂA is more effective than placebo or a nonÃƒÂ¢Ã¢â€šÂ¬Ã‚Âplacebo control at improving gait, joint range of motion, satisfaction, and lower limb spasticity in children with CP, whereas the results for function were contradictory. The rate of adverse events with BoNTÃƒÂ¢Ã¢â€šÂ¬Ã‚ÂA is similar to placebo. BoNTÃƒÂ¢Ã¢â€šÂ¬Ã‚ÂA is not more effective than ankle serial casting to treat ankle contractures for any of the assessed outcomes, but is more effective than orthotics at improving range of motion and spasticity. Plain language summary Botulinum toxin type A injections for the treatment of lower limb spasticity in cerebral palsy Background Cerebral palsy (CP) is a nonÃƒÂ¢Ã¢â€šÂ¬Ã‚Âprogressive, lifelong condition resulting from damage to the developing brain. Over time, most children with CP will develop abnormal muscle activity and stiffness/overactivity (spasticity) that affects at least one limb and interferes with their normal movement. Treatments for spasticity include physiotherapy, oral antispasticity drugs (a type of medication that works to relax the muscles and relieve spasticity), casts, splints, orthopaedic surgery, and botulinum toxin A (BoNTÃƒÂ¢Ã¢â€šÂ¬Ã‚ÂA; a poisonous biological substance that is thought to relieve spasticity by reducing muscle overactivity when injected into the muscle). This review looked at the effects of BoNTÃƒÂ¢Ã¢â€šÂ¬Ã‚ÂA. Review question The aim of this review was to assess and summarise scientific studies comparing BoNTÃƒÂ¢Ã¢â€šÂ¬Ã‚ÂA injections to other treatments for lower limb spasticity in children with CP. Study characteristics We found 31 studies assessing 1508 participants. The use of BoNTÃƒÂ¢Ã¢â€šÂ¬Ã‚ÂA in the lower limb muscles was compared to: (1) children's regular care or physiotherapy, (2) placebo (fake injections), (3) a series of belowÃƒÂ¢Ã¢â€šÂ¬Ã‚Âknee plaster casts, and (4) leg splints. Key results Children receiving BoNTÃƒÂ¢Ã¢â€šÂ¬Ã‚ÂA injections tended to have improved walking pattern (gait), joint range of motion, satisfaction with outcome of treatment, and muscle spasms compared with their usual programme of care or physiotherapy, or placebo. Measures of function tended to show only modest improvements in children receiving BoNTÃƒÂ¢Ã¢â€šÂ¬Ã‚ÂA injections. The rate of side effects was similar when comparing BoNTÃƒÂ¢Ã¢â€šÂ¬Ã‚ÂA injections to placebo. BoNTÃƒÂ¢Ã¢â€šÂ¬Ã‚ÂA injections and plaster cas s below the knee produced similar benefits in walking and joint motion and relieving spasms. In addition, BoNTÃƒÂ¢Ã¢â€šÂ¬Ã‚ÂA provided better results in terms of joint range of motion compared to a specific type of splinting (Johnstone pressure splints). Quality of the evidence We considered the quality of the evidence as very low for the comparison BoNTÃƒÂ¢Ã¢â€šÂ¬Ã‚ÂA versus usual care or physiotherapy; moderate for the comparison BoNTÃƒÂ¢Ã¢â€šÂ¬Ã‚ÂA versus placebo; moderate and low for the comparison BoNTÃƒÂ¢Ã¢â€šÂ¬Ã‚ÂA versus plaster casts; and very low for the comparison BoNTÃƒÂ¢Ã¢â€šÂ¬Ã‚ÂA versus splints. Conclusion There is limited evidence that, compared to placebo or regular care, BoNTÃƒÂ¢Ã¢â€šÂ¬Ã‚ÂA improves walking, joint motion, satisfaction with the outcome of treatment, and muscle spasticity in children with CP. The rate of side effects with BoNTÃƒÂ¢Ã¢â€šÂ¬Ã‚ÂA was similar to placebo. BoNTÃƒÂ¢Ã¢â€šÂ¬Ã‚ÂA was no better than plaster casts in any of our analyses, but was better than splints at improving range of motion and spasticity. | E12: FALSE | F12: Focuses on treatment efficacy, not NHS Three Shifts. | G12: None | I12: 0.9
A13: J530 | B13: 2019 | C13: Cyclical progestogens for heavy menstrual bleeding | D13: - Background Heavy menstrual bleeding (HMB) is a menstrual blood loss perceived by women as excessive that affects the health of women of reproductive age, interfering with their physical, emotional, social and material quality of life. Whilst abnormal menstrual bleeding may be associated with underlying pathology, in the present context, HMB is defined as excessive menstrual bleeding in the absence of other systemic or gynaecological disease. The firstÃƒÂ¢Ã¢â€šÂ¬Ã‚Âline therapy is usually medical, avoiding possibly unnecessary surgery. Of the wide variety of medications used to reduce HMB, oral progestogens were originally the most commonly prescribed agents. This review assesses the effectiveness of two different types and regimens of oral progestogens in reducing ovulatory HMB. This is the update of a Cochrane review last updated in 2007, and originally named Effectiveness of cyclical progestagen therapy in reducing heavy menstrual bleeding" (1998). Objectives To determine the effectiveness, safety and tolerability of oral progestogen therapy taken either during the luteal phase (short cycle) or for a longer course of 21 days per cycle (long cycle), in achieving a reduction in menstrual blood loss in women of reproductive age with HMB. Search methods In January 2019 we searched Cochrane Gynaecology and Fertility's specialized register, CENTRAL, MEDLINE, Embase, CINAHL and PsycInfo. We also searched trials registers, other sources of unpublished or grey literature and reference lists of retrieved trials. We also checked citation lists of review articles to identify trials. Selection criteria Randomized controlled trials (RCTs) comparing different treatments for HMB that included cyclical oral progestogens were eligible. Data collection and analysis Two review authors independently selected trials for inclusion, assessed trials for risk of bias and extracted data. We contacted trial authors for clarification of methods or additional data when necessary. We only assessed adverse events if they were separately measured in the included trials. We compared cyclical oral progestogen in different regimens and placebo or other treatments. Our primary outcomes were menstrual blood loss and satisfaction with treatment; the secondary outcomes were number of days of bleeding, quality of life, compliance and acceptability of treatment, adverse events and costs. Main results This review identified 15 randomized controlled trials (RCTs) with 1071 women in total. Most of the women knew which treatment they were receiving, which may have influenced their judgements about menstrual blood loss and satisfaction. Other aspects of trial quality varied among trials. We did not identify any RCTs comparing progestogen treatment with placebo . We assessed comparisons between oral progestogens and other medical therapies separately according to different regimens. ShortÃƒÂ¢Ã¢â€šÂ¬Ã‚Âcycle progestogen therapy during the luteal phase (medroxyprogesterone acetate or norethisterone for 7 to 10 days, from day 15 to 19) was inferior to other medical therapy, including tranexamic acid, danazol and the progestogenÃƒÂ¢Ã¢â€šÂ¬Ã‚Âreleasing intrauterine system (PgÃƒÂ¢Ã¢â€šÂ¬Ã‚ÂIUS (off the market since 2001)), releasing 60 mcg of progesterone daily, with respect to reduction of menstrual blood loss (mean difference (MD) 37.29, 95% confidence interval (CI) 17.67 to 56.91; I 2 = 50%; 6 trials, 145 women, lowÃƒÂ¢Ã¢â€šÂ¬Ã‚Âquality evidence). The rate of satisfaction and the quality of life with treatment was similar in both groups. The number of bleeding days was greater on the short cycle progestogen group compared to other medical treatments. Adverse events (such as gastrointestinal symptoms and weight gain) were more likely with danazol when compared with progestogen treatment. We note that danazol is no longer in general use for treating HMB. LongÃƒÂ¢Ã¢â€šÂ¬Ã‚Âcycle progestogen therapy (medroxyprogesterone acetate or norethisterone), from day 5 to day 26 of the menstrual cycle, is also inferior compared to the levonorgestrelÃƒÂ¢Ã¢â€šÂ¬Ã‚Âreleasing intrauterine system (LNGÃƒÂ¢Ã¢â€šÂ¬Ã‚ÂIUS), tranexamic acid and ormeloxifene, ut may be similar to the combined vaginal ring with respect to reduction of menstrual blood loss (MD 16.88, 95% CI 10.93 to 22.84; I 2 = 87%; 4 trials, 355 women, very lowÃƒÂ¢Ã¢â€šÂ¬Ã‚Âquality evidence). There was no clear evidence of a difference between progestogen therapy long cycle and other medical therapy in terms of headache (OR 1.45, 95% CI 0.40 to 5.31; I 2 = 0%; 2 trials, 189 women; lowÃƒÂ¢Ã¢â€šÂ¬Ã‚Âquality evidence). Breakthrough bleeding or spotting was more likely in women with the LNGÃƒÂ¢Ã¢â€šÂ¬Ã‚ÂIUS (OR 0.18, 95% CI 0.06 to 0.55; I 2 = 0%; 3 trials, 220 women; lowÃƒÂ¢Ã¢â€šÂ¬Ã‚Âquality evidence). No trials reported on days of bleeding or quality of life for this comparison. The evidence supporting these findings was limited by low or very low gradings of quality; thus, we are uncertain about the findings and there is a potential that they may change if we identify other trials. Authors' conclusions LowÃƒÂ¢Ã¢â€šÂ¬Ã‚Â or very lowÃƒÂ¢Ã¢â€šÂ¬Ã‚Âquality evidence suggests that shortÃƒÂ¢Ã¢â€šÂ¬Ã‚Âcourse progestogen was inferior to other medical therapy, including tranexamic acid, danazol and the PgÃƒÂ¢Ã¢â€šÂ¬Ã‚ÂIUS with respect to reduction of menstrual blood loss. Long cycle progestogen therapy (medroxyprogesterone acetate or norethisterone) was also inferior to the LNGÃƒÂ¢Ã¢â€šÂ¬Ã‚ÂIUS, tranexamic acid and ormeloxifene, but may be similar to the combined vaginal ring with respect to reduction of menstrual blood loss. Plain language summary Are cyclical progestogens an effective and safe treatment for heavy menstrual bleeding compared to other medical treatments? Background Heavy menstrual bleeding (HMB) is menstrual bleeding (periods) that interferes with a woman's quality of life, either physical, emotional, social or material, independently of the actual amount of blood loss. Most women with HMB do not have any associated physical cause, such as fibroids, so getting help that does not involve surgery is an attractive alternative. A cyclical progestogen is a hormone tablet that can be taken by mouth for either 10 days or 3 to 4 weeks per month for the treatment of HMB (short or long course cyclical progestogen). Trial characteristics This review identified 15 randomized controlled trials (clinical studies where people are randomly put into one of two or more treatment groups) with 1071 women in total comparing oral progestogens to other medical treatment for HMB (other oral treatments, intrauterine device and vaginal ring). Our primary outcomes were menstrual blood loss and satisfaction with treatment; the secondary outcomes were number of days of bleeding, quality of life, compliance and acceptability of treatment, adverse events and costs. Evidence is current to January 2019. Key results This review of trials found that progestogen hormone tablets taken by mouth for 10 days per month (short course) were less effective at reducing menstrual blood loss when compared to other medical treatments. We are uncertain whether they improved satisfaction or quality of life in women with HMB, or were associated with any difference in adverse effects when compared to other medical treatments. Even though it was less effective at reducing menstrual blood loss, satisfaction with treatment was similar to other medical treatments such as tranexamic acid and PgÃƒÂ¢Ã¢â€šÂ¬Ã‚ÂIUS. We found that progestogen hormone tablets, taken by mouth for three to four weeks from day 5 to 26 of the menstrual cycle (long course), reduced menstrual blood loss but this treatment may be less effective than tranexamic acid, combined hormonal contraceptives and the levonorgestrelÃƒÂ¢Ã¢â€šÂ¬Ã‚Âreleasing intrauterine device. No studies in this comparison reported on quality of life. Satisfaction with treatment was similar to women using the combined vaginal ring, but there were no data to compare satisfaction between long cycle and LNGÃƒÂ¢Ã¢â€šÂ¬Ã‚ÂIUS or tranexamic acid. There was no evidence of a difference in the occurrence of headache, but long course oral progestogens were associated with a significantly lower incidence of breakthrough bleeding compared with other medical treatment. Quality of the evidence The quality of the evidence that compared oral progestogens (shor and long course) to other medical treatments for HMB was either low or very low which means that we are very uncertain of the findings of the review. The main limitations were risk of bias (women and researchers were aware of the treatment they were receiving which was likely to interfere with the responses, and there was a high number of dropouts from studies) and inconsistency (the results varied among studies)." | E13: FALSE | F13: Focuses on treatment efficacy for HMB, not NHS shifts. | G13: None | I13: 0.95
A14: J535 | B14: 2019 | C14: Interventions for prodromal stage of psychosis | D14: - Background Psychosis is a serious mental condition characterised by a loss of contact with reality. There may be a prodromal period or stage of psychosis, where early signs of symptoms indicating onset of first episode psychosis (FEP) occur. A number of services, incorporating multimodal treatment approaches (pharmacotherapy, psychotherapy and psychosocial interventions), developed worldwide, now focus on this prodromal period with the aim of preventing psychosis in people at risk of developing FEP. Objectives The primary objective is to assess the safety and efficacy of early interventions for people in the prodromal stage of psychosis. The secondary objective is, if possible, to compare the effectiveness of the various different interventions. Search methods We searched Cochrane Schizophrenia's studyÃƒÂ¢Ã¢â€šÂ¬Ã‚Âbased Register of studies (including trials registers) on 8 June 2016 and 4 August 2017. Selection criteria All randomised controlled trials (RCTs) evaluating interventions for participants older than 12 years, who had developed a prodromal stage of psychosis. Data collection and analysis Review authors independently inspected citations, selected studies, extracted data, and assessed study quality. Main results We included 20 studies with 2151 participants. The studies analysed 13 different comparisons. Group A comparisons explored the absolute effects of the experimental intervention. Group B were comparisons within which we could not be clear whether differential interactive effects were also ongoing. Group C comparisons explored differential effects between clearly distinct treatments. A key outcome for this review was ÃƒÂ¢Ã¢â€šÂ¬Ã‹Å“transition to psychosisÃƒÂ¢Ã¢â€šÂ¬Ã¢â€žÂ¢. For details of other main outcomes please see 'Summary of findings' tables. In Group A (comparisons of absolute effects) we found no clear difference between amino acids and placebo (risk ratio (RR) 0.48 95% confidence interval (CI) 0.08 to 2.98; 2 RCTs, 52 participants; very lowÃƒÂ¢Ã¢â€šÂ¬Ã‚Âquality evidence). When omegaÃƒÂ¢Ã¢â€šÂ¬Ã‚Â3 fatty acids were compared to placebo, fewer participants given the omegaÃƒÂ¢Ã¢â€šÂ¬Ã‚Â3 (10%) transitioned to psychosis compared to the placebo group (33%) during longÃƒÂ¢Ã¢â€šÂ¬Ã‚Âterm followÃƒÂ¢Ã¢â€šÂ¬Ã‚Âup of seven years (RR 0.24 95% CI 0.09 to 0.67; 1 RCT, 81 participants; lowÃƒÂ¢Ã¢â€šÂ¬Ã‚Âquality evidence). In Group B (comparisons where complex interactions are probable) and in the subgroup focusing on antipsychotic drugs added to specific care packages, the amisulpiride + needsÃƒÂ¢Ã¢â€šÂ¬Ã‚Âfocused intervention (NFI) compared to NFI comparison (no reporting of transition to psychosis; 1 RCT, 102 participants; very lowÃƒÂ¢Ã¢â€šÂ¬Ã‚Âquality evidence) and the olanzapine + supportive intervention compared to supportive intervention alone comparison (RR 0.58 95% CI 0.28 to 1.18; 1 RCT, 60 participants; very lowÃƒÂ¢Ã¢â€šÂ¬Ã‚Âquality evidence) showed no clear differences between groups. In the second Group B subgroup (cognitive behavioural therapies (CBT)), when CBT + supportive therapy was compared with supportive therapy alone around 8% of participants allocated to the combination of CBT and supportive therapy group transitioned to psychosis during followÃƒÂ¢Ã¢â€šÂ¬Ã‚Âup by 18 months, compared with double that percentage in the supportive therapy alone group (RR 0.45 95% CI 0.23 to 0.89; 2 RCTs, 252 participants; very lowÃƒÂ¢Ã¢â€šÂ¬Ã‚Âquality evidence). The CBT + risperidone versus CBT + placebo comparison identified no clear difference between treatments (RR 1.02 95% CI 0.39 to 2.67; 1 RCT, 87 participants; very lowÃƒÂ¢Ã¢â€šÂ¬Ã‚Âquality evidence) and this also applies to the CBT + needsÃƒÂ¢Ã¢â€šÂ¬Ã‚Âbased intervention (NBI) + risperidone versus NBI comparison (RR 0.75 95% CI 0.39 to 1.46; 1 RCT, 59 participants; very lowÃƒÂ¢Ã¢â€šÂ¬Ã‚Âquality evidence). Group C (differential effects) also involved six comparisons. The first compared CBT with supportive therapy. No clear difference was found for the ÃƒÂ¢Ã¢â€šÂ¬Ã‹Å“transition to psychosisÃƒÂ¢Ã¢â€šÂ¬Ã¢â€žÂ¢ outcome (RR 0.74 95% CI 0.28 to 1.98; 1 RCT, 72 participants; very lowÃƒÂ¢Ã¢â€šÂ¬Ã‚Âquality evidence). The second subgroup compared CBT + supportive intervention was compared with a NBI + supportive intervention, again, data were equivocal, few and of very low quality (RR 6.32 95% CI 0.34 to 117.09; 1 RCT, 57 participants). In the CBT + risperidone versus supportive therapy comparison, again there was no clear difference between groups (RR 0.76 95% CI 0.28 to 2.03; 1 RCT, 71 participants; very lowÃƒÂ¢Ã¢â€šÂ¬Ã‚Âquality evidence). The three other comparisons in Group C demonstrated no clear differences between treatment groups. When cognitive training was compared to active control (tablet games) (no reporting of transition to psychosis; 1 RCT, 62 participants; very low quality data), family treatment compared with enhanced care comparison (RR 0.54 95% CI 0.18 to 1.59; 2 RCTs, 229 participants; very lowÃƒÂ¢Ã¢â€šÂ¬Ã‚Âquality evidence) and integrated treatment compared to standard treatment comparison (RR 0.57 95% CI 0.28 to 1.15; 1 RCT, 79 participants; very lowÃƒÂ¢Ã¢â€šÂ¬Ã‚Âquality evidence) no effects of any of these approaches was evident. Authors' conclusions There has been considerable research effort in this area and several interventions have been trialled. The evidence available suggests that omegaÃƒÂ¢Ã¢â€šÂ¬Ã‚Â3 fatty acids may prevent transition to psychosis but this evidence is low quality and more research is needed to confirm this finding. Other comparisons did not show any clear differences in effect for preventing transition to psychosis but again, the quality of this evidence is very low or low and not strong enough to make firm conclusions. Plain language summary Early interventions for people at risk of developing psychosis Review question Is there highÃƒÂ¢Ã¢â€šÂ¬Ã‚Âquality evidence indicating that interventions for people at risk of developing psychosis are effective? Background Psychoses are serious mental conditions characterised by a loss of contact with reality. The first clear episode of psychosis can be preceded by a 'prodromal' period of at least six months, where a person experiences gradual nonÃƒÂ¢Ã¢â€šÂ¬Ã‚Âspecific changes in thoughts, perceptions, behaviours and functioning. Although an individual is experiencing changes, they have not yet started to experience the more obvious psychotic symptoms such as delusions (fixed false beliefs) or hallucinations (perceptions without a cause). A number of services with treatment approaches that combine pharmacotherapy, psychotherapy and psychosocial treatments, developed worldwide, are now focusing on prevention of psychosis in people at risk by giving treatments during this prodromal period. This review assesses the evidence available concerning the effects of different treatment approaches for people not yet diagnosed with a non affective psychosis but who are in the prodromal stage of psychosis. Searching for evidence On 8 June 2016 and 4 August 2017 we ran electronic searches of the Cochrane Schizophrenia's specialised register of studies in order to find clinical studies that randomly allocated individuals at risk of developing psychosis to receive various treatments for preventing development of psychosis. Evidence found We were able to include 20 studies with 2151 participants. These studies analysed a wide range of treatments. All the review findings are of, at very best, low quality. There is some suggestion from one small study that people at risk of psychosis may benefit from taking omegaÃƒÂ¢Ã¢â€šÂ¬Ã‚Â3 fatty acids in terms of reduced transition to psychosis. Other studies found adding antipsychotic drugs to supportiveÃƒÂ¢Ã¢â€šÂ¬Ã‚Âcare packages did not seem to make much difference in terms of transition to full illness. When cognitive behavioural therapy (CBT) + supportive therapy was compared with supportive therapy alone around 8% of participants treated allocated to the combination of CBT and supportive therapy transitioned to psychosis during followÃƒÂ¢Ã¢â€šÂ¬Ã‚Âup by 18 months, compared with double that percentage in people who just received supportive therapy. This could be important but these data are of very low quality. All other testing of CBT and other packages of care found no clear difference between treatments for transition to psychosis. Conclusions There has been considerable effort and expense invested testing treatment approaches for prevention of the first episode of schizophr nia. Currently, there is some lowÃƒÂ¢Ã¢â€šÂ¬Ã‚Âquality evidence suggesting that omegaÃƒÂ¢Ã¢â€šÂ¬Ã‚Â3 fatty acids may be effective, but there is no highÃƒÂ¢Ã¢â€šÂ¬Ã‚Âquality evidence to suggest that any type of treatment is effective, and no firm conclusions can be made. | E14: TRUE | F14: Focus on preventing psychosis aligns with proactive early interventions. | G14: Prevention | H14: Prevention | I14: 0.9
A15: J537 | B15: 2019 | C15: Screening Women for Abdominal Aortic Aneurysms: Clinical and Economic Effectiveness Results from a Discrete Event Simulation Model | D15: Introduction - Abdominal aortic aneurysm (AAA) screening programmes have been established for men in several countries. Whether screening should be extended to women is uncertain. The objective of this study was to evaluate the cost-effectiveness of population screening for AAA in women, and compare a range of screening options. Methods - A discrete event simulation model was developed to provide a clinically realistic model of screening, surveillance, and elective and emergency AAA repair in women. Input parameters specifically for women were obtained from surgical registries, published literature and national administrative datasets. Screening was modelled for women aged 65 years or over. The model was run for 10-million women, with parameter uncertainty addressed by probabilistic and deterministic sensitivity analyses. UK costs in pounds sterling were converted to Euros based on 2016 average OECD purchasing power parity. Results - The prevalence of AAA (aortic diameter 33.0cm) was estimated as 0.43% in women aged 65 years and 1.15% at age 75. The corresponding attendance rates following invitation to screening were estimated as 73% and 62%. The base-case model adopted the same age at screening (65 years), definition of AAA (33.0cm), surveillance intervals (1 year for 3.0-4.4cm AAAs, 3 months for 4.5-5.4cm) and AAA diameter for consideration of surgery (5.5cm) as in the UK NHS AAA screening programmes. For screening at age 65, per woman invited to screening, the estimated gain in QALYs was 0.00075 (just under one day of life per woman screened), and the incremental cost was 33.51 (36.33) (all values discounted). This gave an incremental cost-effectiveness ratio (ICER) of 45,000 (48,782) per quality-adjusted life-year (QALY) gained (current UK threshold for implementation approximately 20,000 (21,681)). Under the base-case model around 2800 women would need to be invited to screening to prevent one death from AAA and screening would cost 100,000 (108,406) per death from AAA prevented (non-discounted). Sensitivity analyses did not bring the ICER below 20,000 per QALY gained, with the exception of doubling the AAA prevalence to 0.86% where the ICER was 18,000 (19,513). Alternative screening options (increasing the screening age to 70 years, lowering the threshold for considering surgery to 5.0 or 4.5cm, lowering the diameter defining an AAA in women to 2.5cm, and lengthening the surveillance intervals for the smallest AAAs) did not bring the ICER below 30,000 (32,522) per QALY gained when considered either singly or in combination. Conclusion - The current UK cost-effectiveness criteria for a population-based AAA screening programme in women are not currently met. Copyright Ãƒâ€šÃ‚Â© 2019 | E15: FALSE | F15: Focuses on screening effectiveness, not on NHS shifts. | G15: None | I15: 0.95
A16: J540 | B16: 2019 | C16: Conservative management following closed reduction of traumatic anterior dislocation of the shoulder | D16: - Background Acute anterior shoulder dislocation, which is the most common type of dislocation, usually results from an injury. Subsequently, the shoulder is less stable and is more susceptible to reÃƒÂ¢Ã¢â€šÂ¬Ã‚Âdislocation or recurrent instability (e.g. subluxation), especially in active young adults. After closed reduction, most of these injuries are treated with immobilisation of the injured arm in a sling or brace for a few weeks, followed by exercises. This is an update of a Cochrane Review first published in 2006 and last updated in 2014. Objectives To assess the effects (benefits and harms) of conservative interventions after closed reduction of traumatic anterior dislocation of the shoulder. These might include immobilisation, rehabilitative interventions or both. Search methods We searched the Cochrane Bone, Joint and Muscle Trauma Group Specialised Register, the Cochrane Central Register of Controlled Trials, MEDLINE, Embase, CINAHL, PEDro and trial registries. We also searched conference proceedings and reference lists of included studies. Date of last search: May 2018. Selection criteria We included randomised or quasiÃƒÂ¢Ã¢â€šÂ¬Ã‚Ârandomised controlled trials comparing conservative interventions with no treatment, a different intervention or a variant of the intervention (e.g. a different duration) for treating people after closed reduction of a primary traumatic anterior shoulder dislocation. Inclusion was regardless of age, sex or mechanism of injury. Primary outcomes were reÃƒÂ¢Ã¢â€šÂ¬Ã‚Âdislocation, patientÃƒÂ¢Ã¢â€šÂ¬Ã‚Âreported shoulder instability measures and return to preÃƒÂ¢Ã¢â€šÂ¬Ã‚Âinjury activities. Secondary outcomes included participant satisfaction, healthÃƒÂ¢Ã¢â€šÂ¬Ã‚Ârelated quality of life, any instability and adverse events. Data collection and analysis Both review authors independently selected studies, assessed risk of bias and extracted data. We contacted study authors for additional information. We pooled results of comparable groups of studies. We assessed risk of bias with the Cochrane 'Risk of bias' tool and the quality of the evidence with the GRADE approach. Main results We included seven trials (six randomised controlled trials and one quasiÃƒÂ¢Ã¢â€šÂ¬Ã‚Ârandomised controlled trial) with 704 participants; three of these trials (234 participants) are new to this update. The mean age across the trials was 29 years (range 12 to 90 years), and 82% of the participants were male. All trials compared immobilisation in external rotation (with or without an additional abduction component) versus internal rotation (the traditional method) following closed reduction. No trial evaluated any other interventions or comparisons, such as rehabilitation. All trials provided data for a followÃƒÂ¢Ã¢â€šÂ¬Ã‚Âup of one year or longer; the commonest length was two years or longer. All trials were at some risk of bias, commonly performance and detection biases given the lack of blinding. Two trials were at high risk of selection bias and some trials were affected by attrition bias for some outcomes. We rated the certainty of the evidence as very low for all outcomes. We are uncertain whether immobilisation in external rotation makes a difference to the risk of reÃƒÂ¢Ã¢â€šÂ¬Ã‚Âdislocation after 12 months' or longer followÃƒÂ¢Ã¢â€šÂ¬Ã‚Âup compared with immobilisation in internal rotation (55/245 versus 73/243; risk ratio (RR) 0.67, 95% confidence interval (CI) 0.38 to 1.19; 488 participants; 6 studies; IÃƒâ€šÃ‚Â² = 61%; very low certainty evidence). In a moderateÃƒÂ¢Ã¢â€šÂ¬Ã‚Ârisk population with an illustrative risk of 312 per 1000 people experiencing a dislocation in the internal rotation group, this equates to 103 fewer (95% CI 194 fewer to 60 more) reÃƒÂ¢Ã¢â€šÂ¬Ã‚Âdislocations after immobilisation in external rotation. Thus this result covers the possibility of a benefit for each intervention. Individually, the four studies (380 participants) reporting on validated patientÃƒÂ¢Ã¢â€šÂ¬Ã‚Âreported outcome measures for shoulder instability at a minimum of 12 months' followÃƒÂ¢Ã¢â€šÂ¬Ã‚Âup found no evidence of a clinically important difference between the two interventions. We are uncertain of the relative effects of the two methods of immobilisat on on resumption of preÃƒÂ¢Ã¢â€šÂ¬Ã‚Âinjury activities or sports. One study (169 participants) found no evidence of a difference between interventions in the return to preÃƒÂ¢Ã¢â€šÂ¬Ã‚Âinjury activity of the affected arm. Two studies (135 participants) found greater return to sports in the external rotation group in a subgroup of participants who had sustained their injury during sports activities. None of the trials reported on participant satisfaction or healthÃƒÂ¢Ã¢â€šÂ¬Ã‚Ârelated quality of life. We are uncertain whether there is a difference between the two interventions in the number of participants experiencing instability, defined as either reÃƒÂ¢Ã¢â€šÂ¬Ã‚Âdislocation or subluxation (RR 0.84, 95% CI 0.62 to 1.14; 395 participants, 3 studies; very low certainty evidence). Data on adverse events were collected only in an ad hoc way in the seven studies. Reported transient and resolved adverse events" were nine cases of shoulder stiffness or rigidity in the external rotation group and two cases of axillary rash in the internal rotation group. There were three "important" adverse events: hyperaesthesia and moderate hand pain; eighth cervical dermatome paraesthesia; and major movement restriction between 6 and 12 months. It was unclear to what extent these three events could be attributed to the treatment. Authors' conclusions The available evidence from randomised trials is limited to that comparing immobilisation in external versus internal rotation. Overall, the evidence is insufficient to draw firm conclusions about whether immobilisation in external rotation confers any benefit over immobilisation in internal rotation. Considering that there are several unpublished and ongoing trials evaluating immobilisation in external versus internal rotation, the main priority for research on this question consists of the publication of completed trials and the completion and publication of ongoing trials. Meanwhile, evaluation of other interventions, including rehabilitation, is warranted. There is a need for sufficiently large, goodÃƒÂ¢Ã¢â€šÂ¬Ã‚Âquality, wellÃƒÂ¢Ã¢â€šÂ¬Ã‚Âreported randomised controlled trials with longÃƒÂ¢Ã¢â€šÂ¬Ã‚Âterm followÃƒÂ¢Ã¢â€šÂ¬Ã‚Âup. Future research should aim to determine the optimal immobilisation duration, precise indications for immobilisation, optimal rehabilitation interventions, and the acceptability of these different interventions. Plain language summary NonÃƒÂ¢Ã¢â€šÂ¬Ã‚Âsurgical management after nonÃƒÂ¢Ã¢â€šÂ¬Ã‚Âsurgical repositioning of traumatic anterior dislocation of the shoulder Background Acute anterior shoulder dislocation is an injury in which the top end of the upper arm bone is pushed out of the joint socket in a forward direction. Afterwards, the shoulder is less stable, and prone to either partial or complete reÃƒÂ¢Ã¢â€šÂ¬Ã‚Âdislocation, especially in active young adults. Initial treatment involves putting the joint back in place. This is called ÃƒÂ¢Ã¢â€šÂ¬Ã‹Å“closed reductionÃƒÂ¢Ã¢â€šÂ¬Ã¢â€žÂ¢ when it is done without surgery. Subsequent treatment is often conservative (nonÃƒÂ¢Ã¢â€šÂ¬Ã‚Âsurgical) and usually involves a period of immobilisation of the injured arm in a sling or brace, followed by exercises. Review question What are the benefits and harms of different conservative interventions for treating people after closed reduction of a primary traumatic anterior shoulder dislocation? This is an update of a review that was first published in 2006 and last updated in 2014. We reviewed the evidence from clinical studies comparing any conservative intervention (e.g. immobilisation, rehabilitation) versus no treatment or a different intervention, or comparing different variants of an intervention (e.g. different duration). The primary outcomes of interest were reÃƒÂ¢Ã¢â€šÂ¬Ã‚Âdislocation, patientÃƒÂ¢Ã¢â€šÂ¬Ã‚Âreported shoulder instability measures (usually questionnaires) and return to preÃƒÂ¢Ã¢â€šÂ¬Ã‚Âinjury activities. Further outcomes of interest included patientsÃƒÂ¢Ã¢â€šÂ¬Ã¢â€žÂ¢ satisfaction with the intervention, healthÃƒÂ¢Ã¢â€šÂ¬Ã‚Ârelated quality of life and adverse events. Search date We conducted the searches of healthcare literature for this review in May 2018. Study characteristics We identified three new relevant studies in this update. In total, this review now includes seven studies with 704 participants. Most of the participants (82%) were male; the average age across the studies was 29 years (range 12 to 90 years). All of the studies investigated just one comparison: immobilisation in external rotation (when the arm is orientated outwards with the forearm away from the chest) versus immobilisation in internal rotation (the usual sling position, where the arm rests against the chest) following closed reduction. Participants were followed over different lengths of time; the most common duration was two years or longer. Key results We are uncertain whether immobilisation in external rotation makes a difference to the risk of reÃƒÂ¢Ã¢â€šÂ¬Ã‚Âdislocation at oneÃƒÂ¢Ã¢â€šÂ¬Ã‚Âyear or more followÃƒÂ¢Ã¢â€šÂ¬Ã‚Âup compared with immobilisation in internal rotation. None of the four studies reporting on patientÃƒÂ¢Ã¢â€šÂ¬Ã‚Âreported outcome measures for shoulder instability at a minimum of oneÃƒÂ¢Ã¢â€šÂ¬Ã‚Âyear followÃƒÂ¢Ã¢â€šÂ¬Ã‚Âup found evidence of any important difference between the two interventions. We are uncertain of the relative effects of the two methods of immobilisation on resumption of preÃƒÂ¢Ã¢â€šÂ¬Ã‚Âinjury activities or sports. One study found no evidence of a difference between interventions in the return to preÃƒÂ¢Ã¢â€šÂ¬Ã‚Âinjury activity of the affected arm. Two other studies found greater return to sports in the external rotation group in a small group of participants who had sustained their injury during sports activities. None of the trials reported on participant satisfaction or healthÃƒÂ¢Ã¢â€šÂ¬Ã‚Ârelated quality of life. We are uncertain whether there is a difference between the two interventions in the number of participants experiencing instability, defined as either reÃƒÂ¢Ã¢â€šÂ¬Ã‚Âdislocation or subluxation (a partial dislocation). The reporting of adverse events (complications) was unsatisfactory. There were reports of nine cases of shortÃƒÂ¢Ã¢â€šÂ¬Ã‚Âterm shoulder stiffness in the external rotation group and two cases of underÃƒÂ¢Ã¢â€šÂ¬Ã‚Âarm rash in the internal fixation group. There were three more serious adverse events: abnormal sensitivity and hand pain; abnormal sensation such as tingling in the little finger and along to the elbow; and major movement restriction. It was unclear to what extent these three adverse events could be attributed to the treatment. Certainty of the evidence We rated the certainty of the evidence as very low for all outcomes. This was mainly because there were not enough data and we were unsure how reliable the results were from the individual studies. Thus we are uncertain about the estimates of effect. Conclusions Overall, the current evidence is insufficient to inform the choice of immobilisation in external versus internal rotation. There is no evidence to inform on any other conservative interventions following closed reduction of traumatic anterior dislocation of the shoulder." | E16: FALSE | F16: Focuses on treatment post-injury, not on NHS Three Shifts. | G16: None | I16: 0.95
A17: J541 | B17: 2019 | C17: Surgical treatments for women with stress urinary incontinence: the ESTER systematic review and economic evaluation | D17: <b>BACKGROUND</b>: Urinary incontinence in women is a distressing condition that restricts quality of life and results in a large economic burden to both the NHS and women themselves._x000D_ <b>OBJECTIVE</b>: To evaluate the clinical effectiveness, safety and cost-effectiveness of surgical treatment for stress urinary incontinence (SUI) in women and explore women's preferences._x000D_ <b>DESIGN</b>: An evidence synthesis, a discrete choice experiment (DCE) and an economic decision model, with a value-of-information (VOI) analysis. Nine surgical interventions were compared. Previous Cochrane reviews for each were identified and updated to include additional studies. Systematic review methods were applied. The outcomes of interest were 'cure' and 'improvement'. Both a pairwise and a network meta-analysis (NMA) were conducted for all available surgical comparisons. A DCE was undertaken to assess the preferences of women for treatment outcomes. An economic model assessed the cost-effectiveness of alternative surgeries and a VOI analysis was undertaken._x000D_ <b>RESULTS</b>: Data from 175 studies were included in the effectiveness review. The majority of included studies were rated as being at high or unclear risk of bias across all risk-of-bias domains. The NMA, which included 120 studies that reported data on 'cure' or 'improvement', showed that retropubic mid-urethral sling (MUS), transobturator MUS, traditional sling and open colposuspension were more effective than other surgical procedures for both primary outcomes. The results for other interventions were variable. In general, rate of tape and mesh exposure was higher after transobturator MUS than after retropubic MUS or single-incision sling, whereas the rate of tape or mesh erosion/extrusion was similar between transobturator MUS and retropubic MUS. The results of the DCE, in which 789 women completed an anonymous online questionnaire, indicate that women tend to prefer surgical treatments associated with no pain or mild chronic pain and shorter length of hospital stay as well as those treatments that have a smaller risk for urinary symptoms to reoccur after surgery. The cost-effectiveness results suggest that, over a lifetime, retropubic MUS is, on average, the least costly and most effective surgery. However, the high level of uncertainty makes robust estimates difficult to ascertain. The VOI analysis highlighted that further research around the incidence rates of complications would be of most value._x000D_ <b>LIMITATIONS</b>: Overall, the quality of the clinical evidence was low, with limited data available for the assessment of complications. Furthermore, there is a lack of robust evidence and significant uncertainty around some parameters in the economic modelling._x000D_ <b>CONCLUSIONS</b>: To our knowledge, this is the most comprehensive assessment of published evidence for the treatment of SUI. There is some evidence that retropubic MUS, transobturator MUS and traditional sling are effective in the short to medium term and that retropubic MUS is cost-effective in the medium to long term. The VOI analysis highlights the value of further research to reduce the uncertainty around the incidence rates of complications. There is a need to obtain robust clinical data in future work, particularly around long-term complication rates._x000D_ <b>STUDY REGISTRATION</b>: This study is registered as PROSPERO CRD42016049339._x000D_ <b>FUNDING</b>: The National Institute for Health Research Health Technology Assessment programme. | E17: FALSE | F17: Focuses on surgical treatments, not aligned with NHS shifts. | G17: None | I17: 0.9
A18: J545 | B18: 2019 | C18: Estimating the cost-effectiveness of salt reformulation and increasing access to leisure centres in England, with PRIMEtime CE model validation using the AdViSHE tool | D18: BACKGROUND: PRIMEtime CE is a multistate life table model that can directly compare the cost effectiveness of public health interventions affecting diet and physical activity levels, helping to inform decisions about how to spend finite resources. This paper estimates the costs and health outcomes in England of two scenarios: reformulating salt and expanding subsidised access to leisure centres. The results are used to help validate PRIMEtime CE, following the steps outlined in the Assessment of the Validation Status of Health-Economic decision models (AdViSHE) tool. METHOD(S): The PRIMEtime CE model estimates the difference in quality adjusted life years (QALYs) and difference in NHS and social care costs of modelled interventions compared with doing nothing. The salt reformulation scenario models how salt consumption would change if food producers met the 2017 UK Food Standards Agency salt reformulation targets. The leisure centre scenario models change in physical activity levels if the Birmingham Be Active scheme (where swimming pools and gym access is free to residents during defined periods) was rolled out across England. The AdViSHE tool was developed by health economic modellers and divides model validation into five parts: validation of the conceptual model, input data validation, validation of computerised model, operational validation, and other validation techniques. PRIMEtime CE is discussed in relation to each part. RESULT(S): Salt reformulation was dominant compared with doing nothing, and had a 10-year return on investment of 1.44 (0.50 to 2.94) for every 1 spent. By contrast, over 10 years the Be Active expansion would cost 727,000 (514,000 to 1,064,000) per QALY. PRIMEtime CE has good face validity of its conceptual model and has robust input data. Cross-validation produces mixed results and shows the impact of model scope, input parameters, and model structure on cost-per-QALY estimates. CONCLUSION(S): This paper illustrates how PRIMEtime CE can be used to compare the cost-effectiveness of two different public health measures affecting diet and physical activity levels. The AdViSHE tool helps to validate PRIMEtime CE, identifies some of the key drivers of model estimates, and highlights the challenges of externally validating public health economic models against independent data. | E18: TRUE | F18: Focus on prevention through diet and physical activity interventions. | G18: Prevention | H18: Prevention | I18: 0.9
A19: J547 | B19: 2019 | C19: Individualised screening for diabetic retinopathy: The ISDR study-a randomised controlled trial of safety, efficacy, and cost-effectiveness | D19: Background: Varying the intervals in retinopathy screening informed by personal risk offers reallocation of resources to better target high risk groups and address the increasing prevalence of diabetes. However, safety data especially on extended intervals is minimal. Aim(s): To evaluate the safety, efficacy and cost effectiveness (CE) of individualized variable-interval risk-based screening in a population setting compared to usual care. Method(s): Masked 2 arm, parallel assignment, equivalence RCT (largest to date in screening) with independent trials unit monitoring in people with diabetes aged >=12 years attending screening in a single English program. Randomization was 1:1 to individualized screening (active group; 6, 12 or 24 months for high, medium and low risk) determined by a risk calculation engine using real-time local demographic, retinal and clinical data, compared with annual screening (control). CE analysis measuring NHS and societal costs took a 2-year time horizon. Finding(s): 4534 participants entered the study-after withdrawals/loss to follow-up: active 2097; control 2224. Attendance rates at first follow-up visit (primary outcome, safety) were equivalent (per protocol analysis, 5% margin): active 83.6% control 84.7% (difference 1.0, 90% CI-0.8, 2.9). STDR detection rates were non-inferior (1.5% margin): active 1.43% control 1.71% (difference-0.28, CI-0.93, 0.36). Quality of life (EQ5D5L, HUI3) was not significantly different between the groups. Incremental cost saving per person was 18.75 (NHS cost) rising to 49.96 with societal costs. A 39.3% reduction in number of appointments was seen. Conclusion(s): All parties involved in diabetes care can be reassured that extended and personalized screening intervals can safely be introduced in established screening program. Scale-up with further validation outside a research setting is recommended. Views expressed are solely those of the authors. | E19: TRUE | F19: Study focuses on personalized screening to prevent diabetic complications. | G19: Prevention | H19: Prevention | I19: 0.9

Sheet ID_Lookup
A1: id
A2: J502
A3: J503
A4: J504
A5: J505
A6: J508
A7: J510
A8: J520
A9: J522
A10: J523
A11: J524
A12: J527
... A19: J547

Sheet Stage_6_FF_50
A1: Unique ID | B1: Year | C1: Title | D1: Abstract | E1: FF screen | F1: FF reason | G1: FF_include_stage6 | H1: Id_flag
A2: J500 | B2: 2019 | C2: The lifetime costs of pediatric abusive head trauma and a cost-effectiveness analysis of the Period of Purple crying program in British Columbia, Canada | D2: Background: Abusive head trauma (AHT) is a severe form of child abuse causing devastating outcomes for children and families, but its economic costs in Canada has yet to be determined. The Period of PURPLE crying program (PURPLE) is an AHT prevention program implemented in British Columbia for which success in reducing AHT events was recently reported. Objective(s): This study estimated the lifetime costs to society of incidental AHT events and compared the benefits and associated costs of AHT before and after the implementation of the PURPLE program. Participants and Setting: Children aged 0-24 months old with a definite diagnosis of AHT between 2002 and 2014 in British Columbia were included in this study. Method(s): An incidence-based cost-of-illness analysis, using the human capital approach was used to quantify the lifetime costs of AHT events according to their severity (least severe, severe and fatal). A cost-effectiveness analysis of the PURPLE program was conducted from both a societal and a health services' perspectives using decision tree models. Result(s): There were sixty-four AHT events between 2002-2014, resulting in a total cost of $354,359,080 to society. The costs associated with fatal, severe and least severe AHT averaged $7,147,548, $6,057,761 and $1,675,099, respectively. The investment of $5 per newborn through the PURPLE program resulted in a $273.52 and $14.49 per child cost avoidance by society and by the healthcare system. Conclusion(s): This study provides evidence to policymakers and health practitioners that investing upstream in well-developed AHT prevention programs, such as PURPLE, not only promote child safety and health, but also translates into avoided costs to society. Copyright © 2019 Elsevier Ltd | E2: Include | F2: Prevention | G2: =IF(E2="Include", TRUE, FALSE) -> TRUE | H2: =VLOOKUP(A2,ID_Lookup!$A:$A,1,FALSE) -> #N/A
A3: J501 | B3: 2019 | C3: Impact of Weekend Treatment on Short-term and Long-term Survival Following Urgent Repair of Ruptured Aortic Aneurysms in Germany | D3: Introduction - There is some evidence that weekend admission to hospital is associated with worse outcomes compared to weekday admission. However only a few studies focused on weekend versus weekday surgery. This study aims to determine if there is a weekend effect in the treatment of ruptured aortic aneurysms in Germany. Methods - Health insurance claims of Germany's third largest insurance provider, DAK-Gesundheit, was used to investigate short-term and long-term mortality after weekend versus weekday treatment for ruptured aortic aneurysm (rAA). Patients undergoing endovascular (ER) or open-surgical (OR) repair between January 2008 and December 2016 were included in the study. A one-to-one propensity score matching was used to address selection bias. Results - There were 1,477 patients in the cohort of which 517 (35.0%) underwent ER and 960 (65.0%) OR. Overall, 987 (66.8%) patients were operated on weekdays (Monday to Thursday) and 490 (33.2%) patients were operated on a weekend (Friday to Sunday). In multivariable models, patients operated on weekend were at higher risk of in-hospital death within both ER (Odds Ratio 1.62, p=0.038) and OR (Odds Ratio 1.68, p=0.001) groups. Furthermore, OR conducted on weekends was associated with lower long-term survival (Hazard Ratio 1.23, p=0.014). Finally, OR of thoracic or abdominal aorta was associated with significantly lower in-hospital mortality and higher long-term survival when compared to thoracic-abdominal aortic repair. Conclusion - Weekend repairs of ruptured aortic aneurysms are associated with worse in-hospital and long-term survival when compared to weekday surgery. Negative effect of weekend surgery was strongest for thoracic-abdominal aneurysms. References 1. Wise J. The weekend effect-how strong is the evidence? BMJ 2016;353:i2781. 2. Metcalfe D, Perry DC, Bouamra O, Salim A, Lecky FE, Woodford M, et al. Is there a 'weekend effect' in major trauma? Emergency medicine journal. Emerg Med J 2016;33:836-842. 3. Groves EM, Khoshchehreh M, Le C, Malik S. Effects of weekend admission on the outcomes and management of ruptured aortic aneurysms. J Vasc Surg 2014;60:318-24. 4. Glance LG, Osler T, Li Y, Lustik SJ, Eaton MP, Dutton RP, et al. Outcomes are Worse in US Patients Undergoing Surgery on Weekends Compared With Weekdays. Med Care 2016;54:608-15. 5. Gallerani M, Volpato S, Boari B, Pala M, De Giorgi A, Fabbian F, et al. Outcomes of weekend versus weekday admission for acute aortic dissection or rupture: a retrospective study on the Italian National Hospital Database. Int J Cardiol 2013;168:3117-9. 6. Kumar N, Venkatraman A, Pandey A, Khera R, Garg N. Weekend hospitalizations for acute aortic dissection have a higher risk of in-hospital mortality compared to weekday hospitalizations. Int J Cardiol 2016;214:448-50. 7. Kostis WJ, Demissie K, Marcella SW, Shao YH, Wilson AC, Moreyra AE, et al. Weekend versus weekday admission and mortality from myocardial infarction. N Engl J Med 2007;356:1099-109. 8. Orandi BJ, Selvarajah S, Orion KC, Lum YW, Perler BA, Abularrage CJ. Outcomes of nonelective weekend admissions for lower extremity ischemia. J Vasc Surg 2014;60:1572-9 e1. 9. Aujesky D, Jimenez D, Mor MK, Geng M, Fine MJ, Ibrahim SA. Weekend versus weekday admission and mortality after acute pulmonary embolism. Circulation 2009;119:962-8. 10. Nanchal R, Kumar G, Taneja A, Patel J, Deshmukh A, Tarima S, et al. Pulmonary embolism: the weekend effect. Chest 2012;142:690-6. 11. Bell CM, Redelmeier DA. Mortality among Patients Admitted to Hospitals on Weekends as Compared with Weekdays. N Engl J Med 2001;345:663-668. 12. Mohammed MA, Sidhu KS, Rudge G, Stevens AJ. Weekend admission to hospital has a higher risk of death in the elective setting than in the emergency setting: a retrospective database study of national health service hospitals in England. BMC Health Serv Res 2012;12:87. 13. Zhou Y, Li W, Herath C, Xia J, Hu B, Song F, et al. Off-Hour Admission and Mortality Risk for 28 Specific Diseases: A Systematic Review and Meta-Analysis of 251 Cohorts. J Am Heart Assoc 2 16;5:e003102. 14. Ozdemir BA, Sinha S, Karthikesalingam A, Poloniecki JD, Pearse RM, Grocott MP, Thompson MM, Holt PJ. Mortality of emergency general surgical patients and associations with hospital structures and processes. Br J Anaesth 2016;116:54-62. 15. Behrendt CA, Sedrakyan A, Riess HC, Heidemann F, Kolbel T, Petersen J, et al. Short-term and long-term results of endovascular and open repair of abdominal aortic aneurysms in Germany. J Vasc Surg 2017;66:1704-1711.e3. 16. Muller I, Freitag MH, Poggensee G, Scharnetzky E, Straube E, Schoerner C, et al. Evaluating Frequency, Diagnostic Quality, and Cost of Lyme Borreliosis Testing in Germany: A Retrospective Model Analysis. Clin Dev Immunol 2012;2012:1-13. 17. Augustin M, Anastasiadou Z, Schaarschmidt ML, Krensel M, Schafer I, Reusch M. Versorgung des Hautkrebses in Deutschland. Hautarzt 2016;67:544-548. 18. Fischer F, Hoffmann K, Monter N, Walle M, Beneke R, Negenborn S, et al. Kostenevaluation eines Modells der Integrierten Versorgung fur schwer psychisch Kranke. Gesundheitswesen 2013;76:86-95. 19. Debus ES, Nullen H, Torsello G, Lang W, Flessenkamper I, Hupp T, et al. Zur Behandlung des abdominellen Aortenaneurysmas in Deutschland. Gefasschirurgie 2014;19:412-421. 20. Grundmann RT. Versorgung des abdominellen Aortenaneurysmas (AAA) 2014. Gefasschirurgie 2015;20:376-384. 21. Debus ES, Torsello G, Behrendt CA, Petersen J, Grundmann RT. [Perioperative mortality following repair for abdominal aortic aneurysm in Germany : Comparison of administrative data of the DAK health insurance and clinical registry data of the German Vascular Society]. Chirurg 2015;86:1041-50. 22. Elixhauser A, Steiner C, Harris DR, Coffey RM. Comorbidity measures for use with administrative data. Med Care 1998;36:8-27. 23. Quan H, Sundararajan V, Halfon P, Fong A, Burnand B, Luthi JC, et al. Coding algorithms for defining comorbidities in ICD-9-CM and ICD-10 administrative data. Med Care 2005;43:1130-9. 24. van Walraven C, Austin PC, Jennings A, Quan H, Forster AJ. A modification of the Elixhauser comorbidity measures into a point system for hospital death using administrative data. Med Care 2009;47:626-33. 25. Rosenbaum PR, Rubin DB. The central role of the propensity score in observational studies for causal effects. Biometrika 1983;70:41-55. 26. Gallerani M, Imberti D, Bossone E, Eagle KA, Manfredini R. Higher mortality in patients hospitalized for acute aortic rupture or dissection during weekends. J Vasc Surg 2012;55:1247-54. 27. Cram P, Hillis SL, Barnett M, Rosenthal GE. Effects of weekend admission and hospital teaching status on in-hospital mortality. Am J Med 2004;117:151-7. 28. Investigators IT. Comparative clinical effectiveness and cost effectiveness of endovascular strategy v open repair for ruptured abdominal aortic aneurysm: three year results of the IMPROVE randomised trial. BMJ 2017;359:j4859. 29. Patel R, Sweeting MJ, Powell JT, Greenhalgh RM. Endovascular versus open repair of abdominal aortic aneurysm in 15-years' follow-up of the UK endovascular aneurysm repair trial 1 (EVAR trial 1): a randomised controlled trial. Lancet 2016;388:2366-2374. 30. Thorpe KE. House Staff Supervision and Working Hours. JAMA 1990;263:3177. 31. McKee M, Black N. Does the current use of junior doctors in the United Kingdom affect the quality of medical care? Soc Sci Med 1992;34:549-58. 32. Tarnow-Mordi WO, Hau C, Warden A, Shearer AJ. Hospital mortality in relation to staff workload: a 4-year study in an adult intensive-care unit. Lancet 2000;356:185-9. 33. Beck AW, Sedrakyan A, Mao J, Venermo M, Faizer R, Debus S, et al. Variations in Abdominal Aortic Aneurysm Care: A Report From the International Consortium of Vascular Registries. Circulation 2016;134:1948-1958. 34. Budtz-Lilly J, Bjorck M, Venermo M, Debus S, Behrendt C-A, Altreuther M, et al. The Impact of Centralisation and Endovascular Aneurysm Repair on Treatment of Ruptured Abdominal Aortic Aneurysms Based on International Registries. Eur J Vasc Endovasc Surg. Article in Press. Doi: 10.1016/j.ejvs.2018.01.014. 35. Behrendt CA, Heidemann F, R ess HC, Stoberock K, Debus SE. Registry and health insurance claims data in vascular research and quality improvement. Vasa 2017;46:11-15. Copyright © 2019 | E3: Exclude | F3: No shift | G3: =IF(E3="Include", TRUE, FALSE) -> FALSE | H3: =VLOOKUP(A3,ID_Lookup!$A:$A,1,FALSE) -> #N/A
A4: J502 | B4: 2019 | C4: Pdb16 Assessment of Cost-Effectiveness of a 0.2 Mcg/Day Fluocinolone Acetonide (Fac) Implant in Patients with Chronic Diabetic Macular Oedema (Dmo) in an Eye with Cataract | D4: Objectives: The fluocinolone acetonide 0.2 mug/day implant (FAc) is effective in improving visual acuity in patients with chronic diabetic macular oedema (cDMO) but is associated with worsening of cataract. A model previously suggested that FAc is cost-effective in patients with cDMO, who have undergone cataract surgery or not. The aim of this study was to update this model and assess the cost-effectiveness of FAc in the subgroup of patients with symptomatic cataract. Method(s): The existing Markov model was designed to assess costs and QALYs over lifetime in patients treated with FAc implant, compared to usual care (UC), consisting of laser photocoagulation and anti-VEGFs from the UK NHS perspective. Unit costs and health state utility values (HSUVs) were updated. The FAc price was NHS list price. HSUVs were obtained from the FAME trial using the VFQ-UI utility index. Best-Corrected Visual Acuity (BCVA) with UC was supposed to be stable. Additional scenarios were considered, with BCVA decreasing over time in UC arm, according to real-world data, and with possibility of administering FAc after cataract surgery in the UC arm. Result(s): New HSUVs ranged from 0.48 for blind patients to 0.91 for patients with perfect vision in both eyes. The FAc strategy was more expensive compared to usual care, by 3,445 per patients over lifetime, and produced more QALYs (+0.247). The incremental cost-effectiveness ratio (ICER) was estimated at 13,932 per QALY gained. The ICER was sensitive to the baseline visual acuity, patients' age and the probability of cataract surgery. The probability of FAc being cost-effective was 66.1% at a threshold of 20,000 per QALY gained. Scenario analyses showed that the efficacy of UC had a strong influence on results, and ICER decreased to 1,686 per QALY gained when BCVA decreased under UC Conclusion(s): The FAc implant is a cost-effective treatment for cDMO in patients with symptomatic cataract. Copyright © 2019 | E4: Exclude | F4: No shift | G4: =IF(E4="Include", TRUE, FALSE) -> FALSE | H4: =VLOOKUP(A4,ID_Lookup!$A:$A,1,FALSE) -> J502
A5: J503 | B5: 2019 | C5: Fluorides for preventing early tooth decay (demineralised lesions) during fixed brace treatment | D5: - Background Early dental decay or demineralised lesions (DLs, also known as white spot lesions) can appear on teeth during fixed orthodontic (brace) treatment. Fluoride reduces decay in susceptible individuals, including orthodontic patients. This review compared various forms of topical fluoride to prevent the development of DLs during orthodontic treatment. This is the second update of the Cochrane Review first published in 2004 and previously updated in 2013. Objectives The primary objective was to evaluate whether topical fluoride reduces the proportion of orthodontic patients with new DLs after fixed appliances. The secondary objectives were to examine the effectiveness of different modes of topical fluoride delivery in reducing the proportions of orthodontic patients with new DLs, as well as the severity of lesions, in terms of number, size and colour. Participant‐assessed outcomes, such as perception of DLs, and oral health‐related quality of life data were to be included, as would reports of adverse effects. Search methods Cochrane Oral Health's Information Specialist searched the following databases: Cochrane Oral Health's Trials Register (to 1 February 2019), the Cochrane Central Register of Controlled Trials (CENTRAL; 2019, Issue 1) in the Cochrane Library (searched 1 February 2019), MEDLINE Ovid (1946 to 1 February 2019), and Embase Ovid (1980 to 1 February 2019). The US National Institutes of Health Ongoing Trials Register (ClinicalTrials.gov) and the World Health Organization International Clinical Trials Registry Platform were searched for ongoing trials. No restrictions were placed on the language or date of publication when searching the electronic databases. Selection criteria Parallel‐group, randomised controlled trials comparing the use of a fluoride‐containing product versus a placebo, no treatment or a different type of fluoride treatment, in which the outcome of enamel demineralisation was assessed at the start and at the end of orthodontic treatment. Data collection and analysis At least two review authors independently, in duplicate, conducted risk of bias assessments and extracted data. Authors of trials were contacted to obtain missing data or to ask for clarification of aspects of trial methodology. Cochrane's statistical guidelines were followed. Main results This update includes 10 studies and contains data from nine studies, comparing eight interventions, involving 1798 randomised participants (1580 analysed). One report contained insufficient information and the authors have been contacted. We assessed two studies as at low risk of bias, six at unclear risk of bias, and two at high risk of bias. Two placebo (non‐fluoride) controlled studies, at low risk of bias, investigated the professional application of varnish (7700 or 10,000 parts per million (ppm) fluoride (F)), every six weeks and found insufficient evidence of a difference regarding its effectiveness in preventing new DLs (risk ratio (RR) 0.52, 95% confidence interval (CI) 0.14 to 1.93; 405 participants; low‐certainty evidence). One placebo (non‐fluoride) controlled study, at unclear risk of bias, provides a low level of certainty that fluoride foam (12,300 ppm F), professionally applied every two months, may reduce the incidence of new DLs (12% versus 49%) after fixed orthodontic treatment (RR 0.26, 95% CI 0.11 to 0.57; 95 participants). One study, at unclear risk of bias, also provides a low level of certainty that use of a high‐concentration fluoride toothpaste (5000 ppm F) by patients may reduce the incidence of new DLs (18% versus 27%) compared with a conventional fluoride toothpaste (1450 ppm F) (RR 0.68, 95% CI 0.46 to 1.00; 380 participants). There was no evidence for a difference in the proportions of orthodontic patients with new DLs on the teeth after treatment with fixed orthodontic appliances for the following comparisons: ‐ an amine fluoride and stannous fluoride toothpaste/mouthrinse combination versus a sodium fluoride toothpaste/mouthrinse, ‐ an amine fluoride gel versus a non‐fluoride placebo applied by participants at home once a week and by professional application every three months, ‐ resin‐modified glass ionomer cement versus light‐cured composite resin for bonding orthodontic brackets, ‐ a 250 ppm F mouthrinse versus 0 ppm F placebo mouthrinse, ‐ the use of an intraoral fluoride‐releasing glass bead device attached to the brace versus a daily fluoride mouthrinse. The last two comparisons involved studies that were assessed at high risk of bias, because a substantial number of participants were lost to follow‐up. Unfortunately, although the internal validity and hence the quality of the studies has improved since the first version of the review, they have compared different interventions; therefore, the findings are only considered to provide low level of certainty, because none has been replicated by follow‐up studies, in different settings, to confirm external validity. A patient‐reported outcome, such as concern about the aesthetics of any DLs, was still not included as an outcome in any study. Reports of adverse effects from topical fluoride applications were rare and unlikely to be significant. One study involving fluoride‐containing glass beads reported numerous breakages. Authors' conclusions This review found a low level of certainty that 12,300 ppm F foam applied by a professional every 6 to 8 weeks throughout fixed orthodontic treatment, might be effective in reducing the proportion of orthodontic patients with new DLs. In addition, there is a low level of certainty that the patient use of a high fluoride toothpaste (5000 ppm F) throughout orthodontic treatment, might be more effective than a conventional fluoride toothpaste. These two comparisons were based on single studies. There was insufficient evidence of a difference regarding the professional application of fluoride varnish (7700 or 10,000 ppm F). Further adequately powered, randomised controlled trials are required to increase the certainty of these findings and to determine the best means of preventing DLs in patients undergoing fixed orthodontic treatment. The most accurate means of assessing adherence with the use of fluoride products by patients and any possible adverse effects also need to be considered. Future studies should follow up participants beyond the end of orthodontic treatment to determine the effect of DLs on patient satisfaction with treatment. Plain language summary Fluorides for preventing early tooth decay (demineralised lesions) during fixed brace treatment Review question Ugly white or brown marks sometimes appear on the teeth during treatment with braces to straighten teeth. These are due to early tooth decay and usually occur with fixed, glued‐on 'train track', braces, which make it more difficult to clean the teeth. We know that fluoride in toothpaste helps to prevent tooth decay and think that if extra fluoride is given to people wearing fixed braces, it will protect them from getting these marks. The aim of this Cochrane Oral Health's review was to look at how well fluorides help to prevent early tooth decay during fixed brace treatment and to find out the best way to get fluoride to the teeth. Background Wearing a fixed brace makes it harder for people to keep their teeth clean and may also cause pain. Pain can make it more difficult for people to brush their teeth. This can lead to a build‐up of dental plaque around the brackets that attach the fixed brace to the teeth, and if the plaque stays on the tooth for long enough, it will cause early tooth decay, which looks like white or brown marks (demineralised lesions, also known as white spot lesions). People often wear braces for 18 months or longer and if the decay is left to progress, it can cause holes, which are sometimes bad enough to need fillings to be done in the teeth. Fluoride helps the tooth to heal, reducing tooth decay in people who are at risk of developing it. People receiving fixed brace treatment may be given different forms of fluoride treatment. It is important to think about how the fluoride gets to the teeth. Does the fluoride need to be placed by a dentist or dental nurse, or can people having treatment with braces apply the fluoride to their own teeth? Study characteristics This review is up‐to‐date as of 1 February 2019. The review includes 10 studies but we could only use the information from nine studies involving 1798 randomised people. We have asked for more information about one study. The review looks at eight different ways of applying fluoride to the teeth. People taking part in the studies were all having treatment with fixed braces. The number of people with new decay on the teeth at end of fixed brace treatment, as well as the amount of decay in each person, were measured and counted. We compared the following treatments: ‐ dentist or nurse‐applied fluoride e.g. varnish, gel or foam, ‐ patient‐applied/used fluoride e.g. toothpaste, mouthwash, gel or foam, and ‐ materials that release fluoride over time e.g. glues, elastic bands. Key results One study showed that when the dentist applies a foam with a high level of fluoride in it onto the teeth every time the patient is seen, this might reduce the risk of new decay. Another study found that if patients use a toothpaste with a higher level of fluoride than normal, then this might also reduce the risk of new marks on their teeth. No studies have shown that other ways of giving the teeth extra fluoride reduced the number and/or size of new decay on teeth in people wearing fixed braces. Harmful effects of the different ways of giving the teeth more fluoride were not reported in any of the included studies. Certainty of the evidence The level of belief we have in these findings is low, due to the lack of studies testing the same fluorides and showing the same results. We suggest that more, well‐conducted studies should be done in this area. | E5: Include | F5: Prevention | G5: =IF(E5="Include", TRUE, FALSE) -> TRUE | H5: =VLOOKUP(A5,ID_Lookup!$A:$A,1,FALSE) -> J503
A6: J504 | B6: 2019 | C6: Pmh28 Assessing the Life-Cycle Value Added of Second-Generation Antipsychotics in Sweden and the Uk: The Case of Risperidone | D6: To estimate the life-cycle value of risperidone - representative of Second-Generation Antipsychotics- relative to First Generation Antipsychotics to balance the view that cost per Quality-Adjusted Life Year (QALY) at launch are enough to guide access decisions. Study aims to drive the discussion on access and price, through recognition of the dynamic nature of value added by pharmaceutical innovation over the long-run. We estimated the number of patients with schizophrenia treated with risperidone in Sweden and the UK (1994-2017). We collected cost-effectiveness data from the literature of risperidone and haloperidol - representative of First-Generation Antipsychotics. We modelled the life-cycle uptake of risperidone to estimate the life-cycle incremental cost, incremental QALYs and Net monetary Benefit (NMB). We also assessed the life-cycle distribution of the consumer (the payer) and the producer (innovator) surpluses. For the UK, the producer surplus represents around 28% of the total surplus before patent expiration and around 5% after patent expiration. Life-cycle NMB for the health system is estimated at 1,116m. During the life-cycle, the NMB significantly increased in response to two events: (i) the launch of Risperidone Long-Acting Injectable (RLAI); and (ii) generic entry. The ICER was negative (dominant) for the whole period. For Sweden, the producer surplus represents around 6% of the total surplus before patent expiration and around 1% after generic competition. Life-cycle NMB is estimated at 803m, and both NMB and ICER follow the same pattern as in the UK. Analysis shows that health systems appropriated most of the life-cycle value (surplus) generated. This suggests that, considering the entire life-cycle, the value added by SGAs to the system is higher than the value estimated using cost-effectiveness analysis at launch. Pricing and reimbursement decisions should take into account the dynamic nature of pharmaceutical markets and the value added by innovative medicines over the long-run. Copyright © 2019 | E6: Include | F6: Prevention? | G6: =IF(E6="Include", TRUE, FALSE) -> TRUE | H6: =VLOOKUP(A6,ID_Lookup!$A:$A,1,FALSE) -> J504
A7: J505 | B7: 2019 | C7: Fetal fibronectin testing for reducing the risk of preterm birth | D7: - Background Fetal fibronectin (FFN) is an extracellular matrix glycoprotein localized at the maternal‐fetal interface of the amniotic membranes, between chorion and decidua, where it is concentrated in this area between decidua and trophoblast. In normal conditions, FFN is found at very low levels in cervicovaginal secretions. Levels greater than or equal to 50 ng/mL at or after 22 weeks have been associated with an increased risk of spontaneous preterm birth. In fact, FFN is one of the best predictors of preterm birth in all populations studied so far, and can help in selecting which women are at significant risk for preterm birth. This is an update of a review first published in 2008. Objectives To assess the effectiveness of management based on knowledge of FFN testing results for preventing preterm birth. Search methods For this update, we searched Cochrane Pregnancy and Childbirth’s Trials Register (7 September 2018), ClinicalTrials.gov , the WHO International Clinical Trials Registry Platform ( ICTRP ) (7 September 2018), and reference lists of retrieved studies. Selection criteria Randomized controlled trials of pregnant women screened with FFN for risk of preterm birth. Studies included are based exclusively on knowledge of FFN results versus no such knowledge, and we have excluded studies including women with only positive or only negative FFN results. Data collection and analysis Two review authors independently assessed trials for inclusion and risk of bias, extracted data, and checked them for accuracy. The quality of the evidence was assessed using the GRADE approach. Main results We identified 16 trials, of which six were eligible for inclusion. The six included studies randomized 546 women with singleton gestations and threatened preterm labor (PTL) at 23 0/7 to 34 6/7 weeks. A total of 277 women were randomized to knowledge and 269 to no knowledge of FFN. No trials were identified on asymptomatic women or multiple gestations. The risk of bias of included studies was mixed. For selected important outcomes, preterm birth before 37, 34, and 32 weeks, and maternal hospitalization, we graded the quality of the evidence and created a 'Summary of findings' table. For these outcomes, the evidence was graded as mainly low quality due to the imprecision of effect estimates. Management based on knowledge of FFN results may reduce preterm birth before 37 weeks (20.7%) versus controls without such knowledge (29.2%) (risk ratio (RR) 0.72, 95% confidence interval (CI) 0.52 to 1.01; 5 trials; 434 women; low‐quality evidence). However, management based on knowledge of FFN results may make little or no difference to preterm birth before 34 (RR 1.09, 95% CI 0.54 to 2.18; 4 trials; 357 women; low‐quality evidence) or maternal hospitalization (RR 1.06, 95% CI 0.79 to 1.43; 5 trials; 441 women; low‐quality evidence). The evidence for preterm birth before 32 weeks is uncertain because the quality was found to be very low (average RR 0.79, 95% CI 0.16 to 3.96; 4 trials; 357 women; very low‐quality evidence). For all other outcomes, for which there were available data (preterm birth less than 28 weeks; gestational age at delivery (weeks); birthweight less than 2500 g; perinatal death; tocolysis; steroids for fetal lung maturity; time to evaluate; respiratory distress syndrome; neonatal intensive care unit (NICU) admission; and NICU days), knowledge of FFN results may make little or no difference to the outcomes. Authors' conclusions The evidence from this review suggests that management based on knowledge of FFN results may reduce preterm birth before 37 weeks. However, our confidence in this result is limited as the evidence was found to be of low quality. Effects on other substantive outcomes are uncertain due to serious concerns in study design, inconsistency, and imprecision of effect estimates. No trials were identified on asymptomatic women, or multiple gestations. Future studies are needed that include specific populations (e.g. singleton gestations with symptoms of preterm labor), a study gro p managed with a protocol based on the FFN results, and that report not only maternal but also important perinatal outcomes. Cost‐effectiveness analyses are also needed. Plain language summary Fetal fibronectin testing for reducing the risk of preterm birth What is the issue? To assess the effectiveness of management of pregnant women based on a knowledge of fetal fibronectin test results for preventing preterm birth, compared with not having that knowledge. Fetal fibronectin (FFN) acts as a ‘glue’ between the pregnancy and the uterus. Normally very low levels of FFN can be found in secretions of the vagina and cervix. Raised levels at or after 22 weeks have been associated with an increased risk of spontaneous preterm birth. Why is this important? Preterm birth before 37 weeks is the main cause of sickness and death for newborn infants. Most women who give birth preterm have preterm labor symptoms such as contractions but many of the women with symptoms go on to deliver at term (37 weeks or more). Fetal fibronectin (FFN) is a test that can identify the women with symptoms of preterm labor who are most at risk for preterm birth. The level of FFN is measured in secretions from the vagina or cervix. What evidence did we find? We found six randomised controlled studies involving 546 women who were pregnant with one baby and were showing signs of preterm labor at between 23 to 34 weeks' gestation. We graded the following evidence as mainly low quality because of the low number of women in the studies and a wide variation in findings. We found that the number of births before 37 weeks may be slightly reduced when women and their doctors know the results of the FFN test (20.7% versus 29.2%; 5 trials; 434 women). However, knowledge of FFN results may make little or no difference for the other outcomes with available data, including: maternal hospitalization (5 trials; 441 women); use of uterine relaxants (tocolysis) to try to prevent labor; earlier preterm births; women’s gestational age at delivery; babies with a birthweight less than 2500 g; newborn deaths; the number of babies with respiratory distress syndrome; giving steroids to mature the unborn babies’ lungs; and number of days in a neonatal intensive care unit (NICU). What does this mean? This review of six studies did not find enough evidence to say whether or not the FFN test should be used in the management of women showing signs of preterm labor. A screening test such as FFN can only be considered effective if interventions based on the screening results, such as giving drugs to relax the uterus, reduce the number of preterm births. Further research should be encouraged. | E7: Include | F7: Prevention? | G7: =IF(E7="Include", TRUE, FALSE) -> TRUE | H7: =VLOOKUP(A7,ID_Lookup!$A:$A,1,FALSE) -> J505
A8: J506 | B8: 2019 | C8: Cervical assessment by ultrasound for preventing preterm delivery | D8: - Background Measurement of cervical length by ultrasound is predictive of preterm birth (PTB). There are three methods of ultrasound cervical assessment: transvaginal (TVU), transabdominal (TAU), and transperineal (TPU, also called translabial). Cervical length measured by TVU is a relatively new screening test, and has been associated with better prediction of PTB than previously available tests. It is unclear if cervical length measured by ultrasound is effective for preventing PTB. This is an update of a review last published in 2013. Objectives To assess the effectiveness of antenatal management based on transvaginal, transabdominal, and transperineal (also called translabial) ultrasound screening of cervical length for preventing preterm birth. Search methods For this update, we searched the Cochrane Pregnancy and Childbirth’s Trials Register, ClinicalTrials.gov , and the WHO International Clinical Trials Registry Platform ( ICTRP ) to 30 August 2018; reviewed the reference lists of all articles, and contacted experts in the field for additional and ongoing trials. Selection criteria We included published and unpublished randomised controlled trials (RCT) including pregnant women between the gestational ages of 14 to 32 weeks, for whom the cervical length was screened for risk of PTB with TVU, TAU, or TPU. This review focused on studies based on knowledge versus no knowledge of cervical length results, or ultrasound versus no ultrasound for cervical length. We excluded studies based on interventions (e.g. progesterone, cerclage) for short cervical length. Data collection and analysis We followed standard Cochrane methods. Main results We included seven RCTs (N = 923): one examined asymptomatic women with twin pregnancies; four included women with singleton pregnancies and symptoms of preterm labour (PTL); one included women with singleton pregnancies and symptoms of preterm premature rupture of membranes (PPROM); and one included asymptomatic singletons. All trials used TVU for screening. We assessed the risk of bias of the included studies as mixed, and the quality of the evidence for primary outcomes as very low for all populations. For asymptomatic women with twin pregnancies, it is uncertain whether knowledge of TVU‐measured cervical length compared to no knowledge reduces PTB at less than 34 weeks (risk ratio (RR) 0.62, 95% confidence intervals (CI) 0.30 to 1.25; 1 study, 125 participants) because the quality of the evidence is very low. The results were also inconclusive for preterm birth at 36, 32, or 30 weeks; gestational age at birth, and other maternal and perinatal outcomes. Four trials examined knowledge of TVU‐measured cervical length of singletons with symptoms of PTL versus no knowledge. We are uncertain of the effects because of inconclusive results and very low‐quality evidence for: preterm births at less than 37 weeks (average RR 0.59, 95% CI 0.26 to 1.32; 2 studies, 242 participants; I² = 66%; Tau² = 0.23). Birth occurred about four days later in the knowledge groups (mean difference (MD) 0.64 weeks, 95% CI 0.03 to 1.25; 3 trials, 290 women). The results were inconclusive for the other outcomes for which there were available data: PTB at less than 34 or 28 weeks; birthweight less than 2500 g; perinatal death; maternal hospitalisation; tocolysis; and steroids for fetal lung maturity. The trial of singletons with PPROM (N = 92) evaluated safety of using TVU to measure cervical length in this population as its primary outcome, not its effect on management. The results were inconclusive for incidence of maternal and neonatal infections between the TVU and no ultrasound groups. In the trial of asymptomatic singletons (N = 296), in which women either received TVU or not, the results were inconclusive for preterm birth at less than 37 weeks (RR 1.27, 95% CI 0.61 to 2.61; I² = 0%), gestational age at birth, and other perinatal and maternal outcomes. We downgraded evidence for limitations in study design, inconsistency between the trials, and imprecision, due to small sample si e and wide confidence intervals crossing the line of no effect. No trial compared the effect of knowledge of the CL with no knowledge of CL in other populations, such as asymptomatic women with singleton pregnancies, or symptomatic women with twin pregnancies. Authors' conclusions There are limited data on the effects of knowing the cervical length, measured by ultrasound, for preventing preterm births, which preclude us from drawing any conclusions for women with asymptomatic twin or singleton pregnancies, singleton pregnancies with PPROM, or other populations and clinical scenarios. Limited evidence suggests that knowledge of transvaginal ultrasound‐measured cervical length, used to inform the management of women with singleton pregnancies and symptoms of preterm labour, appears to prolong pregnancy by about four days over women in the no knowledge groups. Future studies could look at specific populations separately (e.g. singleton versus twins; symptoms versus no symptoms of PTL), report on all pertinent maternal and perinatal outcomes, and include cost‐effectiveness analyses. Most importantly, future studies should include a clear protocol for management of women based on TVU‐measured cervical length. Plain language summary Cervical assessment by ultrasound for preventing preterm delivery We set out to assess the effectiveness of knowing the cervical length, measured with ultrasound, for preventing preterm birth compared with not knowing the cervical length. What is the issue? The cervix is the lower part of the uterus that connects to the vagina. When women are not pregnant, it is normally at least 3 cm long. During pregnancy, a short cervical length is associated with a risk of spontaneous preterm birth. The shorter the cervical length, the greater the risk. Therefore, measuring cervical length by ultrasound can help predict spontaneous preterm birth. The cervical length is measured by an ultrasound scan through the vagina (transvaginal or TVU), abdomen (transabdominal), or the perineum (transperineal). The most common causes of spontaneous preterm birth are preterm labour or preterm premature rupture of the membranes. Many of the interventions used to prevent preterm birth are used once symptoms develop. Why is this important? Preterm birth before 37 weeks is the main cause of a newborn baby being sick and disabled, or dying. The cervix is the opening or passage through which the baby must pass before being born vaginally. Ultrasound can detect early changes of the cervix, such as shortening of the cervical length, to predict preterm birth. On identifying a short cervical length, interventions can be applied to prevent preterm birth. These interventions include giving the expectant mother progesterone to relax the uterus, or applying a stitch, known as a cerclage, to tighten the opening of the cervix. What evidence did we find? This review assessed if knowing the cervical length can prevent preterm birth. We included seven randomised controlled studies, which involved 923 pregnant women at 14 to 32 weeks' gestation. One study included expectant mothers with twins, without any symptoms of preterm birth or labour, and looked at the number of babies born prematurely before 36 weeks. Four studies included expectant mothers of single babies with threatened preterm labour, and one study involving women with premature rupture of the membranes looked at the safety of transvaginal ultrasound. One trial included expectant mothers with singleton pregnancies who did not have any symptoms of preterm birth or labour to look at the efficacy of transvaginal ultrasound cervical length screening. All studies used transvaginal ultrasound to assess cervical length. For women with twin pregnancies and not showing symptoms of preterm birth, we are unclear of the impact of knowing the cervical length on whether babies are born before 34 weeks' gestation, or their gestational age at birth (1 study, 125 women), because we assessed the quality of the evidence to be very low. For women with a single baby and threatened preterm labour, knowledge of their cervical length may have led to a longer pregnancy by about four days (4 studies, 410 women), but the evidence on the number of babies born before 37 weeks was unclear (2 studies, 242 women). For women whose waters had broken, it is unclear whether healthcare provider knowledge makes any difference to whether the women gave birth preterm, or on the number of infections, again because we judged the quality of evidence as very low. For women with singleton pregnancies not showing symptoms of preterm birth, it is unclear whether an ultrasound to measure cervical length made any difference to whether their babies were born before 37 weeks' gestation (1 study, 296 women; very low‐quality evidence). What does this mean? We found a limited number of studies including small numbers of women. The studies varied in their design and had a broad spread of results. Women were not blinded to whether they had an ultrasound or not. Currently, there is not enough high quality research to show if knowledge of cervical length in women with twin or singleton pregnancies has any effect. Future studies could include ways of managing women as a result of the cervical length results, and it would be useful to look at specific populations separately, such as single babies versus twins and women with and without symptoms of preterm labour. They could also report on all important maternal and perinatal outcomes, and include cost‐effectiveness analyses. | E8: Include | F8: Prevention? | G8: =IF(E8="Include", TRUE, FALSE) -> TRUE | H8: =VLOOKUP(A8,ID_Lookup!$A:$A,1,FALSE) -> #N/A
A9: J507 | B9: 2019 | C9: Comparison of different human papillomavirus (HPV) vaccine types and dose schedules for prevention of HPV‐related disease in females and males | D9: - Background Uptake of human papillomavirus (HPV) vaccine remains low in many countries, although the bivalent and quadrivalent HPV vaccines given as a three‐dose schedule are effective in the prevention of precancerous lesions of the cervix in women. Simpler immunisation schedules, such as those with fewer doses, might reduce barriers to vaccination, as may programmes that include males. Objectives To evaluate the efficacy, immunogenicity, and harms of different dose schedules and different types of HPV vaccines in females and males. Search methods We conducted electronic searches on 27 September 2018 in Ovid MEDLINE, the Cochrane Central Register of Controlled Trials (CENTRAL) (in the Cochrane Library), and Ovid Embase. We also searched the WHO International Clinical Trials Registry Platform, and ClinicalTrials.gov (both 27 September 2018), vaccine manufacturer websites, and checked reference lists from an index of HPV studies and other relevant systematic reviews. Selection criteria We included randomised controlled trials (RCTs) with no language restriction. We considered studies if they enrolled HIV‐negative males or females aged 9 to 26 years, or HIV‐positive males or females of any age. Data collection and analysis We used methods recommended by Cochrane. We use the term 'control' to refer to comparator products containing an adjuvant or active vaccine and 'placebo' to refer to products that contain no adjuvant or active vaccine. Most primary outcomes in this review were clinical outcomes. However, for comparisons comparing dose schedules, the included RCTs were designed to measure antibody responses (i.e. immunogenicity) as the primary outcome, rather than clinical outcomes, since it is unethical to collect cervical samples from girls under 16 years of age. We analysed immunogenicity outcomes (i.e. geometric mean titres) with ratios of means, clinical outcomes (e.g. cancer and intraepithelial neoplasia) with risk ratios or rate ratios and, for serious adverse events and deaths, we calculated odds ratios. We rated the certainty of evidence with GRADE. Main results We included 20 RCTs with 31,940 participants. The length of follow‐up in the included studies ranged from seven months to five years. Two doses versus three doses of HPV vaccine in 9‐ to 15‐year‐old females Antibody responses after two‐dose and three‐dose HPV vaccine schedules were similar after up to five years of follow‐up (4 RCTs, moderate‐ to high‐certainty evidence). No RCTs collected clinical outcome data. Evidence about serious adverse events in studies comparing dose schedules was of very low‐certainty owing to imprecision and indirectness (three doses 35/1159; two doses 36/1158; 4 RCTs). One death was reported in the three‐dose group (1/898) and none in the two‐dose group (0/899) (low‐certainty evidence). Interval between doses of HPV vaccine in 9‐ to 14‐year‐old females and males Antibody responses were stronger with a longer interval (6 or 12 months) between the first two doses of HPV vaccine than a shorter interval (2 or 6 months) at up to three years of follow‐up (4 RCTs, moderate‐ to high‐certainty evidence). No RCTs collected data about clinical outcomes. Evidence about serious adverse events in studies comparing intervals was of very low‐certainty, owing to imprecision and indirectness. No deaths were reported in any of the studies (0/1898, 3 RCTs, low‐certainty evidence). HPV vaccination of 10‐ to 26‐year‐old males In one RCT there was moderate‐certainty evidence that quadrivalent HPV vaccine, compared with control, reduced the incidence of external genital lesions (control 36 per 3081 person‐years; quadrivalent 6 per 3173 person‐years; rate ratio 0.16, 95% CI 0.07 to 0.38; 6254 person‐years) and anogenital warts (control 28 per 2814 person‐years; quadrivalent 3 per 2831 person‐years; rate ratio 0.11, 95% CI 0.03 to 0.38; 5645 person‐years). The quadrivalent vaccine resulted in more injection‐site adverse events, such as pain or redness, than control (5 7 versus 601 per 1000; risk ratio (RR) 1.12, 95% CI 1.06 to 1.18, 3895 participants, high‐certainty evidence). There was very low‐certainty evidence from two RCTs about serious adverse events with quadrivalent vaccine (control 12/2588; quadrivalent 8/2574), and about deaths (control 11/2591; quadrivalent 3/2582), owing to imprecision and indirectness. Nonavalent versus quadrivalent vaccine in 9‐ to 26‐year‐old females and males Three RCTs were included; one in females aged 9‐ to 15‐years (n = 600), one in females aged 16‐ to 26‐years (n = 14,215), and one in males aged 16‐ to 26‐years (n = 500). The RCT in 16‐ to 26‐year‐old females reported clinical outcomes. There was little to no difference in the incidence of the combined outcome of high‐grade cervical epithelial neoplasia, adenocarcinoma in situ, or cervical cancer between the HPV vaccines (quadrivalent 325/6882, nonavalent 326/6871; OR 1.00, 95% CI 0.85 to 1.16; 13,753 participants; high‐certainty evidence). The other two RCTs did not collect data about clinical outcomes. There were slightly more local adverse events with the nonavalent vaccine (905 per 1000) than the quadrivalent vaccine (846 per 1000) (RR 1.07, 95% CI 1.05 to 1.08; 3 RCTs, 15,863 participants; high‐certainty evidence). Comparative evidence about serious adverse events in the three RCTs (nonavalent 243/8234, quadrivalent 192/7629; OR 0.60, 95% CI 0.14 to 2.61) was of low certainty, owing to imprecision and indirectness. HPV vaccination for people living with HIV Seven RCTs reported on HPV vaccines in people with HIV, with two small trials that collected data about clinical outcomes. Antibody responses were higher following vaccination with either bivalent or quadrivalent HPV vaccine than with control, and these responses could be demonstrated to have been maintained for up to 24 months in children living with HIV (low‐certainty evidence). The evidence about clinical outcomes and harms for HPV vaccines in people with HIV is very uncertain (low‐ to very low‐certainty evidence), owing to imprecision and indirectness. Authors' conclusions The immunogenicity of two‐dose and three‐dose HPV vaccine schedules, measured using antibody responses in young females, is comparable. The quadrivalent vaccine probably reduces external genital lesions and anogenital warts in males compared with control. The nonavalent and quadrivalent vaccines offer similar protection against a combined outcome of cervical, vaginal, and vulval precancer lesions or cancer. In people living with HIV, both the bivalent and quadrivalent HPV vaccines result in high antibody responses. For all comparisons of alternative HPV vaccine schedules, the certainty of the body of evidence about serious adverse events reported during the study periods was low or very low, either because the number of events was low, or the evidence was indirect, or both. Post‐marketing surveillance is needed to continue monitoring harms that might be associated with HPV vaccines in the population, and this evidence will be incorporated in future updates of this review. Long‐term observational studies are needed to determine the effectiveness of reduced‐dose schedules against HPV‐related cancer endpoints, and whether adopting these schedules improves vaccine coverage rates. Plain language summary Comparison of different human papillomavirus (HPV) vaccines and the number of doses administered to prevent HPV‐related disease in females and males Human papillomaviruses (HPV) are a group of viruses that infect the skin and mucous membranes. Some types of HPV are sexually transmitted and are common in young people. Most infections will be cleared by the immune system, but some people will experience persistent infection with certain HPV types that go on to cause abnormalities in infected cells. These changes are called 'precancerous' because they can develop into cancers of the cervix, vagina, vulva, anal canal, penis, and head and neck. Infection with other HPV types causes warts in the genital area or around the anu . Vaccination aims to prevent future HPV infections. Three HPV vaccines are in use – a bivalent one (protects against two HPV types), a quadrivalent one (protects against four HPV types), and a nonavalent one (protects against nine HPV types). In women, three doses of the bivalent or the quadrivalent HPV vaccines protect against precancer of the cervix caused by the HPV types contained in the vaccine. Evidence about the nonavalent vaccine, about the effects of the quadrivalent vaccine in males, and about the effects of HPV vaccines in people with HIV infection, has not yet been reviewed thoroughly. Uptake of HPV vaccines remains low in many countries. Simpler vaccine schedules, or giving the vaccine to both girls and boys, could increase the number of people being vaccinated. Trials of HPV vaccines are not always designed to collect data about precancer and cancer, for several reasons. Firstly, HPV vaccine is routinely given before girls become sexually active, and it is not ethical to take specimens from the cervix of girls who have not had sex. Secondly, HPV‐related precancer and cancer are rare and do not develop until years after HPV infection has occurred. Thirdly, participants in a trial will be offered treatment if precancer develops, so progression to cervical cancer would be even rarer, even without vaccination. An international committee of experts states that, in some circumstances, antibody levels (i.e. showing a strong immune system response), can be used to demonstrate protection against cervical and anal cancer. The antibody levels following vaccination in a trial should not be lower than those found in other studies on adults in whom the vaccine has been shown to protect against severe HPV‐related cervical or anal disease. Review question(s) How effective or harmful are different HPV vaccine schedules (i.e. number and timing of doses) and different HPV vaccines in females and males? Main results These results are based on research evidence to 27 September 2018. We analysed 20 studies involving 31,940 people. Studies comparing two doses of HPV vaccine to three doses, or comparing the time interval between doses, focus on immune system responses rather than infection or disease outcomes. Two doses of HPV vaccine result in similar immune system responses to three doses, and a longer interval (up to 12 months) between doses gives a stronger immune system response than a shorter interval. There is insufficient evidence to determine whether there was a difference between the vaccine schedules for serious adverse events and death. In 16‐ to 26‐year‐old men, one study showed evidence of moderate certainty that a quadrivalent HPV vaccine provides better protection against external genital lesions and genital warts than a dummy treatment (control). In 16‐ to 26‐year‐old women, one study showed that the nonavalent and quadrivalent vaccines provide the same levels of protection against cervical, vaginal, and vulval precancer lesions and cancer (high‐certainty evidence). There was evidence that the quadrivalent vaccine resulted in more local adverse events (such as pain, swelling, and redness at the injection site) than a control treatment in males, and that the nonavalent vaccine resulted in more local adverse events than the quadrivalent vaccine in males and females. Evidence about serious adverse events and deaths from studies comparing different HPV vaccine types or dose schedules was of low or very low‐certainty. In people living with HIV, HPV vaccines result in reasonable levels of immune system response, but evidence about their effects on persistent HPV infection or HPV‐related disease outcomes and harms is limited. Certainty of the evidence No major issues were identified with the methodological quality of the studies for the measurements of infection and disease outcomes, or for immune system responses. Our certainty in the evidence about serious harms and deaths across all the studies comparing different HPV vaccines and vaccine schedules is low, either because of their low frequency or because the evidence is indirect, or both. Evidence graded as high certainty means that we were confident that further research is unlikely to change our findings. Moderate‐certainty evidence means that there is a possibility that further research may have an important effect on our findings, whilst low‐certainty evidence means that our confidence was limited and further research may have an important impact on our findings. Very low‐certainty evidence means that we were uncertain about the result. Conclusion A two‐dose schedule of HPV vaccines in young females results in immune system responses that are comparable with a three‐dose schedule. In males, the quadrivalent HPV vaccine appears to be effective in the prevention of external genital lesions and genital warts. Quadrivalent and nonavalent HPV vaccines in young women result in similar levels of protection against cervical, vaginal, and vulval precancer lesions and cancer. Evidence about the efficacy and harms in people living with HIV is limited. Further long‐term population‐level studies are needed to continue monitoring safety of these vaccines, to determine for how long two doses of vaccine can provide protection against HPV‐related disease, the effect against HPV‐related cancer, and whether a two‐dose immunisation schedule will increase vaccine coverage. | E9: Include | F9: Prevention | G9: =IF(E9="Include", TRUE, FALSE) -> TRUE | H9: =VLOOKUP(A9,ID_Lookup!$A:$A,1,FALSE) -> #N/A
A10: J508 | B10: 2019 | C10: Adalimumab for non-infectious uveitis: Is it cost-effective? | D10: Background/Aims: Uveitis is inflammation inside the eye. Our objective was to assess the cost-effectiveness of adalimumab compared with current practice (immunosuppressants and systemic corticosteroids) in patients with non-infectious intermediate, posterior or panuveitis and to identify areas for future research. Method(s): A Markov model was built to estimate costs and benefits of the interventions. Systematic reviews were performed to identify the available relevant clinical and cost-effectiveness evidence. Data collected in two key randomised controlled trials (VISUAL I and VISUAL II) were used to estimate the interventions' effectiveness compared with the trials' comparator arms (placebo plus limited current practice (LCP)). The analysis was performed from the National Health Service and Personal Social Services perspective. Costs were calculated based on standard UK sources. Result(s): The estimated incremental cost-effectiveness ratios (ICERs) of adalimumab versus LCP for the base case are 92 600 and 318 075 per quality-adjusted life year (QALY) gained for active and inactive uveitis, respectively. In sensitivity analyses, the ICER varied from 15 579 to 120 653 and 35 642 to 800 775 per QALY for active and inactive uveitis. Conclusion(s): The estimated ICERs of adalimumab versus LCP are above generally accepted thresholds for cost-effectiveness in the UK. Adalimumab may be more cost-effective in patients with active uveitis at greater risk of blindness. However, there is an unmet need for additional primary data to provide more reliable estimates in several important areas, including effectiveness of adalimumab versus current practice (instead of LCP), incidence of long-term blindness, adalimumab effectiveness in avoiding blindness, and rates and time to remission while on adalimumab. Copyright © 2019 Author(s). | E10: Include | F10: Prevention? | G10: =IF(E10="Include", TRUE, FALSE) -> TRUE | H10: =VLOOKUP(A10,ID_Lookup!$A:$A,1,FALSE) -> J508
A11: J509 | B11: 2019 | C11: Burden of varicella complications in secondary care, England, 2004 to 2017 | D11: Background: Strategies to control varicella vary across Europe. Evidence from established programmes has prompted the United Kingdom to re-evaluate the need for universal vaccination. The burden of complicated varicella is a key parameter in the cost-effectiveness analysis. Aim(s): Our objective was to estimate the burden of complicated varicella in England. Method(s): This electronic health record surveillance study used data from all NHS hospitals in England to identify varicella admissions between 2004 and 2017. The incidence of pre-defined complications of varicella was estimated using ICD-10 codes. Inpatient costs were calculated based on the payment rules for providers of NHS services. Result(s): There were 61,024 admissions with varicella between 2004 and 2017 and 38.1% had a recognised varicella complication. Incidence of hospitalisation increased by 25% and the proportion with complicated varicella by 24% from 2004/05 to 2016/17. The most common complications were bacterial skin infections (11.25%), pneumonia (4.82%), febrile convulsions (3.39%) and encephalitis (2.44%). Complication rates were higher in older age groups and the type of complications more severe. Length of stay for complicated varicella was 3.1 times longer than for uncomplicated varicella and inpatient costs were 72% greater. Conclusion(s): Complicated varicella has a substantial health and economic burden. These data together with data on impact on quality of life are important in informing the cost-effectiveness analysis of universal varicella vaccination. Copyright © 2019 European Centre for Disease Prevention and Control (ECDC). All rights reserved. | E11: Include | F11: Prevention? | G11: =IF(E11="Include", TRUE, FALSE) -> TRUE | H11: =VLOOKUP(A11,ID_Lookup!$A:$A,1,FALSE) -> #N/A
A12: J510 | B12: 2019 | C12: Treatment for hepatorenal syndrome in people with decompensated liver cirrhosis: a network meta‐analysis | D12: - Background Hepatorenal syndrome is defined as renal failure in people with cirrhosis in the absence of other causes. In addition to supportive treatment such as albumin to restore fluid balance, the other potential treatments include systemic vasoconstrictor drugs (such as vasopressin analogues or noradrenaline), renal vasodilator drugs (such as dopamine), transjugular intrahepatic portosystemic shunt (TIPS), and liver support with molecular adsorbent recirculating system (MARS). There is uncertainty over the best treatment regimen for hepatorenal syndrome. Objectives To compare the benefits and harms of different treatments for hepatorenal syndrome in people with decompensated liver cirrhosis. Search methods We searched CENTRAL, MEDLINE, Embase, Science Citation Index Expanded, World Health Organization International Clinical Trials Registry Platform, and trial registers until December 2018 to identify randomised clinical trials on hepatorenal syndrome in people with cirrhosis. Selection criteria We included only randomised clinical trials (irrespective of language, blinding, or publication status) in adults with cirrhosis and hepatorenal syndrome. We excluded randomised clinical trials in which participants had previously undergone liver transplantation. Data collection and analysis Two authors independently identified eligible trials and collected data. The outcomes for this review included mortality, serious adverse events, any adverse events, resolution of hepatorenal syndrome, liver transplantation, and other decompensation events. We performed a network meta‐analysis with OpenBUGS using Bayesian methods and calculated the odds ratio (OR), rate ratio, hazard ratio (HR), and mean difference (MD) with 95% credible intervals (CrI) based on an available‐case analysis, according to National Institute of Health and Care Excellence Decision Support Unit guidance. Main results We included a total of 25 trials (1263 participants; 12 interventions) in the review. Twenty‐three trials (1185 participants) were included in one or more outcomes. All the trials but two were at high risk of bias, and all the evidence was of low or very low certainty. The trials included participants with liver cirrhosis of varied aetiologies as well as a mixture of type I hepatorenal syndrome only, type II hepatorenal syndrome only, or people with both type I and type II hepatorenal syndrome. Participant age ranged from 42 to 60 years, and the proportion of females ranged from 5.8% to 61.5% in the trials that reported this information. The follow‐up in the trials ranged from one week to six months. Overall, 59% of participants died during this period and about 35% of participants recovered from hepatorenal syndrome. The most common interventions compared were albumin plus terlipressin, albumin plus noradrenaline, and albumin alone. There was no evidence of a difference in mortality (22 trials; 1153 participants) at maximal follow‐up between the different interventions. None of the trials reported health‐related quality of life. There was no evidence of differences in the proportion of people with serious adverse events (three trials; 428 participants), number of participants with serious adverse events per participant (two trials; 166 participants), proportion of participants with any adverse events (four trials; 402 participants), the proportion of people who underwent liver transplantation at maximal follow‐up (four trials; 342 participants), or other features of decompensation at maximal follow‐up (one trial; 466 participants). Five trials (293 participants) reported number of any adverse events, and five trials (219 participants) reported treatment costs. Albumin plus noradrenaline had fewer numbers of adverse events per participant (rate ratio 0.51, 95% CrI 0.28 to 0.87). Eighteen trials (1047 participants) reported recovery from hepatorenal syndrome (as per definition of hepatorenal syndrome). In terms of recovery from hepatorenal syndrome, in the direct comparisons, albumin plus midodrine plus octreotide and albumin plus octreotide had lower recovery from hepatorenal syndrome than albumin plus terlipressin (HR 0.04; 95% CrI 0.00 to 0.25 and HR 0.26, 95% CrI 0.07 to 0.80 respectively). There was no evidence of differences between the groups in any of the other direct comparisons. In the network meta‐analysis, albumin and albumin plus midodrine plus octreotide had lower recovery from hepatorenal syndrome compared with albumin plus terlipressin. Funding: two trials were funded by pharmaceutical companies; five trials were funded by parties who had no vested interest in the results of the trial; and 18 trials did not report the source of funding. Authors' conclusions Based on very low‐certainty evidence, there is no evidence of benefit or harm of any of the interventions for hepatorenal syndrome with regards to the following outcomes: all‐cause mortality, serious adverse events (proportion), number of serious adverse events per participant, any adverse events (proportion), liver transplantation, or other decompensation events. Low‐certainty evidence suggests that albumin plus noradrenaline had fewer 'any adverse events per participant' than albumin plus terlipressin. Low‐ or very low‐certainty evidence also found that albumin plus midodrine plus octreotide and albumin alone had lower recovery from hepatorenal syndrome compared with albumin plus terlipressin. Future randomised clinical trials should be adequately powered; employ blinding, avoid post‐randomisation dropouts or planned cross‐overs (or perform an intention‐to‐treat analysis); and report clinically important outcomes such as mortality, health‐related quality of life, adverse events, and recovery from hepatorenal syndrome. Albumin plus noradrenaline and albumin plus terlipressin appear to be the interventions that should be compared in future trials. Plain language summary Treatment of hepatorenal syndrome What is the aim of this Cochrane review? To find out the best treatment for decreased kidney function (hepatorenal syndrome) in people with liver cirrhosis (a form of advanced liver disease with scarring of the liver) with complications. The authors collected and analysed all relevant studies to answer this question and found 25 randomised controlled trials (participants receive the treatment based on method similar to coin toss or lottery; this is to ensure that the people who receive the different treatments are similar in all aspects except the treatment, so that any differences in the results between the treatments can be attributed to the treatment rather than differences in the type of people who received the treatment). During analysis of data, authors used standard Cochrane techniques, which allows comparison of two treatments at a time. Authors also used advanced techniques, that allow comparison of many treatments at the same time (usually referred as 'network meta‐analysis' or 'multiple treatment comparisons'). The aim is to gather reliable evidence on the relative benefits and harms of the different treatments. Date of literature search December 2018 Key messages Only two studies were conducted well. The remaining studies had one or more flaws. Therefore, there is high uncertainty in the results of the analysis. The authors could not recommend one treatment over another on the basis of risk of death, serious complications, percentage of people who developed any complication, percentage of participants who underwent liver transplantation (replacement of a diseased liver with a healthy one), or the number of other liver failure events. Health‐related quality of life was not reported in any of the trials. The number of complications of any severity was lower with albumin plus noradrenaline than albumin plus terlipressin. Recovery from hepatorenal syndrome may be lower with albumin plus midodrine plus octreotide and albumin alone than albumin plus terlipressin and albumin plus noradrenaline. Funding source was unclear in 18 studies. Industrial organisations funded two studies and the remaining five studies did not receive any funding from industrial organisations. What was studied in the review? This review studied people of any sex, age, and origin, having advanced liver disease due to various causes, and who had developed hepatorenal syndrome. People were administered different treatments. The review authors excluded studies with liver‐transplanted participants. Participants age, when reported, ranged from 42 to 60 years. The number of females ranged from 6 to 62 out of 100 in the studies that reported this information. The main treatments compared were albumin alone, albumin plus terlipressin, and albumin plus noradrenaline. The authors gathered and analysed data on death, quality of life, serious and non‐serious complications, time to liver transplantation, recovery from hepatorenal syndrome, and disappearance of symptoms. What were the main results of the review? The 25 studies included a small number of participants (1263 participants). Study data were sparse. Twenty‐three studies with 1185 participants provided data for analyses. The follow‐up in the trials ranged from one week to six months. The review shows that: ‐ About 60 out of every 100 people died within three months, and 35 out of every 100 people recovered from hepatorenal syndrome. ‐ The provided treatment may make no difference to the percentage of people who died or developed serious complications, number of serious complications per person, percentage of people who developed complications of any severity, or the percentage of people undergoing liver transplantation. ‐ None of the trials reported health‐related quality of life. ‐ The number of complications of any severity was lower with albumin plus noradrenaline than albumin plus terlipressin. ‐ Recovery from hepatorenal syndrome may be lower with albumin plus midodrine plus octreotide and albumin alone than albumin plus terlipressin and albumin plus noradrenaline. ‐ We have very low confidence in the overall results. ‐ Future trials with proper design and quality are needed to clarify the best treatment for people with advanced liver disease having hepatorenal syndrome. | E12: Exclude | F12: No shift | G12: =IF(E12="Include", TRUE, FALSE) -> FALSE | H12: =VLOOKUP(A12,ID_Lookup!$A:$A,1,FALSE) -> J510
A13: J511 | B13: 2019 | C13: Switching from originator infliximab to CT-P13: Single-centre experience from the UK | D13: Background: The infliximab biosimilar (CT-P13) received market authorisation for inflammatory bowel disease in late 2016 with the aim of reducing cost and increasing access to therapy. The prospect of 'switching' patients from originator to CT-P13 has concerned clinicians. #8232;We present an experience of 'switching' from originator infliximab (IFX-O) to CT-P13 and present efficacy, safety, and immunogenicity data from our cohort. Method(s): We performed a retrospective review of patients switched from IFX-O to CT-P13. Disease demographics, clinical course and outcomes were analysed from electronic case records at a median of 8 months and at last follow-up at 13 months. Result(s): Ninety-six patients (35 females) were 'switched' from IFX-O to CT-P13. Of these 44 had Ulcerative colitis (UC) and 52 had Crohn's disease (CD) with a mean age at diagnosis of 34.7 years (median = 33, IQR = 24.5). Montreal phenotype for UC was E1 = 1, E2 = 16, E3 = 27 and for CD (L1 = 10, L2 = 12 , L3 = 29, L4 = 1) and (B1 = 27, #8232;B2 = 14 , B3 = 11), 9 patients had perianal disease. Mean duration of IFX-O treatment was 49. 8 months (median = 44, IQR = 52) and on CT-P13 11.5 months (median 13). At switch, 76 patients had a normal CRP (UC = 33, CD = 43), and in 15 patients it was elevated (UC = 10, CD = 5). At 8 months, 80 patients remained in biochemical remission (UC = 35, CD = 45 ) and in 14 patients (UC = 8, CD = 6 ) CRP increased. Seventy-two patients (UC = 34, CD = 38 ) were in clinical remission (pMayo < 2 and HBI < 5). Of 51 patients (UC = 21, CD = 30) undergoing endoscopic assessment, 31 achieved mucosal healing (UC = 13, CD = 18). At 13 months, 69 patients remained on CT-P13. Twenty-seven discontinued the drug due to immunogenicity (n = 10), loss of response (n = 5), surgery (n = 5), remission (n = 5) , side effects (n = 2 ), and 1 patient died of hospital acquired pneumonia. 39 out of 96 patients had therapeutic drug levels checked within 13 months of switch, of whom 27 had sub-therapeutic levels (below 4 mug/ml). Antibodies to Infliximab were seen in 15 of 39 patients (38.5%), of whom 8 were switched to an alternative biologic, 2 had dose escalation (10 mg/kg IFX), 4 patients stopped IFX with no other intervention, and 1 person continued treatment at same dose with low antibody titre of 6. Conclusion(s): Biosimilar IFX (CT-P13) was well tolerated. Clinical efficacy and loss of response rates with CT-P13 appears to be similar to IFX-O. This holds promise for a wider adoption of 'switching' to fulfil the purported aims of wider access to treatment at a lower cost. | E13: Exclude | F13: No shift | G13: =IF(E13="Include", TRUE, FALSE) -> FALSE | H13: =VLOOKUP(A13,ID_Lookup!$A:$A,1,FALSE) -> #N/A
... A52: J550 | B52: 2019 | C52: Characteristics of successful interventions to reduce turnover and increase retention of early career nurses: A systematic review | D52: BACKGROUND: Nurse shortages have been identified as central to workforce issues in healthcare systems globally and although interventions to increase the nursing workforce have been implemented, nurses leaving their roles, particularly in the first year after qualification, present a significant barrier to building the nurse workforce. OBJECTIVE(S): To evaluate the characteristics of successful interventions to promote retention and reduce turnover of early career nurses. DESIGN: This is a systematic review DATA SOURCES: Online databases including Academic Search Complete, Medline, Health Policy reference Centre, EMBASE, Psychinfo, CINAHL and the Cochran Library were searched to identify relevant publications in English published between 2001 and April 2018. Studies included evaluated an intervention to increase retention or reduce turnover and used turnover or retention figures as a measure. REVIEW METHODS: The review was conducted according to the Preferred Reporting Items for Systematic Reviews and Meta-analyses (PRISMA) guidelines. Studies were quality-assessed using the Joanna Briggs Institute Critical Appraisal tools for Quasi Experimental and Randomised Controlled Trials. Retention/turnover data were used to guide the comparison between studies and appropriate measures of central tendency and dispersion were calculated and presented, based on the normality of the data. RESULT(S): A total of 11, 656 papers were identified, of which 53 were eligible studies. A wide variety of interventions and components within those interventions were identified to improve nurse retention. Promising interventions appear to be either internship/residency programmes or orientation/transition to practice programmes, lasting between 27-52 weeks, with a teaching and preceptor and mentor component. CONCLUSION(S): Methodological issues impacted on the extent to which conclusions could be drawn, even though a large number of studies were identified. Future research should focus on standardising the reporting of interventions and outcome measures used to evaluate these interventions and carrying out further research with rigorous methodology. Clinical practice areas are recommended to assess their current interventions against the identified criteria to guide development of their effectiveness. Evaluations of cost-effectiveness are considered an important next step to maximise return on investment. Copyright © 2019 Elsevier Ltd. All rights reserved. | E52: Exclude | F52: No shift | G52: =IF(E52="Include", TRUE, FALSE) -> FALSE | H52: =VLOOKUP(A52,ID_Lookup!$A:$A,1,FALSE) -> #N/A

Sheet Merged results table
A1: id | B1: Year | C1: Title | D1: Abstract | E1: include_stage6 | F1: reason_stage6 | G1: main_shift | H1: shifts_detected | I1: confidence_stage6 | J1: FF screen | K1: FF reason | L1: FF_include_stage6
A2: J502 | B2: 2019 | C2: Pdb16 Assessment of Cost-Effectiveness of a 0.2 Mcg/Day Fluocinolone Acetonide (Fac) Implant in Patients with Chronic Diabetic Macular Oedema (Dmo) in an Eye with Cataract | D2: Objectives: The fluocinolone acetonide 0.2 mug/day implant (FAc) is effective in improving visual acuity in patients with chronic diabetic macular oedema (cDMO) but is associated with worsening of cataract. A model previously suggested that FAc is cost-effective in patients with cDMO, who have undergone cataract surgery or not. The aim of this study was to update this model and assess the cost-effectiveness of FAc in the subgroup of patients with symptomatic cataract. Method(s): The existing Markov model was designed to assess costs and QALYs over lifetime in patients treated with FAc implant, compared to usual care (UC), consisting of laser photocoagulation and anti-VEGFs from the UK NHS perspective. Unit costs and health state utility values (HSUVs) were updated. The FAc price was NHS list price. HSUVs were obtained from the FAME trial using the VFQ-UI utility index. Best-Corrected Visual Acuity (BCVA) with UC was supposed to be stable. Additional scenarios were considered, with BCVA decreasing over time in UC arm, according to real-world data, and with possibility of administering FAc after cataract surgery in the UC arm. Result(s): New HSUVs ranged from 0.48 for blind patients to 0.91 for patients with perfect vision in both eyes. The FAc strategy was more expensive compared to usual care, by 3,445 per patients over lifetime, and produced more QALYs (+0.247). The incremental cost-effectiveness ratio (ICER) was estimated at 13,932 per QALY gained. The ICER was sensitive to the baseline visual acuity, patients' age and the probability of cataract surgery. The probability of FAc being cost-effective was 66.1% at a threshold of 20,000 per QALY gained. Scenario analyses showed that the efficacy of UC had a strong influence on results, and ICER decreased to 1,686 per QALY gained when BCVA decreased under UC Conclusion(s): The FAc implant is a cost-effective treatment for cDMO in patients with symptomatic cataract. Copyright Ãƒâ€šÃ‚Â© 2019 | E2: FALSE | F2: Focuses on cost-effectiveness of a treatment, not NHS shifts. | G2: None | I2: 0.9 | J2: Exclude | K2: No shift | L2: FALSE
