Workbook

Sheet Stage_7_API_200
A1: id | B1: Year | C1: Title | D1: Abstract | E1: include_stage7 | F1: reason_stage7 | G1: cash_release_flags | H1: confidence_stage7
A2: J505 | B2: 2019 | C2: Fetal fibronectin testing for reducing the risk of preterm birth | D2: - Background Fetal fibronectin (FFN) is an extracellular matrix glycoprotein localized at the maternalÃƒÆ’Ã‚Â¢ÃƒÂ¢Ã¢â‚¬Å¡Ã‚Â¬Ãƒâ€šÃ‚Âfetal interface of the amniotic membranes, between chorion and decidua, where it is concentrated in this area between decidua and trophoblast. In normal conditions, FFN is found at very low levels in cervicovaginal secretions. Levels greater than or equal to 50 ng/mL at or after 22 weeks have been associated with an increased risk of spontaneous preterm birth. In fact, FFN is one of the best predictors of preterm birth in all populations studied so far, and can help in selecting which women are at significant risk for preterm birth. This is an update of a review first published in 2008. Objectives To assess the effectiveness of management based on knowledge of FFN testing results for preventing preterm birth. Search methods For this update, we searched Cochrane Pregnancy and ChildbirthÃƒÆ’Ã‚Â¢ÃƒÂ¢Ã¢â‚¬Å¡Ã‚Â¬ÃƒÂ¢Ã¢â‚¬Å¾Ã‚Â¢s Trials Register (7 September 2018), ClinicalTrials.gov , the WHO International Clinical Trials Registry Platform ( ICTRP ) (7 September 2018), and reference lists of retrieved studies. Selection criteria Randomized controlled trials of pregnant women screened with FFN for risk of preterm birth. Studies included are based exclusively on knowledge of FFN results versus no such knowledge, and we have excluded studies including women with only positive or only negative FFN results. Data collection and analysis Two review authors independently assessed trials for inclusion and risk of bias, extracted data, and checked them for accuracy. The quality of the evidence was assessed using the GRADE approach. Main results We identified 16 trials, of which six were eligible for inclusion. The six included studies randomized 546 women with singleton gestations and threatened preterm labor (PTL) at 23 0/7 to 34 6/7 weeks. A total of 277 women were randomized to knowledge and 269 to no knowledge of FFN. No trials were identified on asymptomatic women or multiple gestations. The risk of bias of included studies was mixed. For selected important outcomes, preterm birth before 37, 34, and 32 weeks, and maternal hospitalization, we graded the quality of the evidence and created a 'Summary of findings' table. For these outcomes, the evidence was graded as mainly low quality due to the imprecision of effect estimates. Management based on knowledge of FFN results may reduce preterm birth before 37 weeks (20.7%) versus controls without such knowledge (29.2%) (risk ratio (RR) 0.72, 95% confidence interval (CI) 0.52 to 1.01; 5 trials; 434 women; lowÃƒÆ’Ã‚Â¢ÃƒÂ¢Ã¢â‚¬Å¡Ã‚Â¬Ãƒâ€šÃ‚Âquality evidence). However, management based on knowledge of FFN results may make little or no difference to preterm birth before 34 (RR 1.09, 95% CI 0.54 to 2.18; 4 trials; 357 women; lowÃƒÆ’Ã‚Â¢ÃƒÂ¢Ã¢â‚¬Å¡Ã‚Â¬Ãƒâ€šÃ‚Âquality evidence) or maternal hospitalization (RR 1.06, 95% CI 0.79 to 1.43; 5 trials; 441 women; lowÃƒÆ’Ã‚Â¢ÃƒÂ¢Ã¢â‚¬Å¡Ã‚Â¬Ãƒâ€šÃ‚Âquality evidence). The evidence for preterm birth before 32 weeks is uncertain because the quality was found to be very low (average RR 0.79, 95% CI 0.16 to 3.96; 4 trials; 357 women; very lowÃƒÆ’Ã‚Â¢ÃƒÂ¢Ã¢â‚¬Å¡Ã‚Â¬Ãƒâ€šÃ‚Âquality evidence). For all other outcomes, for which there were available data (preterm birth less than 28 weeks; gestational age at delivery (weeks); birthweight less than 2500 g; perinatal death; tocolysis; steroids for fetal lung maturity; time to evaluate; respiratory distress syndrome; neonatal intensive care unit (NICU) admission; and NICU days), knowledge of FFN results may make little or no difference to the outcomes. Authors' conclusions The evidence from this review suggests that management based on knowledge of FFN results may reduce preterm birth before 37 weeks. However, our confidence in this result is limited as the evidence was found to be of low quality. Effects on other substantive outcomes are uncertain due to serious concerns in study design, inconsistency, and imprecision of effect estimates. No trials were identified on asymptomatic women, or multiple gestations. Future studies are needed that include specific populations (e.g. singleton gestations with symptoms of preterm labor), a study gro p managed with a protocol based on the FFN results, and that report not only maternal but also important perinatal outcomes. CostÃƒÆ’Ã‚Â¢ÃƒÂ¢Ã¢â‚¬Å¡Ã‚Â¬Ãƒâ€šÃ‚Âeffectiveness analyses are also needed. Plain language summary Fetal fibronectin testing for reducing the risk of preterm birth What is the issue? To assess the effectiveness of management of pregnant women based on a knowledge of fetal fibronectin test results for preventing preterm birth, compared with not having that knowledge. Fetal fibronectin (FFN) acts as a ÃƒÆ’Ã‚Â¢ÃƒÂ¢Ã¢â‚¬Å¡Ã‚Â¬Ãƒâ€¹Ã…â€œglueÃƒÆ’Ã‚Â¢ÃƒÂ¢Ã¢â‚¬Å¡Ã‚Â¬ÃƒÂ¢Ã¢â‚¬Å¾Ã‚Â¢ between the pregnancy and the uterus. Normally very low levels of FFN can be found in secretions of the vagina and cervix. Raised levels at or after 22 weeks have been associated with an increased risk of spontaneous preterm birth. Why is this important? Preterm birth before 37 weeks is the main cause of sickness and death for newborn infants. Most women who give birth preterm have preterm labor symptoms such as contractions but many of the women with symptoms go on to deliver at term (37 weeks or more). Fetal fibronectin (FFN) is a test that can identify the women with symptoms of preterm labor who are most at risk for preterm birth. The level of FFN is measured in secretions from the vagina or cervix. What evidence did we find? We found six randomised controlled studies involving 546 women who were pregnant with one baby and were showing signs of preterm labor at between 23 to 34 weeks' gestation. We graded the following evidence as mainly low quality because of the low number of women in the studies and a wide variation in findings. We found that the number of births before 37 weeks may be slightly reduced when women and their doctors know the results of the FFN test (20.7% versus 29.2%; 5 trials; 434 women). However, knowledge of FFN results may make little or no difference for the other outcomes with available data, including: maternal hospitalization (5 trials; 441 women); use of uterine relaxants (tocolysis) to try to prevent labor; earlier preterm births; womenÃƒÆ’Ã‚Â¢ÃƒÂ¢Ã¢â‚¬Å¡Ã‚Â¬ÃƒÂ¢Ã¢â‚¬Å¾Ã‚Â¢s gestational age at delivery; babies with a birthweight less than 2500 g; newborn deaths; the number of babies with respiratory distress syndrome; giving steroids to mature the unborn babiesÃƒÆ’Ã‚Â¢ÃƒÂ¢Ã¢â‚¬Å¡Ã‚Â¬ÃƒÂ¢Ã¢â‚¬Å¾Ã‚Â¢ lungs; and number of days in a neonatal intensive care unit (NICU). What does this mean? This review of six studies did not find enough evidence to say whether or not the FFN test should be used in the management of women showing signs of preterm labor. A screening test such as FFN can only be considered effective if interventions based on the screening results, such as giving drugs to relax the uterus, reduce the number of preterm births. Further research should be encouraged. | E2: FALSE | F2: No explicit budget reduction or cash-releasing benefits mentioned. | G2: no_cost_shift_or_harm | H2: 0.9
A3: J535 | B3: 2019 | C3: Interventions for prodromal stage of psychosis | D3: - Background Psychosis is a serious mental condition characterised by a loss of contact with reality. There may be a prodromal period or stage of psychosis, where early signs of symptoms indicating onset of first episode psychosis (FEP) occur. A number of services, incorporating multimodal treatment approaches (pharmacotherapy, psychotherapy and psychosocial interventions), developed worldwide, now focus on this prodromal period with the aim of preventing psychosis in people at risk of developing FEP. Objectives The primary objective is to assess the safety and efficacy of early interventions for people in the prodromal stage of psychosis. The secondary objective is, if possible, to compare the effectiveness of the various different interventions. Search methods We searched Cochrane Schizophrenia's studyÃƒÆ’Ã‚Â¢ÃƒÂ¢Ã¢â‚¬Å¡Ã‚Â¬Ãƒâ€šÃ‚Âbased Register of studies (including trials registers) on 8 June 2016 and 4 August 2017. Selection criteria All randomised controlled trials (RCTs) evaluating interventions for participants older than 12 years, who had developed a prodromal stage of psychosis. Data collection and analysis Review authors independently inspected citations, selected studies, extracted data, and assessed study quality. Main results We included 20 studies with 2151 participants. The studies analysed 13 different comparisons. Group A comparisons explored the absolute effects of the experimental intervention. Group B were comparisons within which we could not be clear whether differential interactive effects were also ongoing. Group C comparisons explored differential effects between clearly distinct treatments. A key outcome for this review was ÃƒÆ’Ã‚Â¢ÃƒÂ¢Ã¢â‚¬Å¡Ã‚Â¬Ãƒâ€¹Ã…â€œtransition to psychosisÃƒÆ’Ã‚Â¢ÃƒÂ¢Ã¢â‚¬Å¡Ã‚Â¬ÃƒÂ¢Ã¢â‚¬Å¾Ã‚Â¢. For details of other main outcomes please see 'Summary of findings' tables. In Group A (comparisons of absolute effects) we found no clear difference between amino acids and placebo (risk ratio (RR) 0.48 95% confidence interval (CI) 0.08 to 2.98; 2 RCTs, 52 participants; very lowÃƒÆ’Ã‚Â¢ÃƒÂ¢Ã¢â‚¬Å¡Ã‚Â¬Ãƒâ€šÃ‚Âquality evidence). When omegaÃƒÆ’Ã‚Â¢ÃƒÂ¢Ã¢â‚¬Å¡Ã‚Â¬Ãƒâ€šÃ‚Â3 fatty acids were compared to placebo, fewer participants given the omegaÃƒÆ’Ã‚Â¢ÃƒÂ¢Ã¢â‚¬Å¡Ã‚Â¬Ãƒâ€šÃ‚Â3 (10%) transitioned to psychosis compared to the placebo group (33%) during longÃƒÆ’Ã‚Â¢ÃƒÂ¢Ã¢â‚¬Å¡Ã‚Â¬Ãƒâ€šÃ‚Âterm followÃƒÆ’Ã‚Â¢ÃƒÂ¢Ã¢â‚¬Å¡Ã‚Â¬Ãƒâ€šÃ‚Âup of seven years (RR 0.24 95% CI 0.09 to 0.67; 1 RCT, 81 participants; lowÃƒÆ’Ã‚Â¢ÃƒÂ¢Ã¢â‚¬Å¡Ã‚Â¬Ãƒâ€šÃ‚Âquality evidence). In Group B (comparisons where complex interactions are probable) and in the subgroup focusing on antipsychotic drugs added to specific care packages, the amisulpiride + needsÃƒÆ’Ã‚Â¢ÃƒÂ¢Ã¢â‚¬Å¡Ã‚Â¬Ãƒâ€šÃ‚Âfocused intervention (NFI) compared to NFI comparison (no reporting of transition to psychosis; 1 RCT, 102 participants; very lowÃƒÆ’Ã‚Â¢ÃƒÂ¢Ã¢â‚¬Å¡Ã‚Â¬Ãƒâ€šÃ‚Âquality evidence) and the olanzapine + supportive intervention compared to supportive intervention alone comparison (RR 0.58 95% CI 0.28 to 1.18; 1 RCT, 60 participants; very lowÃƒÆ’Ã‚Â¢ÃƒÂ¢Ã¢â‚¬Å¡Ã‚Â¬Ãƒâ€šÃ‚Âquality evidence) showed no clear differences between groups. In the second Group B subgroup (cognitive behavioural therapies (CBT)), when CBT + supportive therapy was compared with supportive therapy alone around 8% of participants allocated to the combination of CBT and supportive therapy group transitioned to psychosis during followÃƒÆ’Ã‚Â¢ÃƒÂ¢Ã¢â‚¬Å¡Ã‚Â¬Ãƒâ€šÃ‚Âup by 18 months, compared with double that percentage in the supportive therapy alone group (RR 0.45 95% CI 0.23 to 0.89; 2 RCTs, 252 participants; very lowÃƒÆ’Ã‚Â¢ÃƒÂ¢Ã¢â‚¬Å¡Ã‚Â¬Ãƒâ€šÃ‚Âquality evidence). The CBT + risperidone versus CBT + placebo comparison identified no clear difference between treatments (RR 1.02 95% CI 0.39 to 2.67; 1 RCT, 87 participants; very lowÃƒÆ’Ã‚Â¢ÃƒÂ¢Ã¢â‚¬Å¡Ã‚Â¬Ãƒâ€šÃ‚Âquality evidence) and this also applies to the CBT + needsÃƒÆ’Ã‚Â¢ÃƒÂ¢Ã¢â‚¬Å¡Ã‚Â¬Ãƒâ€šÃ‚Âbased intervention (NBI) + risperidone versus NBI comparison (RR 0.75 95% CI 0.39 to 1.46; 1 RCT, 59 participants; very lowÃƒÆ’Ã‚Â¢ÃƒÂ¢Ã¢â‚¬Å¡Ã‚Â¬Ãƒâ€šÃ‚Âquality evidence). Group C (differential effects) also involved six comparisons. The first compared CBT with supportive therapy. No clear difference was found for the ÃƒÆ’Ã‚Â¢ÃƒÂ¢Ã¢â‚¬Å¡Ã‚Â¬Ãƒâ€¹Ã…â€œtransition to psychosisÃƒÆ’Ã‚Â¢ÃƒÂ¢Ã¢â‚¬Å¡Ã‚Â¬ÃƒÂ¢Ã¢â‚¬Å¾Ã‚Â¢ outcome (RR 0.74 95% CI 0.28 to 1.98; 1 RCT, 72 participants; very lowÃƒÆ’Ã‚Â¢ÃƒÂ¢Ã¢â‚¬Å¡Ã‚Â¬Ãƒâ€šÃ‚Âquality evidence). The second subgroup compared CBT + supportive intervention was compared with a NBI + supportive intervention, again, data were equivocal, few and of very low quality (RR 6.32 95% CI 0.34 to 117.09; 1 RCT, 57 participants). In the CBT + risperidone versus supportive therapy comparison, again there was no clear difference between groups (RR 0.76 95% CI 0.28 to 2.03; 1 RCT, 71 participants; very lowÃƒÆ’Ã‚Â¢ÃƒÂ¢Ã¢â‚¬Å¡Ã‚Â¬Ãƒâ€šÃ‚Âquality evidence). The three other comparisons in Group C demonstrated no clear differences between treatment groups. When cognitive training was compared to active control (tablet games) (no reporting of transition to psychosis; 1 RCT, 62 participants; very low quality data), family treatment compared with enhanced care comparison (RR 0.54 95% CI 0.18 to 1.59; 2 RCTs, 229 participants; very lowÃƒÆ’Ã‚Â¢ÃƒÂ¢Ã¢â‚¬Å¡Ã‚Â¬Ãƒâ€šÃ‚Âquality evidence) and integrated treatment compared to standard treatment comparison (RR 0.57 95% CI 0.28 to 1.15; 1 RCT, 79 participants; very lowÃƒÆ’Ã‚Â¢ÃƒÂ¢Ã¢â‚¬Å¡Ã‚Â¬Ãƒâ€šÃ‚Âquality evidence) no effects of any of these approaches was evident. Authors' conclusions There has been considerable research effort in this area and several interventions have been trialled. The evidence available suggests that omegaÃƒÆ’Ã‚Â¢ÃƒÂ¢Ã¢â‚¬Å¡Ã‚Â¬Ãƒâ€šÃ‚Â3 fatty acids may prevent transition to psychosis but this evidence is low quality and more research is needed to confirm this finding. Other comparisons did not show any clear differences in effect for preventing transition to psychosis but again, the quality of this evidence is very low or low and not strong enough to make firm conclusions. Plain language summary Early interventions for people at risk of developing psychosis Review question Is there highÃƒÆ’Ã‚Â¢ÃƒÂ¢Ã¢â‚¬Å¡Ã‚Â¬Ãƒâ€šÃ‚Âquality evidence indicating that interventions for people at risk of developing psychosis are effective? Background Psychoses are serious mental conditions characterised by a loss of contact with reality. The first clear episode of psychosis can be preceded by a 'prodromal' period of at least six months, where a person experiences gradual nonÃƒÆ’Ã‚Â¢ÃƒÂ¢Ã¢â‚¬Å¡Ã‚Â¬Ãƒâ€šÃ‚Âspecific changes in thoughts, perceptions, behaviours and functioning. Although an individual is experiencing changes, they have not yet started to experience the more obvious psychotic symptoms such as delusions (fixed false beliefs) or hallucinations (perceptions without a cause). A number of services with treatment approaches that combine pharmacotherapy, psychotherapy and psychosocial treatments, developed worldwide, are now focusing on prevention of psychosis in people at risk by giving treatments during this prodromal period. This review assesses the evidence available concerning the effects of different treatment approaches for people not yet diagnosed with a non affective psychosis but who are in the prodromal stage of psychosis. Searching for evidence On 8 June 2016 and 4 August 2017 we ran electronic searches of the Cochrane Schizophrenia's specialised register of studies in order to find clinical studies that randomly allocated individuals at risk of developing psychosis to receive various treatments for preventing development of psychosis. Evidence found We were able to include 20 studies with 2151 participants. These studies analysed a wide range of treatments. All the review findings are of, at very best, low quality. There is some suggestion from one small study that people at risk of psychosis may benefit from taking omegaÃƒÆ’Ã‚Â¢ÃƒÂ¢Ã¢â‚¬Å¡Ã‚Â¬Ãƒâ€šÃ‚Â3 fatty acids in terms of reduced transition to psychosis. Other studies found adding antipsychotic drugs to supportiveÃƒÆ’Ã‚Â¢ÃƒÂ¢Ã¢â‚¬Å¡Ã‚Â¬Ãƒâ€šÃ‚Âcare packages did not seem to make much difference in terms of transition to full illness. When cognitive behavioural therapy (CBT) + supportive therapy was compared with supportive therapy alone around 8% of participants treated allocated to the combination of CBT and supportive therapy transitioned to psychosis during followÃƒÆ’Ã‚Â¢ÃƒÂ¢Ã¢â‚¬Å¡Ã‚Â¬Ãƒâ€šÃ‚Âup by 18 months, compared with double that percentage in people who just received supportive therapy. This could be important but these data are of very low quality. All other testing of CBT and other packages of care found no clear difference between treatments for transition to psychosis. Conclusions There has been considerable effort and expense invested testing treatment approaches for prevention of the first episode of schizophr nia. Currently, there is some lowÃƒÆ’Ã‚Â¢ÃƒÂ¢Ã¢â‚¬Å¡Ã‚Â¬Ãƒâ€šÃ‚Âquality evidence suggesting that omegaÃƒÆ’Ã‚Â¢ÃƒÂ¢Ã¢â‚¬Å¡Ã‚Â¬Ãƒâ€šÃ‚Â3 fatty acids may be effective, but there is no highÃƒÆ’Ã‚Â¢ÃƒÂ¢Ã¢â‚¬Å¡Ã‚Â¬Ãƒâ€šÃ‚Âquality evidence to suggest that any type of treatment is effective, and no firm conclusions can be made. | E3: FALSE | F3: Focus on efficacy and safety, not budget or cost reduction. | H3: 0.9
A4: J545 | B4: 2019 | C4: Estimating the cost-effectiveness of salt reformulation and increasing access to leisure centres in England, with PRIMEtime CE model validation using the AdViSHE tool | D4: BACKGROUND: PRIMEtime CE is a multistate life table model that can directly compare the cost effectiveness of public health interventions affecting diet and physical activity levels, helping to inform decisions about how to spend finite resources. This paper estimates the costs and health outcomes in England of two scenarios: reformulating salt and expanding subsidised access to leisure centres. The results are used to help validate PRIMEtime CE, following the steps outlined in the Assessment of the Validation Status of Health-Economic decision models (AdViSHE) tool. METHOD(S): The PRIMEtime CE model estimates the difference in quality adjusted life years (QALYs) and difference in NHS and social care costs of modelled interventions compared with doing nothing. The salt reformulation scenario models how salt consumption would change if food producers met the 2017 UK Food Standards Agency salt reformulation targets. The leisure centre scenario models change in physical activity levels if the Birmingham Be Active scheme (where swimming pools and gym access is free to residents during defined periods) was rolled out across England. The AdViSHE tool was developed by health economic modellers and divides model validation into five parts: validation of the conceptual model, input data validation, validation of computerised model, operational validation, and other validation techniques. PRIMEtime CE is discussed in relation to each part. RESULT(S): Salt reformulation was dominant compared with doing nothing, and had a 10-year return on investment of 1.44 (0.50 to 2.94) for every 1 spent. By contrast, over 10 years the Be Active expansion would cost 727,000 (514,000 to 1,064,000) per QALY. PRIMEtime CE has good face validity of its conceptual model and has robust input data. Cross-validation produces mixed results and shows the impact of model scope, input parameters, and model structure on cost-per-QALY estimates. CONCLUSION(S): This paper illustrates how PRIMEtime CE can be used to compare the cost-effectiveness of two different public health measures affecting diet and physical activity levels. The AdViSHE tool helps to validate PRIMEtime CE, identifies some of the key drivers of model estimates, and highlights the challenges of externally validating public health economic models against independent data. | E4: FALSE | F4: Focuses on cost-effectiveness, not explicit budget reduction. | G4: has_baseline_and_counterfactual; no_cost_shift_or_harm | H4: 0.9
A5: J547 | B5: 2019 | C5: Individualised screening for diabetic retinopathy: The ISDR study-a randomised controlled trial of safety, efficacy, and cost-effectiveness | D5: Background: Varying the intervals in retinopathy screening informed by personal risk offers reallocation of resources to better target high risk groups and address the increasing prevalence of diabetes. However, safety data especially on extended intervals is minimal. Aim(s): To evaluate the safety, efficacy and cost effectiveness (CE) of individualized variable-interval risk-based screening in a population setting compared to usual care. Method(s): Masked 2 arm, parallel assignment, equivalence RCT (largest to date in screening) with independent trials unit monitoring in people with diabetes aged >=12 years attending screening in a single English program. Randomization was 1:1 to individualized screening (active group; 6, 12 or 24 months for high, medium and low risk) determined by a risk calculation engine using real-time local demographic, retinal and clinical data, compared with annual screening (control). CE analysis measuring NHS and societal costs took a 2-year time horizon. Finding(s): 4534 participants entered the study-after withdrawals/loss to follow-up: active 2097; control 2224. Attendance rates at first follow-up visit (primary outcome, safety) were equivalent (per protocol analysis, 5% margin): active 83.6% control 84.7% (difference 1.0, 90% CI-0.8, 2.9). STDR detection rates were non-inferior (1.5% margin): active 1.43% control 1.71% (difference-0.28, CI-0.93, 0.36). Quality of life (EQ5D5L, HUI3) was not significantly different between the groups. Incremental cost saving per person was 18.75 (NHS cost) rising to 49.96 with societal costs. A 39.3% reduction in number of appointments was seen. Conclusion(s): All parties involved in diabetes care can be reassured that extended and personalized screening intervals can safely be introduced in established screening program. Scale-up with further validation outside a research setting is recommended. Views expressed are solely those of the authors. | E5: FALSE | F5: Mentions cost savings but lacks explicit budget reduction or cash-releasing mechanism. | G5: no_cost_shift_or_harm | H5: 0.7
A6: J552 | B6: 2019 | C6: PharmacyÃƒÆ’Ã‚Â¢ÃƒÂ¢Ã¢â‚¬Å¡Ã‚Â¬Ãƒâ€šÃ‚Âbased management for depression in adults | D6: - Background It is common for people not to take antidepressant medication as prescribed, with around 50% of people likely to prematurely discontinue taking their medication after six months. Community pharmacists may be well placed to have a role in antidepressant management because of their unique pharmacotherapeutic knowledge and ease of access for people. Pharmacists are in an ideal position to offer proactive interventions to people with depression or depressive symptoms. However, the effectiveness and acceptability of existing pharmacistÃƒÆ’Ã‚Â¢ÃƒÂ¢Ã¢â‚¬Å¡Ã‚Â¬Ãƒâ€šÃ‚Âbased interventions is not yet well understood. The degree to which a pharmacyÃƒÆ’Ã‚Â¢ÃƒÂ¢Ã¢â‚¬Å¡Ã‚Â¬Ãƒâ€šÃ‚Âbased management approach might be beneficial, acceptable to people, and effective as part of the overall management for those with depression is, to date, unclear. A systematic review of randomised controlled trials (RCTs) will help answer these questions and add important knowledge to the currently sparse evidence base. Objectives To examine the effects of pharmacyÃƒÆ’Ã‚Â¢ÃƒÂ¢Ã¢â‚¬Å¡Ã‚Â¬Ãƒâ€šÃ‚Âbased management interventions compared with active control (e.g. patient information materials or any other active intervention delivered by someone other than the pharmacist or the pharmacy team), waiting list, or treatment as usual (e.g. standard pharmacist advice or antidepressant education, signposting to support available in primary care services, brief medication counselling, and/or (selfÃƒÆ’Ã‚Â¢ÃƒÂ¢Ã¢â‚¬Å¡Ã‚Â¬Ãƒâ€šÃ‚Â)monitoring of medication adherence offered by a healthcare professional outside the pharmacy team) at improving depression outcomes in adults. Search methods We searched the Cochrane Common Mental Disorders Controlled Trials Register (CCMDÃƒÆ’Ã‚Â¢ÃƒÂ¢Ã¢â‚¬Å¡Ã‚Â¬Ãƒâ€šÃ‚ÂCTR) to June 2016; the Cochrane Library (Issue 11, 2018); and Ovid MEDLINE, Embase, and PsycINFO to December 2018. We searched theses and dissertation databases and international trial registers for unpublished/ongoing trials. We applied no restrictions on date, language, or publication status to the searches. Selection criteria We included all RCTs and clusterÃƒÆ’Ã‚Â¢ÃƒÂ¢Ã¢â‚¬Å¡Ã‚Â¬Ãƒâ€šÃ‚ÂRCTs where a pharmacyÃƒÆ’Ã‚Â¢ÃƒÂ¢Ã¢â‚¬Å¡Ã‚Â¬Ãƒâ€šÃ‚Âbased intervention was compared with treatment as usual, waiting list, or an alternative intervention in the management of depression in adults over 16 years of age. Eligible studies had to report at least one of the following outcomes at any time point: depression symptom change, acceptability of the intervention, diagnosis of depression, nonÃƒÆ’Ã‚Â¢ÃƒÂ¢Ã¢â‚¬Å¡Ã‚Â¬Ãƒâ€šÃ‚Âadherence to medication, frequency of primary care appointments, quality of life, social functioning, or adverse events. Data collection and analysis Two authors independently, and in duplicate, conducted all stages of study selection, data extraction, and quality assessment (including GRADE). We discussed disagreements within the team until we reached consensus. Where data did not allow metaÃƒÆ’Ã‚Â¢ÃƒÂ¢Ã¢â‚¬Å¡Ã‚Â¬Ãƒâ€šÃ‚Âanalyses, we synthesised results narratively. Main results Twelve studies (2215 participants) met the inclusion criteria and compared pharmacyÃƒÆ’Ã‚Â¢ÃƒÂ¢Ã¢â‚¬Å¡Ã‚Â¬Ãƒâ€šÃ‚Âbased management with treatment as usual. Two studies (291 participants) also included an active control (both used patient information leaflets providing information about the prescribed antidepressant). Neither of these studies reported depression symptom change. A narrative synthesis of results on acceptability of the intervention was inconclusive, with one study reporting better acceptability of pharmacyÃƒÆ’Ã‚Â¢ÃƒÂ¢Ã¢â‚¬Å¡Ã‚Â¬Ãƒâ€šÃ‚Âbased management and the other better acceptability of the active control. One study reported that participants in the pharmacyÃƒÆ’Ã‚Â¢ÃƒÂ¢Ã¢â‚¬Å¡Ã‚Â¬Ãƒâ€šÃ‚Âbased management group had better medication adherence than the control participants. One study reported adverse events with no difference between groups. The studies reported no other outcomes. MetaÃƒÆ’Ã‚Â¢ÃƒÂ¢Ã¢â‚¬Å¡Ã‚Â¬Ãƒâ€šÃ‚Âanalyses comparing pharmacyÃƒÆ’Ã‚Â¢ÃƒÂ¢Ã¢â‚¬Å¡Ã‚Â¬Ãƒâ€šÃ‚Âbased management with treatment as usual showed no evidence of a difference in the effect of the intervention on depression symptom change (dichotomous data; improvement in symptoms yes/no: risk ratio (RR), 0.95, 95% confidence interval (CI) 0.86 to 1.05; 4 RCTs, 475 participants; moderateÃƒÆ’Ã‚Â¢ÃƒÂ¢Ã¢â‚¬Å¡Ã‚Â¬Ãƒâ€šÃ‚Âquality evidence; continuous data: standard mean difference (SMD) ÃƒÆ’Ã‚Â¢ÃƒÂ¢Ã¢â‚¬Å¡Ã‚Â¬Ãƒâ€šÃ‚Â0.04, 95% | E6: FALSE | F6: No explicit budget reduction or cash-releasing benefits mentioned. | G6: no_cost_shift_or_harm | H6: 0.9
A7: J571 | B7: 2019 | C7: Alternative community-based models of care for young people with anorexia nervosa: the CostED national surveillance study | D7: <b>BACKGROUND</b>: Evidence suggests that investing in specialist eating disorders services for young people with anorexia nervosa could have important implications for the NHS, with the potential to improve health outcomes and reduce costs through reductions in the number and length of hospital admissions._x000D_ <b>OBJECTIVES</b>: The primary objectives were to evaluate the costs and cost-effectiveness of alternative community-based models of service provision for young people with anorexia nervosa and to model the impact of potential changes to the provision of specialist services._x000D_ <b>DESIGN</b>: Observational surveillance study using the Child and Adolescent Psychiatry Surveillance System._x000D_ <b>SETTING</b>: Community-based secondary or tertiary child and adolescent mental health services (CAMHS) in the UK and the Republic of Ireland._x000D_ <b>PARTICIPANTS</b>: A total of 298 young people aged 8-17 years in contact with CAMHS for a first episode of anorexia nervosa in accordance with Diagnostic and Statistical Manual of Mental Disorders, Fifth Edition, diagnostic criteria._x000D_ <b>INTERVENTIONS</b>: Community-based specialist eating disorders services and generic CAMHS._x000D_ <b>MAIN OUTCOME MEASURES</b>: Children's Global Assessment Scale (CGAS) score (primary outcome) and percentage of median expected body mass index (BMI) for age and sex (%mBMI) (secondary outcome) were assessed at baseline and at 6 and 12 months._x000D_ <b>DATA SOURCES</b>: Data were collected by clinicians from clinical records._x000D_ <b>RESULTS</b>: Total costs incurred by young people initially assessed in specialist eating disorders services were not significantly different from those incurred by young people initially assessed in generic CAMHS. However, adjustment for baseline covariates resulted in observed differences favouring specialist services (costs were lower, on average) because of the significantly poorer clinical status of the specialist group at baseline. At the 6-month follow-up, mean %mBMI was significantly higher in the specialist group, but no other significant differences in outcomes were evident. Cost-effectiveness analyses suggest that initial assessment in a specialist service has a higher probability of being cost-effective than initial assessment in generic CAMHS, as determined by CGAS score and %mBMI. However, no firm conclusion can be drawn without knowledge of society's willingness to pay for improvements in these outcomes. Decision modelling did not support the hypothesis that changes to the provision of specialist services would generate savings for the NHS, with results suggesting that cost per 10-point improvement in CGAS score (improvement from one CGAS category to the next) varies little as the percentage of participants taking the specialist or generic pathway is varied._x000D_ <b>LIMITATIONS</b>: Follow-up rates were lower than expected, but the sample was still larger than has been achieved to date in RCTs carried out in this population in the UK, and an exploration of the impact of missing cost and outcome data produced very similar results to those of the main analyses._x000D_ <b>CONCLUSIONS</b>: The results of this study suggest that initial assessment in a specialist eating disorders service for young people with anorexia nervosa may have a higher probability of being cost-effective than initial assessment in generic CAMHS, although the associated uncertainty makes it hard to draw firm conclusions. Although costs and outcomes were similar, young people in specialist services were more severely ill at baseline, suggesting that specialist services were achieving larger clinical effectiveness gains without the need for additional expenditure. The results did not suggest that providing more specialist services would save money for the NHS, given similar costs and outcomes, so decisions about which service type to fund could be made with reference to other factors, such as the preferences of patients and carers._x000D_ <b>FUTURE WORK</b>: Data on measures of quality of life capable of generating quality-adjusted life-years are needed to confirm the cost-effectiveness of specialist services._x000D_ <b>TRIAL REGISTRATION</b>: Current Controlled Trials ISRCTN12676087._x000D_ <b>FUNDING</b>: This project was funded by the National Institute for Health Research (NIHR) Health Services and Delivery Research programme and will be published in full in Health Services and Delivery Research; Vol. 7, No. 37. See the NIHR Journals Library website for further project information. | E7: FALSE | F7: Study shows no cost savings; similar costs and outcomes. | G7: has_baseline_and_counterfactual; no_cost_shift_or_harm | H7: 0.9
A8: J574 | B8: 2019 | C8: Abstract 2415: Polygenic risk-tailored screening for prostate cancer: A costeffectiveness Analysis | D8: Background Screening for prostate cancer with prostate specific antigen (PSA) remains controversial. Risk-tailoring based on age and polygenic profile might conserve the benefits of PSA screening whilst reducing overdiagnosis. This study evaluates the cost-effectiveness and benefit-to-harm balance of polygenic risk-tailored screening for prostate cancer. Methods A life-table approach was used. A hypothetical cohort of 4.48 million men in England between the ages of 55 and 70 was followed to the age of 90. Three scenarios were compared: No screening, age-based screening (PSA testing every four years from 55 to 70), and risk-tailored screening based on age and polygenic risk profile (men above the risk threshold receive PSA testing four-yearly from the age they reach the risk threshold to 70). The number of prostate cancer cases, deaths from prostate cancer, overdiagnosed cases, life-years and quality-adjusted life-years (QALYs), incremental cost per QALY, and net monetary benefit were calculated. Sensitivity analyses investigated the impact of parameter uncertainty, and the impact of varying the risk threshold, on outcomes. Costs were estimated from the perspective of the UK National Health Service; both costs and benefits were discounted at 3.5%. Results The incremental cost per additional QALY for age-based screening compared to no screening was 58,254 ($75,899), with 27% simulations having an incremental cost-effectiveness ratio of less than 20,000 ($26,058), the threshold set by the UK National Institute for Health and Care Excellence for an intervention to be considered costeffective. In risk-tailored screening, as the 10-year absolute risk-threshold was progressively increased from 2.6%, equivalent to the 10-year absolute risk of a 55-year old man, to 7.1%, the corresponding risk of a 69-year old man, the cost per additional QALY gained reduced from 36,065 ($46,989) to 26,210 ($34,149), when compared to no screening. By comparison with age-based screening, risk-tailored screening with a threshold between 2.6% and 7.1% led to 8 (2.5%) and 45 (13%) fewer deaths prevented from prostate cancer per 10,000 men, with a 0.1% rise and 10% reduction in costs, respectively. Raising the risk threshold from 2.6% to 7.1% led to fewer men being screened (cumulative total of 35% of men screened by comparison with 83%), 53% fewer overdiagnosed cases, 22% fewer biopsies and 10% lower costs, at the expense of 10% fewer prostate cancer deaths averted. Conclusion Risk-tailored screening reduces the harms of screening for prostate cancer whilst preserving much of the mortality benefit. This study raises the prospect of risktailored population-based screening for prostate cancer; the precise risk-thresholds selected will depend on societal judgements regarding the appropriate trade-offs between harms and benefits. | E8: FALSE | F8: Focuses on cost-effectiveness, not explicit budget reduction or cash-releasing benefits. | G8: has_baseline_and_counterfactual | H8: 0.8
A9: J575 | B9: 2019 | C9: Polygenic risk-tailored screening for prostate cancer: A benefit-harm and cost-effectiveness modelling study | D9: Background The United States Preventive Services Task Force supports individualised decision-making for prostate-specific antigen (PSA)-based screening in men aged 55-69. Knowing how the potential benefits and harms of screening vary by an individual's risk of developing prostate cancer could inform decision-making about screening at both an individual and population level. This modelling study examined the benefit-harm tradeoffs and the cost-effectiveness of a risk-tailored screening programme compared to age-based and no screening. Methods and findings A life-table model, projecting age-specific prostate cancer incidence and mortality, was developed of a hypothetical cohort of 4.48 million men in England aged 55 to 69 years with follow-up to age 90. Risk thresholds were based on age and polygenic profile. We compared no screening, age-based screening (quadrennial PSA testing from 55 to 69), and risk-tailored screening (men aged 55 to 69 years with a 10-year absolute risk greater than a threshold receive quadrennial PSA testing from the age they reach the risk threshold). The analysis was undertaken from the health service perspective, including direct costs borne by the health system for risk assessment, screening, diagnosis, and treatment. We used probabilistic sensitivity analyses to account for parameter uncertainty and discounted future costs and benefits at 3.5% per year. Our analysis should be considered cautiously in light of limitations related to our model's cohort-based structure and the uncertainty of input parameters in mathematical models. Compared to no screening over 35 years follow-up, age-based screening prevented the most deaths from prostate cancer (39,272, 95% uncertainty interval [UI]: 16,792-59,685) at the expense of 94,831 (95% UI: 84,827-105,630) overdiagnosed cancers. Age-based screening was the least cost-effective strategy studied. The greatest number of quality-adjusted life-years (QALYs) was generated by risk-based screening at a 10-year absolute risk threshold of 4%. At this threshold, risk-based screening led to one-third fewer overdiagnosed cancers (64,384, 95% UI: 57,382-72,050) but averted 6.3% fewer (9,695, 95% UI: 2,853-15,851) deaths from prostate cancer by comparison with age-based screening. Relative to no screening, risk-based screening at a 4% 10-year absolute risk threshold was cost-effective in 48.4% and 57.4% of the simulations at willingness-to-pay thresholds of GBP20,000 (US$26,000) and 30,000 ($39,386) per QALY, respectively. The cost-effectiveness of risk-tailored screening improved as the threshold rose. Conclusions Based on the results of this modelling study, offering screening to men at higher risk could potentially reduce overdiagnosis and improve the benefit-harm tradeoff and the cost-effectiveness of a prostate cancer screening program. The optimal threshold will depend on societal judgements of the appropriate balance of benefits-harms and cost-effectiveness. Copyright: ÃƒÆ’Ã¢â‚¬Å¡Ãƒâ€šÃ‚Â© 2019 Callender et al. This is an open access article distributed under the terms of the Creative Commons Attribution License, which permits unrestricted use, distribution, and reproduction in any medium, provided the original author and source are credited. | E9: FALSE | F9: Focuses on cost-effectiveness, not explicit budget reduction. | G9: has_baseline_and_counterfactual | H9: 0.8
A10: J583 | B10: 2019 | C10: Community pharmacy personnel interventions for smoking cessation | D10: - Background Community pharmacists could provide effective smoking cessation treatment because they offer easy access to members of the community. They are well placed to provide both advice on the correct use of smoking cessation products and behavioural support to aid smoking cessation. Objectives To assess the effectiveness of interventions delivered by community pharmacy personnel to assist people to stop smoking, with or without concurrent use of pharmacotherapy. Search methods We searched the Cochrane Tobacco Addiction Group Specialised Register, along with clinicaltrials.gov and the ICTRP, for smoking cessation studies conducted in a community pharmacy setting, using the search terms pharmacist* or pharmacy or pharmacies. Date of the most recent search: January 2019. Selection criteria Randomised controlled trials of interventions delivered by community pharmacy personnel to promote smoking cessation amongst their clients who were smokers, compared with usual pharmacy support or any less intensive programme. The main outcome measure was smoking cessation rates at six months or more after the start of the intervention. Data collection and analysis We used standard methodological procedures expected by Cochrane for study screening, data extraction and management. We conducted a metaÃƒÆ’Ã‚Â¢ÃƒÂ¢Ã¢â‚¬Å¡Ã‚Â¬Ãƒâ€šÃ‚Âanalysis using a MantelÃƒÆ’Ã‚Â¢ÃƒÂ¢Ã¢â‚¬Å¡Ã‚Â¬Ãƒâ€šÃ‚ÂHaenszel randomÃƒÆ’Ã‚Â¢ÃƒÂ¢Ã¢â‚¬Å¡Ã‚Â¬Ãƒâ€šÃ‚Âeffects model to generate risk ratios (RRs) and 95% confidence intervals (CIs). Main results We identified seven studies including 1774 participants. We judged three studies to be at high risk of bias and four to be at unclear risk. Each study provided faceÃƒÆ’Ã‚Â¢ÃƒÂ¢Ã¢â‚¬Å¡Ã‚Â¬Ãƒâ€šÃ‚ÂtoÃƒÆ’Ã‚Â¢ÃƒÂ¢Ã¢â‚¬Å¡Ã‚Â¬Ãƒâ€šÃ‚Âface behavioural support delivered by pharmacy staff, and required pharmacy personnel training. Typically such programmes comprised support starting before quit day and continuing with weekly appointments for several weeks afterwards. Comparators were either minimal or less intensive behavioural support for smoking cessation, typically comprising a few minutes of oneÃƒÆ’Ã‚Â¢ÃƒÂ¢Ã¢â‚¬Å¡Ã‚Â¬Ãƒâ€šÃ‚Âoff advice on how to quit. Participants in both intervention and control arms received equivalent smoking cessation pharmacotherapy in all but one study. All studies took place in highÃƒÆ’Ã‚Â¢ÃƒÂ¢Ã¢â‚¬Å¡Ã‚Â¬Ãƒâ€šÃ‚Âincome countries, and recruited participants visiting pharmacies. We pooled six studies of 1614 participants and detected a benefit of more intensive behavioural smoking cessation interventions delivered by community pharmacy personnel compared with less intensive cessation interventions at longest followÃƒÆ’Ã‚Â¢ÃƒÂ¢Ã¢â‚¬Å¡Ã‚Â¬Ãƒâ€šÃ‚Âup (RR 2.30, 95% CI 1.33 to 3.97; I 2 = 54%; lowÃƒÆ’Ã‚Â¢ÃƒÂ¢Ã¢â‚¬Å¡Ã‚Â¬Ãƒâ€šÃ‚Âcertainty evidence). Authors' conclusions Community pharmacists can provide effective behavioural support to people trying to stop smoking. However, this conclusion is based on lowÃƒÆ’Ã‚Â¢ÃƒÂ¢Ã¢â‚¬Å¡Ã‚Â¬Ãƒâ€šÃ‚Âcertainty evidence, limited by risk of bias and imprecision. Further research could change this conclusion. Plain language summary Does quitÃƒÆ’Ã‚Â¢ÃƒÂ¢Ã¢â‚¬Å¡Ã‚Â¬Ãƒâ€šÃ‚Âsmoking support delivered by community pharmacy staff help people to stop smoking? Background Tobacco smoking is the leading cause of preventable death and disease worldwide. Community pharmacists are respected healthcare professionals who provide easily accessible and convenient healthcare services to their communities, and they are well placed to provide their clients with help to quit smoking. Indeed, many governments recognise community pharmacies as a useful way of delivering many healthcare services. However, we need evidence that these services are effective before we develop them more widely. Study characteristics We searched for relevant studies in January 2019, and found seven studies including 1774 people. Three studies took place in the UK, and one each in Australia, United States, Qatar, and Italy. Each study provided faceÃƒÆ’Ã‚Â¢ÃƒÂ¢Ã¢â‚¬Å¡Ã‚Â¬Ãƒâ€šÃ‚ÂtoÃƒÆ’Ã‚Â¢ÃƒÂ¢Ã¢â‚¬Å¡Ã‚Â¬Ãƒâ€šÃ‚Âface behavioural support delivered by pharmacy staff, who received specific training. Studies compared the structured programme to less intensive support to stop smoking. Key results We found evidence that more intensive structured care given by community pharmacy staff probably helps more people to quit smoking than less intensive support to quit. Qualit of the evidence We found lowÃƒÆ’Ã‚Â¢ÃƒÂ¢Ã¢â‚¬Å¡Ã‚Â¬Ãƒâ€šÃ‚Âquality evidence that community pharmacy support helps people to quit smoking. Limitations of the evidence came from potential problems with the ways some of the studies were carried out and the low numbers of people who quit smoking across the included studies, which means we are not sure how effective these programmes really are. | E10: FALSE | F10: Focuses on effectiveness, not budget impact. | G10: no_cost_shift_or_harm | H10: 0.9
A11: J587 | B11: 2019 | C11: Digital and online symptom checkers and assessment services for urgent care to inform a new digital platform: a systematic review | D11: <b>BACKGROUND</b>: Digital and online symptom checkers and assessment services are used by patients seeking guidance about health problems. NHS England is planning to introduce a digital platform (NHS111 Online) to operate alongside the NHS111 urgent-care telephone service. This review focuses on digital and online symptom checkers for urgent health problems._x000D_ <b>OBJECTIVES</b>: This systematic review was commissioned to provide NHS England with an independent review of previous research in this area to inform strategic decision-making and service design._x000D_ <b>DATA SOURCES</b>: Focused searches of seven bibliographic databases were performed and supplemented by phrase searching for names of symptom checker systems and citation searches of key included studies. The bibliographic databases searched were MEDLINE, EMBASE, The Cochrane Library, CINAHL (Cumulative Index to Nursing and Allied Health Literature), HMIC (Health Management Information Consortium), Web of Science and the Association of Computing Machinery (ACM) Digital Library, from inception up to April 2018._x000D_ <b>REVIEW METHODS</b>: Brief inclusion criteria were (1) population - general population seeking information online or digitally to address an urgent health problem; (2) intervention - any online or digital service designed to assess symptoms, provide health advice and direct patients to appropriate services; and (3) comparator - telephone or face-to-face assessment, comparative performance in tests or simulations (studies with no comparator were included if they reported relevant outcomes). Outcomes of interest included safety, clinical effectiveness, costs or cost-effectiveness, diagnostic and triage accuracy, use of and contacts with health services, compliance with advice received, patient/carer satisfaction, and equity and inclusion. Inclusion was not restricted by study design. Screening studies for inclusion, data extraction and quality assessment were carried out by one reviewer with a sample checked for accuracy and consistency. Final decisions on study inclusion were taken by consensus of the review team. A narrative synthesis of the included studies was performed and structured around the predefined research questions and key outcomes. The overall strength of evidence for each outcome was classified as 'stronger', 'weaker', 'conflicting' or 'insufficient', based on study numbers and design._x000D_ <b>RESULTS</b>: In total, 29 publications describing 27 studies were included. Studies were diverse in their design and methodology. The overall strength of the evidence was weak because it was largely based on observational studies and with a substantial component of non-peer-reviewed grey literature. There was little evidence to suggest that symptom checkers are unsafe, but studies evaluating their safety were generally short term and small scale. Diagnostic accuracy was highly variable between different systems but was generally low. Algorithm-based triage tended to be more risk averse than that of health professionals. Inconsistent evidence was found on effects on service use. There was very limited evidence on patients' reactions to online triage advice. The studies showed that younger and more highly educated people are more likely to use these services. Study participants generally expressed high levels of satisfaction with digital and online triage services, albeit in uncontrolled studies._x000D_ <b>LIMITATIONS</b>: Findings from symptom checker systems for specific conditions may not be applicable to more general systems and vice versa. Studies of symptom checkers as part of electronic consultation systems in general practice were also included, which is a slightly different setting from a general 'digital 111' service. Most studies were screened by one reviewer._x000D_ <b>CONCLUSIONS</b>: Major uncertainties surround the probable impact of digital 111 services on most outcomes. It will be important to monitor and evaluate the services using all available data sources and by commissioning high-quality research._x000D_ <b>FUTURE WORK</b>: Priorities for research include comparisons of different systems, rigorous economic evaluations and investigations of patient pathways._x000D_ <b>STUDY REGISTRATION</b>: The study is registered as PROSPERO CRD42018093564._x000D_ <b>FUNDING</b>: The National Institute for Health Research Health Services and Delivery Research programme. | E11: FALSE | F11: No explicit budget reduction or cash-releasing benefits mentioned. | H11: 0.9
A12: J2833 | B12: 2021 | C12: Mobile phoneÃƒÆ’Ã‚Â¢ÃƒÂ¢Ã¢â‚¬Å¡Ã‚Â¬Ãƒâ€šÃ‚Âbased interventions for improving adherence to medication prescribed for the primary prevention of cardiovascular disease in adults | D12: - Background Cardiovascular disease (CVD) is a major cause of disability and mortality globally. Premature fatal and nonÃƒÆ’Ã‚Â¢ÃƒÂ¢Ã¢â‚¬Å¡Ã‚Â¬Ãƒâ€šÃ‚Âfatal CVD is considered to be largely preventable through the control of risk factors by lifestyle modifications and preventive medication. LipidÃƒÆ’Ã‚Â¢ÃƒÂ¢Ã¢â‚¬Å¡Ã‚Â¬Ãƒâ€šÃ‚Âlowering and antihypertensive drug therapies for primary prevention are costÃƒÆ’Ã‚Â¢ÃƒÂ¢Ã¢â‚¬Å¡Ã‚Â¬Ãƒâ€šÃ‚Âeffective in reducing CVD morbidity and mortality among highÃƒÆ’Ã‚Â¢ÃƒÂ¢Ã¢â‚¬Å¡Ã‚Â¬Ãƒâ€šÃ‚Ârisk people and are recommended by international guidelines. However, adherence to medication prescribed for the prevention of CVD can be poor. Approximately 9% of CVD cases in the EU are attributed to poor adherence to vascular medications. LowÃƒÆ’Ã‚Â¢ÃƒÂ¢Ã¢â‚¬Å¡Ã‚Â¬Ãƒâ€šÃ‚Âcost, scalable interventions to improve adherence to medications for the primary prevention of CVD have potential to reduce morbidity, mortality and healthcare costs associated with CVD. Objectives To establish the effectiveness of interventions delivered by mobile phone to improve adherence to medication prescribed for the primary prevention of CVD in adults. Search methods We searched CENTRAL, MEDLINE, Embase, and two other databases on 7 January 2020. We also searched two clinical trials registers on 5 February 2020. We searched reference lists of relevant papers. We applied no language or date restrictions. Selection criteria We included randomised controlled trials investigating interventions delivered wholly or partly by mobile phones to improve adherence to cardiovascular medications prescribed for the primary prevention of CVD. We only included trials with a minimum of oneÃƒÆ’Ã‚Â¢ÃƒÂ¢Ã¢â‚¬Å¡Ã‚Â¬Ãƒâ€šÃ‚Âyear followÃƒÆ’Ã‚Â¢ÃƒÂ¢Ã¢â‚¬Å¡Ã‚Â¬Ãƒâ€šÃ‚Âup in order that the outcome measures related to longerÃƒÆ’Ã‚Â¢ÃƒÂ¢Ã¢â‚¬Å¡Ã‚Â¬Ãƒâ€šÃ‚Âterm, sustained medication adherence behaviours and outcomes. Eligible comparators were usual care or control groups receiving no mobile phoneÃƒÆ’Ã‚Â¢ÃƒÂ¢Ã¢â‚¬Å¡Ã‚Â¬Ãƒâ€šÃ‚Âdelivered component of the intervention. Data collection and analysis We used standard methodological procedures recommended by Cochrane. The main outcomes of interest were objective measures of medication adherence (blood pressure (BP) and cholesterol), CVD events, and adverse events. We contacted study authors for further information when this was not reported. Main results We included 14 trials with 25,633 randomised participants. Participants were recruited from communityÃƒÆ’Ã‚Â¢ÃƒÂ¢Ã¢â‚¬Å¡Ã‚Â¬Ãƒâ€šÃ‚Âbased primary and tertiary care or outpatient clinics. The interventions varied widely from those delivered solely through short messaging service (SMS) to those involving a combination of modes of delivery, such as SMS in addition to healthcare worker training, faceÃƒÆ’Ã‚Â¢ÃƒÂ¢Ã¢â‚¬Å¡Ã‚Â¬Ãƒâ€šÃ‚ÂtoÃƒÆ’Ã‚Â¢ÃƒÂ¢Ã¢â‚¬Å¡Ã‚Â¬Ãƒâ€šÃ‚Âface counselling, electronic pillboxes, written materials, and home blood pressure monitors. Some interventions only targeted medication adherence, while others additionally targeted lifestyle changes such as diet and exercise. Due to heterogeneity in the nature and delivery of the interventions and study populations, we reported most results narratively, with the exception of two trials which were similar enough to meaningfully pool in metaÃƒÆ’Ã‚Â¢ÃƒÂ¢Ã¢â‚¬Å¡Ã‚Â¬Ãƒâ€šÃ‚Âanalyses. The body of evidence for the effect of mobile phoneÃƒÆ’Ã‚Â¢ÃƒÂ¢Ã¢â‚¬Å¡Ã‚Â¬Ãƒâ€šÃ‚Âbased interventions on objective outcomes of adherence (BP and cholesterol) was of low certainty, due to most trials being at high risk of bias, and inconsistency in outcome effects. Two trials were at low risk of bias. Among five trials (total study enrolment: 5441 participants) recording lowÃƒÆ’Ã‚Â¢ÃƒÂ¢Ã¢â‚¬Å¡Ã‚Â¬Ãƒâ€šÃ‚Âdensity lipoprotein cholesterol (LDLÃƒÆ’Ã‚Â¢ÃƒÂ¢Ã¢â‚¬Å¡Ã‚Â¬Ãƒâ€šÃ‚ÂC), two studies found evidence for a small beneficial intervention effect on reducing LDLÃƒÆ’Ã‚Â¢ÃƒÂ¢Ã¢â‚¬Å¡Ã‚Â¬Ãƒâ€šÃ‚ÂC (ÃƒÆ’Ã‚Â¢Ãƒâ€¹Ã¢â‚¬Â ÃƒÂ¢Ã¢â€šÂ¬Ã¢â€žÂ¢5.30 mg/dL, 95% confidence interval (CI) ÃƒÆ’Ã‚Â¢Ãƒâ€¹Ã¢â‚¬Â ÃƒÂ¢Ã¢â€šÂ¬Ã¢â€žÂ¢8.30 to ÃƒÆ’Ã‚Â¢Ãƒâ€¹Ã¢â‚¬Â ÃƒÂ¢Ã¢â€šÂ¬Ã¢â€žÂ¢2.30; and ÃƒÆ’Ã‚Â¢Ãƒâ€¹Ã¢â‚¬Â ÃƒÂ¢Ã¢â€šÂ¬Ã¢â€žÂ¢9.20 mg/dL, 95% CI ÃƒÆ’Ã‚Â¢Ãƒâ€¹Ã¢â‚¬Â ÃƒÂ¢Ã¢â€šÂ¬Ã¢â€žÂ¢17.70 to ÃƒÆ’Ã‚Â¢Ãƒâ€¹Ã¢â‚¬Â ÃƒÂ¢Ã¢â€šÂ¬Ã¢â€žÂ¢0.70). The other three studies found results varying from a small reduction (ÃƒÆ’Ã‚Â¢Ãƒâ€¹Ã¢â‚¬Â ÃƒÂ¢Ã¢â€šÂ¬Ã¢â€žÂ¢7.7 mg/dL) to a small increase in LDLÃƒÆ’Ã‚Â¢ÃƒÂ¢Ã¢â‚¬Å¡Ã‚Â¬Ãƒâ€šÃ‚ÂC (0.77 mg/dL). All of which had wide confidence intervals that included no effect. Across 13 studies (25,166 participants) measuring systolic blood pressure, effect estimates ranged from a large reduction (MD ÃƒÆ’Ã‚Â¢Ãƒâ€¹Ã¢â‚¬Â ÃƒÂ¢Ã¢â€šÂ¬Ã¢â€žÂ¢12.45 mmHg, 95% CI ÃƒÆ’Ã‚Â¢Ãƒâ€¹Ã¢â‚¬Â ÃƒÂ¢Ã¢â€šÂ¬Ã¢â€žÂ¢15.02 to ÃƒÆ’Ã‚Â¢Ãƒâ€¹Ã¢â‚¬Â ÃƒÂ¢Ã¢â€šÂ¬Ã¢â€žÂ¢9.88) to a small increase (MD 2.80 mmHg, 95% CI 0.30 to 5.30). We found a similar range of effect estimates for diastolic BP, ranging from ÃƒÆ’Ã‚Â¢Ãƒâ€¹Ã¢â‚¬Â ÃƒÂ¢Ã¢â€šÂ¬Ã¢â€žÂ¢12.23 mmHg (95% CI ÃƒÆ’Ã‚Â¢Ãƒâ€¹Ã¢â‚¬Â ÃƒÂ¢Ã¢â€šÂ¬Ã¢â€žÂ¢14.03 to ÃƒÆ’Ã‚Â¢Ãƒâ€¹Ã¢â‚¬Â ÃƒÂ¢Ã¢â€šÂ¬Ã¢â€žÂ¢10.43) to 1.64 mmHg (95% CI ÃƒÆ’Ã‚Â¢Ãƒâ€¹Ã¢â‚¬Â ÃƒÂ¢Ã¢â€šÂ¬Ã¢â€žÂ¢0.55 to 3.83) (11 trials, 19,716 participants). Four trials showed intervention benefits for systolic and diastolic BP with confidence intervals excluding no effect, and among these were all three of the trials evaluating selfÃƒÆ’Ã‚Â¢ÃƒÂ¢Ã¢â‚¬Å¡Ã‚Â¬Ãƒâ€šÃ‚Âmonitoring of blood pressure with mobile phoneÃƒÆ’Ã‚Â¢ÃƒÂ¢Ã¢â‚¬Å¡Ã‚Â¬Ãƒâ€šÃ‚Âbased telemedicine. The fourth trial included SMS and provider support (with additional varied features). Seven studies (19,185 participants) reported 'controlled' BP as an outcome, and intervention effect estimates varied from negligible effects (odds ratio (OR) 1.01, 95% CI 0.76 to 1.34) to large improvements in BP control (OR 2.41, 95% CI: 1.57 to 3.68). The three trials of clinician training or decision support combined with SMS (with additional varied features) had confidence intervals encompassing benefits and harms, with point estimates close to zero. Pooled analyses of the two trials of interventions solely delivered through SMS were indicative of little or no beneficial intervention effect on systolic BP (MD ÃƒÆ’Ã‚Â¢Ãƒâ€¹Ã¢â‚¬Â ÃƒÂ¢Ã¢â€šÂ¬Ã¢â€žÂ¢1.55 mmHg, 95% CI ÃƒÆ’Ã‚Â¢Ãƒâ€¹Ã¢â‚¬Â ÃƒÂ¢Ã¢â€šÂ¬Ã¢â€žÂ¢3.36 to 0.25; I 2 = 0%) and small increases in controlled BP (OR 1.32, 95% CI 1.06 to 1.65; I 2 = 0%). Based on four studies (12,439 participants), there was very lowÃƒÆ’Ã‚Â¢ÃƒÂ¢Ã¢â‚¬Å¡Ã‚Â¬Ãƒâ€šÃ‚Âcertainty evidence (downgraded twice for imprecision and once for risk of bias) relating to the intervention effect on combined (fatal and nonÃƒÆ’Ã‚Â¢ÃƒÂ¢Ã¢â‚¬Å¡Ã‚Â¬Ãƒâ€šÃ‚Âfatal) CVD events. Two studies (2535 participants) provided lowÃƒÆ’Ã‚Â¢ÃƒÂ¢Ã¢â‚¬Å¡Ã‚Â¬Ãƒâ€šÃ‚Âcertainty evidence for the effect of the intervention on cognitive outcomes, with little or no difference between trial arms for perceived quality of care and satisfaction with treatment. There was moderateÃƒÆ’Ã‚Â¢ÃƒÂ¢Ã¢â‚¬Å¡Ã‚Â¬Ãƒâ€šÃ‚Âcertainty evidence (downgraded due to risk of bias) that the interventions did not cause harm, based on six studies (8285 participants). Three studies reported no adverse events attributable to the intervention. One study reported no difference between groups in experience of adverse effects of statins, and that no participants reported interventionÃƒÆ’Ã‚Â¢ÃƒÂ¢Ã¢â‚¬Å¡Ã‚Â¬Ãƒâ€šÃ‚Ârelated adverse events. One study stated that potential side effects were similar between groups. One study reported a similar number of deaths in each arm, but did not provide further information relating to potential adverse events. Authors' conclusions There is lowÃƒÆ’Ã‚Â¢ÃƒÂ¢Ã¢â‚¬Å¡Ã‚Â¬Ãƒâ€šÃ‚Âcertainty evidence on the effects of mobile phoneÃƒÆ’Ã‚Â¢ÃƒÂ¢Ã¢â‚¬Å¡Ã‚Â¬Ãƒâ€šÃ‚Âdelivered interventions to increase adherence to medication prescribed for the primary prevention of CVD. Trials of BP selfÃƒÆ’Ã‚Â¢ÃƒÂ¢Ã¢â‚¬Å¡Ã‚Â¬Ãƒâ€šÃ‚Âmonitoring with mobileÃƒÆ’Ã‚Â¢ÃƒÂ¢Ã¢â‚¬Å¡Ã‚Â¬Ãƒâ€šÃ‚Âphone telemedicine support reported modest benefits. One trial at low risk of bias reported modest reductions in LDL cholesterol but no benefits for BP. There is moderateÃƒÆ’Ã‚Â¢ÃƒÂ¢Ã¢â‚¬Å¡Ã‚Â¬Ãƒâ€šÃ‚Âcertainty evidence that these interventions do not result in harm. Further trials of these interventions are warranted. Plain language summary Interventions delivered by mobile phone to help people adhere to medication to prevent heart and circulatory disease Review question We reviewed the evidence on the effect of interventions delivered by mobile phone to help people in taking their medication to prevent cardiovascular disease (for example, heart attacks and strokes). Background Around 17.6 million people die from cardiovascular disease every year. Medications can help to prevent cardiovascular disease, but many people who have been given these medications do not take them as often or as consistently as recommended. This means that the medication will not work as well as it could to prevent cardiovascular disease. Interventions delivered through mobile phones, for example, prompting by text messaging, may be a lowÃƒÆ’Ã‚Â¢ÃƒÂ¢Ã¢â‚¬Å¡Ã‚Â¬Ãƒâ€šÃ‚Âcost way to help people to take their medication as recommended. Study characteristics The evidence is up to date to January 2020. We found 14 studies that tested interventions delivered at least partly by mobile phone, which followed up participants for at least 12 months. Key results We were not able to combine the results of most of the trials, because the interventions were very different. Two studies were at low risk of bias and 12 were at high risk of bias. T e effects of the interventions were inconsistent across studies, and so we are not confident about their findings. SelfÃƒÆ’Ã‚Â¢ÃƒÂ¢Ã¢â‚¬Å¡Ã‚Â¬Ãƒâ€šÃ‚Âmonitoring of blood pressure plus telemedicine support by mobile phone may improve blood pressure control, but we are not confident about the findings due to trials being at risk of bias. Interventions delivered by text message alone may have little or no effect on blood pressure control. Interventions which included text messages and clinician training or clinician decision support (with or without additional features) may have little or no effect on blood pressure or cholesterol. The effects of the interventions which included text messages and provider support (with or without other features) were inconsistent across studies, and so we are not confident about their findings. We are uncertain about the effects of apps held by the patient or apps with additional provider support. Some interventions delivered by mobile phone may help people to take their medication, but the benefits are small or modest. Some trials found that the interventions did not have any beneficial effect. There was no evidence to suggest that these types of interventions caused harm. | E12: FALSE | F12: Focus on adherence improvement, not explicit budget reduction. | G12: no_cost_shift_or_harm | H12: 0.8
A13: J2843 | B13: 2021 | C13: Organising Support for Carers of Stroke Survivors (OSCARSS): a cluster randomised controlled trial with economic evaluation | D13: Objective Investigated clinical effectiveness and cost-effectiveness of a person-centred intervention for informal carers/caregivers of stroke survivors. Design Pragmatic cluster randomised controlled trial (cRCT) with economic and process evaluation. Setting Clusters were services, from a UK voluntary sector specialist provider, delivering support primarily in the homes of stroke survivors and informal carers. Participants Adult carers in participating clusters were referred to the study by cluster staff following initial support contact. Interventions Intervention was the Carer Support Needs Assessment Tool for Stroke: a staff-facilitated, carer-led approach to help identify, prioritise and address the specific support needs of carers. It required at least one face-to-face support contact dedicated to carers, with reviews as required. Control was usual care, which included carer support (unstructured and variable). Outcome measures Participants provided study entry and self-reported outcome data by postal questionnaires, 3 and 6 months after first contact by cluster staff. Primary Outcome: 3-month caregiver strain (Family Appraisal of Caregiving Questionnaire, FACQ). Secondary Outcomes: FACQ subscales of caregiver distress and positive appraisals of caregiving, mood (Hospital Anxiety and Depression Scale) and satisfaction with stroke services (Pound). The economic evaluation included self-reported healthcare utilisation, intervention costs and EQ-5D-5L. Randomisation and masking Clusters were recruited before randomisation to intervention or control, with stratification for size of service. Cluster staff could not be masked as training was required for participation. Carer research participants provided self-reported outcome data unaware of allocation; they consented to follow-up data collection only. Results Between 1 February 2017 and 31 July 2018, 35 randomised clusters (18 intervention; 17 control) recruited 414 cRCT carers (208 intervention; 206 control). Study entry characteristics were well balanced. Primary outcome measure: intention-to-treat analysis for 84% retained participants (175 intervention; 174 control) found mean (SD) FACQ carer strain at 3 months to be 3.11 (0.87) in the control group compared with 3.03 (0.90) in the intervention group, adjusted mean difference of -0.04 (95% CI -0.20 to 0.13). Secondary outcomes had similarly small differences and tight CIs. Sensitivity analyses suggested robust findings. Intervention fidelity was not achieved. Intervention-related group costs were marginally higher with no additional health benefit observed on EQ-5D-5L. No adverse events were related to the intervention. Conclusions The intervention was not fully implemented in this pragmatic trial. As delivered, it conferred no clinical benefits and is unlikely to be cost-effective compared with usual care from a stroke specialist provider organisation. It remains unclear how best to support carers of stroke survivors. To overcome the implementation challenges of person-centred care in carers' research and service development, staff training and organisational support would need to be enhanced. Trial registration number ISRCTN58414120. Copyright ÃƒÆ’Ã¢â‚¬Å¡Ãƒâ€šÃ‚Â© Author(s) (or their employer(s)) 2020. Re-use permitted under CC BY-NC. No commercial re-use. See rights and permissions. Published by BMJ. | E13: FALSE | F13: No cost reduction or cash-releasing benefits identified. | G13: no_cost_shift_or_harm | H13: 0.9
A14: J2861 | B14: 2021 | C14: Integrated disease management interventions for patients with chronic obstructive pulmonary disease | D14: - Background People with chronic obstructive pulmonary disease (COPD) show considerable variation in symptoms, limitations, and wellÃƒÆ’Ã‚Â¢ÃƒÂ¢Ã¢â‚¬Å¡Ã‚Â¬Ãƒâ€šÃ‚Âbeing; this often complicates medical care. A multiÃƒÆ’Ã‚Â¢ÃƒÂ¢Ã¢â‚¬Å¡Ã‚Â¬Ãƒâ€šÃ‚Âdisciplinary and multiÃƒÆ’Ã‚Â¢ÃƒÂ¢Ã¢â‚¬Å¡Ã‚Â¬Ãƒâ€šÃ‚Âcomponent programme that addresses different elements of care could improve quality of life (QoL) and exercise tolerance, while reducing the number of exacerbations. Objectives To compare the effectiveness of integrated disease management (IDM) programmes versus usual care for people with chronic obstructive pulmonary disease (COPD) in terms of healthÃƒÆ’Ã‚Â¢ÃƒÂ¢Ã¢â‚¬Å¡Ã‚Â¬Ãƒâ€šÃ‚Ârelated quality of life (QoL), exercise tolerance, and exacerbationÃƒÆ’Ã‚Â¢ÃƒÂ¢Ã¢â‚¬Å¡Ã‚Â¬Ãƒâ€šÃ‚Ârelated outcomes. Search methods We searched the Cochrane Airways Group Register of Trials, CENTRAL, MEDLINE, Embase, and CINAHL for potentially eligible studies. Searches were current as of September 2020. Selection criteria Randomised controlled trials (RCTs) that compared IDM programmes for COPD versus usual care were included. Interventions consisted of multiÃƒÆ’Ã‚Â¢ÃƒÂ¢Ã¢â‚¬Å¡Ã‚Â¬Ãƒâ€šÃ‚Âdisciplinary (two or more healthcare providers) and multiÃƒÆ’Ã‚Â¢ÃƒÂ¢Ã¢â‚¬Å¡Ã‚Â¬Ãƒâ€šÃ‚Âtreatment (two or more components) IDM programmes of at least three months' duration. Data collection and analysis Two review authors independently assessed trial quality and extracted data. If required, we contacted study authors to request additional data. We performed metaÃƒÆ’Ã‚Â¢ÃƒÂ¢Ã¢â‚¬Å¡Ã‚Â¬Ãƒâ€šÃ‚Âanalyses using randomÃƒÆ’Ã‚Â¢ÃƒÂ¢Ã¢â‚¬Å¡Ã‚Â¬Ãƒâ€šÃ‚Âeffects modelling. We carried out sensitivity analyses for the quality of included studies and performed subgroup analyses based on setting, study design, dominant intervention components, and region. Main results Along with 26 studies included in the 2013 Cochrane Review, we added 26 studies for this update, resulting in 52 studies involving 21,086 participants for inclusion in the metaÃƒÆ’Ã‚Â¢ÃƒÂ¢Ã¢â‚¬Å¡Ã‚Â¬Ãƒâ€šÃ‚Âanalysis. FollowÃƒÆ’Ã‚Â¢ÃƒÂ¢Ã¢â‚¬Å¡Ã‚Â¬Ãƒâ€šÃ‚Âup periods ranged between 3 and 48 months and were classified as shortÃƒÆ’Ã‚Â¢ÃƒÂ¢Ã¢â‚¬Å¡Ã‚Â¬Ãƒâ€šÃ‚Âterm (up to 6 months), mediumÃƒÆ’Ã‚Â¢ÃƒÂ¢Ã¢â‚¬Å¡Ã‚Â¬Ãƒâ€šÃ‚Âterm (6 to 15 months), and longÃƒÆ’Ã‚Â¢ÃƒÂ¢Ã¢â‚¬Å¡Ã‚Â¬Ãƒâ€šÃ‚Âterm (longer than 15 months) followÃƒÆ’Ã‚Â¢ÃƒÂ¢Ã¢â‚¬Å¡Ã‚Â¬Ãƒâ€šÃ‚Âup. Studies were conducted in 19 different countries. The mean age of included participants was 67 years, and 66% were male. Participants were treated in all types of healthcare settings, including primary (n =15), secondary (n = 22), and tertiary care (n = 5), and combined primary and secondary care (n = 10). Overall, the level of certainty of evidence was moderate to high. We found that IDM probably improves healthÃƒÆ’Ã‚Â¢ÃƒÂ¢Ã¢â‚¬Å¡Ã‚Â¬Ãƒâ€šÃ‚Ârelated QoL as measured by St. George's Respiratory Questionnaire (SGRQ) total score at mediumÃƒÆ’Ã‚Â¢ÃƒÂ¢Ã¢â‚¬Å¡Ã‚Â¬Ãƒâ€šÃ‚Âterm followÃƒÆ’Ã‚Â¢ÃƒÂ¢Ã¢â‚¬Å¡Ã‚Â¬Ãƒâ€šÃ‚Âup (mean difference (MD) ÃƒÆ’Ã‚Â¢ÃƒÂ¢Ã¢â‚¬Å¡Ã‚Â¬Ãƒâ€šÃ‚Â3.89, 95% confidence interval (CI) ÃƒÆ’Ã‚Â¢ÃƒÂ¢Ã¢â‚¬Å¡Ã‚Â¬Ãƒâ€šÃ‚Â6.16 to ÃƒÆ’Ã‚Â¢ÃƒÂ¢Ã¢â‚¬Å¡Ã‚Â¬Ãƒâ€šÃ‚Â1.63; 18 RCTs, 4321 participants; moderateÃƒÆ’Ã‚Â¢ÃƒÂ¢Ã¢â‚¬Å¡Ã‚Â¬Ãƒâ€šÃ‚Âcertainty evidence). A comparable effect was observed at shortÃƒÆ’Ã‚Â¢ÃƒÂ¢Ã¢â‚¬Å¡Ã‚Â¬Ãƒâ€šÃ‚Âterm followÃƒÆ’Ã‚Â¢ÃƒÂ¢Ã¢â‚¬Å¡Ã‚Â¬Ãƒâ€šÃ‚Âup (MD ÃƒÆ’Ã‚Â¢ÃƒÂ¢Ã¢â‚¬Å¡Ã‚Â¬Ãƒâ€šÃ‚Â3.78, 95% CI ÃƒÆ’Ã‚Â¢ÃƒÂ¢Ã¢â‚¬Å¡Ã‚Â¬Ãƒâ€šÃ‚Â6.29 to ÃƒÆ’Ã‚Â¢ÃƒÂ¢Ã¢â‚¬Å¡Ã‚Â¬Ãƒâ€šÃ‚Â1.28; 16 RCTs, 1788 participants). However, the common effect did not exceed the minimum clinically important difference (MCID) of 4 points. There was no significant difference between IDM and control for longÃƒÆ’Ã‚Â¢ÃƒÂ¢Ã¢â‚¬Å¡Ã‚Â¬Ãƒâ€šÃ‚Âterm followÃƒÆ’Ã‚Â¢ÃƒÂ¢Ã¢â‚¬Å¡Ã‚Â¬Ãƒâ€šÃ‚Âup and for generic QoL. IDM probably also leads to a large improvement in maximum and functional exercise capacity, as measured by sixÃƒÆ’Ã‚Â¢ÃƒÂ¢Ã¢â‚¬Å¡Ã‚Â¬Ãƒâ€šÃ‚Âminute walking distance (6MWD), at mediumÃƒÆ’Ã‚Â¢ÃƒÂ¢Ã¢â‚¬Å¡Ã‚Â¬Ãƒâ€šÃ‚Âterm followÃƒÆ’Ã‚Â¢ÃƒÂ¢Ã¢â‚¬Å¡Ã‚Â¬Ãƒâ€šÃ‚Âup (MD 44.69, 95% CI 24.01 to 65.37; 13 studies, 2071 participants; moderateÃƒÆ’Ã‚Â¢ÃƒÂ¢Ã¢â‚¬Å¡Ã‚Â¬Ãƒâ€šÃ‚Âcertainty evidence). The effect exceeded the MCID of 35 metres and was even greater at shortÃƒÆ’Ã‚Â¢ÃƒÂ¢Ã¢â‚¬Å¡Ã‚Â¬Ãƒâ€šÃ‚Âterm (MD 52.26, 95% CI 32.39 to 72.74; 17 RCTs, 1390 participants) and longÃƒÆ’Ã‚Â¢ÃƒÂ¢Ã¢â‚¬Å¡Ã‚Â¬Ãƒâ€šÃ‚Âterm (MD 48.83, 95% CI 16.37 to 80.49; 6 RCTs, 7288 participants) followÃƒÆ’Ã‚Â¢ÃƒÂ¢Ã¢â‚¬Å¡Ã‚Â¬Ãƒâ€šÃ‚Âup. The number of participants with respiratoryÃƒÆ’Ã‚Â¢ÃƒÂ¢Ã¢â‚¬Å¡Ã‚Â¬Ãƒâ€šÃ‚Ârelated admissions was reduced from 324 per 1000 participants in the control group to 235 per 1000 participants in the IDM group (odds ratio (OR) 0.64, 95% CI 0.50 to 0.81; 15 RCTs, median followÃƒÆ’Ã‚Â¢ÃƒÂ¢Ã¢â‚¬Å¡Ã‚Â¬Ãƒâ€šÃ‚Âup 12 months, 4207 participants; highÃƒÆ’Ã‚Â¢ÃƒÂ¢Ã¢â‚¬Å¡Ã‚Â¬Ãƒâ€šÃ‚Âcertainty evidence). Likewise, IDM probably results in a reduction in emergency department (ED) visits (OR 0.69, 95%CI 0.50 to 0.93; 9 RCTs, median followÃƒÆ’Ã‚Â¢ÃƒÂ¢Ã¢â‚¬Å¡Ã‚Â¬Ãƒâ€šÃ‚Âup 12 months, 8791 participants; moderateÃƒÆ’Ã‚Â¢ÃƒÂ¢Ã¢â‚¬Å¡Ã‚Â¬Ãƒâ€šÃ‚Âcertainty evidence), a slight reduction in allÃƒÆ’Ã‚Â¢ÃƒÂ¢Ã¢â‚¬Å¡Ã‚Â¬Ãƒâ€šÃ‚Âcause hospital admissions (OR 0.75, 95%CI 0.57 to 0.98; 10 RCT , median followÃƒÆ’Ã‚Â¢ÃƒÂ¢Ã¢â‚¬Å¡Ã‚Â¬Ãƒâ€šÃ‚Âup 12 months, 9030 participants; moderateÃƒÆ’Ã‚Â¢ÃƒÂ¢Ã¢â‚¬Å¡Ã‚Â¬Ãƒâ€šÃ‚Âcertainty evidence), and fewer hospital days per person admitted (MD ÃƒÆ’Ã‚Â¢ÃƒÂ¢Ã¢â‚¬Å¡Ã‚Â¬Ãƒâ€šÃ‚Â2.27, 95% CI ÃƒÆ’Ã‚Â¢ÃƒÂ¢Ã¢â‚¬Å¡Ã‚Â¬Ãƒâ€šÃ‚Â3.98 to ÃƒÆ’Ã‚Â¢ÃƒÂ¢Ã¢â‚¬Å¡Ã‚Â¬Ãƒâ€šÃ‚Â0.56; 14 RCTs, median followÃƒÆ’Ã‚Â¢ÃƒÂ¢Ã¢â‚¬Å¡Ã‚Â¬Ãƒâ€šÃ‚Âup 12 months, 3563 participants; moderateÃƒÆ’Ã‚Â¢ÃƒÂ¢Ã¢â‚¬Å¡Ã‚Â¬Ãƒâ€šÃ‚Âcertainty evidence). Statistically significant improvement was noted on the Medical Research Council (MRC) Dyspnoea Scale at shortÃƒÆ’Ã‚Â¢ÃƒÂ¢Ã¢â‚¬Å¡Ã‚Â¬Ãƒâ€šÃ‚Â and mediumÃƒÆ’Ã‚Â¢ÃƒÂ¢Ã¢â‚¬Å¡Ã‚Â¬Ãƒâ€šÃ‚Âterm followÃƒÆ’Ã‚Â¢ÃƒÂ¢Ã¢â‚¬Å¡Ã‚Â¬Ãƒâ€šÃ‚Âup but not at longÃƒÆ’Ã‚Â¢ÃƒÂ¢Ã¢â‚¬Å¡Ã‚Â¬Ãƒâ€šÃ‚Âterm followÃƒÆ’Ã‚Â¢ÃƒÂ¢Ã¢â‚¬Å¡Ã‚Â¬Ãƒâ€šÃ‚Âup. No differences between groups were reported for mortality, courses of antibiotics/prednisolone, dyspnoea, and depression and anxiety scores. Subgroup analysis of dominant intervention components and regions of study suggested contextÃƒÆ’Ã‚Â¢ÃƒÂ¢Ã¢â‚¬Å¡Ã‚Â¬Ãƒâ€šÃ‚Â and interventionÃƒÆ’Ã‚Â¢ÃƒÂ¢Ã¢â‚¬Å¡Ã‚Â¬Ãƒâ€šÃ‚Âspecific effects. However, some subgroup analyses were marked by considerable heterogeneity or included few studies. These results should therefore be interpreted with caution. Authors' conclusions This review shows that IDM probably results in improvement in diseaseÃƒÆ’Ã‚Â¢ÃƒÂ¢Ã¢â‚¬Å¡Ã‚Â¬Ãƒâ€šÃ‚Âspecific QoL, exercise capacity, hospital admissions, and hospital days per person. Future research should evaluate which combination of IDM components and which intervention duration are most effective for IDM programmes, and should consider contextual determinants of implementation and treatment effect, including processÃƒÆ’Ã‚Â¢ÃƒÂ¢Ã¢â‚¬Å¡Ã‚Â¬Ãƒâ€šÃ‚Ârelated outcomes, longÃƒÆ’Ã‚Â¢ÃƒÂ¢Ã¢â‚¬Å¡Ã‚Â¬Ãƒâ€šÃ‚Âterm followÃƒÆ’Ã‚Â¢ÃƒÂ¢Ã¢â‚¬Å¡Ã‚Â¬Ãƒâ€šÃ‚Âup, and costÃƒÆ’Ã‚Â¢ÃƒÂ¢Ã¢â‚¬Å¡Ã‚Â¬Ãƒâ€šÃ‚Âeffectiveness analyses. Plain language summary Integrated disease management for people with chronic obstructive pulmonary disease What are the effects of integrated disease management (IDM) programmes on quality of life, ability to exercise, and number of lung attacks compared to usual care in people with chronic obstructive pulmonary disease (COPD)? Background Chronic obstructive pulmonary disease (COPD) is a chronic lung disease and is a major cause of ill health worldwide. People with COPD feel the impact of the disease in their daily life through symptoms such as breathlessness and coughing and acute worsening of symptoms in lung attacks. Different healthcare providers, such as doctors, nurses, and physiotherapists, typically provide different types of care to people with COPD (e.g. prescribe medication, guide selfÃƒÆ’Ã‚Â¢ÃƒÂ¢Ã¢â‚¬Å¡Ã‚Â¬Ãƒâ€šÃ‚Âmanagement, provide education, present exercise training). Previously, people with COPD could visit one or more different healthcare providers, and these providers would work independently. The goal of an integrated disease management (IDM) programme is to include different components of care by which different healthcare providers are coÃƒÆ’Ã‚Â¢ÃƒÂ¢Ã¢â‚¬Å¡Ã‚Â¬Ãƒâ€šÃ‚Âoperating and collaborating to provide more efficient care of better quality. Study characteristics We evaluated 52 studies involving 21,086 people with COPD. These studies were conducted in 19 countries spread all over the world. The average age of participants was 67 years, and 66% of participants were men. Some studies took place in general practices, some in hospitals, and some in both settings. Key results We found that people who participate in an IDM programme probably have better quality of life and their ability to exercise is probably improved compared to those receiving usual care. It is likely that people in an IDM programme have fewer hospital admissions for lung attacks and make fewer visits to an emergency department. When hospitalised, the total number of days people have to spend in hospital is reduced by two days. IDM programmes probably do not help to reduce the number of patients who die. The variety of available programmes makes it difficult to say if one IDM programme is the best. Future studies should look at the most important components and the ideal length of the programme. Certainty of the evidence Overall, the certainty of our evidence was moderate to high but sometimes with large differences between studies. This plain language summary is upÃƒÆ’Ã‚Â¢ÃƒÂ¢Ã¢â‚¬Å¡Ã‚Â¬Ãƒâ€šÃ‚ÂtoÃƒÆ’Ã‚Â¢ÃƒÂ¢Ã¢â‚¬Å¡Ã‚Â¬Ãƒâ€šÃ‚Âdate as of February 2021. | E14: FALSE | F14: Focus on QoL and exercise, not budget reduction. | G14: no_cost_shift_or_harm | H14: 0.9
A15: J2881 | B15: 2021 | C15: Using electronic patient records to assess the effect of a complex antenatal intervention in a cluster randomised controlled trial-data management experience from the DESiGN Trial team | D15: Background: The use of electronic patient records for assessing outcomes in clinical trials is a methodological strategy intended to drive faster and more cost-efficient acquisition of results. The aim of this manuscript was to outline the data collection and management considerations of a maternity and perinatal clinical trial using data from electronic patient records, exemplifying the DESiGN Trial as a case study. Method(s): The DESiGN Trial is a cluster randomised control trial assessing the effect of a complex intervention versus standard care for identifying small for gestational age foetuses. Data on maternal/perinatal characteristics and outcomes including infants admitted to neonatal care, parameters from foetal ultrasound and details of hospital activity for health-economic evaluation were collected at two time points from four types of electronic patient records held in 22 different electronic record systems at the 13 research clusters. Data were pseudonymised on site using a bespoke Microsoft Excel macro and securely transferred to the central data store. Data quality checks were undertaken. Rules for data harmonisation of the raw data were developed and a data dictionary produced, along with rules and assumptions for data linkage of the datasets. The dictionary included descriptions of the rationale and assumptions for data harmonisation and quality checks. Result(s): Data were collected on 182,052 babies from 178,350 pregnancies in 165,397 unique women. Data availability and completeness varied across research sites; each of eight variables which were key to calculation of the primary outcome were completely missing in median 3 (range 1-4) clusters at the time of the first data download. This improved by the second data download following clarification of instructions to the research sites (each of the eight key variables were completely missing in median 1 (range 0-1) cluster at the second time point). Common data management challenges were harmonising a single variable from multiple sources and categorising free-text data, solutions were developed for this trial. Conclusion(s): Conduct of clinical trials which use electronic patient records for the assessment of outcomes can be time and cost-effective but still requires appropriate time and resources to maximise data quality. A difficulty for pregnancy and perinatal research in the UK is the wide variety of different systems used to collect patient data across maternity units. In this manuscript, we describe how we managed this and provide a detailed data dictionary covering the harmonisation of variable names and values that will be helpful for other researchers working with these data. Trial registration: Primary registry and trial identifying number: ISRCTN 67698474. Registered on 02/11/16. Copyright ÃƒÆ’Ã¢â‚¬Å¡Ãƒâ€šÃ‚Â© 2021, The Author(s). | E15: FALSE | F15: Focus on cost-efficiency, not explicit budget reduction. | G15: no_cost_shift_or_harm | H15: 0.9
A16: J2899 | B16: 2021 | C16: Primary prevention of variceal bleeding in people with oesophageal varices due to liver cirrhosis: a network metaÃƒÆ’Ã‚Â¢ÃƒÂ¢Ã¢â‚¬Å¡Ã‚Â¬Ãƒâ€šÃ‚Âanalysis | D16: - Background Approximately 40% to 95% of people with cirrhosis have oesophageal varices. About 15% to 20% of oesophageal varices bleed in about one to three years. There are several different treatments to prevent bleeding, including: betaÃƒÆ’Ã‚Â¢ÃƒÂ¢Ã¢â‚¬Å¡Ã‚Â¬Ãƒâ€šÃ‚Âblockers, endoscopic sclerotherapy, and variceal band ligation. However, there is uncertainty surrounding their individual and relative benefits and harms. Objectives To compare the benefits and harms of different treatments for prevention of first variceal bleeding from oesophageal varices in adults with liver cirrhosis through a network metaÃƒÆ’Ã‚Â¢ÃƒÂ¢Ã¢â‚¬Å¡Ã‚Â¬Ãƒâ€šÃ‚Âanalysis and to generate rankings of the different treatments for prevention of first variceal bleeding from oesophageal varices according to their safety and efficacy. Search methods We searched CENTRAL, MEDLINE, Embase, Science Citation Index Expanded, World Health Organization International Clinical Trials Registry Platform, and trials registers to December 2019 to identify randomised clinical trials in people with cirrhosis and oesophageal varices with no history of bleeding. Selection criteria We included only randomised clinical trials (irrespective of language, blinding, or status) in adults with cirrhosis and oesophageal varices with no history of bleeding. We excluded randomised clinical trials in which participants had previous bleeding from oesophageal varices and those who had previously undergone liver transplantation or previously received prophylactic treatment for oesophageal varices. Data collection and analysis We performed a network metaÃƒÆ’Ã‚Â¢ÃƒÂ¢Ã¢â‚¬Å¡Ã‚Â¬Ãƒâ€šÃ‚Âanalysis with OpenBUGS using Bayesian methods and calculated the differences in treatments using hazard ratios (HR), odds ratios (OR), and rate ratios with 95% credible intervals (CrI) based on an availableÃƒÆ’Ã‚Â¢ÃƒÂ¢Ã¢â‚¬Å¡Ã‚Â¬Ãƒâ€šÃ‚Âcase analysis, according to National Institute for Health and Care Excellence Decision Support Unit guidance. We performed the direct comparisons from randomised clinical trials using the same codes and the same technical details. Main results We included 66 randomised clinical trials (6653 participants) in the review. Sixty trials (6212 participants) provided data for one or more comparisons in the review. The trials that provided the information included people with cirrhosis due to varied aetiologies and those at high risk of bleeding from oesophageal varices. The followÃƒÆ’Ã‚Â¢ÃƒÂ¢Ã¢â‚¬Å¡Ã‚Â¬Ãƒâ€šÃ‚Âup in the trials that reported outcomes ranged from 6 months to 60 months. All but one of the trials were at high risk of bias. The interventions compared included betaÃƒÆ’Ã‚Â¢ÃƒÂ¢Ã¢â‚¬Å¡Ã‚Â¬Ãƒâ€šÃ‚Âblockers, no active intervention, variceal band ligation, sclerotherapy, betaÃƒÆ’Ã‚Â¢ÃƒÂ¢Ã¢â‚¬Å¡Ã‚Â¬Ãƒâ€šÃ‚Âblockers plus variceal band ligation, betaÃƒÆ’Ã‚Â¢ÃƒÂ¢Ã¢â‚¬Å¡Ã‚Â¬Ãƒâ€šÃ‚Âblockers plus nitrates, nitrates, betaÃƒÆ’Ã‚Â¢ÃƒÂ¢Ã¢â‚¬Å¡Ã‚Â¬Ãƒâ€šÃ‚Âblockers plus sclerotherapy, and portocaval shunt. Overall, 21.2% of participants who received nonÃƒÆ’Ã‚Â¢ÃƒÂ¢Ã¢â‚¬Å¡Ã‚Â¬Ãƒâ€šÃ‚Âselective betaÃƒÆ’Ã‚Â¢ÃƒÂ¢Ã¢â‚¬Å¡Ã‚Â¬Ãƒâ€šÃ‚Âblockers ('betaÃƒÆ’Ã‚Â¢ÃƒÂ¢Ã¢â‚¬Å¡Ã‚Â¬Ãƒâ€šÃ‚Âblockers') ÃƒÆ’Ã‚Â¢Ãƒâ€¹Ã¢â‚¬Â ÃƒÂ¢Ã¢â€šÂ¬Ã¢â€žÂ¢ the reference treatment (chosen because this was the most common treatment compared in the trials) ÃƒÆ’Ã‚Â¢Ãƒâ€¹Ã¢â‚¬Â ÃƒÂ¢Ã¢â€šÂ¬Ã¢â€žÂ¢ died during 8ÃƒÆ’Ã‚Â¢ÃƒÂ¢Ã¢â‚¬Å¡Ã‚Â¬Ãƒâ€šÃ‚Âmonth to 60ÃƒÆ’Ã‚Â¢ÃƒÂ¢Ã¢â‚¬Å¡Ã‚Â¬Ãƒâ€šÃ‚Âmonth followÃƒÆ’Ã‚Â¢ÃƒÂ¢Ã¢â‚¬Å¡Ã‚Â¬Ãƒâ€šÃ‚Âup. Based on lowÃƒÆ’Ã‚Â¢ÃƒÂ¢Ã¢â‚¬Å¡Ã‚Â¬Ãƒâ€šÃ‚Âcertainty evidence, betaÃƒÆ’Ã‚Â¢ÃƒÂ¢Ã¢â‚¬Å¡Ã‚Â¬Ãƒâ€šÃ‚Âblockers, variceal band ligation, sclerotherapy, and betaÃƒÆ’Ã‚Â¢ÃƒÂ¢Ã¢â‚¬Å¡Ã‚Â¬Ãƒâ€šÃ‚Âblockers plus nitrates all had lower mortality versus no active intervention (betaÃƒÆ’Ã‚Â¢ÃƒÂ¢Ã¢â‚¬Å¡Ã‚Â¬Ãƒâ€šÃ‚Âblockers: HR 0.49, 95% CrI 0.36 to 0.67; direct comparison HR: 0.59, 95% CrI 0.42 to 0.83; 10 trials, 1200 participants; variceal band ligation: HR 0.51, 95% CrI 0.35 to 0.74; direct comparison HR 0.49, 95% CrI 0.12 to 2.14; 3 trials, 355 participants; sclerotherapy: HR 0.66, 95% CrI 0.51 to 0.85; direct comparison HR 0.61, 95% CrI 0.41 to 0.90; 18 trials, 1666 participants; betaÃƒÆ’Ã‚Â¢ÃƒÂ¢Ã¢â‚¬Å¡Ã‚Â¬Ãƒâ€šÃ‚Âblockers plus nitrates: HR 0.41, 95% CrI 0.20 to 0.85; no direct comparison). No trials reported healthÃƒÆ’Ã‚Â¢ÃƒÂ¢Ã¢â‚¬Å¡Ã‚Â¬Ãƒâ€šÃ‚Ârelated quality of life. Based on lowÃƒÆ’Ã‚Â¢ÃƒÂ¢Ã¢â‚¬Å¡Ã‚Â¬Ãƒâ€šÃ‚Âcertainty evidence, variceal band ligation had a higher number of serious adverse events (number of events) than betaÃƒÆ’Ã‚Â¢ÃƒÂ¢Ã¢â‚¬Å¡Ã‚Â¬Ãƒâ€šÃ‚Âblockers (rate ratio 10.49, 95% CrI 2.83 to 60.64; 1 trial, 168 participants). Based on lowÃƒÆ’Ã‚Â¢ÃƒÂ¢Ã¢â‚¬Å¡Ã‚Â¬Ãƒâ€šÃ‚Âcertainty evidence, betaÃƒÆ’Ã‚Â¢ÃƒÂ¢Ã¢â‚¬Å¡Ã‚Â¬Ãƒâ€šÃ‚Âblockers plus nitrates had a higher number of 'any adverse events (number of participants)' than betaÃƒÆ’Ã‚Â¢ÃƒÂ¢Ã¢â‚¬Å¡Ã‚Â¬Ãƒâ€šÃ‚Âblockers alone (OR 3.4 , 95% CrI 1.11 to 11.28; 1 trial, 57 participants). Based on lowÃƒÆ’Ã‚Â¢ÃƒÂ¢Ã¢â‚¬Å¡Ã‚Â¬Ãƒâ€šÃ‚Âcertainty evidence, adverse events (number of events) were higher in sclerotherapy than in betaÃƒÆ’Ã‚Â¢ÃƒÂ¢Ã¢â‚¬Å¡Ã‚Â¬Ãƒâ€šÃ‚Âblockers (rate ratio 2.49, 95% CrI 1.53 to 4.22; direct comparison rate ratio 2.47, 95% CrI 1.27 to 5.06; 2 trials, 90 participants), and in betaÃƒÆ’Ã‚Â¢ÃƒÂ¢Ã¢â‚¬Å¡Ã‚Â¬Ãƒâ€šÃ‚Âblockers plus variceal band ligation than in betaÃƒÆ’Ã‚Â¢ÃƒÂ¢Ã¢â‚¬Å¡Ã‚Â¬Ãƒâ€šÃ‚Âblockers (direct comparison rate ratio 1.72, 95% CrI 1.08 to 2.76; 1 trial, 140 participants). Based on lowÃƒÆ’Ã‚Â¢ÃƒÂ¢Ã¢â‚¬Å¡Ã‚Â¬Ãƒâ€šÃ‚Âcertainty evidence, any variceal bleed was lower in betaÃƒÆ’Ã‚Â¢ÃƒÂ¢Ã¢â‚¬Å¡Ã‚Â¬Ãƒâ€šÃ‚Âblockers plus variceal band ligation than in betaÃƒÆ’Ã‚Â¢ÃƒÂ¢Ã¢â‚¬Å¡Ã‚Â¬Ãƒâ€šÃ‚Âblockers (direct comparison HR 0.21, 95% CrI 0.04 to 0.71; 1 trial, 173 participants). Based on lowÃƒÆ’Ã‚Â¢ÃƒÂ¢Ã¢â‚¬Å¡Ã‚Â¬Ãƒâ€šÃ‚Âcertainty evidence, any variceal bleed was higher in nitrates than betaÃƒÆ’Ã‚Â¢ÃƒÂ¢Ã¢â‚¬Å¡Ã‚Â¬Ãƒâ€šÃ‚Âblockers (direct comparison HR 6.40, 95% CrI 1.58 to 47.42; 1 trial, 52 participants). The evidence indicates considerable uncertainty about the effect of the interventions in the remaining comparisons. Authors' conclusions Based on lowÃƒÆ’Ã‚Â¢ÃƒÂ¢Ã¢â‚¬Å¡Ã‚Â¬Ãƒâ€šÃ‚Âcertainty evidence, betaÃƒÆ’Ã‚Â¢ÃƒÂ¢Ã¢â‚¬Å¡Ã‚Â¬Ãƒâ€šÃ‚Âblockers, variceal band ligation, sclerotherapy, and betaÃƒÆ’Ã‚Â¢ÃƒÂ¢Ã¢â‚¬Å¡Ã‚Â¬Ãƒâ€šÃ‚Âblockers plus nitrates may decrease mortality compared to no intervention in people with highÃƒÆ’Ã‚Â¢ÃƒÂ¢Ã¢â‚¬Å¡Ã‚Â¬Ãƒâ€šÃ‚Ârisk oesophageal varices in people with cirrhosis and no previous history of bleeding. Based on lowÃƒÆ’Ã‚Â¢ÃƒÂ¢Ã¢â‚¬Å¡Ã‚Â¬Ãƒâ€šÃ‚Âcertainty evidence, variceal band ligation may result in a higher number of serious adverse events than betaÃƒÆ’Ã‚Â¢ÃƒÂ¢Ã¢â‚¬Å¡Ã‚Â¬Ãƒâ€šÃ‚Âblockers. The evidence indicates considerable uncertainty about the effect of betaÃƒÆ’Ã‚Â¢ÃƒÂ¢Ã¢â‚¬Å¡Ã‚Â¬Ãƒâ€šÃ‚Âblockers versus variceal band ligation on variceal bleeding. The evidence also indicates considerable uncertainty about the effect of the interventions in most of the remaining comparisons. Plain language summary Treatment to prevent first bleeding from dilated veins in the oesophagus resulting from advanced scarring of the liver What was the aim of this Cochrane Review? We aimed to find the best available treatment for prevention of first bleeding from oesophageal varices (enlarged veins in the food pipe (oesophagus)) in people with advanced liver scarring (liver cirrhosis, or late stage scarring of the liver with complications). People with cirrhosis and oesophageal varices are at significant risk of bleeding and death. Therefore, treatment is important, but the benefits and harms of different treatments available are currently unclear. The review authors collected and analysed 66 randomised clinical trials (clinical studies where people are randomly put into one of two or more treatment groups) with the aim of finding what the best treatment is. During analysis of data, we used standard Cochrane methods, which allow the comparison of only two treatments at a time. We also used advanced techniques that allow comparison of multiple treatments at the same time (referred to as 'network (or indirect) metaÃƒÆ’Ã‚Â¢ÃƒÂ¢Ã¢â‚¬Å¡Ã‚Â¬Ãƒâ€šÃ‚Âanalysis'). Date of literature search December 2019 Key messages We found that only one of the trials was conducted without flaws, and because of this, there is high to very high uncertainty in the findings. Approximately one in five trial participants with cirrhosis and oesophageal varices who never had bleeding previously and received the standard treatment of betaÃƒÆ’Ã‚Â¢ÃƒÂ¢Ã¢â‚¬Å¡Ã‚Â¬Ãƒâ€šÃ‚Âblockers died within five years of treatment. The funding source for the research was unclear in 50 trials; commercial organisations funded five trials. There were no concerns regarding the source of funding for the remaining 11 trials. What was studied in the review? This review looked at adults of any sex, age, and ethnic origin with advanced liver disease due to various causes and oesophageal varices, but never had bleeding from the oesophageal varices. Participants were given different treatments for prevention of first bleeding from oesophageal varices. The authors excluded studies in people who had previous bleeding from the oesophageal varices and those who had had a liver transplant or already received treatment for oesophageal varices previously. The average age of participants, when reported, ranged from 40 years to 63 years. The treatments included 'nonÃƒÆ’Ã‚Â¢ÃƒÂ¢Ã¢â‚¬Å¡Ã‚Â¬Ãƒâ€šÃ‚Âselective betaÃƒÆ’Ã‚Â¢ÃƒÂ¢Ã¢â‚¬Å¡Ã‚Â¬Ãƒâ€šÃ‚Âblockers' or simply 'betaÃƒÆ’Ã‚Â¢ÃƒÂ¢Ã¢â‚¬Å¡Ã‚Â¬Ãƒâ€šÃ‚Âblockers' (drugs that slow the heart and decrease the force of heart pumping resulting in decrease pressure in the blood vessels; they also increase the pressure in the gut blood vessels decreasing the amount of blood reaching the oesophageal veins), endoscopic sclerotherapy (injecting clotting agents into the enlarged veins by looking through a tube inserted through the mouth), variceal band ligation (inserting elastic bands around the widened veins by using a tube inserted through the mouth), and nitrates (medicines that decrease the pressure in the gut blood vessels by widening them). The review authors wanted to gather and analyse data on death (percentage dead at maximal followÃƒÆ’Ã‚Â¢ÃƒÂ¢Ã¢â‚¬Å¡Ã‚Â¬Ãƒâ€šÃ‚Âup), quality of life, serious and nonÃƒÆ’Ã‚Â¢ÃƒÂ¢Ã¢â‚¬Å¡Ã‚Â¬Ãƒâ€šÃ‚Âserious side effects, percentage of people who developed bleeding, and development of other complications of advanced liver disease.ÃƒÆ’Ã‚Â¢ÃƒÂ¢Ã¢â‚¬Å¡Ã‚Â¬Ãƒâ€šÃ‚Â¨ÃƒÆ’Ã‚Â¢ÃƒÂ¢Ã¢â‚¬Å¡Ã‚Â¬Ãƒâ€šÃ‚Â¨ What were the main results of the review? The 66 studies included a relatively small number of participants (6653 people). Sixty studies with 6212 participants provided data for analyses. The followÃƒÆ’Ã‚Â¢ÃƒÂ¢Ã¢â‚¬Å¡Ã‚Â¬Ãƒâ€šÃ‚Âup of the trial ranged from six months to five years in studies that reported the outcomes that we were interested in. The review found the following:ÃƒÆ’Ã‚Â¢ÃƒÂ¢Ã¢â‚¬Å¡Ã‚Â¬Ãƒâ€šÃ‚Â¨ÃƒÆ’Ã‚Â¢ÃƒÂ¢Ã¢â‚¬Å¡Ã‚Â¬ÃƒÂ¢Ã¢â€šÂ¬Ã…â€œ Approximately one in five people with cirrhosis and oesophageal varices (without previous bleeding) who receive the betaÃƒÆ’Ã‚Â¢ÃƒÂ¢Ã¢â‚¬Å¡Ã‚Â¬Ãƒâ€šÃ‚Âblockers died within five years.ÃƒÆ’Ã‚Â¢ÃƒÂ¢Ã¢â‚¬Å¡Ã‚Â¬Ãƒâ€šÃ‚Â¨ÃƒÆ’Ã‚Â¢ÃƒÂ¢Ã¢â‚¬Å¡Ã‚Â¬ÃƒÂ¢Ã¢â€šÂ¬Ã…â€œ BetaÃƒÆ’Ã‚Â¢ÃƒÂ¢Ã¢â‚¬Å¡Ã‚Â¬Ãƒâ€šÃ‚Âblockers, variceal band ligation, sclerotherapy, and betaÃƒÆ’Ã‚Â¢ÃƒÂ¢Ã¢â‚¬Å¡Ã‚Â¬Ãƒâ€šÃ‚Âblockers plus nitrates all may result in fewer deaths than no treatment.ÃƒÆ’Ã‚Â¢ÃƒÂ¢Ã¢â‚¬Å¡Ã‚Â¬Ãƒâ€šÃ‚Â¨ÃƒÆ’Ã‚Â¢ÃƒÂ¢Ã¢â‚¬Å¡Ã‚Â¬ÃƒÂ¢Ã¢â€šÂ¬Ã…â€œ Variceal band ligation may result in a higher number of serious side effects than betaÃƒÆ’Ã‚Â¢ÃƒÂ¢Ã¢â‚¬Å¡Ã‚Â¬Ãƒâ€šÃ‚Âblockers.ÃƒÆ’Ã‚Â¢ÃƒÂ¢Ã¢â‚¬Å¡Ã‚Â¬Ãƒâ€šÃ‚Â¨ÃƒÆ’Ã‚Â¢ÃƒÂ¢Ã¢â‚¬Å¡Ã‚Â¬ÃƒÂ¢Ã¢â€šÂ¬Ã…â€œ Sclerotherapy, betaÃƒÆ’Ã‚Â¢ÃƒÂ¢Ã¢â‚¬Å¡Ã‚Â¬Ãƒâ€šÃ‚Âblockers plus nitrates, and betaÃƒÆ’Ã‚Â¢ÃƒÂ¢Ã¢â‚¬Å¡Ã‚Â¬Ãƒâ€šÃ‚Âblockers plus variceal band ligation may result in more side effects (when serious and nonÃƒÆ’Ã‚Â¢ÃƒÂ¢Ã¢â‚¬Å¡Ã‚Â¬Ãƒâ€šÃ‚Âserious adverse events were put together) than betaÃƒÆ’Ã‚Â¢ÃƒÂ¢Ã¢â‚¬Å¡Ã‚Â¬Ãƒâ€šÃ‚Âblockers.ÃƒÆ’Ã‚Â¢ÃƒÂ¢Ã¢â‚¬Å¡Ã‚Â¬Ãƒâ€šÃ‚Â¨ÃƒÆ’Ã‚Â¢ÃƒÂ¢Ã¢â‚¬Å¡Ã‚Â¬ÃƒÂ¢Ã¢â€šÂ¬Ã…â€œ BetaÃƒÆ’Ã‚Â¢ÃƒÂ¢Ã¢â‚¬Å¡Ã‚Â¬Ãƒâ€šÃ‚Âblockers plus variceal band ligation may result in fewer people who develop bleeding than betaÃƒÆ’Ã‚Â¢ÃƒÂ¢Ã¢â‚¬Å¡Ã‚Â¬Ãƒâ€šÃ‚Âblockers alone based on a single small trial.ÃƒÆ’Ã‚Â¢ÃƒÂ¢Ã¢â‚¬Å¡Ã‚Â¬Ãƒâ€šÃ‚Â¨ÃƒÆ’Ã‚Â¢ÃƒÂ¢Ã¢â‚¬Å¡Ã‚Â¬ÃƒÂ¢Ã¢â€šÂ¬Ã…â€œ Nitrates alone may result in more people who develop bleeding than betaÃƒÆ’Ã‚Â¢ÃƒÂ¢Ã¢â‚¬Å¡Ã‚Â¬Ãƒâ€šÃ‚Âblockers alone.ÃƒÆ’Ã‚Â¢ÃƒÂ¢Ã¢â‚¬Å¡Ã‚Â¬Ãƒâ€šÃ‚Â¨ÃƒÆ’Ã‚Â¢ÃƒÂ¢Ã¢â‚¬Å¡Ã‚Â¬ÃƒÂ¢Ã¢â€šÂ¬Ã…â€œ The evidence indicates considerable uncertainty about the effect of the interventions in the remaining comparisons.ÃƒÆ’Ã‚Â¢ÃƒÂ¢Ã¢â‚¬Å¡Ã‚Â¬Ãƒâ€šÃ‚Â¨ÃƒÆ’Ã‚Â¢ÃƒÂ¢Ã¢â‚¬Å¡Ã‚Â¬ÃƒÂ¢Ã¢â€šÂ¬Ã…â€œ None of the trials reported healthÃƒÆ’Ã‚Â¢ÃƒÂ¢Ã¢â‚¬Å¡Ã‚Â¬Ãƒâ€šÃ‚Ârelated quality of life. What are our conclusions? BetaÃƒÆ’Ã‚Â¢ÃƒÂ¢Ã¢â‚¬Å¡Ã‚Â¬Ãƒâ€šÃ‚Âblockers, variceal band ligation, sclerotherapy, and betaÃƒÆ’Ã‚Â¢ÃƒÂ¢Ã¢â‚¬Å¡Ã‚Â¬Ãƒâ€šÃ‚Âblockers plus nitrates may decrease the death rate compared to no treatment in people with highÃƒÆ’Ã‚Â¢ÃƒÂ¢Ã¢â‚¬Å¡Ã‚Â¬Ãƒâ€šÃ‚Ârisk oesophageal varices in people with cirrhosis and no history of bleeding. Variceal band ligation may result in a higher number of serious side effects than betaÃƒÆ’Ã‚Â¢ÃƒÂ¢Ã¢â‚¬Å¡Ã‚Â¬Ãƒâ€šÃ‚Âblockers. The evidence indicates considerable uncertainty about the effect of betaÃƒÆ’Ã‚Â¢ÃƒÂ¢Ã¢â‚¬Å¡Ã‚Â¬Ãƒâ€šÃ‚Âblockers versus variceal band ligation on variceal bleeding. The evidence also indicates considerable uncertainty about the effect of the interventions in most of the remaining comparisons. Future well designed trials are needed to find out the best treatment to prevent first bleeding from people with cirrhosis and oesophageal varices. | E16: FALSE | F16: Focus on treatment efficacy, not budget impact. | H16: 0.9
A17: J6212 | B17: 2025 | C17: Cost-effectiveness of BOOST online intervention for supported self-management of pain, fatigue and bowel incontinence in Inflammatory Bowel Disease | D17: Background: People with IBD often experience symptoms of abdominal pain, fatigue and bowel incontinence that affect substantially their daily lives1 . IBD-BOOST is the first randomised controlled trial (RCT) assessing the effectiveness of an online self-management intervention, BOOST, in managing these symptoms in IBD2 . We report the cost-effectiveness of BOOST intervention compared to care as usual for people with IBD. Method(s): A cost-utility analysis was conducted alongside the pragmatic IBD-BOOST RCT of 780 patients requesting help for pain, fatigue or incontinence symptoms (mean age 49 years, 67% women, 55% with Crohn's disease)3 . The BOOST intervention costs and costs from patient-reported health service use, out-of-pocket expenses and time off work were calculated for each participant over the 12 months of follow-up. Qualityadjusted life-years (QALYs) over the 12 months were evaluated using the EQ-5D-5L questionnaires administered to participants at baseline, 6- and 12-months. Missing data (13% at 6 months and 38% at 12 months across the trial arms) was imputed using multiple imputation. Differences in total costs and QALYs between study arms were estimated using mixed effects models adjusting for pre-specified baseline factors. Incremental cost effectiveness ratios (ICERs) and net monetary benefit from UK healthcare and societal perspectives are reported. Result(s): At recruitment, study participants reported quality of life (EQ-5D utility) of 0.73 (SD 0.22) and overall IBD-related costs of 2321 (SD 3170) over the previous 3 months with cost of biologics accounting for 47% of these costs, followed by hospital outpatient services (22%) and work productivity loss costs (14%) (Figure 1). After missing data imputation and controlling for covariates, the BOOST intervention (151 per participant) was estimated to have led to health care cost savings of 746 (SE 356), other costs savings of 89 (SE 236) and incremental QALYs of 0.017 (SE 0.007) over the one-year follow-up per participant resulting in cost savings per QALY gained of 34,599 from the health services perspective and 39,745 from the societal perspective. The probability that the BOOST intervention was cost effective when compared with usual care was above 98% for willingness-to-pay thresholds of 20,000 to 30,000 from both health services and societal perspectives (Figure 2). Conclusion(s): Our findings indicate that the BOOST intervention for supported self-management of symptoms of pain, fatigue and bowel incontinence in people with IBD is cost-effective. (Figure Presented). | E17: FALSE | F17: Cost-effectiveness shown but no explicit budget reduction or cash-releasing phrase. | G17: has_baseline_and_counterfactual; no_cost_shift_or_harm | H17: 0.9
A18: J6213 | B18: 2025 | C18: Can home-exercise programmes delivered via a handout format result in sufficient adherence among patients with musculoskeletal conditions/injuries? A systematic review | D18: Purpose: Musculoskeletal (MSK) conditions and injuries are a leading cause of disability globally, with the prevalence continuing to rise due to an increasing ageing population. This consequently increases the demands placed on health services to manage widespread physical disability to support those affected. In the UK, the NHS spends approximately 5bn a year treating MSK conditions, accounting for one of the largest areas of NHS expenditure and the biggest areas of workload. Home exercise programmes (HEPs) are a key component of evidence-based management of MSK conditions. However, effectiveness of treatment relies on patient adherence to these exercise programmes with the wider literature suggesting non-adherence rates may be as high as 70%. Adherence to physiotherapy interventions proves to be a complex issue and the reasons for poor adherence are shown to be multi-faceted. An avenue of exploration is the method of HEP delivery, which traditionally has been by verbal instruction often with a paper handout, although the use of digitised methods (e.g. smartphone Apps) are becoming more popular. Therefore, the purpose of this review was to understand if sufficient HEP adherence can be achieved when delivered via a printed format compared to alternate methods or physiotherapy interventions, specifically among adults treated for a MSK condition/injury. Method(s): This systematic review conducted according to the Preferred Reporting Items for Systematic Reviews and Meta-Analyses (PRISMA) guidelines. Six databases were searched from inception to April 2024: CINAHL, MEDLINE, Academic Search Complete, SPORTDiscus, PsycINFO and PubMed. Randomised clinical trials comparing HEPs delivered via paper handout versus alternate delivery methods or physiotherapy interventions, and the effect on adherence rates, were included. Methodological quality and certainty of evidence were assessed by one reviewer using the Cochrane RoB2 tool and modified GRADE approach, respectively. Result(s): Fifteen studies were included for review, categorised based on the type of intervention compared to paper handout, e.g., smart-device Apps/other digitised methods, supervised exercise, SMS/phone reminders. The findings suggest that while the use of paper handouts is superior to verbal instruction alone, Apps with more extensive functionalities, such as, remote monitoring, self-recording abilities and reminder notifications may promote even greater HEP adherence rates. However, studies were either of 'some concern' or 'high' risk of bias, and the overall quality (certainty) of evidence was determined to be 'low', meaning the ability to draw firm conclusions and recommendations is limited. Conclusion(s): Apps may potentially facilitate better adherence rates, but further high-quality research is required to firmly recommend a HEP delivery method. Clinicians should tailor their approaches specific to patients' needs and profiles, gaining an understanding of their patients' previous experiences, expectations and self-efficacy. Impact: The project highlights the need for more high-quality research in this important area of exercise therapy adherence. Methods of improving the currently poor adherence rates need to be established. Cost-effectiveness of such methods should also be researched prior to any widespread implementation. Facilitating better patient adherence with home-exercise treatment can lead to improved patient outcomes and self-management, which in turn can reduce healthcare provider burden and expenditure. Funding acknowledgements: No funding required. Work not funded. Keywords: Home-exercise, Adherence, Musculoskeletal conditions Copyright ÃƒÆ’Ã¢â‚¬Å¡Ãƒâ€šÃ‚Â© 2025 | E18: FALSE | F18: Focus on adherence, not explicit budget reduction or cash-releasing benefits. | G18: no_cost_shift_or_harm | H18: 0.9

Sheet ID_Lookup
A1: id
A2: J505
A3: J535
A4: J545
A5: J547
A6: J552
A7: J571
A8: J574
A9: J575
A10: J583
A11: J587
A12: J2833
... A18: J6213

Sheet Stage_7_FF_200
A1: Unique ID | B1: Year | C1: Title | D1: Abstract | E1: FF screen | F1: FF reason | G1: FF_include_stage6 | H1: Id_flag
A2: J500 | B2: 2019 | C2: The lifetime costs of pediatric abusive head trauma and a cost-effectiveness analysis of the Period of Purple crying program in British Columbia, Canada | D2: Background: Abusive head trauma (AHT) is a severe form of child abuse causing devastating outcomes for children and families, but its economic costs in Canada has yet to be determined. The Period of PURPLE crying program (PURPLE) is an AHT prevention program implemented in British Columbia for which success in reducing AHT events was recently reported. Objective(s): This study estimated the lifetime costs to society of incidental AHT events and compared the benefits and associated costs of AHT before and after the implementation of the PURPLE program. Participants and Setting: Children aged 0-24 months old with a definite diagnosis of AHT between 2002 and 2014 in British Columbia were included in this study. Method(s): An incidence-based cost-of-illness analysis, using the human capital approach was used to quantify the lifetime costs of AHT events according to their severity (least severe, severe and fatal). A cost-effectiveness analysis of the PURPLE program was conducted from both a societal and a health services' perspectives using decision tree models. Result(s): There were sixty-four AHT events between 2002-2014, resulting in a total cost of $354,359,080 to society. The costs associated with fatal, severe and least severe AHT averaged $7,147,548, $6,057,761 and $1,675,099, respectively. The investment of $5 per newborn through the PURPLE program resulted in a $273.52 and $14.49 per child cost avoidance by society and by the healthcare system. Conclusion(s): This study provides evidence to policymakers and health practitioners that investing upstream in well-developed AHT prevention programs, such as PURPLE, not only promote child safety and health, but also translates into avoided costs to society. Copyright © 2019 Elsevier Ltd | E2: Include | F2: avoided costs | G2: =IF(E2="Include", TRUE, FALSE) -> TRUE | H2: =VLOOKUP(A2,ID_Lookup!A:A,1,FALSE) -> #N/A
A3: J501 | B3: 2019 | C3: Impact of Weekend Treatment on Short-term and Long-term Survival Following Urgent Repair of Ruptured Aortic Aneurysms in Germany | D3: Introduction - There is some evidence that weekend admission to hospital is associated with worse outcomes compared to weekday admission. However only a few studies focused on weekend versus weekday surgery. This study aims to determine if there is a weekend effect in the treatment of ruptured aortic aneurysms in Germany. Methods - Health insurance claims of Germany's third largest insurance provider, DAK-Gesundheit, was used to investigate short-term and long-term mortality after weekend versus weekday treatment for ruptured aortic aneurysm (rAA). Patients undergoing endovascular (ER) or open-surgical (OR) repair between January 2008 and December 2016 were included in the study. A one-to-one propensity score matching was used to address selection bias. Results - There were 1,477 patients in the cohort of which 517 (35.0%) underwent ER and 960 (65.0%) OR. Overall, 987 (66.8%) patients were operated on weekdays (Monday to Thursday) and 490 (33.2%) patients were operated on a weekend (Friday to Sunday). In multivariable models, patients operated on weekend were at higher risk of in-hospital death within both ER (Odds Ratio 1.62, p=0.038) and OR (Odds Ratio 1.68, p=0.001) groups. Furthermore, OR conducted on weekends was associated with lower long-term survival (Hazard Ratio 1.23, p=0.014). Finally, OR of thoracic or abdominal aorta was associated with significantly lower in-hospital mortality and higher long-term survival when compared to thoracic-abdominal aortic repair. Conclusion - Weekend repairs of ruptured aortic aneurysms are associated with worse in-hospital and long-term survival when compared to weekday surgery. Negative effect of weekend surgery was strongest for thoracic-abdominal aneurysms. References 1. Wise J. The weekend effect-how strong is the evidence? BMJ 2016;353:i2781. 2. Metcalfe D, Perry DC, Bouamra O, Salim A, Lecky FE, Woodford M, et al. Is there a 'weekend effect' in major trauma? Emergency medicine journal. Emerg Med J 2016;33:836-842. 3. Groves EM, Khoshchehreh M, Le C, Malik S. Effects of weekend admission on the outcomes and management of ruptured aortic aneurysms. J Vasc Surg 2014;60:318-24. 4. Glance LG, Osler T, Li Y, Lustik SJ, Eaton MP, Dutton RP, et al. Outcomes are Worse in US Patients Undergoing Surgery on Weekends Compared With Weekdays. Med Care 2016;54:608-15. 5. Gallerani M, Volpato S, Boari B, Pala M, De Giorgi A, Fabbian F, et al. Outcomes of weekend versus weekday admission for acute aortic dissection or rupture: a retrospective study on the Italian National Hospital Database. Int J Cardiol 2013;168:3117-9. 6. Kumar N, Venkatraman A, Pandey A, Khera R, Garg N. Weekend hospitalizations for acute aortic dissection have a higher risk of in-hospital mortality compared to weekday hospitalizations. Int J Cardiol 2016;214:448-50. 7. Kostis WJ, Demissie K, Marcella SW, Shao YH, Wilson AC, Moreyra AE, et al. Weekend versus weekday admission and mortality from myocardial infarction. N Engl J Med 2007;356:1099-109. 8. Orandi BJ, Selvarajah S, Orion KC, Lum YW, Perler BA, Abularrage CJ. Outcomes of nonelective weekend admissions for lower extremity ischemia. J Vasc Surg 2014;60:1572-9 e1. 9. Aujesky D, Jimenez D, Mor MK, Geng M, Fine MJ, Ibrahim SA. Weekend versus weekday admission and mortality after acute pulmonary embolism. Circulation 2009;119:962-8. 10. Nanchal R, Kumar G, Taneja A, Patel J, Deshmukh A, Tarima S, et al. Pulmonary embolism: the weekend effect. Chest 2012;142:690-6. 11. Bell CM, Redelmeier DA. Mortality among Patients Admitted to Hospitals on Weekends as Compared with Weekdays. N Engl J Med 2001;345:663-668. 12. Mohammed MA, Sidhu KS, Rudge G, Stevens AJ. Weekend admission to hospital has a higher risk of death in the elective setting than in the emergency setting: a retrospective database study of national health service hospitals in England. BMC Health Serv Res 2012;12:87. 13. Zhou Y, Li W, Herath C, Xia J, Hu B, Song F, et al. Off-Hour Admission and Mortality Risk for 28 Specific Diseases: A Systematic Review and Meta-Analysis of 251 Cohorts. J Am Heart Assoc 2 16;5:e003102. 14. Ozdemir BA, Sinha S, Karthikesalingam A, Poloniecki JD, Pearse RM, Grocott MP, Thompson MM, Holt PJ. Mortality of emergency general surgical patients and associations with hospital structures and processes. Br J Anaesth 2016;116:54-62. 15. Behrendt CA, Sedrakyan A, Riess HC, Heidemann F, Kolbel T, Petersen J, et al. Short-term and long-term results of endovascular and open repair of abdominal aortic aneurysms in Germany. J Vasc Surg 2017;66:1704-1711.e3. 16. Muller I, Freitag MH, Poggensee G, Scharnetzky E, Straube E, Schoerner C, et al. Evaluating Frequency, Diagnostic Quality, and Cost of Lyme Borreliosis Testing in Germany: A Retrospective Model Analysis. Clin Dev Immunol 2012;2012:1-13. 17. Augustin M, Anastasiadou Z, Schaarschmidt ML, Krensel M, Schafer I, Reusch M. Versorgung des Hautkrebses in Deutschland. Hautarzt 2016;67:544-548. 18. Fischer F, Hoffmann K, Monter N, Walle M, Beneke R, Negenborn S, et al. Kostenevaluation eines Modells der Integrierten Versorgung fur schwer psychisch Kranke. Gesundheitswesen 2013;76:86-95. 19. Debus ES, Nullen H, Torsello G, Lang W, Flessenkamper I, Hupp T, et al. Zur Behandlung des abdominellen Aortenaneurysmas in Deutschland. Gefasschirurgie 2014;19:412-421. 20. Grundmann RT. Versorgung des abdominellen Aortenaneurysmas (AAA) 2014. Gefasschirurgie 2015;20:376-384. 21. Debus ES, Torsello G, Behrendt CA, Petersen J, Grundmann RT. [Perioperative mortality following repair for abdominal aortic aneurysm in Germany : Comparison of administrative data of the DAK health insurance and clinical registry data of the German Vascular Society]. Chirurg 2015;86:1041-50. 22. Elixhauser A, Steiner C, Harris DR, Coffey RM. Comorbidity measures for use with administrative data. Med Care 1998;36:8-27. 23. Quan H, Sundararajan V, Halfon P, Fong A, Burnand B, Luthi JC, et al. Coding algorithms for defining comorbidities in ICD-9-CM and ICD-10 administrative data. Med Care 2005;43:1130-9. 24. van Walraven C, Austin PC, Jennings A, Quan H, Forster AJ. A modification of the Elixhauser comorbidity measures into a point system for hospital death using administrative data. Med Care 2009;47:626-33. 25. Rosenbaum PR, Rubin DB. The central role of the propensity score in observational studies for causal effects. Biometrika 1983;70:41-55. 26. Gallerani M, Imberti D, Bossone E, Eagle KA, Manfredini R. Higher mortality in patients hospitalized for acute aortic rupture or dissection during weekends. J Vasc Surg 2012;55:1247-54. 27. Cram P, Hillis SL, Barnett M, Rosenthal GE. Effects of weekend admission and hospital teaching status on in-hospital mortality. Am J Med 2004;117:151-7. 28. Investigators IT. Comparative clinical effectiveness and cost effectiveness of endovascular strategy v open repair for ruptured abdominal aortic aneurysm: three year results of the IMPROVE randomised trial. BMJ 2017;359:j4859. 29. Patel R, Sweeting MJ, Powell JT, Greenhalgh RM. Endovascular versus open repair of abdominal aortic aneurysm in 15-years' follow-up of the UK endovascular aneurysm repair trial 1 (EVAR trial 1): a randomised controlled trial. Lancet 2016;388:2366-2374. 30. Thorpe KE. House Staff Supervision and Working Hours. JAMA 1990;263:3177. 31. McKee M, Black N. Does the current use of junior doctors in the United Kingdom affect the quality of medical care? Soc Sci Med 1992;34:549-58. 32. Tarnow-Mordi WO, Hau C, Warden A, Shearer AJ. Hospital mortality in relation to staff workload: a 4-year study in an adult intensive-care unit. Lancet 2000;356:185-9. 33. Beck AW, Sedrakyan A, Mao J, Venermo M, Faizer R, Debus S, et al. Variations in Abdominal Aortic Aneurysm Care: A Report From the International Consortium of Vascular Registries. Circulation 2016;134:1948-1958. 34. Budtz-Lilly J, Bjorck M, Venermo M, Debus S, Behrendt C-A, Altreuther M, et al. The Impact of Centralisation and Endovascular Aneurysm Repair on Treatment of Ruptured Abdominal Aortic Aneurysms Based on International Registries. Eur J Vasc Endovasc Surg. Article in Press. Doi: 10.1016/j.ejvs.2018.01.014. 35. Behrendt CA, Heidemann F, R ess HC, Stoberock K, Debus SE. Registry and health insurance claims data in vascular research and quality improvement. Vasa 2017;46:11-15. Copyright © 2019 | E3: Exclude | F3: Not cash releasing | G3: =IF(E3="Include", TRUE, FALSE) -> FALSE | H3: =VLOOKUP(A3,ID_Lookup!A:A,1,FALSE) -> #N/A
A4: J502 | B4: 2019 | C4: Pdb16 Assessment of Cost-Effectiveness of a 0.2 Mcg/Day Fluocinolone Acetonide (Fac) Implant in Patients with Chronic Diabetic Macular Oedema (Dmo) in an Eye with Cataract | D4: Objectives: The fluocinolone acetonide 0.2 mug/day implant (FAc) is effective in improving visual acuity in patients with chronic diabetic macular oedema (cDMO) but is associated with worsening of cataract. A model previously suggested that FAc is cost-effective in patients with cDMO, who have undergone cataract surgery or not. The aim of this study was to update this model and assess the cost-effectiveness of FAc in the subgroup of patients with symptomatic cataract. Method(s): The existing Markov model was designed to assess costs and QALYs over lifetime in patients treated with FAc implant, compared to usual care (UC), consisting of laser photocoagulation and anti-VEGFs from the UK NHS perspective. Unit costs and health state utility values (HSUVs) were updated. The FAc price was NHS list price. HSUVs were obtained from the FAME trial using the VFQ-UI utility index. Best-Corrected Visual Acuity (BCVA) with UC was supposed to be stable. Additional scenarios were considered, with BCVA decreasing over time in UC arm, according to real-world data, and with possibility of administering FAc after cataract surgery in the UC arm. Result(s): New HSUVs ranged from 0.48 for blind patients to 0.91 for patients with perfect vision in both eyes. The FAc strategy was more expensive compared to usual care, by 3,445 per patients over lifetime, and produced more QALYs (+0.247). The incremental cost-effectiveness ratio (ICER) was estimated at 13,932 per QALY gained. The ICER was sensitive to the baseline visual acuity, patients' age and the probability of cataract surgery. The probability of FAc being cost-effective was 66.1% at a threshold of 20,000 per QALY gained. Scenario analyses showed that the efficacy of UC had a strong influence on results, and ICER decreased to 1,686 per QALY gained when BCVA decreased under UC Conclusion(s): The FAc implant is a cost-effective treatment for cDMO in patients with symptomatic cataract. Copyright © 2019 | E4: Exclude | F4: Not cash releasing | G4: =IF(E4="Include", TRUE, FALSE) -> FALSE | H4: =VLOOKUP(A4,ID_Lookup!A:A,1,FALSE) -> #N/A
A5: J503 | B5: 2019 | C5: Fluorides for preventing early tooth decay (demineralised lesions) during fixed brace treatment | D5: - Background Early dental decay or demineralised lesions (DLs, also known as white spot lesions) can appear on teeth during fixed orthodontic (brace) treatment. Fluoride reduces decay in susceptible individuals, including orthodontic patients. This review compared various forms of topical fluoride to prevent the development of DLs during orthodontic treatment. This is the second update of the Cochrane Review first published in 2004 and previously updated in 2013. Objectives The primary objective was to evaluate whether topical fluoride reduces the proportion of orthodontic patients with new DLs after fixed appliances. The secondary objectives were to examine the effectiveness of different modes of topical fluoride delivery in reducing the proportions of orthodontic patients with new DLs, as well as the severity of lesions, in terms of number, size and colour. Participant‐assessed outcomes, such as perception of DLs, and oral health‐related quality of life data were to be included, as would reports of adverse effects. Search methods Cochrane Oral Health's Information Specialist searched the following databases: Cochrane Oral Health's Trials Register (to 1 February 2019), the Cochrane Central Register of Controlled Trials (CENTRAL; 2019, Issue 1) in the Cochrane Library (searched 1 February 2019), MEDLINE Ovid (1946 to 1 February 2019), and Embase Ovid (1980 to 1 February 2019). The US National Institutes of Health Ongoing Trials Register (ClinicalTrials.gov) and the World Health Organization International Clinical Trials Registry Platform were searched for ongoing trials. No restrictions were placed on the language or date of publication when searching the electronic databases. Selection criteria Parallel‐group, randomised controlled trials comparing the use of a fluoride‐containing product versus a placebo, no treatment or a different type of fluoride treatment, in which the outcome of enamel demineralisation was assessed at the start and at the end of orthodontic treatment. Data collection and analysis At least two review authors independently, in duplicate, conducted risk of bias assessments and extracted data. Authors of trials were contacted to obtain missing data or to ask for clarification of aspects of trial methodology. Cochrane's statistical guidelines were followed. Main results This update includes 10 studies and contains data from nine studies, comparing eight interventions, involving 1798 randomised participants (1580 analysed). One report contained insufficient information and the authors have been contacted. We assessed two studies as at low risk of bias, six at unclear risk of bias, and two at high risk of bias. Two placebo (non‐fluoride) controlled studies, at low risk of bias, investigated the professional application of varnish (7700 or 10,000 parts per million (ppm) fluoride (F)), every six weeks and found insufficient evidence of a difference regarding its effectiveness in preventing new DLs (risk ratio (RR) 0.52, 95% confidence interval (CI) 0.14 to 1.93; 405 participants; low‐certainty evidence). One placebo (non‐fluoride) controlled study, at unclear risk of bias, provides a low level of certainty that fluoride foam (12,300 ppm F), professionally applied every two months, may reduce the incidence of new DLs (12% versus 49%) after fixed orthodontic treatment (RR 0.26, 95% CI 0.11 to 0.57; 95 participants). One study, at unclear risk of bias, also provides a low level of certainty that use of a high‐concentration fluoride toothpaste (5000 ppm F) by patients may reduce the incidence of new DLs (18% versus 27%) compared with a conventional fluoride toothpaste (1450 ppm F) (RR 0.68, 95% CI 0.46 to 1.00; 380 participants). There was no evidence for a difference in the proportions of orthodontic patients with new DLs on the teeth after treatment with fixed orthodontic appliances for the following comparisons: ‐ an amine fluoride and stannous fluoride toothpaste/mouthrinse combination versus a sodium fluoride toothpaste/mouthrinse, ‐ an amine fluoride gel versus a non‐fluoride placebo applied by participants at home once a week and by professional application every three months, ‐ resin‐modified glass ionomer cement versus light‐cured composite resin for bonding orthodontic brackets, ‐ a 250 ppm F mouthrinse versus 0 ppm F placebo mouthrinse, ‐ the use of an intraoral fluoride‐releasing glass bead device attached to the brace versus a daily fluoride mouthrinse. The last two comparisons involved studies that were assessed at high risk of bias, because a substantial number of participants were lost to follow‐up. Unfortunately, although the internal validity and hence the quality of the studies has improved since the first version of the review, they have compared different interventions; therefore, the findings are only considered to provide low level of certainty, because none has been replicated by follow‐up studies, in different settings, to confirm external validity. A patient‐reported outcome, such as concern about the aesthetics of any DLs, was still not included as an outcome in any study. Reports of adverse effects from topical fluoride applications were rare and unlikely to be significant. One study involving fluoride‐containing glass beads reported numerous breakages. Authors' conclusions This review found a low level of certainty that 12,300 ppm F foam applied by a professional every 6 to 8 weeks throughout fixed orthodontic treatment, might be effective in reducing the proportion of orthodontic patients with new DLs. In addition, there is a low level of certainty that the patient use of a high fluoride toothpaste (5000 ppm F) throughout orthodontic treatment, might be more effective than a conventional fluoride toothpaste. These two comparisons were based on single studies. There was insufficient evidence of a difference regarding the professional application of fluoride varnish (7700 or 10,000 ppm F). Further adequately powered, randomised controlled trials are required to increase the certainty of these findings and to determine the best means of preventing DLs in patients undergoing fixed orthodontic treatment. The most accurate means of assessing adherence with the use of fluoride products by patients and any possible adverse effects also need to be considered. Future studies should follow up participants beyond the end of orthodontic treatment to determine the effect of DLs on patient satisfaction with treatment. Plain language summary Fluorides for preventing early tooth decay (demineralised lesions) during fixed brace treatment Review question Ugly white or brown marks sometimes appear on the teeth during treatment with braces to straighten teeth. These are due to early tooth decay and usually occur with fixed, glued‐on 'train track', braces, which make it more difficult to clean the teeth. We know that fluoride in toothpaste helps to prevent tooth decay and think that if extra fluoride is given to people wearing fixed braces, it will protect them from getting these marks. The aim of this Cochrane Oral Health's review was to look at how well fluorides help to prevent early tooth decay during fixed brace treatment and to find out the best way to get fluoride to the teeth. Background Wearing a fixed brace makes it harder for people to keep their teeth clean and may also cause pain. Pain can make it more difficult for people to brush their teeth. This can lead to a build‐up of dental plaque around the brackets that attach the fixed brace to the teeth, and if the plaque stays on the tooth for long enough, it will cause early tooth decay, which looks like white or brown marks (demineralised lesions, also known as white spot lesions). People often wear braces for 18 months or longer and if the decay is left to progress, it can cause holes, which are sometimes bad enough to need fillings to be done in the teeth. Fluoride helps the tooth to heal, reducing tooth decay in people who are at risk of developing it. People receiving fixed brace treatment may be given different forms of fluoride treatment. It is important to think about how the fluoride gets to the teeth. Does the fluoride need to be placed by a dentist or dental nurse, or can people having treatment with braces apply the fluoride to their own teeth? Study characteristics This review is up‐to‐date as of 1 February 2019. The review includes 10 studies but we could only use the information from nine studies involving 1798 randomised people. We have asked for more information about one study. The review looks at eight different ways of applying fluoride to the teeth. People taking part in the studies were all having treatment with fixed braces. The number of people with new decay on the teeth at end of fixed brace treatment, as well as the amount of decay in each person, were measured and counted. We compared the following treatments: ‐ dentist or nurse‐applied fluoride e.g. varnish, gel or foam, ‐ patient‐applied/used fluoride e.g. toothpaste, mouthwash, gel or foam, and ‐ materials that release fluoride over time e.g. glues, elastic bands. Key results One study showed that when the dentist applies a foam with a high level of fluoride in it onto the teeth every time the patient is seen, this might reduce the risk of new decay. Another study found that if patients use a toothpaste with a higher level of fluoride than normal, then this might also reduce the risk of new marks on their teeth. No studies have shown that other ways of giving the teeth extra fluoride reduced the number and/or size of new decay on teeth in people wearing fixed braces. Harmful effects of the different ways of giving the teeth more fluoride were not reported in any of the included studies. Certainty of the evidence The level of belief we have in these findings is low, due to the lack of studies testing the same fluorides and showing the same results. We suggest that more, well‐conducted studies should be done in this area. | E5: Exclude | F5: Not cash releasing | G5: =IF(E5="Include", TRUE, FALSE) -> FALSE | H5: =VLOOKUP(A5,ID_Lookup!A:A,1,FALSE) -> #N/A
A6: J504 | B6: 2019 | C6: Pmh28 Assessing the Life-Cycle Value Added of Second-Generation Antipsychotics in Sweden and the Uk: The Case of Risperidone | D6: To estimate the life-cycle value of risperidone - representative of Second-Generation Antipsychotics- relative to First Generation Antipsychotics to balance the view that cost per Quality-Adjusted Life Year (QALY) at launch are enough to guide access decisions. Study aims to drive the discussion on access and price, through recognition of the dynamic nature of value added by pharmaceutical innovation over the long-run. We estimated the number of patients with schizophrenia treated with risperidone in Sweden and the UK (1994-2017). We collected cost-effectiveness data from the literature of risperidone and haloperidol - representative of First-Generation Antipsychotics. We modelled the life-cycle uptake of risperidone to estimate the life-cycle incremental cost, incremental QALYs and Net monetary Benefit (NMB). We also assessed the life-cycle distribution of the consumer (the payer) and the producer (innovator) surpluses. For the UK, the producer surplus represents around 28% of the total surplus before patent expiration and around 5% after patent expiration. Life-cycle NMB for the health system is estimated at 1,116m. During the life-cycle, the NMB significantly increased in response to two events: (i) the launch of Risperidone Long-Acting Injectable (RLAI); and (ii) generic entry. The ICER was negative (dominant) for the whole period. For Sweden, the producer surplus represents around 6% of the total surplus before patent expiration and around 1% after generic competition. Life-cycle NMB is estimated at 803m, and both NMB and ICER follow the same pattern as in the UK. Analysis shows that health systems appropriated most of the life-cycle value (surplus) generated. This suggests that, considering the entire life-cycle, the value added by SGAs to the system is higher than the value estimated using cost-effectiveness analysis at launch. Pricing and reimbursement decisions should take into account the dynamic nature of pharmaceutical markets and the value added by innovative medicines over the long-run. Copyright © 2019 | E6: Include | F6: net monetary benefit | G6: =IF(E6="Include", TRUE, FALSE) -> TRUE | H6: =VLOOKUP(A6,ID_Lookup!A:A,1,FALSE) -> #N/A
A7: J505 | B7: 2019 | C7: Fetal fibronectin testing for reducing the risk of preterm birth | D7: - Background Fetal fibronectin (FFN) is an extracellular matrix glycoprotein localized at the maternal‐fetal interface of the amniotic membranes, between chorion and decidua, where it is concentrated in this area between decidua and trophoblast. In normal conditions, FFN is found at very low levels in cervicovaginal secretions. Levels greater than or equal to 50 ng/mL at or after 22 weeks have been associated with an increased risk of spontaneous preterm birth. In fact, FFN is one of the best predictors of preterm birth in all populations studied so far, and can help in selecting which women are at significant risk for preterm birth. This is an update of a review first published in 2008. Objectives To assess the effectiveness of management based on knowledge of FFN testing results for preventing preterm birth. Search methods For this update, we searched Cochrane Pregnancy and Childbirth’s Trials Register (7 September 2018), ClinicalTrials.gov , the WHO International Clinical Trials Registry Platform ( ICTRP ) (7 September 2018), and reference lists of retrieved studies. Selection criteria Randomized controlled trials of pregnant women screened with FFN for risk of preterm birth. Studies included are based exclusively on knowledge of FFN results versus no such knowledge, and we have excluded studies including women with only positive or only negative FFN results. Data collection and analysis Two review authors independently assessed trials for inclusion and risk of bias, extracted data, and checked them for accuracy. The quality of the evidence was assessed using the GRADE approach. Main results We identified 16 trials, of which six were eligible for inclusion. The six included studies randomized 546 women with singleton gestations and threatened preterm labor (PTL) at 23 0/7 to 34 6/7 weeks. A total of 277 women were randomized to knowledge and 269 to no knowledge of FFN. No trials were identified on asymptomatic women or multiple gestations. The risk of bias of included studies was mixed. For selected important outcomes, preterm birth before 37, 34, and 32 weeks, and maternal hospitalization, we graded the quality of the evidence and created a 'Summary of findings' table. For these outcomes, the evidence was graded as mainly low quality due to the imprecision of effect estimates. Management based on knowledge of FFN results may reduce preterm birth before 37 weeks (20.7%) versus controls without such knowledge (29.2%) (risk ratio (RR) 0.72, 95% confidence interval (CI) 0.52 to 1.01; 5 trials; 434 women; low‐quality evidence). However, management based on knowledge of FFN results may make little or no difference to preterm birth before 34 (RR 1.09, 95% CI 0.54 to 2.18; 4 trials; 357 women; low‐quality evidence) or maternal hospitalization (RR 1.06, 95% CI 0.79 to 1.43; 5 trials; 441 women; low‐quality evidence). The evidence for preterm birth before 32 weeks is uncertain because the quality was found to be very low (average RR 0.79, 95% CI 0.16 to 3.96; 4 trials; 357 women; very low‐quality evidence). For all other outcomes, for which there were available data (preterm birth less than 28 weeks; gestational age at delivery (weeks); birthweight less than 2500 g; perinatal death; tocolysis; steroids for fetal lung maturity; time to evaluate; respiratory distress syndrome; neonatal intensive care unit (NICU) admission; and NICU days), knowledge of FFN results may make little or no difference to the outcomes. Authors' conclusions The evidence from this review suggests that management based on knowledge of FFN results may reduce preterm birth before 37 weeks. However, our confidence in this result is limited as the evidence was found to be of low quality. Effects on other substantive outcomes are uncertain due to serious concerns in study design, inconsistency, and imprecision of effect estimates. No trials were identified on asymptomatic women, or multiple gestations. Future studies are needed that include specific populations (e.g. singleton gestations with symptoms of preterm labor), a study gro p managed with a protocol based on the FFN results, and that report not only maternal but also important perinatal outcomes. Cost‐effectiveness analyses are also needed. Plain language summary Fetal fibronectin testing for reducing the risk of preterm birth What is the issue? To assess the effectiveness of management of pregnant women based on a knowledge of fetal fibronectin test results for preventing preterm birth, compared with not having that knowledge. Fetal fibronectin (FFN) acts as a ‘glue’ between the pregnancy and the uterus. Normally very low levels of FFN can be found in secretions of the vagina and cervix. Raised levels at or after 22 weeks have been associated with an increased risk of spontaneous preterm birth. Why is this important? Preterm birth before 37 weeks is the main cause of sickness and death for newborn infants. Most women who give birth preterm have preterm labor symptoms such as contractions but many of the women with symptoms go on to deliver at term (37 weeks or more). Fetal fibronectin (FFN) is a test that can identify the women with symptoms of preterm labor who are most at risk for preterm birth. The level of FFN is measured in secretions from the vagina or cervix. What evidence did we find? We found six randomised controlled studies involving 546 women who were pregnant with one baby and were showing signs of preterm labor at between 23 to 34 weeks' gestation. We graded the following evidence as mainly low quality because of the low number of women in the studies and a wide variation in findings. We found that the number of births before 37 weeks may be slightly reduced when women and their doctors know the results of the FFN test (20.7% versus 29.2%; 5 trials; 434 women). However, knowledge of FFN results may make little or no difference for the other outcomes with available data, including: maternal hospitalization (5 trials; 441 women); use of uterine relaxants (tocolysis) to try to prevent labor; earlier preterm births; women’s gestational age at delivery; babies with a birthweight less than 2500 g; newborn deaths; the number of babies with respiratory distress syndrome; giving steroids to mature the unborn babies’ lungs; and number of days in a neonatal intensive care unit (NICU). What does this mean? This review of six studies did not find enough evidence to say whether or not the FFN test should be used in the management of women showing signs of preterm labor. A screening test such as FFN can only be considered effective if interventions based on the screening results, such as giving drugs to relax the uterus, reduce the number of preterm births. Further research should be encouraged. | E7: Exclude | F7: Not cash releasing | G7: =IF(E7="Include", TRUE, FALSE) -> FALSE | H7: =VLOOKUP(A7,ID_Lookup!A:A,1,FALSE) -> J505
A8: J506 | B8: 2019 | C8: Cervical assessment by ultrasound for preventing preterm delivery | D8: - Background Measurement of cervical length by ultrasound is predictive of preterm birth (PTB). There are three methods of ultrasound cervical assessment: transvaginal (TVU), transabdominal (TAU), and transperineal (TPU, also called translabial). Cervical length measured by TVU is a relatively new screening test, and has been associated with better prediction of PTB than previously available tests. It is unclear if cervical length measured by ultrasound is effective for preventing PTB. This is an update of a review last published in 2013. Objectives To assess the effectiveness of antenatal management based on transvaginal, transabdominal, and transperineal (also called translabial) ultrasound screening of cervical length for preventing preterm birth. Search methods For this update, we searched the Cochrane Pregnancy and Childbirth’s Trials Register, ClinicalTrials.gov , and the WHO International Clinical Trials Registry Platform ( ICTRP ) to 30 August 2018; reviewed the reference lists of all articles, and contacted experts in the field for additional and ongoing trials. Selection criteria We included published and unpublished randomised controlled trials (RCT) including pregnant women between the gestational ages of 14 to 32 weeks, for whom the cervical length was screened for risk of PTB with TVU, TAU, or TPU. This review focused on studies based on knowledge versus no knowledge of cervical length results, or ultrasound versus no ultrasound for cervical length. We excluded studies based on interventions (e.g. progesterone, cerclage) for short cervical length. Data collection and analysis We followed standard Cochrane methods. Main results We included seven RCTs (N = 923): one examined asymptomatic women with twin pregnancies; four included women with singleton pregnancies and symptoms of preterm labour (PTL); one included women with singleton pregnancies and symptoms of preterm premature rupture of membranes (PPROM); and one included asymptomatic singletons. All trials used TVU for screening. We assessed the risk of bias of the included studies as mixed, and the quality of the evidence for primary outcomes as very low for all populations. For asymptomatic women with twin pregnancies, it is uncertain whether knowledge of TVU‐measured cervical length compared to no knowledge reduces PTB at less than 34 weeks (risk ratio (RR) 0.62, 95% confidence intervals (CI) 0.30 to 1.25; 1 study, 125 participants) because the quality of the evidence is very low. The results were also inconclusive for preterm birth at 36, 32, or 30 weeks; gestational age at birth, and other maternal and perinatal outcomes. Four trials examined knowledge of TVU‐measured cervical length of singletons with symptoms of PTL versus no knowledge. We are uncertain of the effects because of inconclusive results and very low‐quality evidence for: preterm births at less than 37 weeks (average RR 0.59, 95% CI 0.26 to 1.32; 2 studies, 242 participants; I² = 66%; Tau² = 0.23). Birth occurred about four days later in the knowledge groups (mean difference (MD) 0.64 weeks, 95% CI 0.03 to 1.25; 3 trials, 290 women). The results were inconclusive for the other outcomes for which there were available data: PTB at less than 34 or 28 weeks; birthweight less than 2500 g; perinatal death; maternal hospitalisation; tocolysis; and steroids for fetal lung maturity. The trial of singletons with PPROM (N = 92) evaluated safety of using TVU to measure cervical length in this population as its primary outcome, not its effect on management. The results were inconclusive for incidence of maternal and neonatal infections between the TVU and no ultrasound groups. In the trial of asymptomatic singletons (N = 296), in which women either received TVU or not, the results were inconclusive for preterm birth at less than 37 weeks (RR 1.27, 95% CI 0.61 to 2.61; I² = 0%), gestational age at birth, and other perinatal and maternal outcomes. We downgraded evidence for limitations in study design, inconsistency between the trials, and imprecision, due to small sample si e and wide confidence intervals crossing the line of no effect. No trial compared the effect of knowledge of the CL with no knowledge of CL in other populations, such as asymptomatic women with singleton pregnancies, or symptomatic women with twin pregnancies. Authors' conclusions There are limited data on the effects of knowing the cervical length, measured by ultrasound, for preventing preterm births, which preclude us from drawing any conclusions for women with asymptomatic twin or singleton pregnancies, singleton pregnancies with PPROM, or other populations and clinical scenarios. Limited evidence suggests that knowledge of transvaginal ultrasound‐measured cervical length, used to inform the management of women with singleton pregnancies and symptoms of preterm labour, appears to prolong pregnancy by about four days over women in the no knowledge groups. Future studies could look at specific populations separately (e.g. singleton versus twins; symptoms versus no symptoms of PTL), report on all pertinent maternal and perinatal outcomes, and include cost‐effectiveness analyses. Most importantly, future studies should include a clear protocol for management of women based on TVU‐measured cervical length. Plain language summary Cervical assessment by ultrasound for preventing preterm delivery We set out to assess the effectiveness of knowing the cervical length, measured with ultrasound, for preventing preterm birth compared with not knowing the cervical length. What is the issue? The cervix is the lower part of the uterus that connects to the vagina. When women are not pregnant, it is normally at least 3 cm long. During pregnancy, a short cervical length is associated with a risk of spontaneous preterm birth. The shorter the cervical length, the greater the risk. Therefore, measuring cervical length by ultrasound can help predict spontaneous preterm birth. The cervical length is measured by an ultrasound scan through the vagina (transvaginal or TVU), abdomen (transabdominal), or the perineum (transperineal). The most common causes of spontaneous preterm birth are preterm labour or preterm premature rupture of the membranes. Many of the interventions used to prevent preterm birth are used once symptoms develop. Why is this important? Preterm birth before 37 weeks is the main cause of a newborn baby being sick and disabled, or dying. The cervix is the opening or passage through which the baby must pass before being born vaginally. Ultrasound can detect early changes of the cervix, such as shortening of the cervical length, to predict preterm birth. On identifying a short cervical length, interventions can be applied to prevent preterm birth. These interventions include giving the expectant mother progesterone to relax the uterus, or applying a stitch, known as a cerclage, to tighten the opening of the cervix. What evidence did we find? This review assessed if knowing the cervical length can prevent preterm birth. We included seven randomised controlled studies, which involved 923 pregnant women at 14 to 32 weeks' gestation. One study included expectant mothers with twins, without any symptoms of preterm birth or labour, and looked at the number of babies born prematurely before 36 weeks. Four studies included expectant mothers of single babies with threatened preterm labour, and one study involving women with premature rupture of the membranes looked at the safety of transvaginal ultrasound. One trial included expectant mothers with singleton pregnancies who did not have any symptoms of preterm birth or labour to look at the efficacy of transvaginal ultrasound cervical length screening. All studies used transvaginal ultrasound to assess cervical length. For women with twin pregnancies and not showing symptoms of preterm birth, we are unclear of the impact of knowing the cervical length on whether babies are born before 34 weeks' gestation, or their gestational age at birth (1 study, 125 women), because we assessed the quality of the evidence to be very low. For women with a single baby and threatened preterm labour, knowledge of their cervical length may have led to a longer pregnancy by about four days (4 studies, 410 women), but the evidence on the number of babies born before 37 weeks was unclear (2 studies, 242 women). For women whose waters had broken, it is unclear whether healthcare provider knowledge makes any difference to whether the women gave birth preterm, or on the number of infections, again because we judged the quality of evidence as very low. For women with singleton pregnancies not showing symptoms of preterm birth, it is unclear whether an ultrasound to measure cervical length made any difference to whether their babies were born before 37 weeks' gestation (1 study, 296 women; very low‐quality evidence). What does this mean? We found a limited number of studies including small numbers of women. The studies varied in their design and had a broad spread of results. Women were not blinded to whether they had an ultrasound or not. Currently, there is not enough high quality research to show if knowledge of cervical length in women with twin or singleton pregnancies has any effect. Future studies could include ways of managing women as a result of the cervical length results, and it would be useful to look at specific populations separately, such as single babies versus twins and women with and without symptoms of preterm labour. They could also report on all important maternal and perinatal outcomes, and include cost‐effectiveness analyses. | E8: Exclude | F8: Not cash releasing | G8: =IF(E8="Include", TRUE, FALSE) -> FALSE | H8: =VLOOKUP(A8,ID_Lookup!A:A,1,FALSE) -> #N/A
A9: J507 | B9: 2019 | C9: Comparison of different human papillomavirus (HPV) vaccine types and dose schedules for prevention of HPV‐related disease in females and males | D9: - Background Uptake of human papillomavirus (HPV) vaccine remains low in many countries, although the bivalent and quadrivalent HPV vaccines given as a three‐dose schedule are effective in the prevention of precancerous lesions of the cervix in women. Simpler immunisation schedules, such as those with fewer doses, might reduce barriers to vaccination, as may programmes that include males. Objectives To evaluate the efficacy, immunogenicity, and harms of different dose schedules and different types of HPV vaccines in females and males. Search methods We conducted electronic searches on 27 September 2018 in Ovid MEDLINE, the Cochrane Central Register of Controlled Trials (CENTRAL) (in the Cochrane Library), and Ovid Embase. We also searched the WHO International Clinical Trials Registry Platform, and ClinicalTrials.gov (both 27 September 2018), vaccine manufacturer websites, and checked reference lists from an index of HPV studies and other relevant systematic reviews. Selection criteria We included randomised controlled trials (RCTs) with no language restriction. We considered studies if they enrolled HIV‐negative males or females aged 9 to 26 years, or HIV‐positive males or females of any age. Data collection and analysis We used methods recommended by Cochrane. We use the term 'control' to refer to comparator products containing an adjuvant or active vaccine and 'placebo' to refer to products that contain no adjuvant or active vaccine. Most primary outcomes in this review were clinical outcomes. However, for comparisons comparing dose schedules, the included RCTs were designed to measure antibody responses (i.e. immunogenicity) as the primary outcome, rather than clinical outcomes, since it is unethical to collect cervical samples from girls under 16 years of age. We analysed immunogenicity outcomes (i.e. geometric mean titres) with ratios of means, clinical outcomes (e.g. cancer and intraepithelial neoplasia) with risk ratios or rate ratios and, for serious adverse events and deaths, we calculated odds ratios. We rated the certainty of evidence with GRADE. Main results We included 20 RCTs with 31,940 participants. The length of follow‐up in the included studies ranged from seven months to five years. Two doses versus three doses of HPV vaccine in 9‐ to 15‐year‐old females Antibody responses after two‐dose and three‐dose HPV vaccine schedules were similar after up to five years of follow‐up (4 RCTs, moderate‐ to high‐certainty evidence). No RCTs collected clinical outcome data. Evidence about serious adverse events in studies comparing dose schedules was of very low‐certainty owing to imprecision and indirectness (three doses 35/1159; two doses 36/1158; 4 RCTs). One death was reported in the three‐dose group (1/898) and none in the two‐dose group (0/899) (low‐certainty evidence). Interval between doses of HPV vaccine in 9‐ to 14‐year‐old females and males Antibody responses were stronger with a longer interval (6 or 12 months) between the first two doses of HPV vaccine than a shorter interval (2 or 6 months) at up to three years of follow‐up (4 RCTs, moderate‐ to high‐certainty evidence). No RCTs collected data about clinical outcomes. Evidence about serious adverse events in studies comparing intervals was of very low‐certainty, owing to imprecision and indirectness. No deaths were reported in any of the studies (0/1898, 3 RCTs, low‐certainty evidence). HPV vaccination of 10‐ to 26‐year‐old males In one RCT there was moderate‐certainty evidence that quadrivalent HPV vaccine, compared with control, reduced the incidence of external genital lesions (control 36 per 3081 person‐years; quadrivalent 6 per 3173 person‐years; rate ratio 0.16, 95% CI 0.07 to 0.38; 6254 person‐years) and anogenital warts (control 28 per 2814 person‐years; quadrivalent 3 per 2831 person‐years; rate ratio 0.11, 95% CI 0.03 to 0.38; 5645 person‐years). The quadrivalent vaccine resulted in more injection‐site adverse events, such as pain or redness, than control (5 7 versus 601 per 1000; risk ratio (RR) 1.12, 95% CI 1.06 to 1.18, 3895 participants, high‐certainty evidence). There was very low‐certainty evidence from two RCTs about serious adverse events with quadrivalent vaccine (control 12/2588; quadrivalent 8/2574), and about deaths (control 11/2591; quadrivalent 3/2582), owing to imprecision and indirectness. Nonavalent versus quadrivalent vaccine in 9‐ to 26‐year‐old females and males Three RCTs were included; one in females aged 9‐ to 15‐years (n = 600), one in females aged 16‐ to 26‐years (n = 14,215), and one in males aged 16‐ to 26‐years (n = 500). The RCT in 16‐ to 26‐year‐old females reported clinical outcomes. There was little to no difference in the incidence of the combined outcome of high‐grade cervical epithelial neoplasia, adenocarcinoma in situ, or cervical cancer between the HPV vaccines (quadrivalent 325/6882, nonavalent 326/6871; OR 1.00, 95% CI 0.85 to 1.16; 13,753 participants; high‐certainty evidence). The other two RCTs did not collect data about clinical outcomes. There were slightly more local adverse events with the nonavalent vaccine (905 per 1000) than the quadrivalent vaccine (846 per 1000) (RR 1.07, 95% CI 1.05 to 1.08; 3 RCTs, 15,863 participants; high‐certainty evidence). Comparative evidence about serious adverse events in the three RCTs (nonavalent 243/8234, quadrivalent 192/7629; OR 0.60, 95% CI 0.14 to 2.61) was of low certainty, owing to imprecision and indirectness. HPV vaccination for people living with HIV Seven RCTs reported on HPV vaccines in people with HIV, with two small trials that collected data about clinical outcomes. Antibody responses were higher following vaccination with either bivalent or quadrivalent HPV vaccine than with control, and these responses could be demonstrated to have been maintained for up to 24 months in children living with HIV (low‐certainty evidence). The evidence about clinical outcomes and harms for HPV vaccines in people with HIV is very uncertain (low‐ to very low‐certainty evidence), owing to imprecision and indirectness. Authors' conclusions The immunogenicity of two‐dose and three‐dose HPV vaccine schedules, measured using antibody responses in young females, is comparable. The quadrivalent vaccine probably reduces external genital lesions and anogenital warts in males compared with control. The nonavalent and quadrivalent vaccines offer similar protection against a combined outcome of cervical, vaginal, and vulval precancer lesions or cancer. In people living with HIV, both the bivalent and quadrivalent HPV vaccines result in high antibody responses. For all comparisons of alternative HPV vaccine schedules, the certainty of the body of evidence about serious adverse events reported during the study periods was low or very low, either because the number of events was low, or the evidence was indirect, or both. Post‐marketing surveillance is needed to continue monitoring harms that might be associated with HPV vaccines in the population, and this evidence will be incorporated in future updates of this review. Long‐term observational studies are needed to determine the effectiveness of reduced‐dose schedules against HPV‐related cancer endpoints, and whether adopting these schedules improves vaccine coverage rates. Plain language summary Comparison of different human papillomavirus (HPV) vaccines and the number of doses administered to prevent HPV‐related disease in females and males Human papillomaviruses (HPV) are a group of viruses that infect the skin and mucous membranes. Some types of HPV are sexually transmitted and are common in young people. Most infections will be cleared by the immune system, but some people will experience persistent infection with certain HPV types that go on to cause abnormalities in infected cells. These changes are called 'precancerous' because they can develop into cancers of the cervix, vagina, vulva, anal canal, penis, and head and neck. Infection with other HPV types causes warts in the genital area or around the anu . Vaccination aims to prevent future HPV infections. Three HPV vaccines are in use – a bivalent one (protects against two HPV types), a quadrivalent one (protects against four HPV types), and a nonavalent one (protects against nine HPV types). In women, three doses of the bivalent or the quadrivalent HPV vaccines protect against precancer of the cervix caused by the HPV types contained in the vaccine. Evidence about the nonavalent vaccine, about the effects of the quadrivalent vaccine in males, and about the effects of HPV vaccines in people with HIV infection, has not yet been reviewed thoroughly. Uptake of HPV vaccines remains low in many countries. Simpler vaccine schedules, or giving the vaccine to both girls and boys, could increase the number of people being vaccinated. Trials of HPV vaccines are not always designed to collect data about precancer and cancer, for several reasons. Firstly, HPV vaccine is routinely given before girls become sexually active, and it is not ethical to take specimens from the cervix of girls who have not had sex. Secondly, HPV‐related precancer and cancer are rare and do not develop until years after HPV infection has occurred. Thirdly, participants in a trial will be offered treatment if precancer develops, so progression to cervical cancer would be even rarer, even without vaccination. An international committee of experts states that, in some circumstances, antibody levels (i.e. showing a strong immune system response), can be used to demonstrate protection against cervical and anal cancer. The antibody levels following vaccination in a trial should not be lower than those found in other studies on adults in whom the vaccine has been shown to protect against severe HPV‐related cervical or anal disease. Review question(s) How effective or harmful are different HPV vaccine schedules (i.e. number and timing of doses) and different HPV vaccines in females and males? Main results These results are based on research evidence to 27 September 2018. We analysed 20 studies involving 31,940 people. Studies comparing two doses of HPV vaccine to three doses, or comparing the time interval between doses, focus on immune system responses rather than infection or disease outcomes. Two doses of HPV vaccine result in similar immune system responses to three doses, and a longer interval (up to 12 months) between doses gives a stronger immune system response than a shorter interval. There is insufficient evidence to determine whether there was a difference between the vaccine schedules for serious adverse events and death. In 16‐ to 26‐year‐old men, one study showed evidence of moderate certainty that a quadrivalent HPV vaccine provides better protection against external genital lesions and genital warts than a dummy treatment (control). In 16‐ to 26‐year‐old women, one study showed that the nonavalent and quadrivalent vaccines provide the same levels of protection against cervical, vaginal, and vulval precancer lesions and cancer (high‐certainty evidence). There was evidence that the quadrivalent vaccine resulted in more local adverse events (such as pain, swelling, and redness at the injection site) than a control treatment in males, and that the nonavalent vaccine resulted in more local adverse events than the quadrivalent vaccine in males and females. Evidence about serious adverse events and deaths from studies comparing different HPV vaccine types or dose schedules was of low or very low‐certainty. In people living with HIV, HPV vaccines result in reasonable levels of immune system response, but evidence about their effects on persistent HPV infection or HPV‐related disease outcomes and harms is limited. Certainty of the evidence No major issues were identified with the methodological quality of the studies for the measurements of infection and disease outcomes, or for immune system responses. Our certainty in the evidence about serious harms and deaths across all the studies comparing different HPV vaccines and vaccine schedules is low, either because of their low frequency or because the evidence is indirect, or both. Evidence graded as high certainty means that we were confident that further research is unlikely to change our findings. Moderate‐certainty evidence means that there is a possibility that further research may have an important effect on our findings, whilst low‐certainty evidence means that our confidence was limited and further research may have an important impact on our findings. Very low‐certainty evidence means that we were uncertain about the result. Conclusion A two‐dose schedule of HPV vaccines in young females results in immune system responses that are comparable with a three‐dose schedule. In males, the quadrivalent HPV vaccine appears to be effective in the prevention of external genital lesions and genital warts. Quadrivalent and nonavalent HPV vaccines in young women result in similar levels of protection against cervical, vaginal, and vulval precancer lesions and cancer. Evidence about the efficacy and harms in people living with HIV is limited. Further long‐term population‐level studies are needed to continue monitoring safety of these vaccines, to determine for how long two doses of vaccine can provide protection against HPV‐related disease, the effect against HPV‐related cancer, and whether a two‐dose immunisation schedule will increase vaccine coverage. | E9: Exclude | F9: Not cash releasing | G9: =IF(E9="Include", TRUE, FALSE) -> FALSE | H9: =VLOOKUP(A9,ID_Lookup!A:A,1,FALSE) -> #N/A
A10: J508 | B10: 2019 | C10: Adalimumab for non-infectious uveitis: Is it cost-effective? | D10: Background/Aims: Uveitis is inflammation inside the eye. Our objective was to assess the cost-effectiveness of adalimumab compared with current practice (immunosuppressants and systemic corticosteroids) in patients with non-infectious intermediate, posterior or panuveitis and to identify areas for future research. Method(s): A Markov model was built to estimate costs and benefits of the interventions. Systematic reviews were performed to identify the available relevant clinical and cost-effectiveness evidence. Data collected in two key randomised controlled trials (VISUAL I and VISUAL II) were used to estimate the interventions' effectiveness compared with the trials' comparator arms (placebo plus limited current practice (LCP)). The analysis was performed from the National Health Service and Personal Social Services perspective. Costs were calculated based on standard UK sources. Result(s): The estimated incremental cost-effectiveness ratios (ICERs) of adalimumab versus LCP for the base case are 92 600 and 318 075 per quality-adjusted life year (QALY) gained for active and inactive uveitis, respectively. In sensitivity analyses, the ICER varied from 15 579 to 120 653 and 35 642 to 800 775 per QALY for active and inactive uveitis. Conclusion(s): The estimated ICERs of adalimumab versus LCP are above generally accepted thresholds for cost-effectiveness in the UK. Adalimumab may be more cost-effective in patients with active uveitis at greater risk of blindness. However, there is an unmet need for additional primary data to provide more reliable estimates in several important areas, including effectiveness of adalimumab versus current practice (instead of LCP), incidence of long-term blindness, adalimumab effectiveness in avoiding blindness, and rates and time to remission while on adalimumab. Copyright © 2019 Author(s). | E10: Exclude | F10: Not cash releasing | G10: =IF(E10="Include", TRUE, FALSE) -> FALSE | H10: =VLOOKUP(A10,ID_Lookup!A:A,1,FALSE) -> #N/A
A11: J509 | B11: 2019 | C11: Burden of varicella complications in secondary care, England, 2004 to 2017 | D11: Background: Strategies to control varicella vary across Europe. Evidence from established programmes has prompted the United Kingdom to re-evaluate the need for universal vaccination. The burden of complicated varicella is a key parameter in the cost-effectiveness analysis. Aim(s): Our objective was to estimate the burden of complicated varicella in England. Method(s): This electronic health record surveillance study used data from all NHS hospitals in England to identify varicella admissions between 2004 and 2017. The incidence of pre-defined complications of varicella was estimated using ICD-10 codes. Inpatient costs were calculated based on the payment rules for providers of NHS services. Result(s): There were 61,024 admissions with varicella between 2004 and 2017 and 38.1% had a recognised varicella complication. Incidence of hospitalisation increased by 25% and the proportion with complicated varicella by 24% from 2004/05 to 2016/17. The most common complications were bacterial skin infections (11.25%), pneumonia (4.82%), febrile convulsions (3.39%) and encephalitis (2.44%). Complication rates were higher in older age groups and the type of complications more severe. Length of stay for complicated varicella was 3.1 times longer than for uncomplicated varicella and inpatient costs were 72% greater. Conclusion(s): Complicated varicella has a substantial health and economic burden. These data together with data on impact on quality of life are important in informing the cost-effectiveness analysis of universal varicella vaccination. Copyright © 2019 European Centre for Disease Prevention and Control (ECDC). All rights reserved. | E11: Exclude | F11: Not cash releasing | G11: =IF(E11="Include", TRUE, FALSE) -> FALSE | H11: =VLOOKUP(A11,ID_Lookup!A:A,1,FALSE) -> #N/A
A12: J510 | B12: 2019 | C12: Treatment for hepatorenal syndrome in people with decompensated liver cirrhosis: a network meta‐analysis | D12: - Background Hepatorenal syndrome is defined as renal failure in people with cirrhosis in the absence of other causes. In addition to supportive treatment such as albumin to restore fluid balance, the other potential treatments include systemic vasoconstrictor drugs (such as vasopressin analogues or noradrenaline), renal vasodilator drugs (such as dopamine), transjugular intrahepatic portosystemic shunt (TIPS), and liver support with molecular adsorbent recirculating system (MARS). There is uncertainty over the best treatment regimen for hepatorenal syndrome. Objectives To compare the benefits and harms of different treatments for hepatorenal syndrome in people with decompensated liver cirrhosis. Search methods We searched CENTRAL, MEDLINE, Embase, Science Citation Index Expanded, World Health Organization International Clinical Trials Registry Platform, and trial registers until December 2018 to identify randomised clinical trials on hepatorenal syndrome in people with cirrhosis. Selection criteria We included only randomised clinical trials (irrespective of language, blinding, or publication status) in adults with cirrhosis and hepatorenal syndrome. We excluded randomised clinical trials in which participants had previously undergone liver transplantation. Data collection and analysis Two authors independently identified eligible trials and collected data. The outcomes for this review included mortality, serious adverse events, any adverse events, resolution of hepatorenal syndrome, liver transplantation, and other decompensation events. We performed a network meta‐analysis with OpenBUGS using Bayesian methods and calculated the odds ratio (OR), rate ratio, hazard ratio (HR), and mean difference (MD) with 95% credible intervals (CrI) based on an available‐case analysis, according to National Institute of Health and Care Excellence Decision Support Unit guidance. Main results We included a total of 25 trials (1263 participants; 12 interventions) in the review. Twenty‐three trials (1185 participants) were included in one or more outcomes. All the trials but two were at high risk of bias, and all the evidence was of low or very low certainty. The trials included participants with liver cirrhosis of varied aetiologies as well as a mixture of type I hepatorenal syndrome only, type II hepatorenal syndrome only, or people with both type I and type II hepatorenal syndrome. Participant age ranged from 42 to 60 years, and the proportion of females ranged from 5.8% to 61.5% in the trials that reported this information. The follow‐up in the trials ranged from one week to six months. Overall, 59% of participants died during this period and about 35% of participants recovered from hepatorenal syndrome. The most common interventions compared were albumin plus terlipressin, albumin plus noradrenaline, and albumin alone. There was no evidence of a difference in mortality (22 trials; 1153 participants) at maximal follow‐up between the different interventions. None of the trials reported health‐related quality of life. There was no evidence of differences in the proportion of people with serious adverse events (three trials; 428 participants), number of participants with serious adverse events per participant (two trials; 166 participants), proportion of participants with any adverse events (four trials; 402 participants), the proportion of people who underwent liver transplantation at maximal follow‐up (four trials; 342 participants), or other features of decompensation at maximal follow‐up (one trial; 466 participants). Five trials (293 participants) reported number of any adverse events, and five trials (219 participants) reported treatment costs. Albumin plus noradrenaline had fewer numbers of adverse events per participant (rate ratio 0.51, 95% CrI 0.28 to 0.87). Eighteen trials (1047 participants) reported recovery from hepatorenal syndrome (as per definition of hepatorenal syndrome). In terms of recovery from hepatorenal syndrome, in the direct comparisons, albumin plus midodrine plus octreotide and albumin plus octreotide had lower recovery from hepatorenal syndrome than albumin plus terlipressin (HR 0.04; 95% CrI 0.00 to 0.25 and HR 0.26, 95% CrI 0.07 to 0.80 respectively). There was no evidence of differences between the groups in any of the other direct comparisons. In the network meta‐analysis, albumin and albumin plus midodrine plus octreotide had lower recovery from hepatorenal syndrome compared with albumin plus terlipressin. Funding: two trials were funded by pharmaceutical companies; five trials were funded by parties who had no vested interest in the results of the trial; and 18 trials did not report the source of funding. Authors' conclusions Based on very low‐certainty evidence, there is no evidence of benefit or harm of any of the interventions for hepatorenal syndrome with regards to the following outcomes: all‐cause mortality, serious adverse events (proportion), number of serious adverse events per participant, any adverse events (proportion), liver transplantation, or other decompensation events. Low‐certainty evidence suggests that albumin plus noradrenaline had fewer 'any adverse events per participant' than albumin plus terlipressin. Low‐ or very low‐certainty evidence also found that albumin plus midodrine plus octreotide and albumin alone had lower recovery from hepatorenal syndrome compared with albumin plus terlipressin. Future randomised clinical trials should be adequately powered; employ blinding, avoid post‐randomisation dropouts or planned cross‐overs (or perform an intention‐to‐treat analysis); and report clinically important outcomes such as mortality, health‐related quality of life, adverse events, and recovery from hepatorenal syndrome. Albumin plus noradrenaline and albumin plus terlipressin appear to be the interventions that should be compared in future trials. Plain language summary Treatment of hepatorenal syndrome What is the aim of this Cochrane review? To find out the best treatment for decreased kidney function (hepatorenal syndrome) in people with liver cirrhosis (a form of advanced liver disease with scarring of the liver) with complications. The authors collected and analysed all relevant studies to answer this question and found 25 randomised controlled trials (participants receive the treatment based on method similar to coin toss or lottery; this is to ensure that the people who receive the different treatments are similar in all aspects except the treatment, so that any differences in the results between the treatments can be attributed to the treatment rather than differences in the type of people who received the treatment). During analysis of data, authors used standard Cochrane techniques, which allows comparison of two treatments at a time. Authors also used advanced techniques, that allow comparison of many treatments at the same time (usually referred as 'network meta‐analysis' or 'multiple treatment comparisons'). The aim is to gather reliable evidence on the relative benefits and harms of the different treatments. Date of literature search December 2018 Key messages Only two studies were conducted well. The remaining studies had one or more flaws. Therefore, there is high uncertainty in the results of the analysis. The authors could not recommend one treatment over another on the basis of risk of death, serious complications, percentage of people who developed any complication, percentage of participants who underwent liver transplantation (replacement of a diseased liver with a healthy one), or the number of other liver failure events. Health‐related quality of life was not reported in any of the trials. The number of complications of any severity was lower with albumin plus noradrenaline than albumin plus terlipressin. Recovery from hepatorenal syndrome may be lower with albumin plus midodrine plus octreotide and albumin alone than albumin plus terlipressin and albumin plus noradrenaline. Funding source was unclear in 18 studies. Industrial organisations funded two studies and the remaining five studies did not receive any funding from industrial organisations. What was studied in the review? This review studied people of any sex, age, and origin, having advanced liver disease due to various causes, and who had developed hepatorenal syndrome. People were administered different treatments. The review authors excluded studies with liver‐transplanted participants. Participants age, when reported, ranged from 42 to 60 years. The number of females ranged from 6 to 62 out of 100 in the studies that reported this information. The main treatments compared were albumin alone, albumin plus terlipressin, and albumin plus noradrenaline. The authors gathered and analysed data on death, quality of life, serious and non‐serious complications, time to liver transplantation, recovery from hepatorenal syndrome, and disappearance of symptoms. What were the main results of the review? The 25 studies included a small number of participants (1263 participants). Study data were sparse. Twenty‐three studies with 1185 participants provided data for analyses. The follow‐up in the trials ranged from one week to six months. The review shows that: ‐ About 60 out of every 100 people died within three months, and 35 out of every 100 people recovered from hepatorenal syndrome. ‐ The provided treatment may make no difference to the percentage of people who died or developed serious complications, number of serious complications per person, percentage of people who developed complications of any severity, or the percentage of people undergoing liver transplantation. ‐ None of the trials reported health‐related quality of life. ‐ The number of complications of any severity was lower with albumin plus noradrenaline than albumin plus terlipressin. ‐ Recovery from hepatorenal syndrome may be lower with albumin plus midodrine plus octreotide and albumin alone than albumin plus terlipressin and albumin plus noradrenaline. ‐ We have very low confidence in the overall results. ‐ Future trials with proper design and quality are needed to clarify the best treatment for people with advanced liver disease having hepatorenal syndrome. | E12: Include | F12: limited evidence of cost saving | G12: =IF(E12="Include", TRUE, FALSE) -> TRUE | H12: =VLOOKUP(A12,ID_Lookup!A:A,1,FALSE) -> #N/A
A13: J511 | B13: 2019 | C13: Switching from originator infliximab to CT-P13: Single-centre experience from the UK | D13: Background: The infliximab biosimilar (CT-P13) received market authorisation for inflammatory bowel disease in late 2016 with the aim of reducing cost and increasing access to therapy. The prospect of 'switching' patients from originator to CT-P13 has concerned clinicians. #8232;We present an experience of 'switching' from originator infliximab (IFX-O) to CT-P13 and present efficacy, safety, and immunogenicity data from our cohort. Method(s): We performed a retrospective review of patients switched from IFX-O to CT-P13. Disease demographics, clinical course and outcomes were analysed from electronic case records at a median of 8 months and at last follow-up at 13 months. Result(s): Ninety-six patients (35 females) were 'switched' from IFX-O to CT-P13. Of these 44 had Ulcerative colitis (UC) and 52 had Crohn's disease (CD) with a mean age at diagnosis of 34.7 years (median = 33, IQR = 24.5). Montreal phenotype for UC was E1 = 1, E2 = 16, E3 = 27 and for CD (L1 = 10, L2 = 12 , L3 = 29, L4 = 1) and (B1 = 27, #8232;B2 = 14 , B3 = 11), 9 patients had perianal disease. Mean duration of IFX-O treatment was 49. 8 months (median = 44, IQR = 52) and on CT-P13 11.5 months (median 13). At switch, 76 patients had a normal CRP (UC = 33, CD = 43), and in 15 patients it was elevated (UC = 10, CD = 5). At 8 months, 80 patients remained in biochemical remission (UC = 35, CD = 45 ) and in 14 patients (UC = 8, CD = 6 ) CRP increased. Seventy-two patients (UC = 34, CD = 38 ) were in clinical remission (pMayo < 2 and HBI < 5). Of 51 patients (UC = 21, CD = 30) undergoing endoscopic assessment, 31 achieved mucosal healing (UC = 13, CD = 18). At 13 months, 69 patients remained on CT-P13. Twenty-seven discontinued the drug due to immunogenicity (n = 10), loss of response (n = 5), surgery (n = 5), remission (n = 5) , side effects (n = 2 ), and 1 patient died of hospital acquired pneumonia. 39 out of 96 patients had therapeutic drug levels checked within 13 months of switch, of whom 27 had sub-therapeutic levels (below 4 mug/ml). Antibodies to Infliximab were seen in 15 of 39 patients (38.5%), of whom 8 were switched to an alternative biologic, 2 had dose escalation (10 mg/kg IFX), 4 patients stopped IFX with no other intervention, and 1 person continued treatment at same dose with low antibody titre of 6. Conclusion(s): Biosimilar IFX (CT-P13) was well tolerated. Clinical efficacy and loss of response rates with CT-P13 appears to be similar to IFX-O. This holds promise for a wider adoption of 'switching' to fulfil the purported aims of wider access to treatment at a lower cost. | E13: Exclude | F13: No figure in abstract for costs saved | G13: =IF(E13="Include", TRUE, FALSE) -> FALSE | H13: =VLOOKUP(A13,ID_Lookup!A:A,1,FALSE) -> #N/A
... A81: J579 | B81: 2019 | C81: Results of a Birth Cohort Hepatitis C Screening Program in an Academic Emergency Department in Canada | D81: BACKGROUND: Epidemiologic and modeling studies suggest that between 45% and 70% of individuals with chronic hepatitis C virus (HCV) infection in Canada remain undiagnosed. The Canadian Association for the Study of the Liver (CASL) recommends one-time screening of baby boomers (1945-1975), based on data showing HCV prevalence is highest in this cohort and screening is cost-effective. Screening programs in the US have shown a very high prevalence of previously undiagnosed HCV among patients seen in the Emergency department (ED). The utility of ED screening has not been evaluated in Canada. PURPOSE: To assess the feasibility of implementing a targeted birth-cohort HCV screening program in the ED setting. METHOD(S): Patients born from 1945 to 1975 presenting to the ED of a tertiary care hospital were offered HCV testing. Patients with lifethreatening conditions and unable to provide verbal consent in English were excluded. Blood samples were collected by finger prick on Dried Blood Spot (DBS) collection cards and tested for anti-HCV with reflex to HCV RNA. Patients with positive HCV RNA were referred to a liver specialist. RESULT(S): During a 14-month period, 6,613 patients in the birth cohort presented to the ED during daytime hours. 77% (5,117) met the eligibility criteria, 52% (2,817) were offered testing: 269 (11%) were previously tested, 487 (20%) declined. 1,639 (66%) individuals underwent testing: median age 58.2 (35-74), 850 male (51.9%). Of these, 29 patients (1.8%; 95% CI 1.2% to 2.4%) were anti-HCV positive: 18 (69.2%) were HCV RNA positive, 7 (26.9%) negative and 3 not done due to inadequate DBS sample. Screening was successfully done by non-medical staff (mean 8/day, median spots on DBS 3). 14 patients (78%) were linked to care and 4 lost to follow-up. The HCV prevalence in the ED was significantly higher than the general Canadian population (1.8% vs 0.7%; p < 0.0001) but much lower than reported rates in American EDs (1.8% vs 10.3%; p < 0.0001). CONCLUSION(S): Acceptance of HCV screening in the ED birth cohort was high and easily performed using DBS to ensure the majority of positive samples were tested for HCV RNA. Challenges with implementation limited the number of people tested. HCV prevalence among this ED birth cohort was higher than the general population but lower than seen in the ED in the US. This may in part be due to exclusion of individuals with more severe medical issues or possibly due to population and health care system differences between countries. | E81: Exclude | F81: Not cash releasing | G81: =IF(E81="Include", TRUE, FALSE) -> FALSE | H81: =VLOOKUP(A81,ID_Lookup!A:A,1,FALSE) -> #N/A
A82: J580 | B82: 2019 | C82: Results of a birth cohort hepatitis C screening program in an academic emergency department in Canada | D82: Background and aims: Epidemiologic and modeling studies suggest that between 45 and 70% of individuals with chronic hepatitis C virus (HCV) infection in Canada remain undiagnosed. The Canadian Association for the Study of the Liver (CASL) recommends one-time screening of baby boomers (1945-1975), based on data showing HCV prevalence is highest in this cohort and screening is cost-effective. Screening programs in the US have shown a very high prevalence of previously undiagnosed HCV among patients seen in the Emergency department (ED). The utility of ED screening has not been evaluated in Canada. To assess the feasibility of implementing a targeted birth-cohort HCV screening program in the ED setting. Method(s): Patients born from 1945 to 1975 presenting to the ED of a tertiary care hospital were offered HCV testing. Patients with life-threatening conditions and unable to provide verbal consent in English were excluded. Blood samples were collected by finger prick on Dried Blood Spot (DBS) collection cards and tested for anti-HCV with reflex to HCV RNA. Patients with positive HCV RNA were referred to a liver specialist. Result(s): During a 14-month period, 6, 613 patients in the birth cohort presented to the ED during daytime hours. 77% (5, 117) met the eligibility criteria, 52% (2, 817) were offered testing: 269 (11%) were previously tested, 487 (20%) declined. 1639 (66%) individuals underwent testing: median age 58.2 (35-74), 850 male (51.9%). Of these, 29 patients (1.8%; 95%CI 1.2%-2.4%) were anti-HCV positive: 18 (69.2%) were HCV RNA positive, 7 (26.9%) negative and 3 not done due to inadequate DBS sample. Screening was successfully done by non-medical staff (mean 8/day, median spots on DBS 3). 14 patients (78%) were linked to care and 4 lost to follow-up. The HCV prevalence in the ED was significantly higher than the general Canadian population (1.8% vs 0.7%; p < 0.0001) but much lower than reported rates in American EDs (1.8% vs 10.3%; p < 0.0001). Conclusion(s): Acceptance of HCV screening in the ED birth cohort was high and easily performed using DBS to ensure the majority of positive samples were tested for HCV RNA. Challenges with implementation limited the number of people tested. HCV prevalence among this ED birth cohort was higher than the general population but lower than seen in the ED in the US. This may in part be due to exclusion of individuals with more severe medical issues or possibly due to population and healthcare system differences between countries. Copyright © 2019 European Association for the Study of the Liver | E82: Exclude | G82: =IF(E82="Include", TRUE, FALSE) -> FALSE | H82: =VLOOKUP(A82,ID_Lookup!A:A,1,FALSE) -> #N/A
A83: J581 | B83: 2019 | C83: Fls implementation: An innovative service support model for secondary fracture prevention in the UK | D83: An FLS systematically finds, assesses, treats and follows-up fragility fracture patients to prevent secondary fractures. Fracture prevention is cost-effective in terms of both social and healthcare budgets. Studies show that half of hip fractures occur after a prior fragility fracture, and 25% of hip fractures could be prevented with effective identification and treatment. Since 2014 the NOS has led an innovative programme providing a 'top-down' (national influencing, policy agenda) and 'bottom-up' (operational health service delivery support) approach to developing FLS in the UK. To date, 29 new services have been set-up; providing FLS to an additional 10m people, potentially preventing over 3200 hip fractures and saving the local health economy 65m over 5 years. This session will share our extensive experience of promoting this model. | E83: Exclude | F83: Not cash releasing | G83: =IF(E83="Include", TRUE, FALSE) -> FALSE | H83: =VLOOKUP(A83,ID_Lookup!A:A,1,FALSE) -> #N/A
A84: J582 | B84: 2019 | C84: Recontacting patients in clinical genetics services: recommendations of the European Society of Human Genetics | D84: Technological advances have increased the availability of genomic data in research and the clinic. If, over time, interpretation of the significance of the data changes, or new information becomes available, the question arises as to whether recontacting the patient and/or family is indicated. The Public and Professional Policy Committee of the European Society of Human Genetics (ESHG), together with research groups from the UK and the Netherlands, developed recommendations on recontacting which, after public consultation, have been endorsed by ESHG Board. In clinical genetics, recontacting for updating patients with new, clinically significant information related to their diagnosis or previous genetic testing may be justifiable and, where possible, desirable. Consensus about the type of information that should trigger recontacting converges around its clinical and personal utility. The organization of recontacting procedures and policies in current health care systems is challenging. It should be sustainable, commensurate with previously obtained consent, and a shared responsibility between healthcare providers, laboratories, patients, and other stakeholders. Optimal use of the limited clinical resources currently available is needed. Allocation of dedicated resources for recontacting should be considered. Finally, there is a need for more evidence, including economic and utility of information for people, to inform which strategies provide the most cost-effective use of healthcare resources for recontacting. Copyright © 2018, The Author(s). | E84: Exclude | F84: Not cash releasing | G84: =IF(E84="Include", TRUE, FALSE) -> FALSE | H84: =VLOOKUP(A84,ID_Lookup!A:A,1,FALSE) -> #N/A
A85: J583 | B85: 2019 | C85: Community pharmacy personnel interventions for smoking cessation | D85: - Background Community pharmacists could provide effective smoking cessation treatment because they offer easy access to members of the community. They are well placed to provide both advice on the correct use of smoking cessation products and behavioural support to aid smoking cessation. Objectives To assess the effectiveness of interventions delivered by community pharmacy personnel to assist people to stop smoking, with or without concurrent use of pharmacotherapy. Search methods We searched the Cochrane Tobacco Addiction Group Specialised Register, along with clinicaltrials.gov and the ICTRP, for smoking cessation studies conducted in a community pharmacy setting, using the search terms pharmacist* or pharmacy or pharmacies. Date of the most recent search: January 2019. Selection criteria Randomised controlled trials of interventions delivered by community pharmacy personnel to promote smoking cessation amongst their clients who were smokers, compared with usual pharmacy support or any less intensive programme. The main outcome measure was smoking cessation rates at six months or more after the start of the intervention. Data collection and analysis We used standard methodological procedures expected by Cochrane for study screening, data extraction and management. We conducted a meta‐analysis using a Mantel‐Haenszel random‐effects model to generate risk ratios (RRs) and 95% confidence intervals (CIs). Main results We identified seven studies including 1774 participants. We judged three studies to be at high risk of bias and four to be at unclear risk. Each study provided face‐to‐face behavioural support delivered by pharmacy staff, and required pharmacy personnel training. Typically such programmes comprised support starting before quit day and continuing with weekly appointments for several weeks afterwards. Comparators were either minimal or less intensive behavioural support for smoking cessation, typically comprising a few minutes of one‐off advice on how to quit. Participants in both intervention and control arms received equivalent smoking cessation pharmacotherapy in all but one study. All studies took place in high‐income countries, and recruited participants visiting pharmacies. We pooled six studies of 1614 participants and detected a benefit of more intensive behavioural smoking cessation interventions delivered by community pharmacy personnel compared with less intensive cessation interventions at longest follow‐up (RR 2.30, 95% CI 1.33 to 3.97; I 2 = 54%; low‐certainty evidence). Authors' conclusions Community pharmacists can provide effective behavioural support to people trying to stop smoking. However, this conclusion is based on low‐certainty evidence, limited by risk of bias and imprecision. Further research could change this conclusion. Plain language summary Does quit‐smoking support delivered by community pharmacy staff help people to stop smoking? Background Tobacco smoking is the leading cause of preventable death and disease worldwide. Community pharmacists are respected healthcare professionals who provide easily accessible and convenient healthcare services to their communities, and they are well placed to provide their clients with help to quit smoking. Indeed, many governments recognise community pharmacies as a useful way of delivering many healthcare services. However, we need evidence that these services are effective before we develop them more widely. Study characteristics We searched for relevant studies in January 2019, and found seven studies including 1774 people. Three studies took place in the UK, and one each in Australia, United States, Qatar, and Italy. Each study provided face‐to‐face behavioural support delivered by pharmacy staff, who received specific training. Studies compared the structured programme to less intensive support to stop smoking. Key results We found evidence that more intensive structured care given by community pharmacy staff probably helps more people to quit smoking than less intensive support to quit. Qualit of the evidence We found low‐quality evidence that community pharmacy support helps people to quit smoking. Limitations of the evidence came from potential problems with the ways some of the studies were carried out and the low numbers of people who quit smoking across the included studies, which means we are not sure how effective these programmes really are. | E85: Exclude | F85: study that demonstrates cost saving is Australian | G85: =IF(E85="Include", TRUE, FALSE) -> FALSE | H85: =VLOOKUP(A85,ID_Lookup!A:A,1,FALSE) -> J583
A86: J584 | B86: 2019 | C86: Physiotherapy triage service for cancer patients - a service evaluation | D86: Purpose: Individuals with cancer experience a plethora of symptoms from diagnosis, through treatment and beyond into survivorship. Allied Health Professionals are uniquely placed to impact upon these symptoms by engaging individuals in rehabilitation. Scoping of rehabilitation services amongst individuals with cancer undergoing haematological and oncological treatment highlighted various issues with fatigue, loss of function, pain and breathlessness. A pilot programme was implemented to address these unmet needs. Method(s): In an acute teaching trust in the South West of England, individuals with cancer were highlighted by health care professionals and referred into the Therapy Treatment Support Service (TTSS). Included individuals had a cancer diagnosis and were adults aged 16 years and over, exclusion criteria specified those under 16 years of age and those without a cancer diagnosis. Telephone triage carried out by a physiotherapist provided appropriate interventions including fatigue management, musculoskeletal treatment, exercise programmes and breathlessness advice for individuals. The Functional Assessment of Cancer Therapy - General (FACT-G) was used as a quality of life outcome measure on initial and final contact. Result(s): Between March 2017 and March 2018 220 individuals were referred to TTSS with the following numbers specifying the primary reason for referral, 81 for fatigue, 71 for musculoskeletal issues, 42 for physical activity issues, 20 for mobility issues and 6 for breathlessness. In total 44 of 53 completed datasets demonstrated positive outcomes in terms of quality of life using the FACT-G. Of 23 completed datasets with fatigue as the primary reason for referral, 21 demonstrated an improvement. Conclusion(s): Fatigue is the primary reason for referral to TTSS and its interventions have shown a positive impact upon quality of life. A more detailed enquiry is required to investigate this service model. Implications: There is discrepancy in service provision for fatigue management amongst the population of those living with and beyond cancer. A cost-effective intervention that can provide equitable access is required to meet the aims stated in the Recovery Package. A standardised intervention delivered via a telephone clinic could reach a significant population of those living with and beyond cancer improving cancer-related fatigue symptoms. Funding acknowledgements: Macmillan Cancer Support provided funding for this pilot programme. The authors report no affiliations or conflicts of interest in the subject matter of this abstract. Copyright © 2018 | E86: Exclude | F86: Not cash releasing | G86: =IF(E86="Include", TRUE, FALSE) -> FALSE | H86: =VLOOKUP(A86,ID_Lookup!A:A,1,FALSE) -> #N/A
A87: J585 | B87: 2019 | C87: Fortification of wheat and maize flour with folic acid for population health outcomes | D87: - Background Folate is a B‐vitamin required for DNA synthesis, methylation, and cellular division. Wheat and maize (corn) flour are staple crops consumed widely throughout the world and have been fortified with folic acid in over 80 countries to prevent neural tube defects. Folic acid fortification may be an effective strategy to improve folate status and other health outcomes in the overall population. Objectives To evaluate the health benefits and safety of folic acid fortification of wheat and maize flour (i.e. alone or in combination with other micronutrients) on folate status and health outcomes in the overall population, compared to wheat or maize flour without folic acid (or no intervention). Search methods We searched the following databases in March and May 2018: Cochrane Central Register of Controlled Trials (CENTRAL), MEDLINE and MEDLINE In Process, Embase, CINAHL, Web of Science (SSCI, SCI), BIOSIS, Popline, Bibliomap, TRoPHI, ASSIA, IBECS, SCIELO, Global Index Medicus‐AFRO and EMRO, LILACS, PAHO, WHOLIS, WPRO, IMSEAR, IndMED, and Native Health Research Database. We searched the International Clinical Trials Registry Platform and ClinicalTrials.gov for ongoing or planned studies in June 2018, and contacted authors for further information. Selection criteria We included randomised controlled trials (RCTs), with randomisation at the individual or cluster level. We also included non‐RCTs and prospective observational studies with a control group; these studies were not included in meta‐analyses, although their characteristics and findings were described. Interventions included wheat or maize flour fortified with folic acid (i.e. alone or in combination with other micronutrients), compared to unfortified flour (or no intervention). Participants were individuals over two years of age (including pregnant and lactating women), from any country. Data collection and analysis Two review authors independently assessed study eligibility, extracted data, and assessed risk of bias. Main results We included 10 studies: four provided data for quantitative analyses (437 participants); five studies were randomised trials (1182 participants); three studies were non‐RCTs (1181 participants, 8037 live births); two studies were interrupted time series (ITS) studies (1 study population of 2,242,438, 1 study unreported). Six studies were conducted in upper‐middle‐income countries (China, Mexico, South Africa), one study was conducted in a lower‐middle‐income country (Bangladesh), and three studies were conducted in a high‐income country (Canada). Seven studies examined wheat flour fortified with folic acid alone or with other micronutrients. Three studies included maize flour fortified with folic acid alone or with other micronutrients. The duration of interventions ranged from two weeks to 36 months, and the ITS studies included postfortification periods of up to seven years. Most studies had unclear risk of bias for randomisation, blinding, and reporting, and low/unclear risk of bias for attrition and contamination. Neural tube defects : none of the included RCTs reported neural tube defects as an outcome. In one non‐RCT, wheat flour fortified with folic acid and other micronutrients was associated with significantly lower occurrence of total neural tube defects, spina bifida, and encephalocoele, but not anencephaly, compared to unfortified flour (total neural tube defects risk ratio (RR) 0.32, 95% confidence interval (CI) 0.21 to 0.48; 1 study, 8037 births; low‐certainty evidence). Folate status : pregnant women who received folic acid‐fortified maize porridge had significantly higher erythrocyte folate concentrations (mean difference (MD) 238.90 nmol/L, 95% CI 149.40 to 328.40); 1 study, 38 participants; very low‐certainty evidence) and higher plasma folate (MD 14.98 nmol/L, 95% CI 9.63 to 20.33; 1 study, 38 participants; very low‐certainty evidence), compared to no intervention. Women of reproductive age consuming maize flour fortified with folic acid and other micronutrients did no have higher erythrocyte folate (MD ‐61.80 nmol/L, 95% CI ‐152.98 to 29.38; 1 study, 35 participants; very low‐certainty evidence) or plasma folate (MD 0.00 nmol/L, 95% CI ‐0.00 to 0.00; 1 study, 35 participants; very low‐certainty evidence) concentrations, compared to women consuming unfortified maize flour. Adults consuming folic acid‐fortified wheat flour bread rolls had higher erythrocyte folate (MD 0.66 nmol/L, 95% CI 0.13 to 1.19; 1 study, 30 participants; very low‐certainty evidence) and plasma folate (MD 27.00 nmol/L, 95% CI 15.63 to 38.37; 1 study, 30 participants; very low‐certainty evidence), versus unfortified flour. In two non‐RCTs, serum folate concentrations were significantly higher among women who consumed flour fortified with folic acid and other micronutrients compared to women who consumed unfortified flour (MD 2.92 nmol/L, 95% CI 1.99 to 3.85; 2 studies, 657 participants; very low‐certainty evidence). Haemoglobin or anaemia : in a cluster‐randomised trial among children, there were no significant effects of fortified wheat flour flatbread on haemoglobin concentrations (MD 0.00 nmol/L, 95% CI ‐2.08 to 2.08; 1 study, 334 participants; low‐certainty evidence) or anaemia (RR 1.07, 95% CI 0.74 to 1.55; 1 study, 334 participants; low‐certainty evidence), compared to unfortified wheat flour flatbread. Authors' conclusions Fortification of wheat flour with folic acid may reduce the risk of neural tube defects; however, this outcome was only reported in one non‐RCT. Fortification of wheat or maize flour with folic acid (i.e. alone or with other micronutrients) may increase erythrocyte and serum/plasma folate concentrations. Evidence is limited for the effects of folic acid‐fortified wheat or maize flour on haemoglobin levels or anaemia. The effects of folic acid fortification of wheat or maize flour on other primary outcomes assessed in this review is not known. No studies reported on the occurrence of adverse effects. Limitations of this review were the small number of studies and participants, limitations in study design, and low‐certainty of evidence due to how included studies were designed and reported. Plain language summary The effects of fortification of wheat and maize flour with folic acid on population health outcomes Background Folate is an essential vitamin that is needed to make and repair DNA and for cell division. Folate has two main forms: folate, the natural form found in foods, and folic acid, the form that is used in supplements and fortified foods. Wheat and maize (corn) flour are staple crops consumed widely throughout the world. Fortification (i.e. the addition of vitamins and minerals to foods, to increase their nutritional value) of wheat or maize flour with folic acid has been introduced in over 80 countries to prevent neural tube defects among women of reproductive age. However, no previous systematic reviews have been conducted to evaluate the effects of folic acid‐fortified flour on folate status or other health outcomes in the general population. Review question This review aimed to determine the benefits and safety of fortification of wheat and maize flour with folic acid (i.e. alone or with other vitamins and minerals), compared to wheat or maize flour without folic acid (or no intervention), on folate status and different measures of health in the general population. Study characteristics We conducted the literature search in March and May 2018. We included 10 studies; four studies provided data for meta‐analyses. Six studies were conducted in upper‐middle‐income countries (China, Mexico, South Africa), one study was conducted in a lower‐middle‐income country (Bangladesh), and three studies were conducted in a high‐income country (Canada). Seven studies examined the effects of wheat flour fortified with folic acid alone (3 studies) or with other micronutrients (4 studies). Three studies assessed the effects of maize flour fortified with folic acid alone (1 study) or with other micronutrients (two studies). Key results and certain y of the evidence Fortification of wheat flour with folic acid may reduce the likelihood of neural tube defects (i.e. total neural tube defects and two specific types of neural tube defects, spina bifida and encephalocoele (a type of neural tube defect that affects the brain and the membranes that cover it through an opening in the skull). Fortification of wheat or maize flour with folic acid (i.e. alone or with other vitamins and minerals) may increase folate status. There was limited evidence of the effects of folic acid‐fortified wheat flour on haemoglobin levels or anaemia. The effects of folic acid fortification of wheat or maize flour on other main outcomes assessed in this review is not known. No studies reported on the occurrence of adverse effects. Limitations of this review were the small number of studies and participants, and the low‐certainty of evidence due to how included studies were designed and reported. | E87: Exclude | F87: Not cash releasing | G87: =IF(E87="Include", TRUE, FALSE) -> FALSE | H87: =VLOOKUP(A87,ID_Lookup!A:A,1,FALSE) -> #N/A
